Workbook

Sheet README
A1: Original Hospital Revenue Cycle Charge Demo
A2: Independent synthetic demonstration workbook. It is not an Epic product, replica, extract, or proprietary build.
A3: Purpose
A4: Provides an original hospital revenue-cycle dataset with payer-specific pricing for Athena Health Insurance and Care Gap Health. | B4: Provides an original hospital revenue-cycle dataset with separate inpatient and outpatient charge-detail views, CDM controls, routing, billing edits, contracts, governance, and auditability.
A5: Epic alignment | B5: Uses common US hospital billing concepts such as hospital accounts, charge routing, workqueues, facility/professional split, institutional claims, and reimbursement. No proprietary EHR design is reproduced.
A6: Primary sheets | B6: CDM Master; IPD Encounter; Charge Router Rules; Claim Edits; Payer Contracts; Price Transparency; Governance; Audit Trail; Data Source Map; Data Dictionary; Dashboard.
A7: Color convention | B7: Blue = editable input; black = formula/derived; green = linked/imported; gray = static reference; orange = review; red = error/hold; purple = control logic; teal = KPI/visualization.
A8: Data disclaimer | B8: All patients, payers, prices, contracts, identifiers, effective dates, and operational scenarios are synthetic. No PHI is included.
A9: Sources | B9: Epic public financial interface documentation: https://open.epic.com/Financial/Billing CMS Hospital Price Transparency: https://www.cms.gov/priorities/key-initiatives/hospital-price-transparency CMS technical implementation guide: https://github.com/CMSgov/hospital-price-transparency

Sheet Charge Summary
A1: IPD and OPD Charge Summary
A2: Executive comparison of 420 payer-priced charge rows: 220 IPD and 200 OPD.
A4: Setting | B4: Charge Lines | C4: Gross Charges ($) | D4: Expected Allowed ($) | E4: Patient Responsibility ($) | F4: Adjustments ($) | G4: Held Charges | H4: Review Edits
A5: IPD | B5: =COUNTA('IPD Charges'!A5:A500) | C5: =SUM('IPD Charges'!O:O) | D5: =SUM('IPD Charges'!P:P) | E5: =SUM('IPD Charges'!Q:Q) | F5: =SUM('IPD Charges'!R:R) | G5: =COUNTIF('IPD Charges'!Z:Z,"Hold") | H5: =COUNTIF('IPD Charges'!AB:AB,"Review")
A6: OPD | B6: =COUNTA('OPD Charges'!A5:A500) | C6: =SUM('OPD Charges'!O:O) | D6: =SUM('OPD Charges'!P:P) | E6: =SUM('OPD Charges'!Q:Q) | F6: =SUM('OPD Charges'!R:R) | G6: =COUNTIF('OPD Charges'!Z:Z,"Hold") | H6: =COUNTIF('OPD Charges'!AB:AB,"Review")
A7: TOTAL | B7: =SUM(B5:B6) | C7: =SUM(C5:C6) | D7: =SUM(D5:D6) | E7: =SUM(E5:E6) | F7: =SUM(F5:F6) | G7: =SUM(G5:G6) | H7: =SUM(H5:H6)

Sheet Payer Pricing Comparison
A1: Payer Pricing Comparison
A2: Care Gap Health negotiated allowed amounts are 10% lower than Athena for every IPD and OPD charge line.
A4: Setting | B4: Original Services | C4: Athena Rows | D4: Care Gap Rows | E4: Total Rows | F4: Athena Pricing | G4: Care Gap Pricing | H4: Patient Coinsurance
A5: IPD | B5: 110 | C5: 110 | D5: 110 | E5: 220 | F5: Original allowed amount | G5: 10% below Athena | H5: Athena 20% / Care Gap 15%
A6: OPD | B6: 100 | C6: 100 | D6: 100 | E6: 200 | F6: Original allowed amount | G6: 10% below Athena | H6: Athena 20% / Care Gap 15%
A7: TOTAL | B7: =SUM(B5:B6) | C7: =SUM(C5:C6) | D7: =SUM(D5:D6) | E7: =SUM(E5:E6)

Sheet IPD Charges
A1: Inpatient Charge Detail
A2: 110 original synthetic inpatient charge lines, each represented for Athena Health Insurance and Care Gap Health (220 payer-priced rows).
A4: Charge Line ID | B4: Patient Account | C4: Encounter ID | D4: Patient Class | E4: Facility | F4: Department | G4: Service Date | H4: Charge Code | I4: Charge Description | J4: Revenue Code | K4: CPT/HCPCS | L4: Modifier | M4: Quantity | N4: Unit Charge ($) | O4: Extended Gross ($) | P4: Expected Allowed ($) | Q4: Patient Responsibility ($) | R4: Contractual Adjustment ($) | S4: Payer | T4: Plan | U4: Authorization ID | V4: Ordering Provider | W4: Performing Provider | X4: Source System | Y4: Charge Trigger | Z4: Charge Status | AA4: Reconciliation Status | AB4: Claim Edit Status | AC4: Workqueue | AD4: Medical Necessity | AE4: Diagnosis Link | AF4: Place of Service | AG4: Posting Date/Time | AH4: Notes
A5: IPD-CHG-0001-ATH | B5: HAR-202600001-ATH | C5: CSN-IPD-780001-ATH | D5: Inpatient | E5: Demo Regional Medical Center | F5: Accommodation | G5: 2026-09-02 | H5: RM-SEMI-DAY | I5: Semiprivate Medical/Surgical Room | J5: 0120 | M5: 1 | N5: 3500 | O5: =M5*N5 | P5: 1496.26 | Q5: =P5*20% | R5: =O5-P5 | S5: Athena Health Insurance | T5: Athena PPO | V5: Eleanor Brooks, MD | W5: Assigned Department Provider | X5: ADT | Y5: Midnight census | Z5: Posted | AA5: Matched | AB5: Passed | AD5: N/A | AE5: M17.11 | AF5: 21 | AG5: 2026-09-02 16:30 | AH5: Synthetic Athena negotiated charge
A6: IPD-CHG-0001-CGH | B6: HAR-202600001-CGH | C6: CSN-IPD-780001-CGH | D6: Inpatient | E6: Demo Regional Medical Center | F6: Accommodation | G6: 2026-09-02 | H6: RM-SEMI-DAY | I6: Semiprivate Medical/Surgical Room | J6: 0120 | M6: 1 | N6: 3500 | O6: =M6*N6 | P6: 1346.63 | Q6: =P6*15% | R6: =O6-P6 | S6: Care Gap Health | T6: Care Gap Value PPO | V6: Eleanor Brooks, MD | W6: Assigned Department Provider | X6: ADT | Y6: Midnight census | Z6: Posted | AA6: Matched | AB6: Passed | AD6: N/A | AE6: M17.11 | AF6: 21 | AG6: 2026-09-02 16:30 | AH6: Synthetic Care Gap charge; 10% below Athena allowed amount
A7: IPD-CHG-0002-ATH | B7: HAR-202600002-ATH | C7: CSN-IPD-780002-ATH | D7: Inpatient | E7: Demo Regional Medical Center | F7: Accommodation | G7: 2026-09-03 | H7: RM-PRIV-DAY | I7: Private Medical/Surgical Room | J7: 0110 | M7: 3 | N7: 4600 | O7: =M7*N7 | P7: 6809.85 | Q7: =P7*20% | R7: =O7-P7 | S7: Athena Health Insurance | T7: Athena PPO | V7: Eleanor Brooks, MD | W7: Assigned Department Provider | X7: ADT | Y7: Midnight census | Z7: Posted | AA7: Matched | AB7: Passed | AD7: N/A | AE7: M17.11 | AF7: 21 | AG7: 2026-09-03 16:30 | AH7: Synthetic Athena negotiated charge
A8: IPD-CHG-0002-CGH | B8: HAR-202600002-CGH | C8: CSN-IPD-780002-CGH | D8: Inpatient | E8: Demo Regional Medical Center | F8: Accommodation | G8: 2026-09-03 | H8: RM-PRIV-DAY | I8: Private Medical/Surgical Room | J8: 0110 | M8: 3 | N8: 4600 | O8: =M8*N8 | P8: 6128.87 | Q8: =P8*15% | R8: =O8-P8 | S8: Care Gap Health | T8: Care Gap Value PPO | V8: Eleanor Brooks, MD | W8: Assigned Department Provider | X8: ADT | Y8: Midnight census | Z8: Posted | AA8: Matched | AB8: Passed | AD8: N/A | AE8: M17.11 | AF8: 21 | AG8: 2026-09-03 16:30 | AH8: Synthetic Care Gap charge; 10% below Athena allowed amount
A9: IPD-CHG-0003-ATH | B9: HAR-202600003-ATH | C9: CSN-IPD-780003-ATH | D9: Inpatient | E9: Demo Regional Medical Center | F9: Intensive Care | G9: 2026-09-04 | H9: ICU-DAY | I9: Intensive Care Unit Room | J9: 0200 | M9: 2 | N9: 8200 | O9: =M9*N9 | P9: 10511.44 | Q9: =P9*20% | R9: =O9-P9 | S9: Athena Health Insurance | T9: Athena PPO | V9: Eleanor Brooks, MD | W9: Assigned Department Provider | X9: ADT | Y9: Midnight census | Z9: Posted | AA9: Matched | AB9: Passed | AD9: N/A | AE9: J96.01 | AF9: 21 | AG9: 2026-09-04 16:30 | AH9: Synthetic Athena negotiated charge
A10: IPD-CHG-0003-CGH | B10: HAR-202600003-CGH | C10: CSN-IPD-780003-CGH | D10: Inpatient | E10: Demo Regional Medical Center | F10: Intensive Care | G10: 2026-09-04 | H10: ICU-DAY | I10: Intensive Care Unit Room | J10: 0200 | M10: 2 | N10: 8200 | O10: =M10*N10 | P10: 9460.3 | Q10: =P10*15% | R10: =O10-P10 | S10: Care Gap Health | T10: Care Gap Value PPO | V10: Eleanor Brooks, MD | W10: Assigned Department Provider | X10: ADT | Y10: Midnight census | Z10: Posted | AA10: Matched | AB10: Passed | AD10: N/A | AE10: J96.01 | AF10: 21 | AG10: 2026-09-04 16:30 | AH10: Synthetic Care Gap charge; 10% below Athena allowed amount
A11: IPD-CHG-0004-ATH | B11: HAR-202600004-ATH | C11: CSN-IPD-780004-ATH | D11: Inpatient | E11: Demo Regional Medical Center | F11: Operating Room | G11: 2026-09-05 | H11: OR-MAJOR-1H | I11: Major Operating Room, First Hour | J11: 0360 | M11: 1 | N11: 10250 | O11: =M11*N11 | P11: 6120.76 | Q11: =P11*20% | R11: =O11-P11 | S11: Athena Health Insurance | T11: Athena PPO | V11: Eleanor Brooks, MD | W11: Assigned Department Provider | X11: Perioperative | Y11: Procedure end | Z11: Posted | AA11: Matched | AB11: Passed | AD11: Procedure-specific | AE11: M17.11 | AF11: 21 | AG11: 2026-09-05 16:30 | AH11: Synthetic Athena negotiated charge
A12: IPD-CHG-0004-CGH | B12: HAR-202600004-CGH | C12: CSN-IPD-780004-CGH | D12: Inpatient | E12: Demo Regional Medical Center | F12: Operating Room | G12: 2026-09-05 | H12: OR-MAJOR-1H | I12: Major Operating Room, First Hour | J12: 0360 | M12: 1 | N12: 10250 | O12: =M12*N12 | P12: 5508.68 | Q12: =P12*15% | R12: =O12-P12 | S12: Care Gap Health | T12: Care Gap Value PPO | V12: Eleanor Brooks, MD | W12: Assigned Department Provider | X12: Perioperative | Y12: Procedure end | Z12: Posted | AA12: Matched | AB12: Passed | AD12: Procedure-specific | AE12: M17.11 | AF12: 21 | AG12: 2026-09-05 16:30 | AH12: Synthetic Care Gap charge; 10% below Athena allowed amount
A13: IPD-CHG-0005-ATH | B13: HAR-202600005-ATH | C13: CSN-IPD-780005-ATH | D13: Inpatient | E13: Demo Regional Medical Center | F13: Operating Room | G13: 2026-09-06 | H13: OR-ADD-15 | I13: Operating Room, Additional 15 Minutes | J13: 0360 | M13: 2 | N13: 1280 | O13: =M13*N13 | P13: 1098.08 | Q13: =P13*20% | R13: =O13-P13 | S13: Athena Health Insurance | T13: Athena PPO | V13: Eleanor Brooks, MD | W13: Assigned Department Provider | X13: Perioperative | Y13: Procedure end | Z13: Posted | AA13: Matched | AB13: Passed | AD13: Procedure-specific | AE13: M17.11 | AF13: 21 | AG13: 2026-09-06 16:30 | AH13: Synthetic Athena negotiated charge
A14: IPD-CHG-0005-CGH | B14: HAR-202600005-CGH | C14: CSN-IPD-780005-CGH | D14: Inpatient | E14: Demo Regional Medical Center | F14: Operating Room | G14: 2026-09-06 | H14: OR-ADD-15 | I14: Operating Room, Additional 15 Minutes | J14: 0360 | M14: 2 | N14: 1280 | O14: =M14*N14 | P14: 988.27 | Q14: =P14*15% | R14: =O14-P14 | S14: Care Gap Health | T14: Care Gap Value PPO | V14: Eleanor Brooks, MD | W14: Assigned Department Provider | X14: Perioperative | Y14: Procedure end | Z14: Posted | AA14: Matched | AB14: Passed | AD14: Procedure-specific | AE14: M17.11 | AF14: 21 | AG14: 2026-09-06 16:30 | AH14: Synthetic Care Gap charge; 10% below Athena allowed amount
A15: IPD-CHG-0006-ATH | B15: HAR-202600006-ATH | C15: CSN-IPD-780006-ATH | D15: Inpatient | E15: Demo Regional Medical Center | F15: Recovery Room | G15: 2026-09-07 | H15: PACU-1H | I15: Post-Anesthesia Care, First Hour | J15: 0710 | M15: 1 | N15: 2100 | O15: =M15*N15 | P15: 1019.74 | Q15: =P15*20% | R15: =O15-P15 | S15: Athena Health Insurance | T15: Athena PPO | V15: Eleanor Brooks, MD | W15: Assigned Department Provider | X15: Perioperative | Y15: PACU discharge | Z15: Posted | AA15: Matched | AB15: Passed | AD15: N/A | AE15: Z47.1 | AF15: 21 | AG15: 2026-09-07 16:30 | AH15: Synthetic Athena negotiated charge
A16: IPD-CHG-0006-CGH | B16: HAR-202600006-CGH | C16: CSN-IPD-780006-CGH | D16: Inpatient | E16: Demo Regional Medical Center | F16: Recovery Room | G16: 2026-09-07 | H16: PACU-1H | I16: Post-Anesthesia Care, First Hour | J16: 0710 | M16: 1 | N16: 2100 | O16: =M16*N16 | P16: 917.77 | Q16: =P16*15% | R16: =O16-P16 | S16: Care Gap Health | T16: Care Gap Value PPO | V16: Eleanor Brooks, MD | W16: Assigned Department Provider | X16: Perioperative | Y16: PACU discharge | Z16: Posted | AA16: Matched | AB16: Passed | AD16: N/A | AE16: Z47.1 | AF16: 21 | AG16: 2026-09-07 16:30 | AH16: Synthetic Care Gap charge; 10% below Athena allowed amount
A17: IPD-CHG-0007-ATH | B17: HAR-202600007-ATH | C17: CSN-IPD-780007-ATH | D17: Inpatient | E17: Demo Regional Medical Center | F17: Surgical Supplies | G17: 2026-09-08 | H17: SUP-MAJOR-PACK | I17: Major Surgery Disposable Supply Pack | J17: 0270 | M17: 1 | N17: 4200 | O17: =M17*N17 | P17: 2400.75 | Q17: =P17*20% | R17: =O17-P17 | S17: Athena Health Insurance | T17: Athena PPO | V17: Eleanor Brooks, MD | W17: Assigned Department Provider | X17: Inventory | Y17: Supply issue | Z17: Posted | AA17: Matched | AB17: Passed | AD17: Contract rule | AE17: Z47.1 | AF17: 21 | AG17: 2026-09-08 16:30 | AH17: Synthetic Athena negotiated charge
A18: IPD-CHG-0007-CGH | B18: HAR-202600007-CGH | C18: CSN-IPD-780007-CGH | D18: Inpatient | E18: Demo Regional Medical Center | F18: Surgical Supplies | G18: 2026-09-08 | H18: SUP-MAJOR-PACK | I18: Major Surgery Disposable Supply Pack | J18: 0270 | M18: 1 | N18: 4200 | O18: =M18*N18 | P18: 2160.68 | Q18: =P18*15% | R18: =O18-P18 | S18: Care Gap Health | T18: Care Gap Value PPO | V18: Eleanor Brooks, MD | W18: Assigned Department Provider | X18: Inventory | Y18: Supply issue | Z18: Posted | AA18: Matched | AB18: Passed | AD18: Contract rule | AE18: Z47.1 | AF18: 21 | AG18: 2026-09-08 16:30 | AH18: Synthetic Care Gap charge; 10% below Athena allowed amount
A19: IPD-CHG-0008-ATH | B19: HAR-202600008-ATH | C19: CSN-IPD-780008-ATH | D19: Inpatient | E19: Demo Regional Medical Center | F19: Implants | G19: 2026-09-09 | H19: IMP-KNEE-CEM | I19: Cemented Knee Implant System | J19: 0278 | M19: 1 | N19: 20500 | O19: =M19*N19 | P19: 8773.2 | Q19: =P19*20% | R19: =O19-P19 | S19: Athena Health Insurance | T19: Athena PPO | V19: Eleanor Brooks, MD | W19: Assigned Department Provider | X19: Inventory | Y19: Implant scan | Z19: Posted | AA19: Matched | AB19: Passed | AD19: Contract rule | AE19: M17.11 | AF19: 21 | AG19: 2026-09-09 16:30 | AH19: Synthetic Athena negotiated charge
A20: IPD-CHG-0008-CGH | B20: HAR-202600008-CGH | C20: CSN-IPD-780008-CGH | D20: Inpatient | E20: Demo Regional Medical Center | F20: Implants | G20: 2026-09-09 | H20: IMP-KNEE-CEM | I20: Cemented Knee Implant System | J20: 0278 | M20: 1 | N20: 20500 | O20: =M20*N20 | P20: 7895.88 | Q20: =P20*15% | R20: =O20-P20 | S20: Care Gap Health | T20: Care Gap Value PPO | V20: Eleanor Brooks, MD | W20: Assigned Department Provider | X20: Inventory | Y20: Implant scan | Z20: Posted | AA20: Matched | AB20: Passed | AD20: Contract rule | AE20: M17.11 | AF20: 21 | AG20: 2026-09-09 16:30 | AH20: Synthetic Care Gap charge; 10% below Athena allowed amount
A21: IPD-CHG-0009-ATH | B21: HAR-202600009-ATH | C21: CSN-IPD-780009-ATH | D21: Inpatient | E21: Demo Regional Medical Center | F21: Implants | G21: 2026-09-10 | H21: IMP-SCREW | I21: Orthopedic Fixation Screw | J21: 0278 | K21: C1713 | M21: 1 | N21: 950 | O21: =M21*N21 | P21: 455.67 | Q21: =P21*20% | R21: =O21-P21 | S21: Athena Health Insurance | T21: Athena PPO | V21: Eleanor Brooks, MD | W21: Assigned Department Provider | X21: Inventory | Y21: Implant scan | Z21: Posted | AA21: Matched | AB21: Passed | AD21: Contract rule | AE21: M17.11 | AF21: 21 | AG21: 2026-09-10 16:30 | AH21: Synthetic Athena negotiated charge
A22: IPD-CHG-0009-CGH | B22: HAR-202600009-CGH | C22: CSN-IPD-780009-CGH | D22: Inpatient | E22: Demo Regional Medical Center | F22: Implants | G22: 2026-09-10 | H22: IMP-SCREW | I22: Orthopedic Fixation Screw | J22: 0278 | K22: C1713 | M22: 1 | N22: 950 | O22: =M22*N22 | P22: 410.1 | Q22: =P22*15% | R22: =O22-P22 | S22: Care Gap Health | T22: Care Gap Value PPO | V22: Eleanor Brooks, MD | W22: Assigned Department Provider | X22: Inventory | Y22: Implant scan | Z22: Posted | AA22: Matched | AB22: Passed | AD22: Contract rule | AE22: M17.11 | AF22: 21 | AG22: 2026-09-10 16:30 | AH22: Synthetic Care Gap charge; 10% below Athena allowed amount
A23: IPD-CHG-0010-ATH | B23: HAR-202600010-ATH | C23: CSN-IPD-780010-ATH | D23: Inpatient | E23: Demo Regional Medical Center | F23: Pharmacy | G23: 2026-09-11 | H23: DRUG-CEFA-1G | I23: Cefazolin 1 g Injection | J23: 0250 | K23: J0690 | M23: 3 | N23: 500 | O23: =M23*N23 | P23: 945.6 | Q23: =P23*20% | R23: =O23-P23 | S23: Athena Health Insurance | T23: Athena PPO | V23: Eleanor Brooks, MD | W23: Assigned Department Provider | X23: Pharmacy MAR | Y23: Medication administration | Z23: Posted | AA23: Matched | AB23: Passed | AD23: Dose/frequency | AE23: Z79.2 | AF23: 21 | AG23: 2026-09-11 16:30 | AH23: Synthetic Athena negotiated charge
A24: IPD-CHG-0010-CGH | B24: HAR-202600010-CGH | C24: CSN-IPD-780010-CGH | D24: Inpatient | E24: Demo Regional Medical Center | F24: Pharmacy | G24: 2026-09-11 | H24: DRUG-CEFA-1G | I24: Cefazolin 1 g Injection | J24: 0250 | K24: J0690 | M24: 3 | N24: 500 | O24: =M24*N24 | P24: 851.04 | Q24: =P24*15% | R24: =O24-P24 | S24: Care Gap Health | T24: Care Gap Value PPO | V24: Eleanor Brooks, MD | W24: Assigned Department Provider | X24: Pharmacy MAR | Y24: Medication administration | Z24: Posted | AA24: Matched | AB24: Passed | AD24: Dose/frequency | AE24: Z79.2 | AF24: 21 | AG24: 2026-09-11 16:30 | AH24: Synthetic Care Gap charge; 10% below Athena allowed amount
A25: IPD-CHG-0011-ATH | B25: HAR-202600011-ATH | C25: CSN-IPD-780011-ATH | D25: Inpatient | E25: Demo Regional Medical Center | F25: Pharmacy | G25: 2026-09-12 | H25: DRUG-VANC-500 | I25: Vancomycin 500 mg Injection | J25: 0250 | K25: J3370 | M25: 2 | N25: 680 | O25: =M25*N25 | P25: 661.14 | Q25: =P25*20% | R25: =O25-P25 | S25: Athena Health Insurance | T25: Athena PPO | V25: Eleanor Brooks, MD | W25: Assigned Department Provider | X25: Pharmacy MAR | Y25: Medication administration | Z25: Posted | AA25: Matched | AB25: Passed | AD25: Dose/frequency | AE25: Z79.2 | AF25: 21 | AG25: 2026-09-12 16:30 | AH25: Synthetic Athena negotiated charge
A26: IPD-CHG-0011-CGH | B26: HAR-202600011-CGH | C26: CSN-IPD-780011-CGH | D26: Inpatient | E26: Demo Regional Medical Center | F26: Pharmacy | G26: 2026-09-12 | H26: DRUG-VANC-500 | I26: Vancomycin 500 mg Injection | J26: 0250 | K26: J3370 | M26: 2 | N26: 680 | O26: =M26*N26 | P26: 595.03 | Q26: =P26*15% | R26: =O26-P26 | S26: Care Gap Health | T26: Care Gap Value PPO | V26: Eleanor Brooks, MD | W26: Assigned Department Provider | X26: Pharmacy MAR | Y26: Medication administration | Z26: Posted | AA26: Matched | AB26: Passed | AD26: Dose/frequency | AE26: Z79.2 | AF26: 21 | AG26: 2026-09-12 16:30 | AH26: Synthetic Care Gap charge; 10% below Athena allowed amount
A27: IPD-CHG-0012-ATH | B27: HAR-202600012-ATH | C27: CSN-IPD-780012-ATH | D27: Inpatient | E27: Demo Regional Medical Center | F27: Pharmacy | G27: 2026-09-13 | H27: IV-NS-1L | I27: Normal Saline 1,000 mL | J27: 0258 | K27: J7030 | M27: 3 | N27: 90 | O27: =M27*N27 | P27: 135.93 | Q27: =P27*20% | R27: =O27-P27 | S27: Athena Health Insurance | T27: Athena PPO | V27: Eleanor Brooks, MD | W27: Assigned Department Provider | X27: Pharmacy MAR | Y27: Medication administration | Z27: Posted | AA27: Matched | AB27: Passed | AD27: N/A | AE27: E86.0 | AF27: 21 | AG27: 2026-09-13 16:30 | AH27: Synthetic Athena negotiated charge
A28: IPD-CHG-0012-CGH | B28: HAR-202600012-CGH | C28: CSN-IPD-780012-CGH | D28: Inpatient | E28: Demo Regional Medical Center | F28: Pharmacy | G28: 2026-09-13 | H28: IV-NS-1L | I28: Normal Saline 1,000 mL | J28: 0258 | K28: J7030 | M28: 3 | N28: 90 | O28: =M28*N28 | P28: 122.34 | Q28: =P28*15% | R28: =O28-P28 | S28: Care Gap Health | T28: Care Gap Value PPO | V28: Eleanor Brooks, MD | W28: Assigned Department Provider | X28: Pharmacy MAR | Y28: Medication administration | Z28: Posted | AA28: Matched | AB28: Passed | AD28: N/A | AE28: E86.0 | AF28: 21 | AG28: 2026-09-13 16:30 | AH28: Synthetic Care Gap charge; 10% below Athena allowed amount
A29: IPD-CHG-0013-ATH | B29: HAR-202600013-ATH | C29: CSN-IPD-780013-ATH | D29: Inpatient | E29: Demo Regional Medical Center | F29: Laboratory | G29: 2026-09-14 | H29: LAB-CBC | I29: Complete Blood Count with Differential | J29: 0300 | K29: 85025 | M29: 1 | N29: 155 | O29: =M29*N29 | P29: 105.52 | Q29: =P29*20% | R29: =O29-P29 | S29: Athena Health Insurance | T29: Athena PPO | V29: Eleanor Brooks, MD | W29: Assigned Department Provider | X29: LIS | Y29: Final result | Z29: Posted | AA29: Matched | AB29: Passed | AD29: Diagnosis/LCD | AE29: D64.9 | AF29: 21 | AG29: 2026-09-14 16:30 | AH29: Synthetic Athena negotiated charge
A30: IPD-CHG-0013-CGH | B30: HAR-202600013-CGH | C30: CSN-IPD-780013-CGH | D30: Inpatient | E30: Demo Regional Medical Center | F30: Laboratory | G30: 2026-09-14 | H30: LAB-CBC | I30: Complete Blood Count with Differential | J30: 0300 | K30: 85025 | M30: 1 | N30: 155 | O30: =M30*N30 | P30: 94.97 | Q30: =P30*15% | R30: =O30-P30 | S30: Care Gap Health | T30: Care Gap Value PPO | V30: Eleanor Brooks, MD | W30: Assigned Department Provider | X30: LIS | Y30: Final result | Z30: Posted | AA30: Matched | AB30: Passed | AD30: Diagnosis/LCD | AE30: D64.9 | AF30: 21 | AG30: 2026-09-14 16:30 | AH30: Synthetic Care Gap charge; 10% below Athena allowed amount
A31: IPD-CHG-0014-ATH | B31: HAR-202600014-ATH | C31: CSN-IPD-780014-ATH | D31: Inpatient | E31: Demo Regional Medical Center | F31: Laboratory | G31: 2026-09-15 | H31: LAB-CMP | I31: Comprehensive Metabolic Panel | J31: 0301 | K31: 80053 | M31: 1 | N31: 245 | O31: =M31*N31 | P31: 158.67 | Q31: =P31*20% | R31: =O31-P31 | S31: Athena Health Insurance | T31: Athena PPO | V31: Eleanor Brooks, MD | W31: Assigned Department Provider | X31: LIS | Y31: Final result | Z31: Posted | AA31: Matched | AB31: Passed | AD31: Diagnosis/LCD | AE31: E11.9 | AF31: 21 | AG31: 2026-09-15 16:30 | AH31: Synthetic Athena negotiated charge
A32: IPD-CHG-0014-CGH | B32: HAR-202600014-CGH | C32: CSN-IPD-780014-CGH | D32: Inpatient | E32: Demo Regional Medical Center | F32: Laboratory | G32: 2026-09-15 | H32: LAB-CMP | I32: Comprehensive Metabolic Panel | J32: 0301 | K32: 80053 | M32: 1 | N32: 245 | O32: =M32*N32 | P32: 142.8 | Q32: =P32*15% | R32: =O32-P32 | S32: Care Gap Health | T32: Care Gap Value PPO | V32: Eleanor Brooks, MD | W32: Assigned Department Provider | X32: LIS | Y32: Final result | Z32: Posted | AA32: Matched | AB32: Passed | AD32: Diagnosis/LCD | AE32: E11.9 | AF32: 21 | AG32: 2026-09-15 16:30 | AH32: Synthetic Care Gap charge; 10% below Athena allowed amount
A33: IPD-CHG-0015-ATH | B33: HAR-202600015-ATH | C33: CSN-IPD-780015-ATH | D33: Inpatient | E33: Demo Regional Medical Center | F33: Laboratory | G33: 2026-09-16 | H33: LAB-PTINR | I33: Prothrombin Time / INR | J33: 0305 | K33: 85610 | M33: 1 | N33: 125 | O33: =M33*N33 | P33: 58.49 | Q33: =P33*20% | R33: =O33-P33 | S33: Athena Health Insurance | T33: Athena PPO | V33: Eleanor Brooks, MD | W33: Assigned Department Provider | X33: LIS | Y33: Final result | Z33: Posted | AA33: Matched | AB33: Passed | AD33: Diagnosis/LCD | AE33: Z79.01 | AF33: 21 | AG33: 2026-09-16 16:30 | AH33: Synthetic Athena negotiated charge
A34: IPD-CHG-0015-CGH | B34: HAR-202600015-CGH | C34: CSN-IPD-780015-CGH | D34: Inpatient | E34: Demo Regional Medical Center | F34: Laboratory | G34: 2026-09-16 | H34: LAB-PTINR | I34: Prothrombin Time / INR | J34: 0305 | K34: 85610 | M34: 1 | N34: 125 | O34: =M34*N34 | P34: 52.64 | Q34: =P34*15% | R34: =O34-P34 | S34: Care Gap Health | T34: Care Gap Value PPO | V34: Eleanor Brooks, MD | W34: Assigned Department Provider | X34: LIS | Y34: Final result | Z34: Posted | AA34: Matched | AB34: Passed | AD34: Diagnosis/LCD | AE34: Z79.01 | AF34: 21 | AG34: 2026-09-16 16:30 | AH34: Synthetic Care Gap charge; 10% below Athena allowed amount
A35: IPD-CHG-0016-ATH | B35: HAR-202600016-ATH | C35: CSN-IPD-780016-ATH | D35: Inpatient | E35: Demo Regional Medical Center | F35: Radiology | G35: 2026-09-17 | H35: RAD-CHEST-2V | I35: Chest X-ray, 2 Views | J35: 0320 | K35: 71046 | M35: 1 | N35: 185 | O35: =M35*N35 | P35: 101.16 | Q35: =P35*20% | R35: =O35-P35 | S35: Athena Health Insurance | T35: Athena PPO | V35: Eleanor Brooks, MD | W35: Assigned Department Provider | X35: RIS/PACS | Y35: Exam completed | Z35: Posted | AA35: Matched | AB35: Passed | AD35: Diagnosis/LCD | AE35: R06.02 | AF35: 21 | AG35: 2026-09-17 16:30 | AH35: Synthetic Athena negotiated charge
A36: IPD-CHG-0016-CGH | B36: HAR-202600016-CGH | C36: CSN-IPD-780016-CGH | D36: Inpatient | E36: Demo Regional Medical Center | F36: Radiology | G36: 2026-09-17 | H36: RAD-CHEST-2V | I36: Chest X-ray, 2 Views | J36: 0320 | K36: 71046 | M36: 1 | N36: 185 | O36: =M36*N36 | P36: 91.04 | Q36: =P36*15% | R36: =O36-P36 | S36: Care Gap Health | T36: Care Gap Value PPO | V36: Eleanor Brooks, MD | W36: Assigned Department Provider | X36: RIS/PACS | Y36: Exam completed | Z36: Posted | AA36: Matched | AB36: Passed | AD36: Diagnosis/LCD | AE36: R06.02 | AF36: 21 | AG36: 2026-09-17 16:30 | AH36: Synthetic Care Gap charge; 10% below Athena allowed amount
A37: IPD-CHG-0017-ATH | B37: HAR-202600017-ATH | C37: CSN-IPD-780017-ATH | D37: Inpatient | E37: Demo Regional Medical Center | F37: Radiology | G37: 2026-09-18 | H37: RAD-KNEE-2V | I37: Knee X-ray, 1-2 Views | J37: 0320 | K37: 73560 | M37: 1 | N37: 410 | O37: =M37*N37 | P37: 206.38 | Q37: =P37*20% | R37: =O37-P37 | S37: Athena Health Insurance | T37: Athena PPO | V37: Eleanor Brooks, MD | W37: Assigned Department Provider | X37: RIS/PACS | Y37: Exam completed | Z37: Posted | AA37: Matched | AB37: Passed | AD37: Diagnosis/LCD | AE37: M25.561 | AF37: 21 | AG37: 2026-09-18 16:30 | AH37: Synthetic Athena negotiated charge
A38: IPD-CHG-0017-CGH | B38: HAR-202600017-CGH | C38: CSN-IPD-780017-CGH | D38: Inpatient | E38: Demo Regional Medical Center | F38: Radiology | G38: 2026-09-18 | H38: RAD-KNEE-2V | I38: Knee X-ray, 1-2 Views | J38: 0320 | K38: 73560 | M38: 1 | N38: 410 | O38: =M38*N38 | P38: 185.74 | Q38: =P38*15% | R38: =O38-P38 | S38: Care Gap Health | T38: Care Gap Value PPO | V38: Eleanor Brooks, MD | W38: Assigned Department Provider | X38: RIS/PACS | Y38: Exam completed | Z38: Posted | AA38: Matched | AB38: Passed | AD38: Diagnosis/LCD | AE38: M25.561 | AF38: 21 | AG38: 2026-09-18 16:30 | AH38: Synthetic Care Gap charge; 10% below Athena allowed amount
A39: IPD-CHG-0018-ATH | B39: HAR-202600018-ATH | C39: CSN-IPD-780018-ATH | D39: Inpatient | E39: Demo Regional Medical Center | F39: Cardiology | G39: 2026-09-19 | H39: CARD-ECG12 | I39: 12-Lead ECG | J39: 0730 | K39: 93005 | M39: 1 | N39: 190 | O39: =M39*N39 | P39: 92.07 | Q39: =P39*20% | R39: =O39-P39 | S39: Athena Health Insurance | T39: Athena PPO | V39: Eleanor Brooks, MD | W39: Assigned Department Provider | X39: Cardiology | Y39: Test completed | Z39: Posted | AA39: Matched | AB39: Passed | AD39: Diagnosis/LCD | AE39: R07.9 | AF39: 21 | AG39: 2026-09-19 16:30 | AH39: Synthetic Athena negotiated charge
A40: IPD-CHG-0018-CGH | B40: HAR-202600018-CGH | C40: CSN-IPD-780018-CGH | D40: Inpatient | E40: Demo Regional Medical Center | F40: Cardiology | G40: 2026-09-19 | H40: CARD-ECG12 | I40: 12-Lead ECG | J40: 0730 | K40: 93005 | M40: 1 | N40: 190 | O40: =M40*N40 | P40: 82.86 | Q40: =P40*15% | R40: =O40-P40 | S40: Care Gap Health | T40: Care Gap Value PPO | V40: Eleanor Brooks, MD | W40: Assigned Department Provider | X40: Cardiology | Y40: Test completed | Z40: Posted | AA40: Matched | AB40: Passed | AD40: Diagnosis/LCD | AE40: R07.9 | AF40: 21 | AG40: 2026-09-19 16:30 | AH40: Synthetic Care Gap charge; 10% below Athena allowed amount
A41: IPD-CHG-0019-ATH | B41: HAR-202600019-ATH | C41: CSN-IPD-780019-ATH | D41: Inpatient | E41: Demo Regional Medical Center | F41: Respiratory | G41: 2026-09-20 | H41: RESP-NEB | I41: Nebulizer Treatment | J41: 0410 | K41: 94640 | M41: 1 | N41: 245 | O41: =M41*N41 | P41: 159.02 | Q41: =P41*20% | R41: =O41-P41 | S41: Athena Health Insurance | T41: Athena PPO | V41: Eleanor Brooks, MD | W41: Assigned Department Provider | X41: Respiratory | Y41: Treatment completed | Z41: Posted | AA41: Matched | AB41: Passed | AD41: Diagnosis/LCD | AE41: J45.901 | AF41: 21 | AG41: 2026-09-20 16:30 | AH41: Synthetic Athena negotiated charge
A42: IPD-CHG-0019-CGH | B42: HAR-202600019-CGH | C42: CSN-IPD-780019-CGH | D42: Inpatient | E42: Demo Regional Medical Center | F42: Respiratory | G42: 2026-09-20 | H42: RESP-NEB | I42: Nebulizer Treatment | J42: 0410 | K42: 94640 | M42: 1 | N42: 245 | O42: =M42*N42 | P42: 143.12 | Q42: =P42*15% | R42: =O42-P42 | S42: Care Gap Health | T42: Care Gap Value PPO | V42: Eleanor Brooks, MD | W42: Assigned Department Provider | X42: Respiratory | Y42: Treatment completed | Z42: Posted | AA42: Matched | AB42: Passed | AD42: Diagnosis/LCD | AE42: J45.901 | AF42: 21 | AG42: 2026-09-20 16:30 | AH42: Synthetic Care Gap charge; 10% below Athena allowed amount
A43: IPD-CHG-0020-ATH | B43: HAR-202600020-ATH | C43: CSN-IPD-780020-ATH | D43: Inpatient | E43: Demo Regional Medical Center | F43: Physical Therapy | G43: 2026-09-21 | H43: PT-EVAL-LOW | I43: Physical Therapy Evaluation, Low Complexity | J43: 0420 | K43: 97161 | M43: 1 | N43: 710 | O43: =M43*N43 | P43: 319.97 | Q43: =P43*20% | R43: =O43-P43 | S43: Athena Health Insurance | T43: Athena PPO | U43: AUTH-700020 | V43: Eleanor Brooks, MD | W43: Assigned Department Provider | X43: Therapy | Y43: Note signed | Z43: Posted | AA43: Matched | AB43: Passed | AD43: Plan benefits | AE43: R26.2 | AF43: 21 | AG43: 2026-09-21 16:30 | AH43: Synthetic Athena negotiated charge
A44: IPD-CHG-0020-CGH | B44: HAR-202600020-CGH | C44: CSN-IPD-780020-CGH | D44: Inpatient | E44: Demo Regional Medical Center | F44: Physical Therapy | G44: 2026-09-21 | H44: PT-EVAL-LOW | I44: Physical Therapy Evaluation, Low Complexity | J44: 0420 | K44: 97161 | M44: 1 | N44: 710 | O44: =M44*N44 | P44: 287.97 | Q44: =P44*15% | R44: =O44-P44 | S44: Care Gap Health | T44: Care Gap Value PPO | U44: AUTH-700020 | V44: Eleanor Brooks, MD | W44: Assigned Department Provider | X44: Therapy | Y44: Note signed | Z44: Posted | AA44: Matched | AB44: Passed | AD44: Plan benefits | AE44: R26.2 | AF44: 21 | AG44: 2026-09-21 16:30 | AH44: Synthetic Care Gap charge; 10% below Athena allowed amount
A45: IPD-CHG-0021-ATH | B45: HAR-202600021-ATH | C45: CSN-IPD-780021-ATH | D45: Inpatient | E45: Demo Regional Medical Center | F45: Physical Therapy | G45: 2026-09-22 | H45: PT-THEREX-15 | I45: Therapeutic Exercise, 15 Minutes | J45: 0420 | K45: 97110 | M45: 6 | N45: 305 | O45: =M45*N45 | P45: 821.7 | Q45: =P45*20% | R45: =O45-P45 | S45: Athena Health Insurance | T45: Athena PPO | V45: Eleanor Brooks, MD | W45: Assigned Department Provider | X45: Therapy | Y45: Note signed | Z45: Posted | AA45: Matched | AB45: Passed | AD45: Timed units | AE45: M62.81 | AF45: 21 | AG45: 2026-09-22 16:30 | AH45: Synthetic Athena negotiated charge
A46: IPD-CHG-0021-CGH | B46: HAR-202600021-CGH | C46: CSN-IPD-780021-CGH | D46: Inpatient | E46: Demo Regional Medical Center | F46: Physical Therapy | G46: 2026-09-22 | H46: PT-THEREX-15 | I46: Therapeutic Exercise, 15 Minutes | J46: 0420 | K46: 97110 | M46: 6 | N46: 305 | O46: =M46*N46 | P46: 739.53 | Q46: =P46*15% | R46: =O46-P46 | S46: Care Gap Health | T46: Care Gap Value PPO | V46: Eleanor Brooks, MD | W46: Assigned Department Provider | X46: Therapy | Y46: Note signed | Z46: Posted | AA46: Matched | AB46: Passed | AD46: Timed units | AE46: M62.81 | AF46: 21 | AG46: 2026-09-22 16:30 | AH46: Synthetic Care Gap charge; 10% below Athena allowed amount
A47: IPD-CHG-0022-ATH | B47: HAR-202600022-ATH | C47: CSN-IPD-780022-ATH | D47: Inpatient | E47: Demo Regional Medical Center | F47: Occupational Therapy | G47: 2026-09-23 | H47: OT-EVAL-LOW | I47: Occupational Therapy Evaluation, Low Complexity | J47: 0430 | K47: 97165 | M47: 1 | N47: 725 | O47: =M47*N47 | P47: 488.83 | Q47: =P47*20% | R47: =O47-P47 | S47: Athena Health Insurance | T47: Athena PPO | U47: AUTH-700022 | V47: Eleanor Brooks, MD | W47: Assigned Department Provider | X47: Therapy | Y47: Note signed | Z47: Posted | AA47: Matched | AB47: Passed | AD47: Plan benefits | AE47: Z74.09 | AF47: 21 | AG47: 2026-09-23 16:30 | AH47: Synthetic Athena negotiated charge
A48: IPD-CHG-0022-CGH | B48: HAR-202600022-CGH | C48: CSN-IPD-780022-CGH | D48: Inpatient | E48: Demo Regional Medical Center | F48: Occupational Therapy | G48: 2026-09-23 | H48: OT-EVAL-LOW | I48: Occupational Therapy Evaluation, Low Complexity | J48: 0430 | K48: 97165 | M48: 1 | N48: 725 | O48: =M48*N48 | P48: 439.95 | Q48: =P48*15% | R48: =O48-P48 | S48: Care Gap Health | T48: Care Gap Value PPO | U48: AUTH-700022 | V48: Eleanor Brooks, MD | W48: Assigned Department Provider | X48: Therapy | Y48: Note signed | Z48: Posted | AA48: Matched | AB48: Passed | AD48: Plan benefits | AE48: Z74.09 | AF48: 21 | AG48: 2026-09-23 16:30 | AH48: Synthetic Care Gap charge; 10% below Athena allowed amount
A49: IPD-CHG-0023-ATH | B49: HAR-202600023-ATH | C49: CSN-IPD-780023-ATH | D49: Inpatient | E49: Demo Regional Medical Center | F49: Nutrition | G49: 2026-09-24 | H49: NUTR-ASSESS | I49: Inpatient Nutrition Assessment | J49: 0942 | K49: 97802 | M49: 1 | N49: 325 | O49: =M49*N49 | P49: 195.36 | Q49: =P49*20% | R49: =O49-P49 | S49: Athena Health Insurance | T49: Athena PPO | V49: Eleanor Brooks, MD | W49: Assigned Department Provider | X49: Dietary | Y49: Note signed | Z49: Posted | AA49: Matched | AB49: Review | AC49: WQ-NUT-04 | AD49: N/A | AE49: E44.1 | AF49: 21 | AG49: 2026-09-24 16:30 | AH49: Synthetic Athena negotiated charge
A50: IPD-CHG-0023-CGH | B50: HAR-202600023-CGH | C50: CSN-IPD-780023-CGH | D50: Inpatient | E50: Demo Regional Medical Center | F50: Nutrition | G50: 2026-09-24 | H50: NUTR-ASSESS | I50: Inpatient Nutrition Assessment | J50: 0942 | K50: 97802 | M50: 1 | N50: 325 | O50: =M50*N50 | P50: 175.82 | Q50: =P50*15% | R50: =O50-P50 | S50: Care Gap Health | T50: Care Gap Value PPO | V50: Eleanor Brooks, MD | W50: Assigned Department Provider | X50: Dietary | Y50: Note signed | Z50: Posted | AA50: Matched | AB50: Review | AC50: WQ-NUT-04 | AD50: N/A | AE50: E44.1 | AF50: 21 | AG50: 2026-09-24 16:30 | AH50: Synthetic Care Gap charge; 10% below Athena allowed amount
A51: IPD-CHG-0024-ATH | B51: HAR-202600024-ATH | C51: CSN-IPD-780024-ATH | D51: Inpatient | E51: Demo Regional Medical Center | F51: Dialysis | G51: 2026-09-25 | H51: DIALYSIS-IP | I51: Inpatient Hemodialysis Treatment | J51: 0801 | K51: 90935 | M51: 1 | N51: 1600 | O51: =M51*N51 | P51: 1059.42 | Q51: =P51*20% | R51: =O51-P51 | S51: Athena Health Insurance | T51: Athena PPO | V51: Eleanor Brooks, MD | W51: Assigned Department Provider | X51: Dialysis | Y51: Treatment completed | Z51: Posted | AA51: Matched | AB51: Passed | AD51: Diagnosis/LCD | AE51: N18.6 | AF51: 21 | AG51: 2026-09-25 16:30 | AH51: Synthetic Athena negotiated charge
A52: IPD-CHG-0024-CGH | B52: HAR-202600024-CGH | C52: CSN-IPD-780024-CGH | D52: Inpatient | E52: Demo Regional Medical Center | F52: Dialysis | G52: 2026-09-25 | H52: DIALYSIS-IP | I52: Inpatient Hemodialysis Treatment | J52: 0801 | K52: 90935 | M52: 1 | N52: 1600 | O52: =M52*N52 | P52: 953.48 | Q52: =P52*15% | R52: =O52-P52 | S52: Care Gap Health | T52: Care Gap Value PPO | V52: Eleanor Brooks, MD | W52: Assigned Department Provider | X52: Dialysis | Y52: Treatment completed | Z52: Posted | AA52: Matched | AB52: Passed | AD52: Diagnosis/LCD | AE52: N18.6 | AF52: 21 | AG52: 2026-09-25 16:30 | AH52: Synthetic Care Gap charge; 10% below Athena allowed amount
A53: IPD-CHG-0025-ATH | B53: HAR-202600025-ATH | C53: CSN-IPD-780025-ATH | D53: Inpatient | E53: Demo Regional Medical Center | F53: Accommodation | G53: 2026-09-01 | H53: RM-SEMI-DAY | I53: Semiprivate Medical/Surgical Room | J53: 0120 | M53: 4 | N53: 3500 | O53: =M53*N53 | P53: 8132.16 | Q53: =P53*20% | R53: =O53-P53 | S53: Athena Health Insurance | T53: Athena PPO | V53: Eleanor Brooks, MD | W53: Assigned Department Provider | X53: ADT | Y53: Midnight census | Z53: Posted | AA53: Matched | AB53: Passed | AD53: N/A | AE53: M17.11 | AF53: 21 | AG53: 2026-09-01 16:30 | AH53: Synthetic Athena negotiated charge
A54: IPD-CHG-0025-CGH | B54: HAR-202600025-CGH | C54: CSN-IPD-780025-CGH | D54: Inpatient | E54: Demo Regional Medical Center | F54: Accommodation | G54: 2026-09-01 | H54: RM-SEMI-DAY | I54: Semiprivate Medical/Surgical Room | J54: 0120 | M54: 4 | N54: 3500 | O54: =M54*N54 | P54: 7318.94 | Q54: =P54*15% | R54: =O54-P54 | S54: Care Gap Health | T54: Care Gap Value PPO | V54: Eleanor Brooks, MD | W54: Assigned Department Provider | X54: ADT | Y54: Midnight census | Z54: Posted | AA54: Matched | AB54: Passed | AD54: N/A | AE54: M17.11 | AF54: 21 | AG54: 2026-09-01 16:30 | AH54: Synthetic Care Gap charge; 10% below Athena allowed amount
A55: IPD-CHG-0026-ATH | B55: HAR-202600026-ATH | C55: CSN-IPD-780026-ATH | D55: Inpatient | E55: Demo Regional Medical Center | F55: Accommodation | G55: 2026-09-02 | H55: RM-PRIV-DAY | I55: Private Medical/Surgical Room | J55: 0110 | M55: 4 | N55: 4600 | O55: =M55*N55 | P55: 8162.98 | Q55: =P55*20% | R55: =O55-P55 | S55: Athena Health Insurance | T55: Athena PPO | V55: Eleanor Brooks, MD | W55: Assigned Department Provider | X55: ADT | Y55: Midnight census | Z55: Posted | AA55: Matched | AB55: Passed | AD55: N/A | AE55: M17.11 | AF55: 21 | AG55: 2026-09-02 16:30 | AH55: Synthetic Athena negotiated charge
A56: IPD-CHG-0026-CGH | B56: HAR-202600026-CGH | C56: CSN-IPD-780026-CGH | D56: Inpatient | E56: Demo Regional Medical Center | F56: Accommodation | G56: 2026-09-02 | H56: RM-PRIV-DAY | I56: Private Medical/Surgical Room | J56: 0110 | M56: 4 | N56: 4600 | O56: =M56*N56 | P56: 7346.68 | Q56: =P56*15% | R56: =O56-P56 | S56: Care Gap Health | T56: Care Gap Value PPO | V56: Eleanor Brooks, MD | W56: Assigned Department Provider | X56: ADT | Y56: Midnight census | Z56: Posted | AA56: Matched | AB56: Passed | AD56: N/A | AE56: M17.11 | AF56: 21 | AG56: 2026-09-02 16:30 | AH56: Synthetic Care Gap charge; 10% below Athena allowed amount
A57: IPD-CHG-0027-ATH | B57: HAR-202600027-ATH | C57: CSN-IPD-780027-ATH | D57: Inpatient | E57: Demo Regional Medical Center | F57: Intensive Care | G57: 2026-09-03 | H57: ICU-DAY | I57: Intensive Care Unit Room | J57: 0200 | M57: 3 | N57: 8200 | O57: =M57*N57 | P57: 16453.01 | Q57: =P57*20% | R57: =O57-P57 | S57: Athena Health Insurance | T57: Athena PPO | V57: Eleanor Brooks, MD | W57: Assigned Department Provider | X57: ADT | Y57: Midnight census | Z57: Posted | AA57: Matched | AB57: Passed | AD57: N/A | AE57: J96.01 | AF57: 21 | AG57: 2026-09-03 16:30 | AH57: Synthetic Athena negotiated charge
A58: IPD-CHG-0027-CGH | B58: HAR-202600027-CGH | C58: CSN-IPD-780027-CGH | D58: Inpatient | E58: Demo Regional Medical Center | F58: Intensive Care | G58: 2026-09-03 | H58: ICU-DAY | I58: Intensive Care Unit Room | J58: 0200 | M58: 3 | N58: 8200 | O58: =M58*N58 | P58: 14807.71 | Q58: =P58*15% | R58: =O58-P58 | S58: Care Gap Health | T58: Care Gap Value PPO | V58: Eleanor Brooks, MD | W58: Assigned Department Provider | X58: ADT | Y58: Midnight census | Z58: Posted | AA58: Matched | AB58: Passed | AD58: N/A | AE58: J96.01 | AF58: 21 | AG58: 2026-09-03 16:30 | AH58: Synthetic Care Gap charge; 10% below Athena allowed amount
A59: IPD-CHG-0028-ATH | B59: HAR-202600028-ATH | C59: CSN-IPD-780028-ATH | D59: Inpatient | E59: Demo Regional Medical Center | F59: Operating Room | G59: 2026-09-04 | H59: OR-MAJOR-1H | I59: Major Operating Room, First Hour | J59: 0360 | M59: 3 | N59: 10250 | O59: =M59*N59 | P59: 18241.07 | Q59: =P59*20% | R59: =O59-P59 | S59: Athena Health Insurance | T59: Athena PPO | V59: Eleanor Brooks, MD | W59: Assigned Department Provider | X59: Perioperative | Y59: Procedure end | Z59: Posted | AA59: Matched | AB59: Passed | AD59: Procedure-specific | AE59: M17.11 | AF59: 21 | AG59: 2026-09-04 16:30 | AH59: Synthetic Athena negotiated charge
A60: IPD-CHG-0028-CGH | B60: HAR-202600028-CGH | C60: CSN-IPD-780028-CGH | D60: Inpatient | E60: Demo Regional Medical Center | F60: Operating Room | G60: 2026-09-04 | H60: OR-MAJOR-1H | I60: Major Operating Room, First Hour | J60: 0360 | M60: 3 | N60: 10250 | O60: =M60*N60 | P60: 16416.96 | Q60: =P60*15% | R60: =O60-P60 | S60: Care Gap Health | T60: Care Gap Value PPO | V60: Eleanor Brooks, MD | W60: Assigned Department Provider | X60: Perioperative | Y60: Procedure end | Z60: Posted | AA60: Matched | AB60: Passed | AD60: Procedure-specific | AE60: M17.11 | AF60: 21 | AG60: 2026-09-04 16:30 | AH60: Synthetic Care Gap charge; 10% below Athena allowed amount
A61: IPD-CHG-0029-ATH | B61: HAR-202600029-ATH | C61: CSN-IPD-780029-ATH | D61: Inpatient | E61: Demo Regional Medical Center | F61: Operating Room | G61: 2026-09-05 | H61: OR-ADD-15 | I61: Operating Room, Additional 15 Minutes | J61: 0360 | M61: 2 | N61: 1280 | O61: =M61*N61 | P61: 1110.39 | Q61: =P61*20% | R61: =O61-P61 | S61: Athena Health Insurance | T61: Athena PPO | V61: Eleanor Brooks, MD | W61: Assigned Department Provider | X61: Perioperative | Y61: Procedure end | Z61: Hold | AA61: Exception | AB61: Review | AC61: WQ-OPE-02 | AD61: Procedure-specific | AE61: M17.11 | AF61: 21 | AG61: 2026-09-05 16:30 | AH61: Synthetic Athena negotiated charge
A62: IPD-CHG-0029-CGH | B62: HAR-202600029-CGH | C62: CSN-IPD-780029-CGH | D62: Inpatient | E62: Demo Regional Medical Center | F62: Operating Room | G62: 2026-09-05 | H62: OR-ADD-15 | I62: Operating Room, Additional 15 Minutes | J62: 0360 | M62: 2 | N62: 1280 | O62: =M62*N62 | P62: 999.35 | Q62: =P62*15% | R62: =O62-P62 | S62: Care Gap Health | T62: Care Gap Value PPO | V62: Eleanor Brooks, MD | W62: Assigned Department Provider | X62: Perioperative | Y62: Procedure end | Z62: Hold | AA62: Exception | AB62: Review | AC62: WQ-OPE-02 | AD62: Procedure-specific | AE62: M17.11 | AF62: 21 | AG62: 2026-09-05 16:30 | AH62: Synthetic Care Gap charge; 10% below Athena allowed amount
A63: IPD-CHG-0030-ATH | B63: HAR-202600030-ATH | C63: CSN-IPD-780030-ATH | D63: Inpatient | E63: Demo Regional Medical Center | F63: Recovery Room | G63: 2026-09-06 | H63: PACU-1H | I63: Post-Anesthesia Care, First Hour | J63: 0710 | M63: 1 | N63: 2100 | O63: =M63*N63 | P63: 1025.58 | Q63: =P63*20% | R63: =O63-P63 | S63: Athena Health Insurance | T63: Athena PPO | V63: Eleanor Brooks, MD | W63: Assigned Department Provider | X63: Perioperative | Y63: PACU discharge | Z63: Posted | AA63: Matched | AB63: Passed | AD63: N/A | AE63: Z47.1 | AF63: 21 | AG63: 2026-09-06 16:30 | AH63: Synthetic Athena negotiated charge
A64: IPD-CHG-0030-CGH | B64: HAR-202600030-CGH | C64: CSN-IPD-780030-CGH | D64: Inpatient | E64: Demo Regional Medical Center | F64: Recovery Room | G64: 2026-09-06 | H64: PACU-1H | I64: Post-Anesthesia Care, First Hour | J64: 0710 | M64: 1 | N64: 2100 | O64: =M64*N64 | P64: 923.02 | Q64: =P64*15% | R64: =O64-P64 | S64: Care Gap Health | T64: Care Gap Value PPO | V64: Eleanor Brooks, MD | W64: Assigned Department Provider | X64: Perioperative | Y64: PACU discharge | Z64: Posted | AA64: Matched | AB64: Passed | AD64: N/A | AE64: Z47.1 | AF64: 21 | AG64: 2026-09-06 16:30 | AH64: Synthetic Care Gap charge; 10% below Athena allowed amount
A65: IPD-CHG-0031-ATH | B65: HAR-202600031-ATH | C65: CSN-IPD-780031-ATH | D65: Inpatient | E65: Demo Regional Medical Center | F65: Surgical Supplies | G65: 2026-09-07 | H65: SUP-MAJOR-PACK | I65: Major Surgery Disposable Supply Pack | J65: 0270 | M65: 1 | N65: 4200 | O65: =M65*N65 | P65: 2128.63 | Q65: =P65*20% | R65: =O65-P65 | S65: Athena Health Insurance | T65: Athena PPO | V65: Eleanor Brooks, MD | W65: Assigned Department Provider | X65: Inventory | Y65: Supply issue | Z65: Posted | AA65: Matched | AB65: Passed | AD65: Contract rule | AE65: Z47.1 | AF65: 21 | AG65: 2026-09-07 16:30 | AH65: Synthetic Athena negotiated charge
A66: IPD-CHG-0031-CGH | B66: HAR-202600031-CGH | C66: CSN-IPD-780031-CGH | D66: Inpatient | E66: Demo Regional Medical Center | F66: Surgical Supplies | G66: 2026-09-07 | H66: SUP-MAJOR-PACK | I66: Major Surgery Disposable Supply Pack | J66: 0270 | M66: 1 | N66: 4200 | O66: =M66*N66 | P66: 1915.77 | Q66: =P66*15% | R66: =O66-P66 | S66: Care Gap Health | T66: Care Gap Value PPO | V66: Eleanor Brooks, MD | W66: Assigned Department Provider | X66: Inventory | Y66: Supply issue | Z66: Posted | AA66: Matched | AB66: Passed | AD66: Contract rule | AE66: Z47.1 | AF66: 21 | AG66: 2026-09-07 16:30 | AH66: Synthetic Care Gap charge; 10% below Athena allowed amount
A67: IPD-CHG-0032-ATH | B67: HAR-202600032-ATH | C67: CSN-IPD-780032-ATH | D67: Inpatient | E67: Demo Regional Medical Center | F67: Implants | G67: 2026-09-08 | H67: IMP-KNEE-CEM | I67: Cemented Knee Implant System | J67: 0278 | M67: 1 | N67: 20500 | O67: =M67*N67 | P67: 9100.72 | Q67: =P67*20% | R67: =O67-P67 | S67: Athena Health Insurance | T67: Athena PPO | V67: Eleanor Brooks, MD | W67: Assigned Department Provider | X67: Inventory | Y67: Implant scan | Z67: Posted | AA67: Matched | AB67: Passed | AD67: Contract rule | AE67: M17.11 | AF67: 21 | AG67: 2026-09-08 16:30 | AH67: Synthetic Athena negotiated charge
A68: IPD-CHG-0032-CGH | B68: HAR-202600032-CGH | C68: CSN-IPD-780032-CGH | D68: Inpatient | E68: Demo Regional Medical Center | F68: Implants | G68: 2026-09-08 | H68: IMP-KNEE-CEM | I68: Cemented Knee Implant System | J68: 0278 | M68: 1 | N68: 20500 | O68: =M68*N68 | P68: 8190.65 | Q68: =P68*15% | R68: =O68-P68 | S68: Care Gap Health | T68: Care Gap Value PPO | V68: Eleanor Brooks, MD | W68: Assigned Department Provider | X68: Inventory | Y68: Implant scan | Z68: Posted | AA68: Matched | AB68: Passed | AD68: Contract rule | AE68: M17.11 | AF68: 21 | AG68: 2026-09-08 16:30 | AH68: Synthetic Care Gap charge; 10% below Athena allowed amount
A69: IPD-CHG-0033-ATH | B69: HAR-202600033-ATH | C69: CSN-IPD-780033-ATH | D69: Inpatient | E69: Demo Regional Medical Center | F69: Implants | G69: 2026-09-09 | H69: IMP-SCREW | I69: Orthopedic Fixation Screw | J69: 0278 | K69: C1713 | M69: 1 | N69: 950 | O69: =M69*N69 | P69: 465.35 | Q69: =P69*20% | R69: =O69-P69 | S69: Athena Health Insurance | T69: Athena PPO | V69: Eleanor Brooks, MD | W69: Assigned Department Provider | X69: Inventory | Y69: Implant scan | Z69: Posted | AA69: Matched | AB69: Passed | AD69: Contract rule | AE69: M17.11 | AF69: 21 | AG69: 2026-09-09 16:30 | AH69: Synthetic Athena negotiated charge
A70: IPD-CHG-0033-CGH | B70: HAR-202600033-CGH | C70: CSN-IPD-780033-CGH | D70: Inpatient | E70: Demo Regional Medical Center | F70: Implants | G70: 2026-09-09 | H70: IMP-SCREW | I70: Orthopedic Fixation Screw | J70: 0278 | K70: C1713 | M70: 1 | N70: 950 | O70: =M70*N70 | P70: 418.82 | Q70: =P70*15% | R70: =O70-P70 | S70: Care Gap Health | T70: Care Gap Value PPO | V70: Eleanor Brooks, MD | W70: Assigned Department Provider | X70: Inventory | Y70: Implant scan | Z70: Posted | AA70: Matched | AB70: Passed | AD70: Contract rule | AE70: M17.11 | AF70: 21 | AG70: 2026-09-09 16:30 | AH70: Synthetic Care Gap charge; 10% below Athena allowed amount
A71: IPD-CHG-0034-ATH | B71: HAR-202600034-ATH | C71: CSN-IPD-780034-ATH | D71: Inpatient | E71: Demo Regional Medical Center | F71: Pharmacy | G71: 2026-09-10 | H71: DRUG-CEFA-1G | I71: Cefazolin 1 g Injection | J71: 0250 | K71: J0690 | M71: 1 | N71: 500 | O71: =M71*N71 | P71: 267.02 | Q71: =P71*20% | R71: =O71-P71 | S71: Athena Health Insurance | T71: Athena PPO | V71: Eleanor Brooks, MD | W71: Assigned Department Provider | X71: Pharmacy MAR | Y71: Medication administration | Z71: Posted | AA71: Matched | AB71: Passed | AD71: Dose/frequency | AE71: Z79.2 | AF71: 21 | AG71: 2026-09-10 16:30 | AH71: Synthetic Athena negotiated charge
A72: IPD-CHG-0034-CGH | B72: HAR-202600034-CGH | C72: CSN-IPD-780034-CGH | D72: Inpatient | E72: Demo Regional Medical Center | F72: Pharmacy | G72: 2026-09-10 | H72: DRUG-CEFA-1G | I72: Cefazolin 1 g Injection | J72: 0250 | K72: J0690 | M72: 1 | N72: 500 | O72: =M72*N72 | P72: 240.32 | Q72: =P72*15% | R72: =O72-P72 | S72: Care Gap Health | T72: Care Gap Value PPO | V72: Eleanor Brooks, MD | W72: Assigned Department Provider | X72: Pharmacy MAR | Y72: Medication administration | Z72: Posted | AA72: Matched | AB72: Passed | AD72: Dose/frequency | AE72: Z79.2 | AF72: 21 | AG72: 2026-09-10 16:30 | AH72: Synthetic Care Gap charge; 10% below Athena allowed amount
A73: IPD-CHG-0035-ATH | B73: HAR-202600035-ATH | C73: CSN-IPD-780035-ATH | D73: Inpatient | E73: Demo Regional Medical Center | F73: Pharmacy | G73: 2026-09-11 | H73: DRUG-VANC-500 | I73: Vancomycin 500 mg Injection | J73: 0250 | K73: J3370 | M73: 2 | N73: 680 | O73: =M73*N73 | P73: 830.56 | Q73: =P73*20% | R73: =O73-P73 | S73: Athena Health Insurance | T73: Athena PPO | V73: Eleanor Brooks, MD | W73: Assigned Department Provider | X73: Pharmacy MAR | Y73: Medication administration | Z73: Posted | AA73: Matched | AB73: Passed | AD73: Dose/frequency | AE73: Z79.2 | AF73: 21 | AG73: 2026-09-11 16:30 | AH73: Synthetic Athena negotiated charge
A74: IPD-CHG-0035-CGH | B74: HAR-202600035-CGH | C74: CSN-IPD-780035-CGH | D74: Inpatient | E74: Demo Regional Medical Center | F74: Pharmacy | G74: 2026-09-11 | H74: DRUG-VANC-500 | I74: Vancomycin 500 mg Injection | J74: 0250 | K74: J3370 | M74: 2 | N74: 680 | O74: =M74*N74 | P74: 747.5 | Q74: =P74*15% | R74: =O74-P74 | S74: Care Gap Health | T74: Care Gap Value PPO | V74: Eleanor Brooks, MD | W74: Assigned Department Provider | X74: Pharmacy MAR | Y74: Medication administration | Z74: Posted | AA74: Matched | AB74: Passed | AD74: Dose/frequency | AE74: Z79.2 | AF74: 21 | AG74: 2026-09-11 16:30 | AH74: Synthetic Care Gap charge; 10% below Athena allowed amount
A75: IPD-CHG-0036-ATH | B75: HAR-202600036-ATH | C75: CSN-IPD-780036-ATH | D75: Inpatient | E75: Demo Regional Medical Center | F75: Pharmacy | G75: 2026-09-12 | H75: IV-NS-1L | I75: Normal Saline 1,000 mL | J75: 0258 | K75: J7030 | M75: 2 | N75: 90 | O75: =M75*N75 | P75: 84.38 | Q75: =P75*20% | R75: =O75-P75 | S75: Athena Health Insurance | T75: Athena PPO | V75: Eleanor Brooks, MD | W75: Assigned Department Provider | X75: Pharmacy MAR | Y75: Medication administration | Z75: Posted | AA75: Matched | AB75: Passed | AD75: N/A | AE75: E86.0 | AF75: 21 | AG75: 2026-09-12 16:30 | AH75: Synthetic Athena negotiated charge
A76: IPD-CHG-0036-CGH | B76: HAR-202600036-CGH | C76: CSN-IPD-780036-CGH | D76: Inpatient | E76: Demo Regional Medical Center | F76: Pharmacy | G76: 2026-09-12 | H76: IV-NS-1L | I76: Normal Saline 1,000 mL | J76: 0258 | K76: J7030 | M76: 2 | N76: 90 | O76: =M76*N76 | P76: 75.94 | Q76: =P76*15% | R76: =O76-P76 | S76: Care Gap Health | T76: Care Gap Value PPO | V76: Eleanor Brooks, MD | W76: Assigned Department Provider | X76: Pharmacy MAR | Y76: Medication administration | Z76: Posted | AA76: Matched | AB76: Passed | AD76: N/A | AE76: E86.0 | AF76: 21 | AG76: 2026-09-12 16:30 | AH76: Synthetic Care Gap charge; 10% below Athena allowed amount
A77: IPD-CHG-0037-ATH | B77: HAR-202600037-ATH | C77: CSN-IPD-780037-ATH | D77: Inpatient | E77: Demo Regional Medical Center | F77: Laboratory | G77: 2026-09-13 | H77: LAB-CBC | I77: Complete Blood Count with Differential | J77: 0300 | K77: 85025 | M77: 1 | N77: 155 | O77: =M77*N77 | P77: 81.62 | Q77: =P77*20% | R77: =O77-P77 | S77: Athena Health Insurance | T77: Athena PPO | V77: Eleanor Brooks, MD | W77: Assigned Department Provider | X77: LIS | Y77: Final result | Z77: Posted | AA77: Matched | AB77: Passed | AD77: Diagnosis/LCD | AE77: D64.9 | AF77: 21 | AG77: 2026-09-13 16:30 | AH77: Synthetic Athena negotiated charge
A78: IPD-CHG-0037-CGH | B78: HAR-202600037-CGH | C78: CSN-IPD-780037-CGH | D78: Inpatient | E78: Demo Regional Medical Center | F78: Laboratory | G78: 2026-09-13 | H78: LAB-CBC | I78: Complete Blood Count with Differential | J78: 0300 | K78: 85025 | M78: 1 | N78: 155 | O78: =M78*N78 | P78: 73.46 | Q78: =P78*15% | R78: =O78-P78 | S78: Care Gap Health | T78: Care Gap Value PPO | V78: Eleanor Brooks, MD | W78: Assigned Department Provider | X78: LIS | Y78: Final result | Z78: Posted | AA78: Matched | AB78: Passed | AD78: Diagnosis/LCD | AE78: D64.9 | AF78: 21 | AG78: 2026-09-13 16:30 | AH78: Synthetic Care Gap charge; 10% below Athena allowed amount
A79: IPD-CHG-0038-ATH | B79: HAR-202600038-ATH | C79: CSN-IPD-780038-ATH | D79: Inpatient | E79: Demo Regional Medical Center | F79: Laboratory | G79: 2026-09-14 | H79: LAB-CMP | I79: Comprehensive Metabolic Panel | J79: 0301 | K79: 80053 | M79: 1 | N79: 245 | O79: =M79*N79 | P79: 152.16 | Q79: =P79*20% | R79: =O79-P79 | S79: Athena Health Insurance | T79: Athena PPO | V79: Eleanor Brooks, MD | W79: Assigned Department Provider | X79: LIS | Y79: Final result | Z79: Posted | AA79: Matched | AB79: Passed | AD79: Diagnosis/LCD | AE79: E11.9 | AF79: 21 | AG79: 2026-09-14 16:30 | AH79: Synthetic Athena negotiated charge
A80: IPD-CHG-0038-CGH | B80: HAR-202600038-CGH | C80: CSN-IPD-780038-CGH | D80: Inpatient | E80: Demo Regional Medical Center | F80: Laboratory | G80: 2026-09-14 | H80: LAB-CMP | I80: Comprehensive Metabolic Panel | J80: 0301 | K80: 80053 | M80: 1 | N80: 245 | O80: =M80*N80 | P80: 136.94 | Q80: =P80*15% | R80: =O80-P80 | S80: Care Gap Health | T80: Care Gap Value PPO | V80: Eleanor Brooks, MD | W80: Assigned Department Provider | X80: LIS | Y80: Final result | Z80: Posted | AA80: Matched | AB80: Passed | AD80: Diagnosis/LCD | AE80: E11.9 | AF80: 21 | AG80: 2026-09-14 16:30 | AH80: Synthetic Care Gap charge; 10% below Athena allowed amount
A81: IPD-CHG-0039-ATH | B81: HAR-202600039-ATH | C81: CSN-IPD-780039-ATH | D81: Inpatient | E81: Demo Regional Medical Center | F81: Laboratory | G81: 2026-09-15 | H81: LAB-PTINR | I81: Prothrombin Time / INR | J81: 0305 | K81: 85610 | M81: 1 | N81: 125 | O81: =M81*N81 | P81: 78.82 | Q81: =P81*20% | R81: =O81-P81 | S81: Athena Health Insurance | T81: Athena PPO | V81: Eleanor Brooks, MD | W81: Assigned Department Provider | X81: LIS | Y81: Final result | Z81: Posted | AA81: Matched | AB81: Passed | AD81: Diagnosis/LCD | AE81: Z79.01 | AF81: 21 | AG81: 2026-09-15 16:30 | AH81: Synthetic Athena negotiated charge
A82: IPD-CHG-0039-CGH | B82: HAR-202600039-CGH | C82: CSN-IPD-780039-CGH | D82: Inpatient | E82: Demo Regional Medical Center | F82: Laboratory | G82: 2026-09-15 | H82: LAB-PTINR | I82: Prothrombin Time / INR | J82: 0305 | K82: 85610 | M82: 1 | N82: 125 | O82: =M82*N82 | P82: 70.94 | Q82: =P82*15% | R82: =O82-P82 | S82: Care Gap Health | T82: Care Gap Value PPO | V82: Eleanor Brooks, MD | W82: Assigned Department Provider | X82: LIS | Y82: Final result | Z82: Posted | AA82: Matched | AB82: Passed | AD82: Diagnosis/LCD | AE82: Z79.01 | AF82: 21 | AG82: 2026-09-15 16:30 | AH82: Synthetic Care Gap charge; 10% below Athena allowed amount
A83: IPD-CHG-0040-ATH | B83: HAR-202600040-ATH | C83: CSN-IPD-780040-ATH | D83: Inpatient | E83: Demo Regional Medical Center | F83: Radiology | G83: 2026-09-16 | H83: RAD-CHEST-2V | I83: Chest X-ray, 2 Views | J83: 0320 | K83: 71046 | M83: 1 | N83: 185 | O83: =M83*N83 | P83: 115.64 | Q83: =P83*20% | R83: =O83-P83 | S83: Athena Health Insurance | T83: Athena PPO | V83: Eleanor Brooks, MD | W83: Assigned Department Provider | X83: RIS/PACS | Y83: Exam completed | Z83: Posted | AA83: Matched | AB83: Passed | AD83: Diagnosis/LCD | AE83: R06.02 | AF83: 21 | AG83: 2026-09-16 16:30 | AH83: Synthetic Athena negotiated charge
A84: IPD-CHG-0040-CGH | B84: HAR-202600040-CGH | C84: CSN-IPD-780040-CGH | D84: Inpatient | E84: Demo Regional Medical Center | F84: Radiology | G84: 2026-09-16 | H84: RAD-CHEST-2V | I84: Chest X-ray, 2 Views | J84: 0320 | K84: 71046 | M84: 1 | N84: 185 | O84: =M84*N84 | P84: 104.08 | Q84: =P84*15% | R84: =O84-P84 | S84: Care Gap Health | T84: Care Gap Value PPO | V84: Eleanor Brooks, MD | W84: Assigned Department Provider | X84: RIS/PACS | Y84: Exam completed | Z84: Posted | AA84: Matched | AB84: Passed | AD84: Diagnosis/LCD | AE84: R06.02 | AF84: 21 | AG84: 2026-09-16 16:30 | AH84: Synthetic Care Gap charge; 10% below Athena allowed amount
A85: IPD-CHG-0041-ATH | B85: HAR-202600041-ATH | C85: CSN-IPD-780041-ATH | D85: Inpatient | E85: Demo Regional Medical Center | F85: Radiology | G85: 2026-09-17 | H85: RAD-KNEE-2V | I85: Knee X-ray, 1-2 Views | J85: 0320 | K85: 73560 | M85: 1 | N85: 410 | O85: =M85*N85 | P85: 180.98 | Q85: =P85*20% | R85: =O85-P85 | S85: Athena Health Insurance | T85: Athena PPO | V85: Eleanor Brooks, MD | W85: Assigned Department Provider | X85: RIS/PACS | Y85: Exam completed | Z85: Posted | AA85: Matched | AB85: Passed | AD85: Diagnosis/LCD | AE85: M25.561 | AF85: 21 | AG85: 2026-09-17 16:30 | AH85: Synthetic Athena negotiated charge
A86: IPD-CHG-0041-CGH | B86: HAR-202600041-CGH | C86: CSN-IPD-780041-CGH | D86: Inpatient | E86: Demo Regional Medical Center | F86: Radiology | G86: 2026-09-17 | H86: RAD-KNEE-2V | I86: Knee X-ray, 1-2 Views | J86: 0320 | K86: 73560 | M86: 1 | N86: 410 | O86: =M86*N86 | P86: 162.88 | Q86: =P86*15% | R86: =O86-P86 | S86: Care Gap Health | T86: Care Gap Value PPO | V86: Eleanor Brooks, MD | W86: Assigned Department Provider | X86: RIS/PACS | Y86: Exam completed | Z86: Posted | AA86: Matched | AB86: Passed | AD86: Diagnosis/LCD | AE86: M25.561 | AF86: 21 | AG86: 2026-09-17 16:30 | AH86: Synthetic Care Gap charge; 10% below Athena allowed amount
A87: IPD-CHG-0042-ATH | B87: HAR-202600042-ATH | C87: CSN-IPD-780042-ATH | D87: Inpatient | E87: Demo Regional Medical Center | F87: Cardiology | G87: 2026-09-18 | H87: CARD-ECG12 | I87: 12-Lead ECG | J87: 0730 | K87: 93005 | M87: 1 | N87: 190 | O87: =M87*N87 | P87: 115.99 | Q87: =P87*20% | R87: =O87-P87 | S87: Athena Health Insurance | T87: Athena PPO | V87: Eleanor Brooks, MD | W87: Assigned Department Provider | X87: Cardiology | Y87: Test completed | Z87: Posted | AA87: Matched | AB87: Passed | AD87: Diagnosis/LCD | AE87: R07.9 | AF87: 21 | AG87: 2026-09-18 16:30 | AH87: Synthetic Athena negotiated charge
A88: IPD-CHG-0042-CGH | B88: HAR-202600042-CGH | C88: CSN-IPD-780042-CGH | D88: Inpatient | E88: Demo Regional Medical Center | F88: Cardiology | G88: 2026-09-18 | H88: CARD-ECG12 | I88: 12-Lead ECG | J88: 0730 | K88: 93005 | M88: 1 | N88: 190 | O88: =M88*N88 | P88: 104.39 | Q88: =P88*15% | R88: =O88-P88 | S88: Care Gap Health | T88: Care Gap Value PPO | V88: Eleanor Brooks, MD | W88: Assigned Department Provider | X88: Cardiology | Y88: Test completed | Z88: Posted | AA88: Matched | AB88: Passed | AD88: Diagnosis/LCD | AE88: R07.9 | AF88: 21 | AG88: 2026-09-18 16:30 | AH88: Synthetic Care Gap charge; 10% below Athena allowed amount
A89: IPD-CHG-0043-ATH | B89: HAR-202600043-ATH | C89: CSN-IPD-780043-ATH | D89: Inpatient | E89: Demo Regional Medical Center | F89: Respiratory | G89: 2026-09-19 | H89: RESP-NEB | I89: Nebulizer Treatment | J89: 0410 | K89: 94640 | M89: 1 | N89: 245 | O89: =M89*N89 | P89: 142.16 | Q89: =P89*20% | R89: =O89-P89 | S89: Athena Health Insurance | T89: Athena PPO | V89: Eleanor Brooks, MD | W89: Assigned Department Provider | X89: Respiratory | Y89: Treatment completed | Z89: Posted | AA89: Matched | AB89: Passed | AD89: Diagnosis/LCD | AE89: J45.901 | AF89: 21 | AG89: 2026-09-19 16:30 | AH89: Synthetic Athena negotiated charge
A90: IPD-CHG-0043-CGH | B90: HAR-202600043-CGH | C90: CSN-IPD-780043-CGH | D90: Inpatient | E90: Demo Regional Medical Center | F90: Respiratory | G90: 2026-09-19 | H90: RESP-NEB | I90: Nebulizer Treatment | J90: 0410 | K90: 94640 | M90: 1 | N90: 245 | O90: =M90*N90 | P90: 127.94 | Q90: =P90*15% | R90: =O90-P90 | S90: Care Gap Health | T90: Care Gap Value PPO | V90: Eleanor Brooks, MD | W90: Assigned Department Provider | X90: Respiratory | Y90: Treatment completed | Z90: Posted | AA90: Matched | AB90: Passed | AD90: Diagnosis/LCD | AE90: J45.901 | AF90: 21 | AG90: 2026-09-19 16:30 | AH90: Synthetic Care Gap charge; 10% below Athena allowed amount
A91: IPD-CHG-0044-ATH | B91: HAR-202600044-ATH | C91: CSN-IPD-780044-ATH | D91: Inpatient | E91: Demo Regional Medical Center | F91: Physical Therapy | G91: 2026-09-20 | H91: PT-EVAL-LOW | I91: Physical Therapy Evaluation, Low Complexity | J91: 0420 | K91: 97161 | M91: 1 | N91: 710 | O91: =M91*N91 | P91: 350.34 | Q91: =P91*20% | R91: =O91-P91 | S91: Athena Health Insurance | T91: Athena PPO | U91: AUTH-700044 | V91: Eleanor Brooks, MD | W91: Assigned Department Provider | X91: Therapy | Y91: Note signed | Z91: Posted | AA91: Matched | AB91: Passed | AD91: Plan benefits | AE91: R26.2 | AF91: 21 | AG91: 2026-09-20 16:30 | AH91: Synthetic Athena negotiated charge
A92: IPD-CHG-0044-CGH | B92: HAR-202600044-CGH | C92: CSN-IPD-780044-CGH | D92: Inpatient | E92: Demo Regional Medical Center | F92: Physical Therapy | G92: 2026-09-20 | H92: PT-EVAL-LOW | I92: Physical Therapy Evaluation, Low Complexity | J92: 0420 | K92: 97161 | M92: 1 | N92: 710 | O92: =M92*N92 | P92: 315.31 | Q92: =P92*15% | R92: =O92-P92 | S92: Care Gap Health | T92: Care Gap Value PPO | U92: AUTH-700044 | V92: Eleanor Brooks, MD | W92: Assigned Department Provider | X92: Therapy | Y92: Note signed | Z92: Posted | AA92: Matched | AB92: Passed | AD92: Plan benefits | AE92: R26.2 | AF92: 21 | AG92: 2026-09-20 16:30 | AH92: Synthetic Care Gap charge; 10% below Athena allowed amount
A93: IPD-CHG-0045-ATH | B93: HAR-202600045-ATH | C93: CSN-IPD-780045-ATH | D93: Inpatient | E93: Demo Regional Medical Center | F93: Physical Therapy | G93: 2026-09-21 | H93: PT-THEREX-15 | I93: Therapeutic Exercise, 15 Minutes | J93: 0420 | K93: 97110 | M93: 6 | N93: 305 | O93: =M93*N93 | P93: 976.92 | Q93: =P93*20% | R93: =O93-P93 | S93: Athena Health Insurance | T93: Athena PPO | V93: Eleanor Brooks, MD | W93: Assigned Department Provider | X93: Therapy | Y93: Note signed | Z93: Posted | AA93: Matched | AB93: Passed | AD93: Timed units | AE93: M62.81 | AF93: 21 | AG93: 2026-09-21 16:30 | AH93: Synthetic Athena negotiated charge
A94: IPD-CHG-0045-CGH | B94: HAR-202600045-CGH | C94: CSN-IPD-780045-CGH | D94: Inpatient | E94: Demo Regional Medical Center | F94: Physical Therapy | G94: 2026-09-21 | H94: PT-THEREX-15 | I94: Therapeutic Exercise, 15 Minutes | J94: 0420 | K94: 97110 | M94: 6 | N94: 305 | O94: =M94*N94 | P94: 879.23 | Q94: =P94*15% | R94: =O94-P94 | S94: Care Gap Health | T94: Care Gap Value PPO | V94: Eleanor Brooks, MD | W94: Assigned Department Provider | X94: Therapy | Y94: Note signed | Z94: Posted | AA94: Matched | AB94: Passed | AD94: Timed units | AE94: M62.81 | AF94: 21 | AG94: 2026-09-21 16:30 | AH94: Synthetic Care Gap charge; 10% below Athena allowed amount
A95: IPD-CHG-0046-ATH | B95: HAR-202600046-ATH | C95: CSN-IPD-780046-ATH | D95: Inpatient | E95: Demo Regional Medical Center | F95: Occupational Therapy | G95: 2026-09-22 | H95: OT-EVAL-LOW | I95: Occupational Therapy Evaluation, Low Complexity | J95: 0430 | K95: 97165 | M95: 1 | N95: 725 | O95: =M95*N95 | P95: 519.72 | Q95: =P95*20% | R95: =O95-P95 | S95: Athena Health Insurance | T95: Athena PPO | U95: AUTH-700046 | V95: Eleanor Brooks, MD | W95: Assigned Department Provider | X95: Therapy | Y95: Note signed | Z95: Posted | AA95: Matched | AB95: Review | AC95: WQ-OCC-03 | AD95: Plan benefits | AE95: Z74.09 | AF95: 21 | AG95: 2026-09-22 16:30 | AH95: Synthetic Athena negotiated charge
A96: IPD-CHG-0046-CGH | B96: HAR-202600046-CGH | C96: CSN-IPD-780046-CGH | D96: Inpatient | E96: Demo Regional Medical Center | F96: Occupational Therapy | G96: 2026-09-22 | H96: OT-EVAL-LOW | I96: Occupational Therapy Evaluation, Low Complexity | J96: 0430 | K96: 97165 | M96: 1 | N96: 725 | O96: =M96*N96 | P96: 467.75 | Q96: =P96*15% | R96: =O96-P96 | S96: Care Gap Health | T96: Care Gap Value PPO | U96: AUTH-700046 | V96: Eleanor Brooks, MD | W96: Assigned Department Provider | X96: Therapy | Y96: Note signed | Z96: Posted | AA96: Matched | AB96: Review | AC96: WQ-OCC-03 | AD96: Plan benefits | AE96: Z74.09 | AF96: 21 | AG96: 2026-09-22 16:30 | AH96: Synthetic Care Gap charge; 10% below Athena allowed amount
A97: IPD-CHG-0047-ATH | B97: HAR-202600047-ATH | C97: CSN-IPD-780047-ATH | D97: Inpatient | E97: Demo Regional Medical Center | F97: Nutrition | G97: 2026-09-23 | H97: NUTR-ASSESS | I97: Inpatient Nutrition Assessment | J97: 0942 | K97: 97802 | M97: 1 | N97: 325 | O97: =M97*N97 | P97: 198.9 | Q97: =P97*20% | R97: =O97-P97 | S97: Athena Health Insurance | T97: Athena PPO | V97: Eleanor Brooks, MD | W97: Assigned Department Provider | X97: Dietary | Y97: Note signed | Z97: Posted | AA97: Matched | AB97: Passed | AD97: N/A | AE97: E44.1 | AF97: 21 | AG97: 2026-09-23 16:30 | AH97: Synthetic Athena negotiated charge
A98: IPD-CHG-0047-CGH | B98: HAR-202600047-CGH | C98: CSN-IPD-780047-CGH | D98: Inpatient | E98: Demo Regional Medical Center | F98: Nutrition | G98: 2026-09-23 | H98: NUTR-ASSESS | I98: Inpatient Nutrition Assessment | J98: 0942 | K98: 97802 | M98: 1 | N98: 325 | O98: =M98*N98 | P98: 179.01 | Q98: =P98*15% | R98: =O98-P98 | S98: Care Gap Health | T98: Care Gap Value PPO | V98: Eleanor Brooks, MD | W98: Assigned Department Provider | X98: Dietary | Y98: Note signed | Z98: Posted | AA98: Matched | AB98: Passed | AD98: N/A | AE98: E44.1 | AF98: 21 | AG98: 2026-09-23 16:30 | AH98: Synthetic Care Gap charge; 10% below Athena allowed amount
A99: IPD-CHG-0048-ATH | B99: HAR-202600048-ATH | C99: CSN-IPD-780048-ATH | D99: Inpatient | E99: Demo Regional Medical Center | F99: Dialysis | G99: 2026-09-24 | H99: DIALYSIS-IP | I99: Inpatient Hemodialysis Treatment | J99: 0801 | K99: 90935 | M99: 1 | N99: 1600 | O99: =M99*N99 | P99: 939.34 | Q99: =P99*20% | R99: =O99-P99 | S99: Athena Health Insurance | T99: Athena PPO | V99: Eleanor Brooks, MD | W99: Assigned Department Provider | X99: Dialysis | Y99: Treatment completed | Z99: Posted | AA99: Matched | AB99: Passed | AD99: Diagnosis/LCD | AE99: N18.6 | AF99: 21 | AG99: 2026-09-24 16:30 | AH99: Synthetic Athena negotiated charge
A100: IPD-CHG-0048-CGH | B100: HAR-202600048-CGH | C100: CSN-IPD-780048-CGH | D100: Inpatient | E100: Demo Regional Medical Center | F100: Dialysis | G100: 2026-09-24 | H100: DIALYSIS-IP | I100: Inpatient Hemodialysis Treatment | J100: 0801 | K100: 90935 | M100: 1 | N100: 1600 | O100: =M100*N100 | P100: 845.41 | Q100: =P100*15% | R100: =O100-P100 | S100: Care Gap Health | T100: Care Gap Value PPO | V100: Eleanor Brooks, MD | W100: Assigned Department Provider | X100: Dialysis | Y100: Treatment completed | Z100: Posted | AA100: Matched | AB100: Passed | AD100: Diagnosis/LCD | AE100: N18.6 | AF100: 21 | AG100: 2026-09-24 16:30 | AH100: Synthetic Care Gap charge; 10% below Athena allowed amount
A101: IPD-CHG-0049-ATH | B101: HAR-202600049-ATH | C101: CSN-IPD-780049-ATH | D101: Inpatient | E101: Demo Regional Medical Center | F101: Accommodation | G101: 2026-09-25 | H101: RM-SEMI-DAY | I101: Semiprivate Medical/Surgical Room | J101: 0120 | M101: 3 | N101: 3500 | O101: =M101*N101 | P101: 7064.98 | Q101: =P101*20% | R101: =O101-P101 | S101: Athena Health Insurance | T101: Athena PPO | V101: Eleanor Brooks, MD | W101: Assigned Department Provider | X101: ADT | Y101: Midnight census | Z101: Posted | AA101: Matched | AB101: Passed | AD101: N/A | AE101: M17.11 | AF101: 21 | AG101: 2026-09-25 16:30 | AH101: Synthetic Athena negotiated charge
...

Sheet OPD Charges
A1: Outpatient Charge Detail
A2: 100 original synthetic outpatient charge lines, each represented for Athena Health Insurance and Care Gap Health (200 payer-priced rows).
A4: Charge Line ID | B4: Patient Account | C4: Encounter ID | D4: Patient Class | E4: Facility | F4: Department | G4: Service Date | H4: Charge Code | I4: Charge Description | J4: Revenue Code | K4: CPT/HCPCS | L4: Modifier | M4: Quantity | N4: Unit Charge ($) | O4: Extended Gross ($) | P4: Expected Allowed ($) | Q4: Patient Responsibility ($) | R4: Contractual Adjustment ($) | S4: Payer | T4: Plan | U4: Authorization ID | V4: Ordering Provider | W4: Performing Provider | X4: Source System | Y4: Charge Trigger | Z4: Charge Status | AA4: Reconciliation Status | AB4: Claim Edit Status | AC4: Workqueue | AD4: Medical Necessity | AE4: Diagnosis Link | AF4: Place of Service | AG4: Posting Date/Time | AH4: Notes
A5: OPD-CHG-0001-ATH | B5: OP-202600001-ATH | C5: CSN-OPD-780001-ATH | D5: Outpatient | E5: Demo Regional Medical Center | F5: Emergency Department | G5: 2026-09-02 | H5: ED-LEVEL-1 | I5: Emergency Department Visit Level 1 | J5: 0450 | K5: 99281 | M5: 1 | N5: 360 | O5: =M5*N5 | P5: 221.39 | Q5: =P5*20% | R5: =O5-P5 | S5: Athena Health Insurance | T5: Athena PPO | V5: Eleanor Brooks, MD | W5: Assigned Department Provider | X5: ED | Y5: Encounter close | Z5: Posted | AA5: Matched | AB5: Passed | AD5: Documentation | AE5: R50.9 | AF5: 22 | AG5: 2026-09-02 16:30 | AH5: Synthetic Athena negotiated charge
A6: OPD-CHG-0001-CGH | B6: OP-202600001-CGH | C6: CSN-OPD-780001-CGH | D6: Outpatient | E6: Demo Regional Medical Center | F6: Emergency Department | G6: 2026-09-02 | H6: ED-LEVEL-1 | I6: Emergency Department Visit Level 1 | J6: 0450 | K6: 99281 | M6: 1 | N6: 360 | O6: =M6*N6 | P6: 199.25 | Q6: =P6*15% | R6: =O6-P6 | S6: Care Gap Health | T6: Care Gap Value PPO | V6: Eleanor Brooks, MD | W6: Assigned Department Provider | X6: ED | Y6: Encounter close | Z6: Posted | AA6: Matched | AB6: Passed | AD6: Documentation | AE6: R50.9 | AF6: 22 | AG6: 2026-09-02 16:30 | AH6: Synthetic Care Gap charge; 10% below Athena allowed amount
A7: OPD-CHG-0002-ATH | B7: OP-202600002-ATH | C7: CSN-OPD-780002-ATH | D7: Outpatient | E7: Demo Regional Medical Center | F7: Emergency Department | G7: 2026-09-03 | H7: ED-LEVEL-2 | I7: Emergency Department Visit Level 2 | J7: 0450 | K7: 99282 | M7: 1 | N7: 670 | O7: =M7*N7 | P7: 369.46 | Q7: =P7*20% | R7: =O7-P7 | S7: Athena Health Insurance | T7: Athena PPO | V7: Eleanor Brooks, MD | W7: Assigned Department Provider | X7: ED | Y7: Encounter close | Z7: Posted | AA7: Matched | AB7: Passed | AD7: Documentation | AE7: R51.9 | AF7: 22 | AG7: 2026-09-03 16:30 | AH7: Synthetic Athena negotiated charge
A8: OPD-CHG-0002-CGH | B8: OP-202600002-CGH | C8: CSN-OPD-780002-CGH | D8: Outpatient | E8: Demo Regional Medical Center | F8: Emergency Department | G8: 2026-09-03 | H8: ED-LEVEL-2 | I8: Emergency Department Visit Level 2 | J8: 0450 | K8: 99282 | M8: 1 | N8: 670 | O8: =M8*N8 | P8: 332.51 | Q8: =P8*15% | R8: =O8-P8 | S8: Care Gap Health | T8: Care Gap Value PPO | V8: Eleanor Brooks, MD | W8: Assigned Department Provider | X8: ED | Y8: Encounter close | Z8: Posted | AA8: Matched | AB8: Passed | AD8: Documentation | AE8: R51.9 | AF8: 22 | AG8: 2026-09-03 16:30 | AH8: Synthetic Care Gap charge; 10% below Athena allowed amount
A9: OPD-CHG-0003-ATH | B9: OP-202600003-ATH | C9: CSN-OPD-780003-ATH | D9: Outpatient | E9: Demo Regional Medical Center | F9: Emergency Department | G9: 2026-09-04 | H9: ED-LEVEL-3 | I9: Emergency Department Visit Level 3 | J9: 0450 | K9: 99283 | M9: 1 | N9: 1280 | O9: =M9*N9 | P9: 736.35 | Q9: =P9*20% | R9: =O9-P9 | S9: Athena Health Insurance | T9: Athena PPO | V9: Eleanor Brooks, MD | W9: Assigned Department Provider | X9: ED | Y9: Encounter close | Z9: Posted | AA9: Matched | AB9: Passed | AD9: Documentation | AE9: R10.9 | AF9: 22 | AG9: 2026-09-04 16:30 | AH9: Synthetic Athena negotiated charge
A10: OPD-CHG-0003-CGH | B10: OP-202600003-CGH | C10: CSN-OPD-780003-CGH | D10: Outpatient | E10: Demo Regional Medical Center | F10: Emergency Department | G10: 2026-09-04 | H10: ED-LEVEL-3 | I10: Emergency Department Visit Level 3 | J10: 0450 | K10: 99283 | M10: 1 | N10: 1280 | O10: =M10*N10 | P10: 662.72 | Q10: =P10*15% | R10: =O10-P10 | S10: Care Gap Health | T10: Care Gap Value PPO | V10: Eleanor Brooks, MD | W10: Assigned Department Provider | X10: ED | Y10: Encounter close | Z10: Posted | AA10: Matched | AB10: Passed | AD10: Documentation | AE10: R10.9 | AF10: 22 | AG10: 2026-09-04 16:30 | AH10: Synthetic Care Gap charge; 10% below Athena allowed amount
A11: OPD-CHG-0004-ATH | B11: OP-202600004-ATH | C11: CSN-OPD-780004-ATH | D11: Outpatient | E11: Demo Regional Medical Center | F11: Emergency Department | G11: 2026-09-05 | H11: ED-LEVEL-4 | I11: Emergency Department Visit Level 4 | J11: 0450 | K11: 99284 | M11: 1 | N11: 2350 | O11: =M11*N11 | P11: 1072.31 | Q11: =P11*20% | R11: =O11-P11 | S11: Athena Health Insurance | T11: Athena PPO | V11: Eleanor Brooks, MD | W11: Assigned Department Provider | X11: ED | Y11: Encounter close | Z11: Posted | AA11: Matched | AB11: Passed | AD11: Documentation | AE11: R06.02 | AF11: 22 | AG11: 2026-09-05 16:30 | AH11: Synthetic Athena negotiated charge
A12: OPD-CHG-0004-CGH | B12: OP-202600004-CGH | C12: CSN-OPD-780004-CGH | D12: Outpatient | E12: Demo Regional Medical Center | F12: Emergency Department | G12: 2026-09-05 | H12: ED-LEVEL-4 | I12: Emergency Department Visit Level 4 | J12: 0450 | K12: 99284 | M12: 1 | N12: 2350 | O12: =M12*N12 | P12: 965.08 | Q12: =P12*15% | R12: =O12-P12 | S12: Care Gap Health | T12: Care Gap Value PPO | V12: Eleanor Brooks, MD | W12: Assigned Department Provider | X12: ED | Y12: Encounter close | Z12: Posted | AA12: Matched | AB12: Passed | AD12: Documentation | AE12: R06.02 | AF12: 22 | AG12: 2026-09-05 16:30 | AH12: Synthetic Care Gap charge; 10% below Athena allowed amount
A13: OPD-CHG-0005-ATH | B13: OP-202600005-ATH | C13: CSN-OPD-780005-ATH | D13: Outpatient | E13: Demo Regional Medical Center | F13: Emergency Department | G13: 2026-09-06 | H13: ED-LEVEL-5 | I13: Emergency Department Visit Level 5 | J13: 0450 | K13: 99285 | M13: 1 | N13: 4300 | O13: =M13*N13 | P13: 2095.86 | Q13: =P13*20% | R13: =O13-P13 | S13: Athena Health Insurance | T13: Athena PPO | V13: Eleanor Brooks, MD | W13: Assigned Department Provider | X13: ED | Y13: Encounter close | Z13: Posted | AA13: Matched | AB13: Passed | AD13: Documentation | AE13: R07.9 | AF13: 22 | AG13: 2026-09-06 16:30 | AH13: Synthetic Athena negotiated charge
A14: OPD-CHG-0005-CGH | B14: OP-202600005-CGH | C14: CSN-OPD-780005-CGH | D14: Outpatient | E14: Demo Regional Medical Center | F14: Emergency Department | G14: 2026-09-06 | H14: ED-LEVEL-5 | I14: Emergency Department Visit Level 5 | J14: 0450 | K14: 99285 | M14: 1 | N14: 4300 | O14: =M14*N14 | P14: 1886.27 | Q14: =P14*15% | R14: =O14-P14 | S14: Care Gap Health | T14: Care Gap Value PPO | V14: Eleanor Brooks, MD | W14: Assigned Department Provider | X14: ED | Y14: Encounter close | Z14: Posted | AA14: Matched | AB14: Passed | AD14: Documentation | AE14: R07.9 | AF14: 22 | AG14: 2026-09-06 16:30 | AH14: Synthetic Care Gap charge; 10% below Athena allowed amount
A15: OPD-CHG-0006-ATH | B15: OP-202600006-ATH | C15: CSN-OPD-780006-ATH | D15: Outpatient | E15: Demo Regional Medical Center | F15: Hospital Clinic | G15: 2026-09-07 | H15: CLINIC-L2 | I15: Hospital Outpatient Clinic Visit Level 2 | J15: 0510 | K15: 99212 | M15: 1 | N15: 215 | O15: =M15*N15 | P15: 112.11 | Q15: =P15*20% | R15: =O15-P15 | S15: Athena Health Insurance | T15: Athena PPO | V15: Eleanor Brooks, MD | W15: Assigned Department Provider | X15: Ambulatory | Y15: Visit close | Z15: Posted | AA15: Matched | AB15: Passed | AD15: E/M documentation | AE15: I10 | AF15: 22 | AG15: 2026-09-07 16:30 | AH15: Synthetic Athena negotiated charge
A16: OPD-CHG-0006-CGH | B16: OP-202600006-CGH | C16: CSN-OPD-780006-CGH | D16: Outpatient | E16: Demo Regional Medical Center | F16: Hospital Clinic | G16: 2026-09-07 | H16: CLINIC-L2 | I16: Hospital Outpatient Clinic Visit Level 2 | J16: 0510 | K16: 99212 | M16: 1 | N16: 215 | O16: =M16*N16 | P16: 100.9 | Q16: =P16*15% | R16: =O16-P16 | S16: Care Gap Health | T16: Care Gap Value PPO | V16: Eleanor Brooks, MD | W16: Assigned Department Provider | X16: Ambulatory | Y16: Visit close | Z16: Posted | AA16: Matched | AB16: Passed | AD16: E/M documentation | AE16: I10 | AF16: 22 | AG16: 2026-09-07 16:30 | AH16: Synthetic Care Gap charge; 10% below Athena allowed amount
A17: OPD-CHG-0007-ATH | B17: OP-202600007-ATH | C17: CSN-OPD-780007-ATH | D17: Outpatient | E17: Demo Regional Medical Center | F17: Hospital Clinic | G17: 2026-09-08 | H17: CLINIC-L3 | I17: Hospital Outpatient Clinic Visit Level 3 | J17: 0510 | K17: 99213 | M17: 1 | N17: 315 | O17: =M17*N17 | P17: 187.9 | Q17: =P17*20% | R17: =O17-P17 | S17: Athena Health Insurance | T17: Athena PPO | V17: Eleanor Brooks, MD | W17: Assigned Department Provider | X17: Ambulatory | Y17: Visit close | Z17: Posted | AA17: Matched | AB17: Passed | AD17: E/M documentation | AE17: E11.9 | AF17: 22 | AG17: 2026-09-08 16:30 | AH17: Synthetic Athena negotiated charge
A18: OPD-CHG-0007-CGH | B18: OP-202600007-CGH | C18: CSN-OPD-780007-CGH | D18: Outpatient | E18: Demo Regional Medical Center | F18: Hospital Clinic | G18: 2026-09-08 | H18: CLINIC-L3 | I18: Hospital Outpatient Clinic Visit Level 3 | J18: 0510 | K18: 99213 | M18: 1 | N18: 315 | O18: =M18*N18 | P18: 169.11 | Q18: =P18*15% | R18: =O18-P18 | S18: Care Gap Health | T18: Care Gap Value PPO | V18: Eleanor Brooks, MD | W18: Assigned Department Provider | X18: Ambulatory | Y18: Visit close | Z18: Posted | AA18: Matched | AB18: Passed | AD18: E/M documentation | AE18: E11.9 | AF18: 22 | AG18: 2026-09-08 16:30 | AH18: Synthetic Care Gap charge; 10% below Athena allowed amount
A19: OPD-CHG-0008-ATH | B19: OP-202600008-ATH | C19: CSN-OPD-780008-ATH | D19: Outpatient | E19: Demo Regional Medical Center | F19: Hospital Clinic | G19: 2026-09-09 | H19: CLINIC-L4 | I19: Hospital Outpatient Clinic Visit Level 4 | J19: 0510 | K19: 99214 | M19: 1 | N19: 410 | O19: =M19*N19 | P19: 200.5 | Q19: =P19*20% | R19: =O19-P19 | S19: Athena Health Insurance | T19: Athena PPO | V19: Eleanor Brooks, MD | W19: Assigned Department Provider | X19: Ambulatory | Y19: Visit close | Z19: Posted | AA19: Matched | AB19: Passed | AD19: E/M documentation | AE19: J45.40 | AF19: 22 | AG19: 2026-09-09 16:30 | AH19: Synthetic Athena negotiated charge
A20: OPD-CHG-0008-CGH | B20: OP-202600008-CGH | C20: CSN-OPD-780008-CGH | D20: Outpatient | E20: Demo Regional Medical Center | F20: Hospital Clinic | G20: 2026-09-09 | H20: CLINIC-L4 | I20: Hospital Outpatient Clinic Visit Level 4 | J20: 0510 | K20: 99214 | M20: 1 | N20: 410 | O20: =M20*N20 | P20: 180.45 | Q20: =P20*15% | R20: =O20-P20 | S20: Care Gap Health | T20: Care Gap Value PPO | V20: Eleanor Brooks, MD | W20: Assigned Department Provider | X20: Ambulatory | Y20: Visit close | Z20: Posted | AA20: Matched | AB20: Passed | AD20: E/M documentation | AE20: J45.40 | AF20: 22 | AG20: 2026-09-09 16:30 | AH20: Synthetic Care Gap charge; 10% below Athena allowed amount
A21: OPD-CHG-0009-ATH | B21: OP-202600009-ATH | C21: CSN-OPD-780009-ATH | D21: Outpatient | E21: Demo Regional Medical Center | F21: Hospital Clinic | G21: 2026-09-10 | H21: CLINIC-L5 | I21: Hospital Outpatient Clinic Visit Level 5 | J21: 0510 | K21: 99215 | M21: 1 | N21: 570 | O21: =M21*N21 | P21: 277.06 | Q21: =P21*20% | R21: =O21-P21 | S21: Athena Health Insurance | T21: Athena PPO | V21: Eleanor Brooks, MD | W21: Assigned Department Provider | X21: Ambulatory | Y21: Visit close | Z21: Posted | AA21: Matched | AB21: Passed | AD21: E/M documentation | AE21: I50.9 | AF21: 22 | AG21: 2026-09-10 16:30 | AH21: Synthetic Athena negotiated charge
A22: OPD-CHG-0009-CGH | B22: OP-202600009-CGH | C22: CSN-OPD-780009-CGH | D22: Outpatient | E22: Demo Regional Medical Center | F22: Hospital Clinic | G22: 2026-09-10 | H22: CLINIC-L5 | I22: Hospital Outpatient Clinic Visit Level 5 | J22: 0510 | K22: 99215 | M22: 1 | N22: 570 | O22: =M22*N22 | P22: 249.35 | Q22: =P22*15% | R22: =O22-P22 | S22: Care Gap Health | T22: Care Gap Value PPO | V22: Eleanor Brooks, MD | W22: Assigned Department Provider | X22: Ambulatory | Y22: Visit close | Z22: Posted | AA22: Matched | AB22: Passed | AD22: E/M documentation | AE22: I50.9 | AF22: 22 | AG22: 2026-09-10 16:30 | AH22: Synthetic Care Gap charge; 10% below Athena allowed amount
A23: OPD-CHG-0010-ATH | B23: OP-202600010-ATH | C23: CSN-OPD-780010-ATH | D23: Outpatient | E23: Demo Regional Medical Center | F23: Radiology | G23: 2026-09-11 | H23: XR-CHEST-2V | I23: Chest X-ray, 2 Views | J23: 0320 | K23: 71046 | M23: 1 | N23: 185 | O23: =M23*N23 | P23: 81.64 | Q23: =P23*20% | R23: =O23-P23 | S23: Athena Health Insurance | T23: Athena PPO | V23: Eleanor Brooks, MD | W23: Assigned Department Provider | X23: RIS/PACS | Y23: Exam completed | Z23: Posted | AA23: Matched | AB23: Passed | AD23: Diagnosis/LCD | AE23: R05.9 | AF23: 22 | AG23: 2026-09-11 16:30 | AH23: Synthetic Athena negotiated charge
A24: OPD-CHG-0010-CGH | B24: OP-202600010-CGH | C24: CSN-OPD-780010-CGH | D24: Outpatient | E24: Demo Regional Medical Center | F24: Radiology | G24: 2026-09-11 | H24: XR-CHEST-2V | I24: Chest X-ray, 2 Views | J24: 0320 | K24: 71046 | M24: 1 | N24: 185 | O24: =M24*N24 | P24: 73.48 | Q24: =P24*15% | R24: =O24-P24 | S24: Care Gap Health | T24: Care Gap Value PPO | V24: Eleanor Brooks, MD | W24: Assigned Department Provider | X24: RIS/PACS | Y24: Exam completed | Z24: Posted | AA24: Matched | AB24: Passed | AD24: Diagnosis/LCD | AE24: R05.9 | AF24: 22 | AG24: 2026-09-11 16:30 | AH24: Synthetic Care Gap charge; 10% below Athena allowed amount
A25: OPD-CHG-0011-ATH | B25: OP-202600011-ATH | C25: CSN-OPD-780011-ATH | D25: Outpatient | E25: Demo Regional Medical Center | F25: Radiology | G25: 2026-09-12 | H25: CT-HEAD-WO | I25: CT Head Without Contrast | J25: 0350 | K25: 70450 | M25: 1 | N25: 1900 | O25: =M25*N25 | P25: 1157.73 | Q25: =P25*20% | R25: =O25-P25 | S25: Athena Health Insurance | T25: Athena PPO | U25: AUTH-700011 | V25: Eleanor Brooks, MD | W25: Assigned Department Provider | X25: RIS/PACS | Y25: Exam completed | Z25: Posted | AA25: Matched | AB25: Passed | AD25: Prior authorization | AE25: R51.9 | AF25: 22 | AG25: 2026-09-12 16:30 | AH25: Synthetic Athena negotiated charge
A26: OPD-CHG-0011-CGH | B26: OP-202600011-CGH | C26: CSN-OPD-780011-CGH | D26: Outpatient | E26: Demo Regional Medical Center | F26: Radiology | G26: 2026-09-12 | H26: CT-HEAD-WO | I26: CT Head Without Contrast | J26: 0350 | K26: 70450 | M26: 1 | N26: 1900 | O26: =M26*N26 | P26: 1041.96 | Q26: =P26*15% | R26: =O26-P26 | S26: Care Gap Health | T26: Care Gap Value PPO | U26: AUTH-700011 | V26: Eleanor Brooks, MD | W26: Assigned Department Provider | X26: RIS/PACS | Y26: Exam completed | Z26: Posted | AA26: Matched | AB26: Passed | AD26: Prior authorization | AE26: R51.9 | AF26: 22 | AG26: 2026-09-12 16:30 | AH26: Synthetic Care Gap charge; 10% below Athena allowed amount
A27: OPD-CHG-0012-ATH | B27: OP-202600012-ATH | C27: CSN-OPD-780012-ATH | D27: Outpatient | E27: Demo Regional Medical Center | F27: Radiology | G27: 2026-09-13 | H27: CT-CHEST-W | I27: CT Chest With Contrast | J27: 0350 | K27: 71260 | M27: 1 | N27: 2500 | O27: =M27*N27 | P27: 1221.71 | Q27: =P27*20% | R27: =O27-P27 | S27: Athena Health Insurance | T27: Athena PPO | U27: AUTH-700012 | V27: Eleanor Brooks, MD | W27: Assigned Department Provider | X27: RIS/PACS | Y27: Exam completed | Z27: Posted | AA27: Matched | AB27: Passed | AD27: Prior authorization | AE27: R91.1 | AF27: 22 | AG27: 2026-09-13 16:30 | AH27: Synthetic Athena negotiated charge
A28: OPD-CHG-0012-CGH | B28: OP-202600012-CGH | C28: CSN-OPD-780012-CGH | D28: Outpatient | E28: Demo Regional Medical Center | F28: Radiology | G28: 2026-09-13 | H28: CT-CHEST-W | I28: CT Chest With Contrast | J28: 0350 | K28: 71260 | M28: 1 | N28: 2500 | O28: =M28*N28 | P28: 1099.54 | Q28: =P28*15% | R28: =O28-P28 | S28: Care Gap Health | T28: Care Gap Value PPO | U28: AUTH-700012 | V28: Eleanor Brooks, MD | W28: Assigned Department Provider | X28: RIS/PACS | Y28: Exam completed | Z28: Posted | AA28: Matched | AB28: Passed | AD28: Prior authorization | AE28: R91.1 | AF28: 22 | AG28: 2026-09-13 16:30 | AH28: Synthetic Care Gap charge; 10% below Athena allowed amount
A29: OPD-CHG-0013-ATH | B29: OP-202600013-ATH | C29: CSN-OPD-780013-ATH | D29: Outpatient | E29: Demo Regional Medical Center | F29: Radiology | G29: 2026-09-14 | H29: MRI-BRAIN-WO | I29: MRI Brain Without Contrast | J29: 0610 | K29: 70551 | M29: 1 | N29: 3250 | O29: =M29*N29 | P29: 2247.78 | Q29: =P29*20% | R29: =O29-P29 | S29: Athena Health Insurance | T29: Athena PPO | U29: AUTH-700013 | V29: Eleanor Brooks, MD | W29: Assigned Department Provider | X29: RIS/PACS | Y29: Exam completed | Z29: Posted | AA29: Matched | AB29: Passed | AD29: Prior authorization | AE29: G43.909 | AF29: 22 | AG29: 2026-09-14 16:30 | AH29: Synthetic Athena negotiated charge
A30: OPD-CHG-0013-CGH | B30: OP-202600013-CGH | C30: CSN-OPD-780013-CGH | D30: Outpatient | E30: Demo Regional Medical Center | F30: Radiology | G30: 2026-09-14 | H30: MRI-BRAIN-WO | I30: MRI Brain Without Contrast | J30: 0610 | K30: 70551 | M30: 1 | N30: 3250 | O30: =M30*N30 | P30: 2023 | Q30: =P30*15% | R30: =O30-P30 | S30: Care Gap Health | T30: Care Gap Value PPO | U30: AUTH-700013 | V30: Eleanor Brooks, MD | W30: Assigned Department Provider | X30: RIS/PACS | Y30: Exam completed | Z30: Posted | AA30: Matched | AB30: Passed | AD30: Prior authorization | AE30: G43.909 | AF30: 22 | AG30: 2026-09-14 16:30 | AH30: Synthetic Care Gap charge; 10% below Athena allowed amount
A31: OPD-CHG-0014-ATH | B31: OP-202600014-ATH | C31: CSN-OPD-780014-ATH | D31: Outpatient | E31: Demo Regional Medical Center | F31: Radiology | G31: 2026-09-15 | H31: US-ABD-COMP | I31: Ultrasound Abdomen Complete | J31: 0402 | K31: 76700 | M31: 1 | N31: 875 | O31: =M31*N31 | P31: 593.15 | Q31: =P31*20% | R31: =O31-P31 | S31: Athena Health Insurance | T31: Athena PPO | V31: Eleanor Brooks, MD | W31: Assigned Department Provider | X31: RIS/PACS | Y31: Exam completed | Z31: Posted | AA31: Matched | AB31: Passed | AD31: Diagnosis/LCD | AE31: R10.84 | AF31: 22 | AG31: 2026-09-15 16:30 | AH31: Synthetic Athena negotiated charge
A32: OPD-CHG-0014-CGH | B32: OP-202600014-CGH | C32: CSN-OPD-780014-CGH | D32: Outpatient | E32: Demo Regional Medical Center | F32: Radiology | G32: 2026-09-15 | H32: US-ABD-COMP | I32: Ultrasound Abdomen Complete | J32: 0402 | K32: 76700 | M32: 1 | N32: 875 | O32: =M32*N32 | P32: 533.84 | Q32: =P32*15% | R32: =O32-P32 | S32: Care Gap Health | T32: Care Gap Value PPO | V32: Eleanor Brooks, MD | W32: Assigned Department Provider | X32: RIS/PACS | Y32: Exam completed | Z32: Posted | AA32: Matched | AB32: Passed | AD32: Diagnosis/LCD | AE32: R10.84 | AF32: 22 | AG32: 2026-09-15 16:30 | AH32: Synthetic Care Gap charge; 10% below Athena allowed amount
A33: OPD-CHG-0015-ATH | B33: OP-202600015-ATH | C33: CSN-OPD-780015-ATH | D33: Outpatient | E33: Demo Regional Medical Center | F33: Mammography | G33: 2026-09-16 | H33: MAMMO-SCREEN | I33: Screening Mammography, Bilateral | J33: 0403 | K33: 77067 | M33: 1 | N33: 535 | O33: =M33*N33 | P33: 236.07 | Q33: =P33*20% | R33: =O33-P33 | S33: Athena Health Insurance | T33: Athena PPO | V33: Eleanor Brooks, MD | W33: Assigned Department Provider | X33: RIS/PACS | Y33: Exam completed | Z33: Posted | AA33: Matched | AB33: Passed | AD33: Preventive rule | AE33: Z12.31 | AF33: 22 | AG33: 2026-09-16 16:30 | AH33: Synthetic Athena negotiated charge
A34: OPD-CHG-0015-CGH | B34: OP-202600015-CGH | C34: CSN-OPD-780015-CGH | D34: Outpatient | E34: Demo Regional Medical Center | F34: Mammography | G34: 2026-09-16 | H34: MAMMO-SCREEN | I34: Screening Mammography, Bilateral | J34: 0403 | K34: 77067 | M34: 1 | N34: 535 | O34: =M34*N34 | P34: 212.46 | Q34: =P34*15% | R34: =O34-P34 | S34: Care Gap Health | T34: Care Gap Value PPO | V34: Eleanor Brooks, MD | W34: Assigned Department Provider | X34: RIS/PACS | Y34: Exam completed | Z34: Posted | AA34: Matched | AB34: Passed | AD34: Preventive rule | AE34: Z12.31 | AF34: 22 | AG34: 2026-09-16 16:30 | AH34: Synthetic Care Gap charge; 10% below Athena allowed amount
A35: OPD-CHG-0016-ATH | B35: OP-202600016-ATH | C35: CSN-OPD-780016-ATH | D35: Outpatient | E35: Demo Regional Medical Center | F35: Laboratory | G35: 2026-09-17 | H35: CBC-OP | I35: Complete Blood Count with Differential | J35: 0300 | K35: 85025 | M35: 1 | N35: 155 | O35: =M35*N35 | P35: 76.17 | Q35: =P35*20% | R35: =O35-P35 | S35: Athena Health Insurance | T35: Athena PPO | V35: Eleanor Brooks, MD | W35: Assigned Department Provider | X35: LIS | Y35: Final result | Z35: Posted | AA35: Matched | AB35: Passed | AD35: Diagnosis/LCD | AE35: R53.83 | AF35: 22 | AG35: 2026-09-17 16:30 | AH35: Synthetic Athena negotiated charge
A36: OPD-CHG-0016-CGH | B36: OP-202600016-CGH | C36: CSN-OPD-780016-CGH | D36: Outpatient | E36: Demo Regional Medical Center | F36: Laboratory | G36: 2026-09-17 | H36: CBC-OP | I36: Complete Blood Count with Differential | J36: 0300 | K36: 85025 | M36: 1 | N36: 155 | O36: =M36*N36 | P36: 68.55 | Q36: =P36*15% | R36: =O36-P36 | S36: Care Gap Health | T36: Care Gap Value PPO | V36: Eleanor Brooks, MD | W36: Assigned Department Provider | X36: LIS | Y36: Final result | Z36: Posted | AA36: Matched | AB36: Passed | AD36: Diagnosis/LCD | AE36: R53.83 | AF36: 22 | AG36: 2026-09-17 16:30 | AH36: Synthetic Care Gap charge; 10% below Athena allowed amount
A37: OPD-CHG-0017-ATH | B37: OP-202600017-ATH | C37: CSN-OPD-780017-ATH | D37: Outpatient | E37: Demo Regional Medical Center | F37: Laboratory | G37: 2026-09-18 | H37: BMP-OP | I37: Basic Metabolic Panel | J37: 0301 | K37: 80048 | M37: 1 | N37: 185 | O37: =M37*N37 | P37: 114.83 | Q37: =P37*20% | R37: =O37-P37 | S37: Athena Health Insurance | T37: Athena PPO | V37: Eleanor Brooks, MD | W37: Assigned Department Provider | X37: LIS | Y37: Final result | Z37: Posted | AA37: Matched | AB37: Passed | AD37: Diagnosis/LCD | AE37: I10 | AF37: 22 | AG37: 2026-09-18 16:30 | AH37: Synthetic Athena negotiated charge
A38: OPD-CHG-0017-CGH | B38: OP-202600017-CGH | C38: CSN-OPD-780017-CGH | D38: Outpatient | E38: Demo Regional Medical Center | F38: Laboratory | G38: 2026-09-18 | H38: BMP-OP | I38: Basic Metabolic Panel | J38: 0301 | K38: 80048 | M38: 1 | N38: 185 | O38: =M38*N38 | P38: 103.35 | Q38: =P38*15% | R38: =O38-P38 | S38: Care Gap Health | T38: Care Gap Value PPO | V38: Eleanor Brooks, MD | W38: Assigned Department Provider | X38: LIS | Y38: Final result | Z38: Posted | AA38: Matched | AB38: Passed | AD38: Diagnosis/LCD | AE38: I10 | AF38: 22 | AG38: 2026-09-18 16:30 | AH38: Synthetic Care Gap charge; 10% below Athena allowed amount
A39: OPD-CHG-0018-ATH | B39: OP-202600018-ATH | C39: CSN-OPD-780018-ATH | D39: Outpatient | E39: Demo Regional Medical Center | F39: Laboratory | G39: 2026-09-19 | H39: A1C-OP | I39: Hemoglobin A1c | J39: 0301 | K39: 83036 | M39: 1 | N39: 110 | O39: =M39*N39 | P39: 53.27 | Q39: =P39*20% | R39: =O39-P39 | S39: Athena Health Insurance | T39: Athena PPO | V39: Eleanor Brooks, MD | W39: Assigned Department Provider | X39: LIS | Y39: Final result | Z39: Posted | AA39: Matched | AB39: Passed | AD39: Diagnosis/LCD | AE39: E11.9 | AF39: 22 | AG39: 2026-09-19 16:30 | AH39: Synthetic Athena negotiated charge
A40: OPD-CHG-0018-CGH | B40: OP-202600018-CGH | C40: CSN-OPD-780018-CGH | D40: Outpatient | E40: Demo Regional Medical Center | F40: Laboratory | G40: 2026-09-19 | H40: A1C-OP | I40: Hemoglobin A1c | J40: 0301 | K40: 83036 | M40: 1 | N40: 110 | O40: =M40*N40 | P40: 47.94 | Q40: =P40*15% | R40: =O40-P40 | S40: Care Gap Health | T40: Care Gap Value PPO | V40: Eleanor Brooks, MD | W40: Assigned Department Provider | X40: LIS | Y40: Final result | Z40: Posted | AA40: Matched | AB40: Passed | AD40: Diagnosis/LCD | AE40: E11.9 | AF40: 22 | AG40: 2026-09-19 16:30 | AH40: Synthetic Care Gap charge; 10% below Athena allowed amount
A41: OPD-CHG-0019-ATH | B41: OP-202600019-ATH | C41: CSN-OPD-780019-ATH | D41: Outpatient | E41: Demo Regional Medical Center | F41: Laboratory | G41: 2026-09-20 | H41: LIPID-OP | I41: Lipid Panel | J41: 0301 | K41: 80061 | M41: 1 | N41: 215 | O41: =M41*N41 | P41: 98.83 | Q41: =P41*20% | R41: =O41-P41 | S41: Athena Health Insurance | T41: Athena PPO | V41: Eleanor Brooks, MD | W41: Assigned Department Provider | X41: LIS | Y41: Final result | Z41: Posted | AA41: Matched | AB41: Passed | AD41: Diagnosis/LCD | AE41: E78.5 | AF41: 22 | AG41: 2026-09-20 16:30 | AH41: Synthetic Athena negotiated charge
A42: OPD-CHG-0019-CGH | B42: OP-202600019-CGH | C42: CSN-OPD-780019-CGH | D42: Outpatient | E42: Demo Regional Medical Center | F42: Laboratory | G42: 2026-09-20 | H42: LIPID-OP | I42: Lipid Panel | J42: 0301 | K42: 80061 | M42: 1 | N42: 215 | O42: =M42*N42 | P42: 88.95 | Q42: =P42*15% | R42: =O42-P42 | S42: Care Gap Health | T42: Care Gap Value PPO | V42: Eleanor Brooks, MD | W42: Assigned Department Provider | X42: LIS | Y42: Final result | Z42: Posted | AA42: Matched | AB42: Passed | AD42: Diagnosis/LCD | AE42: E78.5 | AF42: 22 | AG42: 2026-09-20 16:30 | AH42: Synthetic Care Gap charge; 10% below Athena allowed amount
A43: OPD-CHG-0020-ATH | B43: OP-202600020-ATH | C43: CSN-OPD-780020-ATH | D43: Outpatient | E43: Demo Regional Medical Center | F43: Cardiology | G43: 2026-09-21 | H43: ECHO-COMP | I43: Complete Transthoracic Echocardiogram | J43: 0483 | K43: 93306 | M43: 1 | N43: 1550 | O43: =M43*N43 | P43: 1086.01 | Q43: =P43*20% | R43: =O43-P43 | S43: Athena Health Insurance | T43: Athena PPO | U43: AUTH-700020 | V43: Eleanor Brooks, MD | W43: Assigned Department Provider | X43: Cardiology | Y43: Test completed | Z43: Posted | AA43: Matched | AB43: Passed | AD43: Prior authorization | AE43: R01.1 | AF43: 22 | AG43: 2026-09-21 16:30 | AH43: Synthetic Athena negotiated charge
A44: OPD-CHG-0020-CGH | B44: OP-202600020-CGH | C44: CSN-OPD-780020-CGH | D44: Outpatient | E44: Demo Regional Medical Center | F44: Cardiology | G44: 2026-09-21 | H44: ECHO-COMP | I44: Complete Transthoracic Echocardiogram | J44: 0483 | K44: 93306 | M44: 1 | N44: 1550 | O44: =M44*N44 | P44: 977.41 | Q44: =P44*15% | R44: =O44-P44 | S44: Care Gap Health | T44: Care Gap Value PPO | U44: AUTH-700020 | V44: Eleanor Brooks, MD | W44: Assigned Department Provider | X44: Cardiology | Y44: Test completed | Z44: Posted | AA44: Matched | AB44: Passed | AD44: Prior authorization | AE44: R01.1 | AF44: 22 | AG44: 2026-09-21 16:30 | AH44: Synthetic Care Gap charge; 10% below Athena allowed amount
A45: OPD-CHG-0021-ATH | B45: OP-202600021-ATH | C45: CSN-OPD-780021-ATH | D45: Outpatient | E45: Demo Regional Medical Center | F45: Cardiology | G45: 2026-09-22 | H45: STRESS-TEST | I45: Cardiovascular Stress Test | J45: 0482 | K45: 93017 | M45: 1 | N45: 1150 | O45: =M45*N45 | P45: 680.01 | Q45: =P45*20% | R45: =O45-P45 | S45: Athena Health Insurance | T45: Athena PPO | U45: AUTH-700021 | V45: Eleanor Brooks, MD | W45: Assigned Department Provider | X45: Cardiology | Y45: Test completed | Z45: Posted | AA45: Matched | AB45: Passed | AD45: Prior authorization | AE45: R07.9 | AF45: 22 | AG45: 2026-09-22 16:30 | AH45: Synthetic Athena negotiated charge
A46: OPD-CHG-0021-CGH | B46: OP-202600021-CGH | C46: CSN-OPD-780021-CGH | D46: Outpatient | E46: Demo Regional Medical Center | F46: Cardiology | G46: 2026-09-22 | H46: STRESS-TEST | I46: Cardiovascular Stress Test | J46: 0482 | K46: 93017 | M46: 1 | N46: 1150 | O46: =M46*N46 | P46: 612.01 | Q46: =P46*15% | R46: =O46-P46 | S46: Care Gap Health | T46: Care Gap Value PPO | U46: AUTH-700021 | V46: Eleanor Brooks, MD | W46: Assigned Department Provider | X46: Cardiology | Y46: Test completed | Z46: Posted | AA46: Matched | AB46: Passed | AD46: Prior authorization | AE46: R07.9 | AF46: 22 | AG46: 2026-09-22 16:30 | AH46: Synthetic Care Gap charge; 10% below Athena allowed amount
A47: OPD-CHG-0022-ATH | B47: OP-202600022-ATH | C47: CSN-OPD-780022-ATH | D47: Outpatient | E47: Demo Regional Medical Center | F47: Endoscopy | G47: 2026-09-23 | H47: COLON-DX | I47: Diagnostic Colonoscopy | J47: 0750 | K47: 45378 | M47: 1 | N47: 3900 | O47: =M47*N47 | P47: 2191.03 | Q47: =P47*20% | R47: =O47-P47 | S47: Athena Health Insurance | T47: Athena PPO | U47: AUTH-700022 | V47: Eleanor Brooks, MD | W47: Assigned Department Provider | X47: Endoscopy | Y47: Procedure completed | Z47: Posted | AA47: Matched | AB47: Passed | AD47: Prior authorization | AE47: Z12.11 | AF47: 22 | AG47: 2026-09-23 16:30 | AH47: Synthetic Athena negotiated charge
A48: OPD-CHG-0022-CGH | B48: OP-202600022-CGH | C48: CSN-OPD-780022-CGH | D48: Outpatient | E48: Demo Regional Medical Center | F48: Endoscopy | G48: 2026-09-23 | H48: COLON-DX | I48: Diagnostic Colonoscopy | J48: 0750 | K48: 45378 | M48: 1 | N48: 3900 | O48: =M48*N48 | P48: 1971.93 | Q48: =P48*15% | R48: =O48-P48 | S48: Care Gap Health | T48: Care Gap Value PPO | U48: AUTH-700022 | V48: Eleanor Brooks, MD | W48: Assigned Department Provider | X48: Endoscopy | Y48: Procedure completed | Z48: Posted | AA48: Matched | AB48: Passed | AD48: Prior authorization | AE48: Z12.11 | AF48: 22 | AG48: 2026-09-23 16:30 | AH48: Synthetic Care Gap charge; 10% below Athena allowed amount
A49: OPD-CHG-0023-ATH | B49: OP-202600023-ATH | C49: CSN-OPD-780023-ATH | D49: Outpatient | E49: Demo Regional Medical Center | F49: Endoscopy | G49: 2026-09-24 | H49: EGD-DX | I49: Diagnostic Upper GI Endoscopy | J49: 0750 | K49: 43235 | M49: 1 | N49: 3300 | O49: =M49*N49 | P49: 2162.77 | Q49: =P49*20% | R49: =O49-P49 | S49: Athena Health Insurance | T49: Athena PPO | U49: AUTH-700023 | V49: Eleanor Brooks, MD | W49: Assigned Department Provider | X49: Endoscopy | Y49: Procedure completed | Z49: Posted | AA49: Matched | AB49: Review | AC49: WQ-END-04 | AD49: Prior authorization | AE49: K21.9 | AF49: 22 | AG49: 2026-09-24 16:30 | AH49: Synthetic Athena negotiated charge
A50: OPD-CHG-0023-CGH | B50: OP-202600023-CGH | C50: CSN-OPD-780023-CGH | D50: Outpatient | E50: Demo Regional Medical Center | F50: Endoscopy | G50: 2026-09-24 | H50: EGD-DX | I50: Diagnostic Upper GI Endoscopy | J50: 0750 | K50: 43235 | M50: 1 | N50: 3300 | O50: =M50*N50 | P50: 1946.49 | Q50: =P50*15% | R50: =O50-P50 | S50: Care Gap Health | T50: Care Gap Value PPO | U50: AUTH-700023 | V50: Eleanor Brooks, MD | W50: Assigned Department Provider | X50: Endoscopy | Y50: Procedure completed | Z50: Posted | AA50: Matched | AB50: Review | AC50: WQ-END-04 | AD50: Prior authorization | AE50: K21.9 | AF50: 22 | AG50: 2026-09-24 16:30 | AH50: Synthetic Care Gap charge; 10% below Athena allowed amount
A51: OPD-CHG-0024-ATH | B51: OP-202600024-ATH | C51: CSN-OPD-780024-ATH | D51: Outpatient | E51: Demo Regional Medical Center | F51: Physical Therapy | G51: 2026-09-25 | H51: PT-EVAL-OP | I51: Outpatient Physical Therapy Evaluation | J51: 0420 | K51: 97162 | M51: 1 | N51: 860 | O51: =M51*N51 | P51: 569.53 | Q51: =P51*20% | R51: =O51-P51 | S51: Athena Health Insurance | T51: Athena PPO | U51: AUTH-700024 | V51: Eleanor Brooks, MD | W51: Assigned Department Provider | X51: Therapy | Y51: Note signed | Z51: Posted | AA51: Matched | AB51: Passed | AD51: Plan benefits | AE51: M54.50 | AF51: 22 | AG51: 2026-09-25 16:30 | AH51: Synthetic Athena negotiated charge
A52: OPD-CHG-0024-CGH | B52: OP-202600024-CGH | C52: CSN-OPD-780024-CGH | D52: Outpatient | E52: Demo Regional Medical Center | F52: Physical Therapy | G52: 2026-09-25 | H52: PT-EVAL-OP | I52: Outpatient Physical Therapy Evaluation | J52: 0420 | K52: 97162 | M52: 1 | N52: 860 | O52: =M52*N52 | P52: 512.58 | Q52: =P52*15% | R52: =O52-P52 | S52: Care Gap Health | T52: Care Gap Value PPO | U52: AUTH-700024 | V52: Eleanor Brooks, MD | W52: Assigned Department Provider | X52: Therapy | Y52: Note signed | Z52: Posted | AA52: Matched | AB52: Passed | AD52: Plan benefits | AE52: M54.50 | AF52: 22 | AG52: 2026-09-25 16:30 | AH52: Synthetic Care Gap charge; 10% below Athena allowed amount
A53: OPD-CHG-0025-ATH | B53: OP-202600025-ATH | C53: CSN-OPD-780025-ATH | D53: Outpatient | E53: Demo Regional Medical Center | F53: Physical Therapy | G53: 2026-09-01 | H53: PT-THEREX-OP | I53: Therapeutic Exercise, 15 Minutes | J53: 0420 | K53: 97110 | M53: 3 | N53: 305 | O53: =M53*N53 | P53: 410.19 | Q53: =P53*20% | R53: =O53-P53 | S53: Athena Health Insurance | T53: Athena PPO | V53: Eleanor Brooks, MD | W53: Assigned Department Provider | X53: Therapy | Y53: Note signed | Z53: Posted | AA53: Matched | AB53: Passed | AD53: Timed units | AE53: M54.50 | AF53: 22 | AG53: 2026-09-01 16:30 | AH53: Synthetic Athena negotiated charge
A54: OPD-CHG-0025-CGH | B54: OP-202600025-CGH | C54: CSN-OPD-780025-CGH | D54: Outpatient | E54: Demo Regional Medical Center | F54: Physical Therapy | G54: 2026-09-01 | H54: PT-THEREX-OP | I54: Therapeutic Exercise, 15 Minutes | J54: 0420 | K54: 97110 | M54: 3 | N54: 305 | O54: =M54*N54 | P54: 369.17 | Q54: =P54*15% | R54: =O54-P54 | S54: Care Gap Health | T54: Care Gap Value PPO | V54: Eleanor Brooks, MD | W54: Assigned Department Provider | X54: Therapy | Y54: Note signed | Z54: Posted | AA54: Matched | AB54: Passed | AD54: Timed units | AE54: M54.50 | AF54: 22 | AG54: 2026-09-01 16:30 | AH54: Synthetic Care Gap charge; 10% below Athena allowed amount
A55: OPD-CHG-0026-ATH | B55: OP-202600026-ATH | C55: CSN-OPD-780026-ATH | D55: Outpatient | E55: Demo Regional Medical Center | F55: Infusion | G55: 2026-09-02 | H55: INFUSION-1H | I55: Therapeutic Infusion, Initial Hour | J55: 0260 | K55: 96365 | M55: 1 | N55: 780 | O55: =M55*N55 | P55: 481.8 | Q55: =P55*20% | R55: =O55-P55 | S55: Athena Health Insurance | T55: Athena PPO | U55: AUTH-700026 | V55: Eleanor Brooks, MD | W55: Assigned Department Provider | X55: Infusion | Y55: Administration completed | Z55: Posted | AA55: Matched | AB55: Passed | AD55: Drug policy | AE55: Z51.11 | AF55: 22 | AG55: 2026-09-02 16:30 | AH55: Synthetic Athena negotiated charge
A56: OPD-CHG-0026-CGH | B56: OP-202600026-CGH | C56: CSN-OPD-780026-CGH | D56: Outpatient | E56: Demo Regional Medical Center | F56: Infusion | G56: 2026-09-02 | H56: INFUSION-1H | I56: Therapeutic Infusion, Initial Hour | J56: 0260 | K56: 96365 | M56: 1 | N56: 780 | O56: =M56*N56 | P56: 433.62 | Q56: =P56*15% | R56: =O56-P56 | S56: Care Gap Health | T56: Care Gap Value PPO | U56: AUTH-700026 | V56: Eleanor Brooks, MD | W56: Assigned Department Provider | X56: Infusion | Y56: Administration completed | Z56: Posted | AA56: Matched | AB56: Passed | AD56: Drug policy | AE56: Z51.11 | AF56: 22 | AG56: 2026-09-02 16:30 | AH56: Synthetic Care Gap charge; 10% below Athena allowed amount
A57: OPD-CHG-0027-ATH | B57: OP-202600027-ATH | C57: CSN-OPD-780027-ATH | D57: Outpatient | E57: Demo Regional Medical Center | F57: Chemotherapy | G57: 2026-09-03 | H57: CHEMO-1H | I57: Chemotherapy Infusion, Initial Hour | J57: 0335 | K57: 96413 | M57: 1 | N57: 1850 | O57: =M57*N57 | P57: 973.64 | Q57: =P57*20% | R57: =O57-P57 | S57: Athena Health Insurance | T57: Athena PPO | U57: AUTH-700027 | V57: Eleanor Brooks, MD | W57: Assigned Department Provider | X57: Infusion | Y57: Administration completed | Z57: Posted | AA57: Matched | AB57: Passed | AD57: Drug policy | AE57: C50.919 | AF57: 22 | AG57: 2026-09-03 16:30 | AH57: Synthetic Athena negotiated charge
A58: OPD-CHG-0027-CGH | B58: OP-202600027-CGH | C58: CSN-OPD-780027-CGH | D58: Outpatient | E58: Demo Regional Medical Center | F58: Chemotherapy | G58: 2026-09-03 | H58: CHEMO-1H | I58: Chemotherapy Infusion, Initial Hour | J58: 0335 | K58: 96413 | M58: 1 | N58: 1850 | O58: =M58*N58 | P58: 876.28 | Q58: =P58*15% | R58: =O58-P58 | S58: Care Gap Health | T58: Care Gap Value PPO | U58: AUTH-700027 | V58: Eleanor Brooks, MD | W58: Assigned Department Provider | X58: Infusion | Y58: Administration completed | Z58: Posted | AA58: Matched | AB58: Passed | AD58: Drug policy | AE58: C50.919 | AF58: 22 | AG58: 2026-09-03 16:30 | AH58: Synthetic Care Gap charge; 10% below Athena allowed amount
A59: OPD-CHG-0028-ATH | B59: OP-202600028-ATH | C59: CSN-OPD-780028-ATH | D59: Outpatient | E59: Demo Regional Medical Center | F59: Behavioral Health | G59: 2026-09-04 | H59: BH-INDIVIDUAL | I59: Outpatient Psychotherapy, 45 Minutes | J59: 0914 | K59: 90834 | M59: 1 | N59: 285 | O59: =M59*N59 | P59: 154.85 | Q59: =P59*20% | R59: =O59-P59 | S59: Athena Health Insurance | T59: Athena PPO | V59: Eleanor Brooks, MD | W59: Assigned Department Provider | X59: Behavioral Health | Y59: Note signed | Z59: Posted | AA59: Matched | AB59: Passed | AD59: Benefits | AE59: F41.1 | AF59: 22 | AG59: 2026-09-04 16:30 | AH59: Synthetic Athena negotiated charge
A60: OPD-CHG-0028-CGH | B60: OP-202600028-CGH | C60: CSN-OPD-780028-CGH | D60: Outpatient | E60: Demo Regional Medical Center | F60: Behavioral Health | G60: 2026-09-04 | H60: BH-INDIVIDUAL | I60: Outpatient Psychotherapy, 45 Minutes | J60: 0914 | K60: 90834 | M60: 1 | N60: 285 | O60: =M60*N60 | P60: 139.37 | Q60: =P60*15% | R60: =O60-P60 | S60: Care Gap Health | T60: Care Gap Value PPO | V60: Eleanor Brooks, MD | W60: Assigned Department Provider | X60: Behavioral Health | Y60: Note signed | Z60: Posted | AA60: Matched | AB60: Passed | AD60: Benefits | AE60: F41.1 | AF60: 22 | AG60: 2026-09-04 16:30 | AH60: Synthetic Care Gap charge; 10% below Athena allowed amount
A61: OPD-CHG-0029-ATH | B61: OP-202600029-ATH | C61: CSN-OPD-780029-ATH | D61: Outpatient | E61: Demo Regional Medical Center | F61: Emergency Department | G61: 2026-09-05 | H61: ED-LEVEL-1 | I61: Emergency Department Visit Level 1 | J61: 0450 | K61: 99281 | M61: 1 | N61: 360 | O61: =M61*N61 | P61: 244.49 | Q61: =P61*20% | R61: =O61-P61 | S61: Athena Health Insurance | T61: Athena PPO | V61: Eleanor Brooks, MD | W61: Assigned Department Provider | X61: ED | Y61: Encounter close | Z61: Hold | AA61: Exception | AB61: Review | AC61: WQ-EME-02 | AD61: Documentation | AE61: R50.9 | AF61: 22 | AG61: 2026-09-05 16:30 | AH61: Synthetic Athena negotiated charge
A62: OPD-CHG-0029-CGH | B62: OP-202600029-CGH | C62: CSN-OPD-780029-CGH | D62: Outpatient | E62: Demo Regional Medical Center | F62: Emergency Department | G62: 2026-09-05 | H62: ED-LEVEL-1 | I62: Emergency Department Visit Level 1 | J62: 0450 | K62: 99281 | M62: 1 | N62: 360 | O62: =M62*N62 | P62: 220.04 | Q62: =P62*15% | R62: =O62-P62 | S62: Care Gap Health | T62: Care Gap Value PPO | V62: Eleanor Brooks, MD | W62: Assigned Department Provider | X62: ED | Y62: Encounter close | Z62: Hold | AA62: Exception | AB62: Review | AC62: WQ-EME-02 | AD62: Documentation | AE62: R50.9 | AF62: 22 | AG62: 2026-09-05 16:30 | AH62: Synthetic Care Gap charge; 10% below Athena allowed amount
A63: OPD-CHG-0030-ATH | B63: OP-202600030-ATH | C63: CSN-OPD-780030-ATH | D63: Outpatient | E63: Demo Regional Medical Center | F63: Emergency Department | G63: 2026-09-06 | H63: ED-LEVEL-2 | I63: Emergency Department Visit Level 2 | J63: 0450 | K63: 99282 | M63: 1 | N63: 670 | O63: =M63*N63 | P63: 292.29 | Q63: =P63*20% | R63: =O63-P63 | S63: Athena Health Insurance | T63: Athena PPO | V63: Eleanor Brooks, MD | W63: Assigned Department Provider | X63: ED | Y63: Encounter close | Z63: Posted | AA63: Matched | AB63: Passed | AD63: Documentation | AE63: R51.9 | AF63: 22 | AG63: 2026-09-06 16:30 | AH63: Synthetic Athena negotiated charge
A64: OPD-CHG-0030-CGH | B64: OP-202600030-CGH | C64: CSN-OPD-780030-CGH | D64: Outpatient | E64: Demo Regional Medical Center | F64: Emergency Department | G64: 2026-09-06 | H64: ED-LEVEL-2 | I64: Emergency Department Visit Level 2 | J64: 0450 | K64: 99282 | M64: 1 | N64: 670 | O64: =M64*N64 | P64: 263.06 | Q64: =P64*15% | R64: =O64-P64 | S64: Care Gap Health | T64: Care Gap Value PPO | V64: Eleanor Brooks, MD | W64: Assigned Department Provider | X64: ED | Y64: Encounter close | Z64: Posted | AA64: Matched | AB64: Passed | AD64: Documentation | AE64: R51.9 | AF64: 22 | AG64: 2026-09-06 16:30 | AH64: Synthetic Care Gap charge; 10% below Athena allowed amount
A65: OPD-CHG-0031-ATH | B65: OP-202600031-ATH | C65: CSN-OPD-780031-ATH | D65: Outpatient | E65: Demo Regional Medical Center | F65: Emergency Department | G65: 2026-09-07 | H65: ED-LEVEL-3 | I65: Emergency Department Visit Level 3 | J65: 0450 | K65: 99283 | M65: 1 | N65: 1280 | O65: =M65*N65 | P65: 788.53 | Q65: =P65*20% | R65: =O65-P65 | S65: Athena Health Insurance | T65: Athena PPO | V65: Eleanor Brooks, MD | W65: Assigned Department Provider | X65: ED | Y65: Encounter close | Z65: Posted | AA65: Matched | AB65: Passed | AD65: Documentation | AE65: R10.9 | AF65: 22 | AG65: 2026-09-07 16:30 | AH65: Synthetic Athena negotiated charge
A66: OPD-CHG-0031-CGH | B66: OP-202600031-CGH | C66: CSN-OPD-780031-CGH | D66: Outpatient | E66: Demo Regional Medical Center | F66: Emergency Department | G66: 2026-09-07 | H66: ED-LEVEL-3 | I66: Emergency Department Visit Level 3 | J66: 0450 | K66: 99283 | M66: 1 | N66: 1280 | O66: =M66*N66 | P66: 709.68 | Q66: =P66*15% | R66: =O66-P66 | S66: Care Gap Health | T66: Care Gap Value PPO | V66: Eleanor Brooks, MD | W66: Assigned Department Provider | X66: ED | Y66: Encounter close | Z66: Posted | AA66: Matched | AB66: Passed | AD66: Documentation | AE66: R10.9 | AF66: 22 | AG66: 2026-09-07 16:30 | AH66: Synthetic Care Gap charge; 10% below Athena allowed amount
A67: OPD-CHG-0032-ATH | B67: OP-202600032-ATH | C67: CSN-OPD-780032-ATH | D67: Outpatient | E67: Demo Regional Medical Center | F67: Emergency Department | G67: 2026-09-08 | H67: ED-LEVEL-4 | I67: Emergency Department Visit Level 4 | J67: 0450 | K67: 99284 | M67: 1 | N67: 2350 | O67: =M67*N67 | P67: 1442.56 | Q67: =P67*20% | R67: =O67-P67 | S67: Athena Health Insurance | T67: Athena PPO | V67: Eleanor Brooks, MD | W67: Assigned Department Provider | X67: ED | Y67: Encounter close | Z67: Posted | AA67: Matched | AB67: Passed | AD67: Documentation | AE67: R06.02 | AF67: 22 | AG67: 2026-09-08 16:30 | AH67: Synthetic Athena negotiated charge
A68: OPD-CHG-0032-CGH | B68: OP-202600032-CGH | C68: CSN-OPD-780032-CGH | D68: Outpatient | E68: Demo Regional Medical Center | F68: Emergency Department | G68: 2026-09-08 | H68: ED-LEVEL-4 | I68: Emergency Department Visit Level 4 | J68: 0450 | K68: 99284 | M68: 1 | N68: 2350 | O68: =M68*N68 | P68: 1298.3 | Q68: =P68*15% | R68: =O68-P68 | S68: Care Gap Health | T68: Care Gap Value PPO | V68: Eleanor Brooks, MD | W68: Assigned Department Provider | X68: ED | Y68: Encounter close | Z68: Posted | AA68: Matched | AB68: Passed | AD68: Documentation | AE68: R06.02 | AF68: 22 | AG68: 2026-09-08 16:30 | AH68: Synthetic Care Gap charge; 10% below Athena allowed amount
A69: OPD-CHG-0033-ATH | B69: OP-202600033-ATH | C69: CSN-OPD-780033-ATH | D69: Outpatient | E69: Demo Regional Medical Center | F69: Emergency Department | G69: 2026-09-09 | H69: ED-LEVEL-5 | I69: Emergency Department Visit Level 5 | J69: 0450 | K69: 99285 | M69: 1 | N69: 4300 | O69: =M69*N69 | P69: 1884.19 | Q69: =P69*20% | R69: =O69-P69 | S69: Athena Health Insurance | T69: Athena PPO | V69: Eleanor Brooks, MD | W69: Assigned Department Provider | X69: ED | Y69: Encounter close | Z69: Posted | AA69: Matched | AB69: Passed | AD69: Documentation | AE69: R07.9 | AF69: 22 | AG69: 2026-09-09 16:30 | AH69: Synthetic Athena negotiated charge
A70: OPD-CHG-0033-CGH | B70: OP-202600033-CGH | C70: CSN-OPD-780033-CGH | D70: Outpatient | E70: Demo Regional Medical Center | F70: Emergency Department | G70: 2026-09-09 | H70: ED-LEVEL-5 | I70: Emergency Department Visit Level 5 | J70: 0450 | K70: 99285 | M70: 1 | N70: 4300 | O70: =M70*N70 | P70: 1695.77 | Q70: =P70*15% | R70: =O70-P70 | S70: Care Gap Health | T70: Care Gap Value PPO | V70: Eleanor Brooks, MD | W70: Assigned Department Provider | X70: ED | Y70: Encounter close | Z70: Posted | AA70: Matched | AB70: Passed | AD70: Documentation | AE70: R07.9 | AF70: 22 | AG70: 2026-09-09 16:30 | AH70: Synthetic Care Gap charge; 10% below Athena allowed amount
A71: OPD-CHG-0034-ATH | B71: OP-202600034-ATH | C71: CSN-OPD-780034-ATH | D71: Outpatient | E71: Demo Regional Medical Center | F71: Hospital Clinic | G71: 2026-09-10 | H71: CLINIC-L2 | I71: Hospital Outpatient Clinic Visit Level 2 | J71: 0510 | K71: 99212 | M71: 1 | N71: 215 | O71: =M71*N71 | P71: 137.27 | Q71: =P71*20% | R71: =O71-P71 | S71: Athena Health Insurance | T71: Athena PPO | V71: Eleanor Brooks, MD | W71: Assigned Department Provider | X71: Ambulatory | Y71: Visit close | Z71: Posted | AA71: Matched | AB71: Passed | AD71: E/M documentation | AE71: I10 | AF71: 22 | AG71: 2026-09-10 16:30 | AH71: Synthetic Athena negotiated charge
A72: OPD-CHG-0034-CGH | B72: OP-202600034-CGH | C72: CSN-OPD-780034-CGH | D72: Outpatient | E72: Demo Regional Medical Center | F72: Hospital Clinic | G72: 2026-09-10 | H72: CLINIC-L2 | I72: Hospital Outpatient Clinic Visit Level 2 | J72: 0510 | K72: 99212 | M72: 1 | N72: 215 | O72: =M72*N72 | P72: 123.54 | Q72: =P72*15% | R72: =O72-P72 | S72: Care Gap Health | T72: Care Gap Value PPO | V72: Eleanor Brooks, MD | W72: Assigned Department Provider | X72: Ambulatory | Y72: Visit close | Z72: Posted | AA72: Matched | AB72: Passed | AD72: E/M documentation | AE72: I10 | AF72: 22 | AG72: 2026-09-10 16:30 | AH72: Synthetic Care Gap charge; 10% below Athena allowed amount
A73: OPD-CHG-0035-ATH | B73: OP-202600035-ATH | C73: CSN-OPD-780035-ATH | D73: Outpatient | E73: Demo Regional Medical Center | F73: Hospital Clinic | G73: 2026-09-11 | H73: CLINIC-L3 | I73: Hospital Outpatient Clinic Visit Level 3 | J73: 0510 | K73: 99213 | M73: 1 | N73: 315 | O73: =M73*N73 | P73: 207.96 | Q73: =P73*20% | R73: =O73-P73 | S73: Athena Health Insurance | T73: Athena PPO | V73: Eleanor Brooks, MD | W73: Assigned Department Provider | X73: Ambulatory | Y73: Visit close | Z73: Posted | AA73: Matched | AB73: Passed | AD73: E/M documentation | AE73: E11.9 | AF73: 22 | AG73: 2026-09-11 16:30 | AH73: Synthetic Athena negotiated charge
A74: OPD-CHG-0035-CGH | B74: OP-202600035-CGH | C74: CSN-OPD-780035-CGH | D74: Outpatient | E74: Demo Regional Medical Center | F74: Hospital Clinic | G74: 2026-09-11 | H74: CLINIC-L3 | I74: Hospital Outpatient Clinic Visit Level 3 | J74: 0510 | K74: 99213 | M74: 1 | N74: 315 | O74: =M74*N74 | P74: 187.16 | Q74: =P74*15% | R74: =O74-P74 | S74: Care Gap Health | T74: Care Gap Value PPO | V74: Eleanor Brooks, MD | W74: Assigned Department Provider | X74: Ambulatory | Y74: Visit close | Z74: Posted | AA74: Matched | AB74: Passed | AD74: E/M documentation | AE74: E11.9 | AF74: 22 | AG74: 2026-09-11 16:30 | AH74: Synthetic Care Gap charge; 10% below Athena allowed amount
A75: OPD-CHG-0036-ATH | B75: OP-202600036-ATH | C75: CSN-OPD-780036-ATH | D75: Outpatient | E75: Demo Regional Medical Center | F75: Hospital Clinic | G75: 2026-09-12 | H75: CLINIC-L4 | I75: Hospital Outpatient Clinic Visit Level 4 | J75: 0510 | K75: 99214 | M75: 1 | N75: 410 | O75: =M75*N75 | P75: 185.64 | Q75: =P75*20% | R75: =O75-P75 | S75: Athena Health Insurance | T75: Athena PPO | V75: Eleanor Brooks, MD | W75: Assigned Department Provider | X75: Ambulatory | Y75: Visit close | Z75: Posted | AA75: Matched | AB75: Passed | AD75: E/M documentation | AE75: J45.40 | AF75: 22 | AG75: 2026-09-12 16:30 | AH75: Synthetic Athena negotiated charge
A76: OPD-CHG-0036-CGH | B76: OP-202600036-CGH | C76: CSN-OPD-780036-CGH | D76: Outpatient | E76: Demo Regional Medical Center | F76: Hospital Clinic | G76: 2026-09-12 | H76: CLINIC-L4 | I76: Hospital Outpatient Clinic Visit Level 4 | J76: 0510 | K76: 99214 | M76: 1 | N76: 410 | O76: =M76*N76 | P76: 167.08 | Q76: =P76*15% | R76: =O76-P76 | S76: Care Gap Health | T76: Care Gap Value PPO | V76: Eleanor Brooks, MD | W76: Assigned Department Provider | X76: Ambulatory | Y76: Visit close | Z76: Posted | AA76: Matched | AB76: Passed | AD76: E/M documentation | AE76: J45.40 | AF76: 22 | AG76: 2026-09-12 16:30 | AH76: Synthetic Care Gap charge; 10% below Athena allowed amount
A77: OPD-CHG-0037-ATH | B77: OP-202600037-ATH | C77: CSN-OPD-780037-ATH | D77: Outpatient | E77: Demo Regional Medical Center | F77: Hospital Clinic | G77: 2026-09-13 | H77: CLINIC-L5 | I77: Hospital Outpatient Clinic Visit Level 5 | J77: 0510 | K77: 99215 | M77: 1 | N77: 570 | O77: =M77*N77 | P77: 272.16 | Q77: =P77*20% | R77: =O77-P77 | S77: Athena Health Insurance | T77: Athena PPO | V77: Eleanor Brooks, MD | W77: Assigned Department Provider | X77: Ambulatory | Y77: Visit close | Z77: Posted | AA77: Matched | AB77: Passed | AD77: E/M documentation | AE77: I50.9 | AF77: 22 | AG77: 2026-09-13 16:30 | AH77: Synthetic Athena negotiated charge
A78: OPD-CHG-0037-CGH | B78: OP-202600037-CGH | C78: CSN-OPD-780037-CGH | D78: Outpatient | E78: Demo Regional Medical Center | F78: Hospital Clinic | G78: 2026-09-13 | H78: CLINIC-L5 | I78: Hospital Outpatient Clinic Visit Level 5 | J78: 0510 | K78: 99215 | M78: 1 | N78: 570 | O78: =M78*N78 | P78: 244.94 | Q78: =P78*15% | R78: =O78-P78 | S78: Care Gap Health | T78: Care Gap Value PPO | V78: Eleanor Brooks, MD | W78: Assigned Department Provider | X78: Ambulatory | Y78: Visit close | Z78: Posted | AA78: Matched | AB78: Passed | AD78: E/M documentation | AE78: I50.9 | AF78: 22 | AG78: 2026-09-13 16:30 | AH78: Synthetic Care Gap charge; 10% below Athena allowed amount
A79: OPD-CHG-0038-ATH | B79: OP-202600038-ATH | C79: CSN-OPD-780038-ATH | D79: Outpatient | E79: Demo Regional Medical Center | F79: Radiology | G79: 2026-09-14 | H79: XR-CHEST-2V | I79: Chest X-ray, 2 Views | J79: 0320 | K79: 71046 | M79: 1 | N79: 185 | O79: =M79*N79 | P79: 107.46 | Q79: =P79*20% | R79: =O79-P79 | S79: Athena Health Insurance | T79: Athena PPO | V79: Eleanor Brooks, MD | W79: Assigned Department Provider | X79: RIS/PACS | Y79: Exam completed | Z79: Posted | AA79: Matched | AB79: Passed | AD79: Diagnosis/LCD | AE79: R05.9 | AF79: 22 | AG79: 2026-09-14 16:30 | AH79: Synthetic Athena negotiated charge
A80: OPD-CHG-0038-CGH | B80: OP-202600038-CGH | C80: CSN-OPD-780038-CGH | D80: Outpatient | E80: Demo Regional Medical Center | F80: Radiology | G80: 2026-09-14 | H80: XR-CHEST-2V | I80: Chest X-ray, 2 Views | J80: 0320 | K80: 71046 | M80: 1 | N80: 185 | O80: =M80*N80 | P80: 96.71 | Q80: =P80*15% | R80: =O80-P80 | S80: Care Gap Health | T80: Care Gap Value PPO | V80: Eleanor Brooks, MD | W80: Assigned Department Provider | X80: RIS/PACS | Y80: Exam completed | Z80: Posted | AA80: Matched | AB80: Passed | AD80: Diagnosis/LCD | AE80: R05.9 | AF80: 22 | AG80: 2026-09-14 16:30 | AH80: Synthetic Care Gap charge; 10% below Athena allowed amount
A81: OPD-CHG-0039-ATH | B81: OP-202600039-ATH | C81: CSN-OPD-780039-ATH | D81: Outpatient | E81: Demo Regional Medical Center | F81: Radiology | G81: 2026-09-15 | H81: CT-HEAD-WO | I81: CT Head Without Contrast | J81: 0350 | K81: 70450 | M81: 1 | N81: 1900 | O81: =M81*N81 | P81: 877.9 | Q81: =P81*20% | R81: =O81-P81 | S81: Athena Health Insurance | T81: Athena PPO | U81: AUTH-700039 | V81: Eleanor Brooks, MD | W81: Assigned Department Provider | X81: RIS/PACS | Y81: Exam completed | Z81: Posted | AA81: Matched | AB81: Passed | AD81: Prior authorization | AE81: R51.9 | AF81: 22 | AG81: 2026-09-15 16:30 | AH81: Synthetic Athena negotiated charge
A82: OPD-CHG-0039-CGH | B82: OP-202600039-CGH | C82: CSN-OPD-780039-CGH | D82: Outpatient | E82: Demo Regional Medical Center | F82: Radiology | G82: 2026-09-15 | H82: CT-HEAD-WO | I82: CT Head Without Contrast | J82: 0350 | K82: 70450 | M82: 1 | N82: 1900 | O82: =M82*N82 | P82: 790.11 | Q82: =P82*15% | R82: =O82-P82 | S82: Care Gap Health | T82: Care Gap Value PPO | U82: AUTH-700039 | V82: Eleanor Brooks, MD | W82: Assigned Department Provider | X82: RIS/PACS | Y82: Exam completed | Z82: Posted | AA82: Matched | AB82: Passed | AD82: Prior authorization | AE82: R51.9 | AF82: 22 | AG82: 2026-09-15 16:30 | AH82: Synthetic Care Gap charge; 10% below Athena allowed amount
A83: OPD-CHG-0040-ATH | B83: OP-202600040-ATH | C83: CSN-OPD-780040-ATH | D83: Outpatient | E83: Demo Regional Medical Center | F83: Radiology | G83: 2026-09-16 | H83: CT-CHEST-W | I83: CT Chest With Contrast | J83: 0350 | K83: 71260 | M83: 1 | N83: 2500 | O83: =M83*N83 | P83: 1187.62 | Q83: =P83*20% | R83: =O83-P83 | S83: Athena Health Insurance | T83: Athena PPO | U83: AUTH-700040 | V83: Eleanor Brooks, MD | W83: Assigned Department Provider | X83: RIS/PACS | Y83: Exam completed | Z83: Posted | AA83: Matched | AB83: Passed | AD83: Prior authorization | AE83: R91.1 | AF83: 22 | AG83: 2026-09-16 16:30 | AH83: Synthetic Athena negotiated charge
A84: OPD-CHG-0040-CGH | B84: OP-202600040-CGH | C84: CSN-OPD-780040-CGH | D84: Outpatient | E84: Demo Regional Medical Center | F84: Radiology | G84: 2026-09-16 | H84: CT-CHEST-W | I84: CT Chest With Contrast | J84: 0350 | K84: 71260 | M84: 1 | N84: 2500 | O84: =M84*N84 | P84: 1068.86 | Q84: =P84*15% | R84: =O84-P84 | S84: Care Gap Health | T84: Care Gap Value PPO | U84: AUTH-700040 | V84: Eleanor Brooks, MD | W84: Assigned Department Provider | X84: RIS/PACS | Y84: Exam completed | Z84: Posted | AA84: Matched | AB84: Passed | AD84: Prior authorization | AE84: R91.1 | AF84: 22 | AG84: 2026-09-16 16:30 | AH84: Synthetic Care Gap charge; 10% below Athena allowed amount
A85: OPD-CHG-0041-ATH | B85: OP-202600041-ATH | C85: CSN-OPD-780041-ATH | D85: Outpatient | E85: Demo Regional Medical Center | F85: Radiology | G85: 2026-09-17 | H85: MRI-BRAIN-WO | I85: MRI Brain Without Contrast | J85: 0610 | K85: 70551 | M85: 1 | N85: 3250 | O85: =M85*N85 | P85: 1816.06 | Q85: =P85*20% | R85: =O85-P85 | S85: Athena Health Insurance | T85: Athena PPO | U85: AUTH-700041 | V85: Eleanor Brooks, MD | W85: Assigned Department Provider | X85: RIS/PACS | Y85: Exam completed | Z85: Posted | AA85: Matched | AB85: Passed | AD85: Prior authorization | AE85: G43.909 | AF85: 22 | AG85: 2026-09-17 16:30 | AH85: Synthetic Athena negotiated charge
A86: OPD-CHG-0041-CGH | B86: OP-202600041-CGH | C86: CSN-OPD-780041-CGH | D86: Outpatient | E86: Demo Regional Medical Center | F86: Radiology | G86: 2026-09-17 | H86: MRI-BRAIN-WO | I86: MRI Brain Without Contrast | J86: 0610 | K86: 70551 | M86: 1 | N86: 3250 | O86: =M86*N86 | P86: 1634.45 | Q86: =P86*15% | R86: =O86-P86 | S86: Care Gap Health | T86: Care Gap Value PPO | U86: AUTH-700041 | V86: Eleanor Brooks, MD | W86: Assigned Department Provider | X86: RIS/PACS | Y86: Exam completed | Z86: Posted | AA86: Matched | AB86: Passed | AD86: Prior authorization | AE86: G43.909 | AF86: 22 | AG86: 2026-09-17 16:30 | AH86: Synthetic Care Gap charge; 10% below Athena allowed amount
A87: OPD-CHG-0042-ATH | B87: OP-202600042-ATH | C87: CSN-OPD-780042-ATH | D87: Outpatient | E87: Demo Regional Medical Center | F87: Radiology | G87: 2026-09-18 | H87: US-ABD-COMP | I87: Ultrasound Abdomen Complete | J87: 0402 | K87: 76700 | M87: 1 | N87: 875 | O87: =M87*N87 | P87: 597.05 | Q87: =P87*20% | R87: =O87-P87 | S87: Athena Health Insurance | T87: Athena PPO | V87: Eleanor Brooks, MD | W87: Assigned Department Provider | X87: RIS/PACS | Y87: Exam completed | Z87: Posted | AA87: Matched | AB87: Passed | AD87: Diagnosis/LCD | AE87: R10.84 | AF87: 22 | AG87: 2026-09-18 16:30 | AH87: Synthetic Athena negotiated charge
A88: OPD-CHG-0042-CGH | B88: OP-202600042-CGH | C88: CSN-OPD-780042-CGH | D88: Outpatient | E88: Demo Regional Medical Center | F88: Radiology | G88: 2026-09-18 | H88: US-ABD-COMP | I88: Ultrasound Abdomen Complete | J88: 0402 | K88: 76700 | M88: 1 | N88: 875 | O88: =M88*N88 | P88: 537.35 | Q88: =P88*15% | R88: =O88-P88 | S88: Care Gap Health | T88: Care Gap Value PPO | V88: Eleanor Brooks, MD | W88: Assigned Department Provider | X88: RIS/PACS | Y88: Exam completed | Z88: Posted | AA88: Matched | AB88: Passed | AD88: Diagnosis/LCD | AE88: R10.84 | AF88: 22 | AG88: 2026-09-18 16:30 | AH88: Synthetic Care Gap charge; 10% below Athena allowed amount
A89: OPD-CHG-0043-ATH | B89: OP-202600043-ATH | C89: CSN-OPD-780043-ATH | D89: Outpatient | E89: Demo Regional Medical Center | F89: Mammography | G89: 2026-09-19 | H89: MAMMO-SCREEN | I89: Screening Mammography, Bilateral | J89: 0403 | K89: 77067 | M89: 1 | N89: 535 | O89: =M89*N89 | P89: 236.8 | Q89: =P89*20% | R89: =O89-P89 | S89: Athena Health Insurance | T89: Athena PPO | V89: Eleanor Brooks, MD | W89: Assigned Department Provider | X89: RIS/PACS | Y89: Exam completed | Z89: Posted | AA89: Matched | AB89: Passed | AD89: Preventive rule | AE89: Z12.31 | AF89: 22 | AG89: 2026-09-19 16:30 | AH89: Synthetic Athena negotiated charge
A90: OPD-CHG-0043-CGH | B90: OP-202600043-CGH | C90: CSN-OPD-780043-CGH | D90: Outpatient | E90: Demo Regional Medical Center | F90: Mammography | G90: 2026-09-19 | H90: MAMMO-SCREEN | I90: Screening Mammography, Bilateral | J90: 0403 | K90: 77067 | M90: 1 | N90: 535 | O90: =M90*N90 | P90: 213.12 | Q90: =P90*15% | R90: =O90-P90 | S90: Care Gap Health | T90: Care Gap Value PPO | V90: Eleanor Brooks, MD | W90: Assigned Department Provider | X90: RIS/PACS | Y90: Exam completed | Z90: Posted | AA90: Matched | AB90: Passed | AD90: Preventive rule | AE90: Z12.31 | AF90: 22 | AG90: 2026-09-19 16:30 | AH90: Synthetic Care Gap charge; 10% below Athena allowed amount
A91: OPD-CHG-0044-ATH | B91: OP-202600044-ATH | C91: CSN-OPD-780044-ATH | D91: Outpatient | E91: Demo Regional Medical Center | F91: Laboratory | G91: 2026-09-20 | H91: CBC-OP | I91: Complete Blood Count with Differential | J91: 0300 | K91: 85025 | M91: 1 | N91: 155 | O91: =M91*N91 | P91: 102.67 | Q91: =P91*20% | R91: =O91-P91 | S91: Athena Health Insurance | T91: Athena PPO | V91: Eleanor Brooks, MD | W91: Assigned Department Provider | X91: LIS | Y91: Final result | Z91: Posted | AA91: Matched | AB91: Passed | AD91: Diagnosis/LCD | AE91: R53.83 | AF91: 22 | AG91: 2026-09-20 16:30 | AH91: Synthetic Athena negotiated charge
A92: OPD-CHG-0044-CGH | B92: OP-202600044-CGH | C92: CSN-OPD-780044-CGH | D92: Outpatient | E92: Demo Regional Medical Center | F92: Laboratory | G92: 2026-09-20 | H92: CBC-OP | I92: Complete Blood Count with Differential | J92: 0300 | K92: 85025 | M92: 1 | N92: 155 | O92: =M92*N92 | P92: 92.4 | Q92: =P92*15% | R92: =O92-P92 | S92: Care Gap Health | T92: Care Gap Value PPO | V92: Eleanor Brooks, MD | W92: Assigned Department Provider | X92: LIS | Y92: Final result | Z92: Posted | AA92: Matched | AB92: Passed | AD92: Diagnosis/LCD | AE92: R53.83 | AF92: 22 | AG92: 2026-09-20 16:30 | AH92: Synthetic Care Gap charge; 10% below Athena allowed amount
A93: OPD-CHG-0045-ATH | B93: OP-202600045-ATH | C93: CSN-OPD-780045-ATH | D93: Outpatient | E93: Demo Regional Medical Center | F93: Laboratory | G93: 2026-09-21 | H93: BMP-OP | I93: Basic Metabolic Panel | J93: 0301 | K93: 80048 | M93: 1 | N93: 185 | O93: =M93*N93 | P93: 125.21 | Q93: =P93*20% | R93: =O93-P93 | S93: Athena Health Insurance | T93: Athena PPO | V93: Eleanor Brooks, MD | W93: Assigned Department Provider | X93: LIS | Y93: Final result | Z93: Posted | AA93: Matched | AB93: Passed | AD93: Diagnosis/LCD | AE93: I10 | AF93: 22 | AG93: 2026-09-21 16:30 | AH93: Synthetic Athena negotiated charge
A94: OPD-CHG-0045-CGH | B94: OP-202600045-CGH | C94: CSN-OPD-780045-CGH | D94: Outpatient | E94: Demo Regional Medical Center | F94: Laboratory | G94: 2026-09-21 | H94: BMP-OP | I94: Basic Metabolic Panel | J94: 0301 | K94: 80048 | M94: 1 | N94: 185 | O94: =M94*N94 | P94: 112.69 | Q94: =P94*15% | R94: =O94-P94 | S94: Care Gap Health | T94: Care Gap Value PPO | V94: Eleanor Brooks, MD | W94: Assigned Department Provider | X94: LIS | Y94: Final result | Z94: Posted | AA94: Matched | AB94: Passed | AD94: Diagnosis/LCD | AE94: I10 | AF94: 22 | AG94: 2026-09-21 16:30 | AH94: Synthetic Care Gap charge; 10% below Athena allowed amount
A95: OPD-CHG-0046-ATH | B95: OP-202600046-ATH | C95: CSN-OPD-780046-ATH | D95: Outpatient | E95: Demo Regional Medical Center | F95: Laboratory | G95: 2026-09-22 | H95: A1C-OP | I95: Hemoglobin A1c | J95: 0301 | K95: 83036 | M95: 1 | N95: 110 | O95: =M95*N95 | P95: 49.43 | Q95: =P95*20% | R95: =O95-P95 | S95: Athena Health Insurance | T95: Athena PPO | V95: Eleanor Brooks, MD | W95: Assigned Department Provider | X95: LIS | Y95: Final result | Z95: Posted | AA95: Matched | AB95: Review | AC95: WQ-LAB-03 | AD95: Diagnosis/LCD | AE95: E11.9 | AF95: 22 | AG95: 2026-09-22 16:30 | AH95: Synthetic Athena negotiated charge
A96: OPD-CHG-0046-CGH | B96: OP-202600046-CGH | C96: CSN-OPD-780046-CGH | D96: Outpatient | E96: Demo Regional Medical Center | F96: Laboratory | G96: 2026-09-22 | H96: A1C-OP | I96: Hemoglobin A1c | J96: 0301 | K96: 83036 | M96: 1 | N96: 110 | O96: =M96*N96 | P96: 44.49 | Q96: =P96*15% | R96: =O96-P96 | S96: Care Gap Health | T96: Care Gap Value PPO | V96: Eleanor Brooks, MD | W96: Assigned Department Provider | X96: LIS | Y96: Final result | Z96: Posted | AA96: Matched | AB96: Review | AC96: WQ-LAB-03 | AD96: Diagnosis/LCD | AE96: E11.9 | AF96: 22 | AG96: 2026-09-22 16:30 | AH96: Synthetic Care Gap charge; 10% below Athena allowed amount
A97: OPD-CHG-0047-ATH | B97: OP-202600047-ATH | C97: CSN-OPD-780047-ATH | D97: Outpatient | E97: Demo Regional Medical Center | F97: Laboratory | G97: 2026-09-23 | H97: LIPID-OP | I97: Lipid Panel | J97: 0301 | K97: 80061 | M97: 1 | N97: 215 | O97: =M97*N97 | P97: 132.36 | Q97: =P97*20% | R97: =O97-P97 | S97: Athena Health Insurance | T97: Athena PPO | V97: Eleanor Brooks, MD | W97: Assigned Department Provider | X97: LIS | Y97: Final result | Z97: Posted | AA97: Matched | AB97: Passed | AD97: Diagnosis/LCD | AE97: E78.5 | AF97: 22 | AG97: 2026-09-23 16:30 | AH97: Synthetic Athena negotiated charge
A98: OPD-CHG-0047-CGH | B98: OP-202600047-CGH | C98: CSN-OPD-780047-CGH | D98: Outpatient | E98: Demo Regional Medical Center | F98: Laboratory | G98: 2026-09-23 | H98: LIPID-OP | I98: Lipid Panel | J98: 0301 | K98: 80061 | M98: 1 | N98: 215 | O98: =M98*N98 | P98: 119.12 | Q98: =P98*15% | R98: =O98-P98 | S98: Care Gap Health | T98: Care Gap Value PPO | V98: Eleanor Brooks, MD | W98: Assigned Department Provider | X98: LIS | Y98: Final result | Z98: Posted | AA98: Matched | AB98: Passed | AD98: Diagnosis/LCD | AE98: E78.5 | AF98: 22 | AG98: 2026-09-23 16:30 | AH98: Synthetic Care Gap charge; 10% below Athena allowed amount
A99: OPD-CHG-0048-ATH | B99: OP-202600048-ATH | C99: CSN-OPD-780048-ATH | D99: Outpatient | E99: Demo Regional Medical Center | F99: Cardiology | G99: 2026-09-24 | H99: ECHO-COMP | I99: Complete Transthoracic Echocardiogram | J99: 0483 | K99: 93306 | M99: 1 | N99: 1550 | O99: =M99*N99 | P99: 902.37 | Q99: =P99*20% | R99: =O99-P99 | S99: Athena Health Insurance | T99: Athena PPO | U99: AUTH-700048 | V99: Eleanor Brooks, MD | W99: Assigned Department Provider | X99: Cardiology | Y99: Test completed | Z99: Posted | AA99: Matched | AB99: Passed | AD99: Prior authorization | AE99: R01.1 | AF99: 22 | AG99: 2026-09-24 16:30 | AH99: Synthetic Athena negotiated charge
A100: OPD-CHG-0048-CGH | B100: OP-202600048-CGH | C100: CSN-OPD-780048-CGH | D100: Outpatient | E100: Demo Regional Medical Center | F100: Cardiology | G100: 2026-09-24 | H100: ECHO-COMP | I100: Complete Transthoracic Echocardiogram | J100: 0483 | K100: 93306 | M100: 1 | N100: 1550 | O100: =M100*N100 | P100: 812.13 | Q100: =P100*15% | R100: =O100-P100 | S100: Care Gap Health | T100: Care Gap Value PPO | U100: AUTH-700048 | V100: Eleanor Brooks, MD | W100: Assigned Department Provider | X100: Cardiology | Y100: Test completed | Z100: Posted | AA100: Matched | AB100: Passed | AD100: Prior authorization | AE100: R01.1 | AF100: 22 | AG100: 2026-09-24 16:30 | AH100: Synthetic Care Gap charge; 10% below Athena allowed amount
A101: OPD-CHG-0049-ATH | B101: OP-202600049-ATH | C101: CSN-OPD-780049-ATH | D101: Outpatient | E101: Demo Regional Medical Center | F101: Cardiology | G101: 2026-09-25 | H101: STRESS-TEST | I101: Cardiovascular Stress Test | J101: 0482 | K101: 93017 | M101: 1 | N101: 1150 | O101: =M101*N101 | P101: 488.09 | Q101: =P101*20% | R101: =O101-P101 | S101: Athena Health Insurance | T101: Athena PPO | U101: AUTH-700049 | V101: Eleanor Brooks, MD | W101: Assigned Department Provider | X101: Cardiology | Y101: Test completed | Z101: Posted | AA101: Matched | AB101: Passed | AD101: Prior authorization | AE101: R07.9 | AF101: 22 | AG101: 2026-09-25 16:30 | AH101: Synthetic Athena negotiated charge
...

Sheet Dashboard
A1: bsolutely original add multiple charges
A2: Executive view of CDM completeness, financial exposure, review status, and charge reconciliation.
A4: Active CDM Records | E4: Gross Charge Value | I4: Expected Allowed
A5: =COUNTIF('CDM Master'!AD:AD,"Active") | E5: =SUM('IPD Encounter'!R5:R15) | I5: =SUM('IPD Encounter'!S5:S15)
A8: Patient Responsibility | E8: Open Governance | I8: Active Claim Edits
A9: =SUM('IPD Encounter'!T5:T15) | E9: =COUNTIF(Governance!O:O,"<>Closed")-1 | I9: =COUNTIF('Claim Edits'!L:L,"Active")
A13: Department | B13: Gross Price Total
A14: Operating Room | B14: =SUMIF('CDM Master'!E:E,A14,'CDM Master'!O:O)
A15: Pharmacy | B15: =SUMIF('CDM Master'!E:E,A15,'CDM Master'!O:O)
A16: Radiology | B16: =SUMIF('CDM Master'!E:E,A16,'CDM Master'!O:O)
A17: Laboratory | B17: =SUMIF('CDM Master'!E:E,A17,'CDM Master'!O:O)
A18: Physical Therapy | B18: =SUMIF('CDM Master'!E:E,A18,'CDM Master'!O:O)
A19: Surgical Supplies | B19: =SUMIF('CDM Master'!E:E,A19,'CDM Master'!O:O)

Sheet CDM Master
A1: Charge Description Master (CDM)
A2: Enterprise master of billable facility items/services, coding, pricing, ownership, and lifecycle controls.
A4: Facility ID | B4: Location | C4: Service Area | D4: Department ID | E4: Department | F4: EAP/CDM Charge Code | G4: Charge Description | H4: Patient-Friendly Description | I4: Charge Type | J4: Revenue Code | K4: CPT/HCPCS | L4: Modifier | M4: NDC / Device ID | N4: Unit Basis | O4: Gross Unit Charge ($) | P4: Cost ($) | Q4: Markup % | R4: HCPCS Units | S4: Bill Area | T4: HB/PB | U4: Charge Trigger | V4: Source System | W4: Orderable/Procedure ID | X4: Price Tier | Y4: Taxable | Z4: Prior Auth Flag | AA4: Medical Necessity Rule | AB4: Effective Date | AC4: Termination Date | AD4: Status | AE4: Owner | AF4: Last Review Date | AG4: Next Review Date | AH4: Review Flag | AI4: Compliance Notes
A5: MAIN | B5: Main Campus | C5: HB | D5: D100 | E5: Inpatient Nursing | F5: RM-SP-001 | G5: Semiprivate Medical/Surgical Room | H5: Semiprivate hospital room | I5: Accommodation | J5: 0120 | N5: Per day | O5: 3500 | P5: 1200 | Q5: =IFERROR((O5-P5)/P5,0) | R5: 1 | S5: HB-NURS | T5: HB | U5: ADT discharge | V5: ADT | W5: BED-SP | X5: Standard | Y5: No | Z5: No | AA5: N/A | AB5: 2026-01-01 | AD5: Active | AE5: Director Revenue Integrity | AF5: 2026-07-15 | AG5: =EDATE(AF5,12) | AH5: =IF(AD5<>"Active","Inactive",IF(AG5<TODAY(),"Overdue",IF(AG5<=TODAY()+60,"Due Soon","Current")))
A6: MAIN | B6: Main Campus | C6: HB | D6: D105 | E6: Intensive Care | F6: ICU-DAY-001 | G6: Intensive Care Unit Room | H6: ICU room and monitoring | I6: Accommodation | J6: 0200 | N6: Per day | O6: 8000 | P6: 3500 | Q6: =IFERROR((O6-P6)/P6,0) | R6: 1 | S6: HB-ICU | T6: HB | U6: ADT bed event | V6: ADT | W6: BED-ICU | X6: Standard | Y6: No | Z6: No | AA6: N/A | AB6: 2026-01-01 | AD6: Active | AE6: Director Revenue Integrity | AF6: 2026-07-15 | AG6: =EDATE(AF6,12) | AH6: =IF(AD6<>"Active","Inactive",IF(AG6<TODAY(),"Overdue",IF(AG6<=TODAY()+60,"Due Soon","Current")))
A7: MAIN | B7: Main Campus | C7: HB | D7: D200 | E7: Operating Room | F7: OR-MAJOR-01 | G7: Major Operating Room, First Hour | H7: Operating room first hour | I7: Timed Service | J7: 0360 | N7: Per hour | O7: 10000 | P7: 4200 | Q7: =IFERROR((O7-P7)/P7,0) | R7: 1 | S7: HB-OR | T7: HB | U7: Procedure end | V7: OpTime | W7: PROC-OR-MAJ | X7: Standard | Y7: No | Z7: Yes | AA7: Procedure-specific | AB7: 2026-01-01 | AD7: Active | AE7: OR Finance Manager | AF7: 2026-08-01 | AG7: =EDATE(AF7,12) | AH7: =IF(AD7<>"Active","Inactive",IF(AG7<TODAY(),"Overdue",IF(AG7<=TODAY()+60,"Due Soon","Current")))
A8: MAIN | B8: Main Campus | C8: HB | D8: D200 | E8: Operating Room | F8: OR-ADD-15 | G8: Operating Room, Additional 15 Minutes | H8: Additional operating room time | I8: Timed Service | J8: 0360 | N8: Per 15 minutes | O8: 1250 | P8: 525 | Q8: =IFERROR((O8-P8)/P8,0) | R8: 1 | S8: HB-OR | T8: HB | U8: Procedure end | V8: OpTime | W8: PROC-OR-15 | X8: Standard | Y8: No | Z8: Yes | AA8: Procedure-specific | AB8: 2026-01-01 | AD8: Active | AE8: OR Finance Manager | AF8: 2026-08-01 | AG8: =EDATE(AF8,12) | AH8: =IF(AD8<>"Active","Inactive",IF(AG8<TODAY(),"Overdue",IF(AG8<=TODAY()+60,"Due Soon","Current")))
A9: MAIN | B9: Main Campus | C9: HB | D9: D210 | E9: Recovery Room | F9: RR-HR-001 | G9: Recovery Room, First Hour | H9: Recovery room first hour | I9: Timed Service | J9: 0710 | N9: Per hour | O9: 2000 | P9: 720 | Q9: =IFERROR((O9-P9)/P9,0) | R9: 1 | S9: HB-PACU | T9: HB | U9: PACU discharge | V9: OpTime | W9: PROC-PACU | X9: Standard | Y9: No | Z9: No | AA9: N/A | AB9: 2026-01-01 | AD9: Active | AE9: OR Finance Manager | AF9: 2026-08-01 | AG9: =EDATE(AF9,12) | AH9: =IF(AD9<>"Active","Inactive",IF(AG9<TODAY(),"Overdue",IF(AG9<=TODAY()+60,"Due Soon","Current")))
A10: MAIN | B10: Main Campus | C10: HB | D10: D220 | E10: Surgical Supplies | F10: IMP-KNEE-01 | G10: Cemented Knee Implant Package | H10: Knee implant package | I10: Implant | J10: 0278 | M10: DI-088590000001 | N10: Per implant | O10: 20000 | P10: 11500 | Q10: =IFERROR((O10-P10)/P10,0) | R10: 1 | S10: HB-SUP | T10: HB | U10: Implant scan | V10: Inventory | W10: ITEM-KNEE-CEM | X10: Carve-Out | Y10: No | Z10: Yes | AA10: Contract rule | AB10: 2026-01-01 | AD10: Active | AE10: Supply Chain Finance | AF10: 2026-06-30 | AG10: =EDATE(AF10,12) | AH10: =IF(AD10<>"Active","Inactive",IF(AG10<TODAY(),"Overdue",IF(AG10<=TODAY()+60,"Due Soon","Current")))
A11: MAIN | B11: Main Campus | C11: HB | D11: D220 | E11: Surgical Supplies | F11: SUP-KNEE-01 | G11: Knee Surgery Supply Pack | H11: Disposable knee surgery supplies | I11: Supply | J11: 0270 | N11: Per pack | O11: 4000 | P11: 1450 | Q11: =IFERROR((O11-P11)/P11,0) | R11: 1 | S11: HB-SUP | T11: HB | U11: Supply issue | V11: Inventory | W11: ITEM-KNEE-PACK | X11: Standard | Y11: No | Z11: No | AA11: N/A | AB11: 2026-01-01 | AD11: Active | AE11: Supply Chain Finance | AF11: 2026-06-30 | AG11: =EDATE(AF11,12) | AH11: =IF(AD11<>"Active","Inactive",IF(AG11<TODAY(),"Overdue",IF(AG11<=TODAY()+60,"Due Soon","Current")))
A12: MAIN | B12: Main Campus | C12: HB | D12: D300 | E12: Pharmacy | F12: PH-IV-ABX-01 | G12: Cefazolin 1 g Injection | H12: Cefazolin antibiotic injection | I12: Drug | J12: 0250 | K12: J0690 | M12: 00071-3069-23 | N12: Per 1 g | O12: 500 | P12: 42 | Q12: =IFERROR((O12-P12)/P12,0) | R12: 1 | S12: HB-PHAR | T12: HB | U12: Medication administration | V12: Willow/MAR | W12: MED-CEFAZ-1G | X12: Drug | Y12: No | Z12: No | AA12: Dose/frequency | AB12: 2026-01-01 | AD12: Active | AE12: Pharmacy Revenue Integrity | AF12: 2026-09-01 | AG12: =EDATE(AF12,12) | AH12: =IF(AD12<>"Active","Inactive",IF(AG12<TODAY(),"Overdue",IF(AG12<=TODAY()+60,"Due Soon","Current")))
A13: MAIN | B13: Main Campus | C13: HB | D13: D400 | E13: Laboratory | F13: LAB-CBC-001 | G13: Complete Blood Count with Automated Differential | H13: Complete blood count test | I13: Lab | J13: 0300 | K13: 85025 | N13: Per test | O13: 150 | P13: 22 | Q13: =IFERROR((O13-P13)/P13,0) | R13: 1 | S13: HB-LAB | T13: HB | U13: Final result | V13: LIS | W13: LAB-CBC | X13: Standard | Y13: No | Z13: No | AA13: Diagnosis/LCD | AB13: 2026-01-01 | AD13: Active | AE13: Lab Finance Manager | AF13: 2026-08-15 | AG13: =EDATE(AF13,12) | AH13: =IF(AD13<>"Active","Inactive",IF(AG13<TODAY(),"Overdue",IF(AG13<=TODAY()+60,"Due Soon","Current")))
A14: MAIN | B14: Main Campus | C14: HB | D14: D500 | E14: Radiology | F14: RAD-KNEE-01 | G14: Knee X-ray, 1-2 Views | H14: Knee X-ray | I14: Imaging | J14: 0320 | K14: 73560 | N14: Per study | O14: 400 | P14: 60 | Q14: =IFERROR((O14-P14)/P14,0) | R14: 1 | S14: HB-RAD | T14: HB | U14: Exam completed | V14: RIS/PACS | W14: IMG-KNEE-2V | X14: Standard | Y14: No | Z14: No | AA14: Diagnosis/LCD | AB14: 2026-01-01 | AD14: Active | AE14: Imaging Finance Manager | AF14: 2026-08-15 | AG14: =EDATE(AF14,12) | AH14: =IF(AD14<>"Active","Inactive",IF(AG14<TODAY(),"Overdue",IF(AG14<=TODAY()+60,"Due Soon","Current")))
A15: OUT | B15: Outpatient Center | C15: HB | D15: D505 | E15: Radiology | F15: RAD-CHEST-02 | G15: Chest X-ray, 2 Views | H15: Two-view chest X-ray | I15: Imaging | J15: 0320 | K15: 71046 | N15: Per study | O15: 180 | P15: 38 | Q15: =IFERROR((O15-P15)/P15,0) | R15: 1 | S15: HB-RAD | T15: HB | U15: Exam completed | V15: RIS/PACS | W15: IMG-CXR-2V | X15: Standard | Y15: No | Z15: No | AA15: Diagnosis/LCD | AB15: 2026-01-01 | AD15: Active | AE15: Imaging Finance Manager | AF15: 2026-08-15 | AG15: =EDATE(AF15,12) | AH15: =IF(AD15<>"Active","Inactive",IF(AG15<TODAY(),"Overdue",IF(AG15<=TODAY()+60,"Due Soon","Current")))
A16: MAIN | B16: Main Campus | C16: HB | D16: D600 | E16: Physical Therapy | F16: PT-EVAL-01 | G16: Physical Therapy Initial Evaluation, Low Complexity | H16: Initial physical therapy evaluation | I16: Therapy | J16: 0420 | K16: 97161 | N16: Per session | O16: 700 | P16: 145 | Q16: =IFERROR((O16-P16)/P16,0) | R16: 1 | S16: HB-THER | T16: HB | U16: Note signed | V16: Therapy | W16: PT-EVAL-LOW | X16: Standard | Y16: No | Z16: Yes | AA16: Plan benefits | AB16: 2026-01-01 | AD16: Active | AE16: Rehab Finance Manager | AF16: 2026-07-31 | AG16: =EDATE(AF16,12) | AH16: =IF(AD16<>"Active","Inactive",IF(AG16<TODAY(),"Overdue",IF(AG16<=TODAY()+60,"Due Soon","Current")))
A17: MAIN | B17: Main Campus | C17: HB | D17: D600 | E17: Physical Therapy | F17: PT-EX-15 | G17: Therapeutic Exercise | H17: Therapeutic exercise | I17: Therapy | J17: 0420 | K17: 97110 | N17: Per 15 minutes | O17: 300 | P17: 62 | Q17: =IFERROR((O17-P17)/P17,0) | R17: 1 | S17: HB-THER | T17: HB | U17: Note signed | V17: Therapy | W17: PT-THEREX | X17: Standard | Y17: No | Z17: Yes | AA17: Timed units | AB17: 2026-01-01 | AD17: Active | AE17: Rehab Finance Manager | AF17: 2026-07-31 | AG17: =EDATE(AF17,12) | AH17: =IF(AD17<>"Active","Inactive",IF(AG17<TODAY(),"Overdue",IF(AG17<=TODAY()+60,"Due Soon","Current")))
A18: OUT | B18: Outpatient Center | C18: HB | D18: D700 | E18: Hospital Clinic | F18: OPD-CLINIC-01 | G18: Hospital Outpatient Clinic Visit, Level 4 | H18: Hospital clinic facility visit | I18: Clinic | J18: 0510 | K18: 99214 | N18: Per visit | O18: 400 | P18: 95 | Q18: =IFERROR((O18-P18)/P18,0) | R18: 1 | S18: HB-CLIN | T18: HB | U18: Visit close | V18: Cadence/ClinDoc | W18: VISIT-L4 | X18: Standard | Y18: No | Z18: No | AA18: E/M documentation | AB18: 2026-01-01 | AD18: Active | AE18: Ambulatory Finance Manager | AF18: 2026-09-01 | AG18: =EDATE(AF18,12) | AH18: =IF(AD18<>"Active","Inactive",IF(AG18<TODAY(),"Overdue",IF(AG18<=TODAY()+60,"Due Soon","Current")))
A19: MAIN | B19: Main Campus | C19: PB | D19: D800 | E19: Orthopedics Professional | F19: PB-ORTH-27447 | G19: Total Knee Arthroplasty, Professional | H19: Surgeon professional service | I19: Professional | K19: 27447 | N19: Per procedure | O19: 3200 | P19: 900 | Q19: =IFERROR((O19-P19)/P19,0) | R19: 1 | S19: PB-ORTH | T19: PB | U19: Charge capture sign | V19: ClinDoc | W19: SURG-TKA | X19: Professional | Y19: No | Z19: Yes | AA19: Procedure-specific | AB19: 2026-01-01 | AD19: Active | AE19: PB Coding Manager | AF19: 2026-08-20 | AG19: =EDATE(AF19,12) | AH19: =IF(AD19<>"Active","Inactive",IF(AG19<TODAY(),"Overdue",IF(AG19<=TODAY()+60,"Due Soon","Current")))

Sheet IPD Encounter
A1: Sample IPD Encounter & Charge Reconciliation
A2: Synthetic total knee replacement hospital account with charge-level status, pricing, and reconciliation controls.
A4: Hospital Account (HAR) | B4: Patient MRN | C4: Encounter CSN | D4: Patient Class | E4: Admit Date/Time | F4: Discharge Date/Time | G4: Payer | H4: Plan | I4: DRG | J4: Charge Code | K4: Service Date | L4: Department | M4: Revenue Code | N4: CPT/HCPCS | O4: Modifier | P4: Quantity | Q4: Unit Charge ($) | R4: Extended Gross ($) | S4: Allowed ($) | T4: Patient Responsibility ($) | U4: Contractual Adjustment ($) | V4: Charge Status | W4: Source | X4: Reconciliation Status | Y4: Edit Status | Z4: Notes
A5: HAR-10004567 | B5: MRN-DEMO-0001 | C5: CSN-2026-784512 | D5: Inpatient | E5: 2026-09-14 08:15 | F5: 2026-09-16 14:10 | G5: Demo PPO | H5: Gold PPO | I5: MS-DRG 470 | J5: RM-SP-001 | K5: 2026-09-14 | L5: ='CDM Master'!E5 | M5: ='CDM Master'!J5 | N5: ='CDM Master'!K5 | O5: ='CDM Master'!L5 | P5: 2 | Q5: ='CDM Master'!O5 | R5: =P5*Q5 | S5: 7000 | T5: =S5*20% | U5: =R5-S5 | V5: Posted | W5: ='CDM Master'!V5 | X5: Matched | Y5: Passed | Z5: Synthetic demo charge
A6: HAR-10004567 | B6: MRN-DEMO-0001 | C6: CSN-2026-784512 | D6: Inpatient | E6: 2026-09-14 08:15 | F6: 2026-09-16 14:10 | G6: Demo PPO | H6: Gold PPO | I6: MS-DRG 470 | J6: OR-MAJOR-01 | K6: 2026-09-14 | L6: ='CDM Master'!E6 | M6: ='CDM Master'!J6 | N6: ='CDM Master'!K6 | O6: ='CDM Master'!L6 | P6: 1 | Q6: ='CDM Master'!O6 | R6: =P6*Q6 | S6: 9000 | T6: =S6*20% | U6: =R6-S6 | V6: Posted | W6: ='CDM Master'!V6 | X6: Matched | Y6: Passed | Z6: Synthetic demo charge
A7: HAR-10004567 | B7: MRN-DEMO-0001 | C7: CSN-2026-784512 | D7: Inpatient | E7: 2026-09-14 08:15 | F7: 2026-09-16 14:10 | G7: Demo PPO | H7: Gold PPO | I7: MS-DRG 470 | J7: OR-ADD-15 | K7: 2026-09-14 | L7: ='CDM Master'!E7 | M7: ='CDM Master'!J7 | N7: ='CDM Master'!K7 | O7: ='CDM Master'!L7 | P7: 2 | Q7: ='CDM Master'!O7 | R7: =P7*Q7 | S7: 1800 | T7: =S7*20% | U7: =R7-S7 | V7: Posted | W7: ='CDM Master'!V7 | X7: Matched | Y7: Passed | Z7: Synthetic demo charge
A8: HAR-10004567 | B8: MRN-DEMO-0001 | C8: CSN-2026-784512 | D8: Inpatient | E8: 2026-09-14 08:15 | F8: 2026-09-16 14:10 | G8: Demo PPO | H8: Gold PPO | I8: MS-DRG 470 | J8: RR-HR-001 | K8: 2026-09-14 | L8: ='CDM Master'!E8 | M8: ='CDM Master'!J8 | N8: ='CDM Master'!K8 | O8: ='CDM Master'!L8 | P8: 1 | Q8: ='CDM Master'!O8 | R8: =P8*Q8 | S8: 1500 | T8: =S8*20% | U8: =R8-S8 | V8: Posted | W8: ='CDM Master'!V8 | X8: Matched | Y8: Passed | Z8: Synthetic demo charge
A9: HAR-10004567 | B9: MRN-DEMO-0001 | C9: CSN-2026-784512 | D9: Inpatient | E9: 2026-09-14 08:15 | F9: 2026-09-16 14:10 | G9: Demo PPO | H9: Gold PPO | I9: MS-DRG 470 | J9: IMP-KNEE-01 | K9: 2026-09-14 | L9: ='CDM Master'!E9 | M9: ='CDM Master'!J9 | N9: ='CDM Master'!K9 | O9: ='CDM Master'!L9 | P9: 1 | Q9: ='CDM Master'!O9 | R9: =P9*Q9 | S9: 9000 | T9: =S9*20% | U9: =R9-S9 | V9: Posted | W9: ='CDM Master'!V9 | X9: Matched | Y9: Passed | Z9: Synthetic demo charge
A10: HAR-10004567 | B10: MRN-DEMO-0001 | C10: CSN-2026-784512 | D10: Inpatient | E10: 2026-09-14 08:15 | F10: 2026-09-16 14:10 | G10: Demo PPO | H10: Gold PPO | I10: MS-DRG 470 | J10: SUP-KNEE-01 | K10: 2026-09-14 | L10: ='CDM Master'!E10 | M10: ='CDM Master'!J10 | N10: ='CDM Master'!K10 | O10: ='CDM Master'!L10 | P10: 1 | Q10: ='CDM Master'!O10 | R10: =P10*Q10 | S10: 1800 | T10: =S10*20% | U10: =R10-S10 | V10: Posted | W10: ='CDM Master'!V10 | X10: Matched | Y10: Passed | Z10: Synthetic demo charge
A11: HAR-10004567 | B11: MRN-DEMO-0001 | C11: CSN-2026-784512 | D11: Inpatient | E11: 2026-09-14 08:15 | F11: 2026-09-16 14:10 | G11: Demo PPO | H11: Gold PPO | I11: MS-DRG 470 | J11: PH-IV-ABX-01 | K11: 2026-09-14 | L11: ='CDM Master'!E11 | M11: ='CDM Master'!J11 | N11: ='CDM Master'!K11 | O11: ='CDM Master'!L11 | P11: 4 | Q11: ='CDM Master'!O11 | R11: =P11*Q11 | S11: 1200 | T11: =S11*20% | U11: =R11-S11 | V11: Posted | W11: ='CDM Master'!V11 | X11: Matched | Y11: Passed | Z11: Synthetic demo charge
A12: HAR-10004567 | B12: MRN-DEMO-0001 | C12: CSN-2026-784512 | D12: Inpatient | E12: 2026-09-14 08:15 | F12: 2026-09-16 14:10 | G12: Demo PPO | H12: Gold PPO | I12: MS-DRG 470 | J12: LAB-CBC-001 | K12: 2026-09-14 | L12: ='CDM Master'!E12 | M12: ='CDM Master'!J12 | N12: ='CDM Master'!K12 | O12: ='CDM Master'!L12 | P12: 2 | Q12: ='CDM Master'!O12 | R12: =P12*Q12 | S12: 180 | T12: =S12*20% | U12: =R12-S12 | V12: Posted | W12: ='CDM Master'!V12 | X12: Matched | Y12: Passed | Z12: Synthetic demo charge
A13: HAR-10004567 | B13: MRN-DEMO-0001 | C13: CSN-2026-784512 | D13: Inpatient | E13: 2026-09-14 08:15 | F13: 2026-09-16 14:10 | G13: Demo PPO | H13: Gold PPO | I13: MS-DRG 470 | J13: RAD-KNEE-01 | K13: 2026-09-14 | L13: ='CDM Master'!E13 | M13: ='CDM Master'!J13 | N13: ='CDM Master'!K13 | O13: ='CDM Master'!L13 | P13: 1 | Q13: ='CDM Master'!O13 | R13: =P13*Q13 | S13: 260 | T13: =S13*20% | U13: =R13-S13 | V13: Posted | W13: ='CDM Master'!V13 | X13: Matched | Y13: Passed | Z13: Synthetic demo charge
A14: HAR-10004567 | B14: MRN-DEMO-0001 | C14: CSN-2026-784512 | D14: Inpatient | E14: 2026-09-14 08:15 | F14: 2026-09-16 14:10 | G14: Demo PPO | H14: Gold PPO | I14: MS-DRG 470 | J14: PT-EVAL-01 | K14: 2026-09-14 | L14: ='CDM Master'!E14 | M14: ='CDM Master'!J14 | N14: ='CDM Master'!K14 | O14: ='CDM Master'!L14 | P14: 1 | Q14: ='CDM Master'!O14 | R14: =P14*Q14 | S14: 450 | T14: =S14*20% | U14: =R14-S14 | V14: Posted | W14: ='CDM Master'!V14 | X14: Matched | Y14: Passed | Z14: Synthetic demo charge
A15: HAR-10004567 | B15: MRN-DEMO-0001 | C15: CSN-2026-784512 | D15: Inpatient | E15: 2026-09-14 08:15 | F15: 2026-09-16 14:10 | G15: Demo PPO | H15: Gold PPO | I15: MS-DRG 470 | J15: PT-EX-15 | K15: 2026-09-14 | L15: ='CDM Master'!E15 | M15: ='CDM Master'!J15 | N15: ='CDM Master'!K15 | O15: ='CDM Master'!L15 | P15: 3 | Q15: ='CDM Master'!O15 | R15: =P15*Q15 | S15: 600 | T15: =S15*20% | U15: =R15-S15 | V15: Posted | W15: ='CDM Master'!V15 | X15: Matched | Y15: Passed | Z15: Synthetic demo charge
O16: TOTAL | R16: =SUM(R5:R15) | S16: =SUM(S5:S15) | T16: =SUM(T5:T15) | U16: =SUM(U5:U15)

Sheet Charge Router Rules
A1: Charge Router & Routing Rules
A2: Illustrative routing logic for automated release, review, suppression, and HB/PB destination control.
A4: Rule ID | B4: Priority | C4: Rule Name | D4: Source Application | E4: Trigger | F4: Patient Class | G4: Service Area | H4: Condition | I4: Action | J4: Destination Bill Area | K4: Hold/Release | L4: Workqueue | M4: Severity | N4: Owner | O4: Effective Date | P4: Status | Q4: Test Scenario | R4: Expected Result
A5: CR-001 | B5: 10 | C5: Missing revenue code | D5: Any | E5: Charge received | F5: All | G5: HB | H5: Revenue code is blank | I5: Hold charge | J5: HB Review | K5: Hold | L5: WQ-REV-001 | M5: Error | N5: Revenue Integrity | O5: 2026-01-01 | P5: Active | Q5: HB charge without revenue code | R5: Held for correction
A6: CR-002 | B6: 20 | C6: Missing CPT on coded outpatient service | D6: Radiology/Lab/Therapy | E6: Completion | F6: Outpatient | G6: HB | H6: CPT/HCPCS blank for coded service | I6: Hold charge | J6: HB Coding | K6: Hold | L6: WQ-CODE-002 | M6: Error | N6: HB Coding | O6: 2026-01-01 | P6: Active | Q6: Outpatient imaging without CPT | R6: Held for coding
A7: CR-003 | B7: 30 | C7: Duplicate charge check | D7: Any | E7: Charge received | F7: All | G7: All | H7: Same HAR, charge code, service date, quantity within 24h | I7: Route to review | J7: Charge Review | K7: Hold | L7: WQ-DUP-003 | M7: Warning | N7: Revenue Integrity | O7: 2026-01-01 | P7: Active | Q7: Repeat same-day CBC | R7: Review duplicate intent
A8: CR-004 | B8: 40 | C8: Implant carve-out review | D8: Inventory | E8: Implant scan | F8: Inpatient | G8: HB | H8: Revenue code 0278 and price tier Carve-Out | I8: Route to contract review | J8: HB Contracting | K8: Hold | L8: WQ-IMP-004 | M8: Warning | N8: Managed Care | O8: 2026-01-01 | P8: Active | Q8: Knee implant on contracted case | R8: Validate invoice/carve-out
A9: CR-005 | B9: 50 | C9: Professional charge split | D9: ClinDoc | E9: Procedure sign | F9: All | G9: PB | H9: HB/PB = PB | I9: Route | J9: PB Charge Entry | K9: Release | L9: WQ-PB-005 | M9: Info | N9: PB Coding | O9: 2026-01-01 | P9: Active | Q9: Surgeon procedure charge | R9: Routes to PB
A10: CR-006 | B10: 60 | C10: Passed automation | D10: Any | E10: Charge received | F10: All | G10: All | H10: All required elements present | I10: Release charge | J10: Target bill area | K10: Release | M10: Info | N10: Revenue Integrity | O10: 2026-01-01 | P10: Active | Q10: Complete valid charge | R10: Released to billing

Sheet Claim Edits
A1: Institutional Claim Edits
A2: Pre-bill data-quality, coding, medical-necessity, and contract controls for a clean 837I workflow.
A4: Edit ID | B4: Claim Type | C4: Stage | D4: Edit Description | E4: Logic / Validation | F4: Disposition | G4: Severity | H4: Related Field | I4: Workqueue | J4: Owner | K4: Regulatory/Contract Basis | L4: Status | M4: Last Tested | N4: Test Outcome
A5: CE-001 | B5: 837I | C5: Pre-bill | D5: Missing/invalid revenue code | E5: Revenue code required and valid for bill type | F5: Hold | G5: Error | H5: Revenue Code | I5: WQ-CLAIM-001 | J5: HB Billing | K5: UB-04/837I data quality | L5: Active | M5: 2026-09-01 | N5: Pass
A6: CE-002 | B6: 837I | C6: Pre-bill | D6: CPT required for outpatient ancillary | E6: CPT/HCPCS required for configured revenue codes | F6: Hold | G6: Error | H6: CPT/HCPCS | I6: WQ-CODE-002 | J6: HB Coding | K6: Payer billing rule | L6: Active | M6: 2026-09-01 | N6: Pass
A7: CE-003 | B7: 837I | C7: Pre-bill | D7: Units inconsistent with timed service | E7: Units must match documented time methodology | F7: Hold | G7: Error | H7: Quantity | I7: WQ-THER-003 | J7: Therapy Coding | K7: CPT timed-unit guidance | L7: Active | M7: 2026-09-02 | N7: Pass
A8: CE-004 | B8: 837I | C8: Pre-bill | D8: Authorization missing | E8: Authorization required for flagged service/plan | F8: Hold | G8: Error | H8: Authorization | I8: WQ-AUTH-004 | J8: Prior Authorization | K8: Payer contract | L8: Active | M8: 2026-09-02 | N8: Pass
A9: CE-005 | B9: 837I | C9: Pre-bill | D9: NDC missing for drug | E9: NDC and unit-of-measure required when payer mandates | F9: Hold | G9: Warning | H9: NDC | I9: WQ-PHAR-005 | J9: Pharmacy Billing | K9: Payer/state rule | L9: Active | M9: 2026-09-03 | N9: Pass
A10: CE-006 | B10: 837I | C10: Pre-bill | D10: Implant invoice missing | E10: Invoice/documentation required for carve-out claim line | F10: Hold | G10: Warning | H10: Attachment | I10: WQ-IMP-006 | J10: Managed Care | K10: Contract carve-out | L10: Active | M10: 2026-09-03 | N10: Pass

Sheet Payer Contracts
A1: Payer Contract Configuration
A2: Synthetic contract assumptions used to separate gross charges from expected allowed and patient responsibility.
A4: Contract ID | B4: Payer | C4: Plan | D4: Facility | E4: Patient Class | F4: Methodology | G4: DRG/APC/Fee Schedule | H4: Base Rate ($) | I4: Per Diem ($) | J4: Carve-Out Type | K4: Carve-Out Rule | L4: Coinsurance % | M4: Deductible Applies | N4: Effective Date | O4: Termination Date | P4: Status | Q4: Owner | R4: Notes
A5: ATH-IPD-001 | B5: Athena Health Insurance | C5: Athena PPO | D5: Main Campus | E5: Inpatient | F5: DRG / negotiated allowed | G5: Synthetic Athena schedule | H5: 30000 | I5: 0 | J5: Implant | K5: Lesser of invoice + 10% or gross charge | L5: 0.2 | M5: Yes | N5: 2026-01-01 | O5: 2026-12-31 | P5: Active | Q5: Managed Care Director | R5: Synthetic demo; baseline allowed amounts
A6: ATH-OPD-001 | B6: Athena Health Insurance | C6: Athena PPO | D6: Outpatient Center | E6: Outpatient | F6: Fee Schedule | G6: Synthetic Athena outpatient schedule | H6: 0 | I6: 0 | J6: Drug | K6: Selected drugs separately payable | L6: 0.2 | M6: Yes | N6: 2026-01-01 | O6: 2026-12-31 | P6: Active | Q6: Managed Care Director | R6: Synthetic demo; baseline allowed amounts
A7: CGH-IPD-001 | B7: Care Gap Health | C7: Care Gap Value PPO | D7: Main Campus | E7: Inpatient | F7: DRG / negotiated allowed | G7: 10% below Athena allowed | H7: 27000 | I7: 0 | J7: Implant | K7: Care Gap allowed amount = 90% of Athena | L7: 0.15 | M7: Yes | N7: 2026-01-01 | O7: 2026-12-31 | P7: Active | Q7: Managed Care Director | R7: Synthetic demo; lower negotiated pricing
A8: CGH-OPD-001 | B8: Care Gap Health | C8: Care Gap Value PPO | D8: Outpatient Center | E8: Outpatient | F8: Fee Schedule | G8: 90% of Athena outpatient allowed | H8: 0 | I8: 0 | J8: Drug | K8: Selected drugs separately payable | L8: 0.15 | M8: Yes | N8: 2026-01-01 | O8: 2026-12-31 | P8: Active | Q8: Managed Care Director | R8: Synthetic demo; lower negotiated pricing

Sheet Price Transparency
A1: Hospital Price Transparency Dataset
A2: Illustrative standard-charge view supporting gross, cash, payer-negotiated, minimum, and maximum charge categories.
A4: Facility Name | B4: Facility Address | C4: License Number | D4: Item/Service Code | E4: Description | F4: Setting | G4: Code Type | H4: Code | I4: Gross Charge ($) | J4: Discounted Cash ($) | K4: Payer | L4: Plan | M4: Negotiated Charge ($) | N4: De-identified Min ($) | O4: De-identified Max ($) | P4: Methodology | Q4: Last Updated | R4: MRF Inclusion | S4: Consumer Shoppable | T4: Source CDM Code | U4: Notes
A5: Demo Regional Medical Center | B5: 100 Innovation Drive, Columbus, OH 43215 | C5: OH-DEMO-1001 | D5: RAD-CHEST-02 | E5: ='CDM Master'!G18 | F5: Outpatient | G5: CPT/HCPCS | H5: ='CDM Master'!K18 | I5: ='CDM Master'!O18 | J5: =I5*65% | K5: Demo PPO | L5: Gold PPO | M5: =I5*72% | N5: =I5*55% | O5: =I5*88% | P5: Negotiated dollar amount | Q5: 2026-09-01 | R5: Yes | S5: Yes | T5: RAD-CHEST-02 | U5: Synthetic demonstration
A6: Demo Regional Medical Center | B6: 100 Innovation Drive, Columbus, OH 43215 | C6: OH-DEMO-1001 | D6: LAB-CBC-001 | E6: ='CDM Master'!G12 | F6: Outpatient | G6: CPT/HCPCS | H6: ='CDM Master'!K12 | I6: ='CDM Master'!O12 | J6: =I6*65% | K6: Demo PPO | L6: Gold PPO | M6: =I6*72% | N6: =I6*55% | O6: =I6*88% | P6: Negotiated dollar amount | Q6: 2026-09-01 | R6: Yes | S6: Yes | T6: LAB-CBC-001 | U6: Synthetic demonstration
A7: Demo Regional Medical Center | B7: 100 Innovation Drive, Columbus, OH 43215 | C7: OH-DEMO-1001 | D7: PT-EVAL-01 | E7: ='CDM Master'!G14 | F7: Outpatient | G7: CPT/HCPCS | H7: ='CDM Master'!K14 | I7: ='CDM Master'!O14 | J7: =I7*65% | K7: Demo PPO | L7: Gold PPO | M7: =I7*72% | N7: =I7*55% | O7: =I7*88% | P7: Negotiated dollar amount | Q7: 2026-09-01 | R7: Yes | S7: Yes | T7: PT-EVAL-01 | U7: Synthetic demonstration
A8: Demo Regional Medical Center | B8: 100 Innovation Drive, Columbus, OH 43215 | C8: OH-DEMO-1001 | D8: OPD-CLINIC-01 | E8: ='CDM Master'!G18 | F8: Outpatient | G8: CPT/HCPCS | H8: ='CDM Master'!K18 | I8: ='CDM Master'!O18 | J8: =I8*65% | K8: Demo PPO | L8: Gold PPO | M8: =I8*72% | N8: =I8*55% | O8: =I8*88% | P8: Negotiated dollar amount | Q8: 2026-09-01 | R8: Yes | S8: Yes | T8: OPD-CLINIC-01 | U8: Synthetic demonstration
A9: Demo Regional Medical Center | B9: 100 Innovation Drive, Columbus, OH 43215 | C9: OH-DEMO-1001 | D9: IMP-KNEE-01 | E9: ='CDM Master'!G9 | F9: Inpatient | G9: CPT/HCPCS | H9: ='CDM Master'!K9 | I9: ='CDM Master'!O9 | J9: =I9*65% | K9: Demo PPO | L9: Gold PPO | M9: =I9*72% | N9: =I9*55% | O9: =I9*88% | P9: Negotiated dollar amount | Q9: 2026-09-01 | R9: Yes | S9: No | T9: IMP-KNEE-01 | U9: Synthetic demonstration

Sheet Governance
A1: CDM Governance & Change Control
A2: Formal intake, approval, build, testing, effective dating, and SLA monitoring for CDM changes.
A4: Request ID | B4: Request Type | C4: Requested Change | D4: Affected Charge Code | E4: Business Justification | F4: Requester | G4: Department Approval | H4: Coding Review | I4: Compliance Review | J4: Finance Approval | K4: IT Build | L4: Test Evidence | M4: Effective Date | N4: Risk Level | O4: Status | P4: SLA Due Date | Q4: Days Open | R4: SLA Flag
A5: CHG-2026-001 | B5: Price Change | C5: Increase chest X-ray gross price | D5: RAD-CHEST-02 | E5: Annual pricing review | F5: Imaging Finance | G5: Approved | H5: Approved | I5: Approved | J5: Approved | K5: Complete | L5: Attached | M5: 2026-10-01 | N5: Medium | O5: Ready for Release | P5: 2026-09-25 | Q5: =TODAY()-DATEVALUE("2026-09-01") | R5: =IF(O5="Closed","Closed",IF(P5<TODAY(),"Overdue","On Track"))
A6: CHG-2026-002 | B6: New Charge | C6: Add robotic surgery disposable kit | D6: NEW-PENDING | E6: New clinical program | F6: OR Finance | G6: Approved | H6: In Review | I6: Pending | J6: Pending | K6: Not Started | L6: Pending | M6: 2026-11-01 | N6: High | O6: In Review | P6: 2026-10-10 | Q6: =TODAY()-DATEVALUE("2026-09-01") | R6: =IF(O6="Closed","Closed",IF(P6<TODAY(),"Overdue","On Track"))
A7: CHG-2026-003 | B7: Retire Charge | C7: Retire obsolete supply pack | D7: SUP-OLD-01 | E7: Item discontinued | F7: Supply Chain | G7: Approved | H7: Approved | I7: Approved | J7: Approved | K7: Complete | L7: Passed | M7: 2026-09-15 | N7: Low | O7: Closed | P7: 2026-09-12 | Q7: =TODAY()-DATEVALUE("2026-09-01") | R7: =IF(O7="Closed","Closed",IF(P7<TODAY(),"Overdue","On Track"))

Sheet Audit Trail
A1: Audit Trail
A2: Synthetic immutable-style event history for CDM, routing, pricing, and release activities.
A4: Audit ID | B4: Timestamp | C4: User/Role | D4: Action | E4: Object Type | F4: Object ID | G4: Field Changed | H4: Old Value | I4: New Value | J4: Reason | K4: Approval/Ticket | L4: Environment | M4: Result
A5: AUD-0001 | B5: 2026-09-01 09:15 | C5: Revenue Integrity Analyst | D5: Update | E5: CDM | F5: RAD-CHEST-02 | G5: Gross Unit Charge | H5: 170 | I5: 180 | J5: Annual pricing review | K5: CHG-2026-001 | L5: Production | M5: Success
A6: AUD-0002 | B6: 2026-09-01 10:05 | C6: HB Coding Analyst | D6: Update | E6: CDM | F6: PH-IV-ABX-01 | G6: HCPCS | H6: Blank | I6: J0690 | J6: Coding validation | K6: INC-2026-118 | L6: Production | M6: Success
A7: AUD-0003 | B7: 2026-09-02 14:20 | C7: Managed Care Analyst | D7: Create | E7: Contract | F7: CNT-001 | G7: Implant carve-out | H7: Blank | I7: Invoice + 10% cap | J7: New payer term | K7: CON-2026-44 | L7: Test | M7: Success
A8: AUD-0004 | B8: 2026-09-03 16:45 | C8: Release Manager | D8: Promote | E8: Router Rule | F8: CR-004 | G8: Status | H8: Test | I8: Active | J8: Approved release | K8: REL-2026-91 | L8: Production | M8: Success

Sheet Data Source Map
A1: Revenue Cycle Data Source Map
A2: Traceability from operational systems through charge generation, billing output, pricing, reconciliation, and ownership.
A4: Data Element | B4: Operational Source | C4: Epic-Aligned Workflow Area | D4: CDM Role | E4: Claim Output | F4: Pricing Source | G4: Reconciliation Control | H4: Owner | I4: Refresh Frequency | J4: Key Risk
A5: Room type and days | B5: ADT / Bed Management | C5: Hospital Billing | D5: Maps accommodation code, revenue code, and daily price | E5: 837I 011X/012X/020X | F5: DRG/per diem/contract | G5: Compare midnight census and billed days | H5: Patient Access + Revenue Integrity | I5: Daily | J5: Incorrect patient class or bed dates
A6: OR time | B6: Perioperative system | C6: Charge Router / HB | D6: Maps room tier and timed units | E6: 837I 036X | F6: Usually packaged | G6: Compare procedure timestamps and units | H6: OR Finance | I6: Daily | J6: Missing/incorrect time units
A7: Implant | B7: Inventory / Supply Chain | C7: Charge Router / HB | D7: Maps item, device identifier, revenue code, gross price | E7: 837I 0278 | F7: DRG or carve-out | G7: Three-way match: scan, invoice, charge | H7: Supply Chain Finance | I7: Daily | J7: Missed charge or unsupported carve-out
A8: Drug administration | B8: Pharmacy / MAR | C8: Hospital Billing | D8: Maps medication, HCPCS, NDC, units, and price | E8: 837I 025X + HCPCS/NDC | F8: Packaged or drug carve-out | G8: MAR-to-charge reconciliation | H8: Pharmacy Revenue Integrity | I8: Daily | J8: NDC/unit mismatch
A9: Lab | B9: LIS | C9: Hospital Billing | D9: Maps completed test to revenue/CPT/price | E9: 837I 030X + CPT | F9: Packaged or fee schedule | G9: Completed tests vs posted charges | H9: Lab Finance | I9: Daily | J9: Cancelled test billed
A10: Imaging | B10: RIS/PACS | C10: Hospital Billing | D10: Maps completed study to revenue/CPT/price | E10: 837I 032X + CPT | F10: Packaged or APC/fee schedule | G10: Exam completion vs charge | H10: Imaging Finance | I10: Daily | J10: Wrong study or duplicate charge
A11: Therapy | B11: Therapy documentation | C11: Hospital Billing | D11: Maps timed and untimed services | E11: 837I 042X + CPT | F11: APC/fee schedule | G11: Documented minutes vs units | H11: Rehab Finance | I11: Daily | J11: Timed-unit over/under billing
A12: Professional services | B12: Clinical documentation | C12: Professional Billing | D12: Separate PB charge and coding workflow | E12: 837P | F12: Professional fee schedule | G12: Provider note vs charge | H12: PB Coding | I12: Daily | J12: HB/PB split error

Sheet Data Dictionary
A1: Data Dictionary
A2: Key business definitions and validation expectations for the demo revenue-cycle data model.
A4: Sheet | B4: Field | C4: Definition | D4: Data Type | E4: Required | F4: Allowed Values / Format | G4: Validation Rule | H4: Source of Truth | I4: Owner | J4: Sensitivity
A5: CDM Master | B5: EAP/CDM Charge Code | C5: Unique internal billable item or service identifier | D5: Text | E5: Yes | F5: Unique, active/effective | G5: No duplicates; cannot be blank | H5: Revenue integrity master | I5: Revenue Integrity | J5: Internal
A6: CDM Master | B6: Revenue Code | C6: Institutional claim category for facility charges | D6: Text | E6: HB only | F6: 4-digit code | G6: Required for HB active charges | H6: Billing configuration | I6: HB Coding | J6: Public standard
A7: CDM Master | B7: CPT/HCPCS | C7: Procedure, service, supply, or drug code when applicable | D7: Text | E7: Conditional | F7: Current valid code | G7: Required by service/revenue/payer rule | H7: Coding master | I7: Coding | J7: Licensed/regulated
A8: CDM Master | B8: NDC / Device ID | C8: Drug NDC or device identifier supporting item-level billing | D8: Text | E8: Conditional | F8: Configured format | G8: Required by payer or regulatory rule | H8: Pharmacy/Inventory | I8: Department owner | J8: Restricted operational
A9: IPD Encounter | B9: HAR | C9: Hospital account identifier for facility billing | D9: Text | E9: Yes | F9: Unique account ID | G9: Must link to encounter and payer | H9: Patient accounting | I9: HB Billing | J9: Synthetic in demo
A10: IPD Encounter | B10: Extended Gross | C10: Quantity multiplied by CDM gross unit charge | D10: Currency | E10: Yes | F10: Formula | G10: Quantity x unit charge | H10: Derived | I10: Revenue Integrity | J10: Financial
A11: Price Transparency | B11: Negotiated Charge | C11: Payer- and plan-specific negotiated amount | D11: Currency | E11: Conditional | F11: Dollar / methodology | G11: Must be current and attributable | H11: Contract management | I11: Managed Care | J11: Public when reported
A12: Governance | B12: Status | C12: Current lifecycle stage of a change request | D12: Text | E12: Yes | F12: Submitted/In Review/Approved/Ready/Closed | G12: Controlled transition | H12: Change control | I12: Revenue Integrity | J12: Internal
