Workbook

Sheet README
A1: Original Hospital Revenue Cycle Charge Demo
A2: Independent synthetic demonstration workbook. It is not an Epic product, replica, extract, or proprietary build.
A4: Purpose | B4: Provides an original hospital revenue-cycle dataset with separate inpatient and outpatient charge-detail views, CDM controls, routing, billing edits, contracts, governance, and auditability.
A5: Epic alignment | B5: Uses common US hospital billing concepts such as hospital accounts, charge routing, workqueues, facility/professional split, institutional claims, and reimbursement. No proprietary EHR design is reproduced.
A6: Primary sheets | B6: CDM Master; IPD Encounter; Charge Router Rules; Claim Edits; Payer Contracts; Price Transparency; Governance; Audit Trail; Data Source Map; Data Dictionary; Dashboard.
A7: Color convention | B7: Blue = editable input; black = formula/derived; green = linked/imported; gray = static reference; orange = review; red = error/hold; purple = control logic; teal = KPI/visualization.
A8: Data disclaimer | B8: All patients, payers, prices, contracts, identifiers, effective dates, and operational scenarios are synthetic. No PHI is included.
A9: Sources | B9: Epic public financial interface documentation: https://open.epic.com/Financial/Billing CMS Hospital Price Transparency: https://www.cms.gov/priorities/key-initiatives/hospital-price-transparency CMS technical implementation guide: https://github.com/CMSgov/hospital-price-transparency

Sheet Charge Summary
A1: IPD and OPD Charge Summary
A2: Executive comparison of the 210 synthetic charge lines included in this workbook.
A4: Setting | B4: Charge Lines | C4: Gross Charges ($) | D4: Expected Allowed ($) | E4: Patient Responsibility ($) | F4: Adjustments ($) | G4: Held Charges | H4: Review Edits
A5: IPD | B5: =COUNTA('IPD Charges'!A5:A500) -> 110 | C5: =SUM('IPD Charges'!O:O) -> 1002840 | D5: =SUM('IPD Charges'!P:P) -> 555691.1 | E5: =SUM('IPD Charges'!Q:Q) -> 111138.22 | F5: =SUM('IPD Charges'!R:R) -> 447148.9 | G5: =COUNTIF('IPD Charges'!Z:Z,"Hold") -> 3 | H5: =COUNTIF('IPD Charges'!AB:AB,"Review") -> 7
A6: OPD | B6: =COUNTA('OPD Charges'!A5:A500) -> 100 | C6: =SUM('OPD Charges'!O:O) -> 250780 | D6: =SUM('OPD Charges'!P:P) -> 140185 | E6: =SUM('OPD Charges'!Q:Q) -> 28037 | F6: =SUM('OPD Charges'!R:R) -> 110595 | G6: =COUNTIF('OPD Charges'!Z:Z,"Hold") -> 3 | H6: =COUNTIF('OPD Charges'!AB:AB,"Review") -> 7
A7: TOTAL | B7: =SUM(B5:B6) -> 210 | C7: =SUM(C5:C6) -> 1253620 | D7: =SUM(D5:D6) -> 695876.1 | E7: =SUM(E5:E6) -> 139175.22 | F7: =SUM(F5:F6) -> 557743.9 | G7: =SUM(G5:G6) -> 6 | H7: =SUM(H5:H6) -> 14

Sheet IPD Charges
A1: Inpatient Charge Detail
A2: 110 original synthetic inpatient charge lines covering accommodation, surgery, implants, drugs, diagnostics, therapies, and ancillary services.
A4: Charge Line ID | B4: Patient Account | C4: Encounter ID | D4: Patient Class | E4: Facility | F4: Department | G4: Service Date | H4: Charge Code | I4: Charge Description | J4: Revenue Code | K4: CPT/HCPCS | L4: Modifier | M4: Quantity | N4: Unit Charge ($) | O4: Extended Gross ($) | P4: Expected Allowed ($) | Q4: Patient Responsibility ($) | R4: Contractual Adjustment ($) | S4: Payer | T4: Plan | U4: Authorization ID | V4: Ordering Provider | W4: Performing Provider | X4: Source System | Y4: Charge Trigger | Z4: Charge Status | AA4: Reconciliation Status | AB4: Claim Edit Status | AC4: Workqueue | AD4: Medical Necessity | AE4: Diagnosis Link | AF4: Place of Service | AG4: Posting Date/Time | AH4: Notes
A5: IPD-CHG-0001 | B5: HAR-202600001 | C5: CSN-IPD-780001 | D5: Inpatient | E5: Demo Regional Medical Center | F5: Accommodation | G5: 2026-09-02 | H5: RM-SEMI-DAY | I5: Semiprivate Medical/Surgical Room | J5: 0120 | M5: 1 | N5: 3500 | O5: =M5*N5 -> 3500 | P5: 1496.26 | Q5: =P5*20% -> 299.252 | R5: =O5-P5 -> 2003.74 | S5: Demo PPO | T5: Gold PPO | V5: Eleanor Brooks, MD | W5: Assigned Department Provider | X5: ADT | Y5: Midnight census | Z5: Posted | AA5: Matched | AB5: Passed | AD5: N/A | AE5: M17.11 | AF5: 21 | AG5: 2026-09-02 16:30 | AH5: Synthetic demonstration charge
A6: IPD-CHG-0002 | B6: HAR-202600002 | C6: CSN-IPD-780002 | D6: Inpatient | E6: Demo Regional Medical Center | F6: Accommodation | G6: 2026-09-03 | H6: RM-PRIV-DAY | I6: Private Medical/Surgical Room | J6: 0110 | M6: 3 | N6: 4600 | O6: =M6*N6 -> 13800 | P6: 6809.85 | Q6: =P6*20% -> 1361.97 | R6: =O6-P6 -> 6990.15 | S6: Demo PPO | T6: Gold PPO | V6: Eleanor Brooks, MD | W6: Assigned Department Provider | X6: ADT | Y6: Midnight census | Z6: Posted | AA6: Matched | AB6: Passed | AD6: N/A | AE6: M17.11 | AF6: 21 | AG6: 2026-09-03 16:30 | AH6: Synthetic demonstration charge
A7: IPD-CHG-0003 | B7: HAR-202600003 | C7: CSN-IPD-780003 | D7: Inpatient | E7: Demo Regional Medical Center | F7: Intensive Care | G7: 2026-09-04 | H7: ICU-DAY | I7: Intensive Care Unit Room | J7: 0200 | M7: 2 | N7: 8200 | O7: =M7*N7 -> 16400 | P7: 10511.44 | Q7: =P7*20% -> 2102.288 | R7: =O7-P7 -> 5888.56 | S7: Demo PPO | T7: Gold PPO | V7: Eleanor Brooks, MD | W7: Assigned Department Provider | X7: ADT | Y7: Midnight census | Z7: Posted | AA7: Matched | AB7: Passed | AD7: N/A | AE7: J96.01 | AF7: 21 | AG7: 2026-09-04 16:30 | AH7: Synthetic demonstration charge
A8: IPD-CHG-0004 | B8: HAR-202600004 | C8: CSN-IPD-780004 | D8: Inpatient | E8: Demo Regional Medical Center | F8: Operating Room | G8: 2026-09-05 | H8: OR-MAJOR-1H | I8: Major Operating Room, First Hour | J8: 0360 | M8: 1 | N8: 10250 | O8: =M8*N8 -> 10250 | P8: 6120.76 | Q8: =P8*20% -> 1224.152 | R8: =O8-P8 -> 4129.24 | S8: Demo PPO | T8: Gold PPO | V8: Eleanor Brooks, MD | W8: Assigned Department Provider | X8: Perioperative | Y8: Procedure end | Z8: Posted | AA8: Matched | AB8: Passed | AD8: Procedure-specific | AE8: M17.11 | AF8: 21 | AG8: 2026-09-05 16:30 | AH8: Synthetic demonstration charge
A9: IPD-CHG-0005 | B9: HAR-202600005 | C9: CSN-IPD-780005 | D9: Inpatient | E9: Demo Regional Medical Center | F9: Operating Room | G9: 2026-09-06 | H9: OR-ADD-15 | I9: Operating Room, Additional 15 Minutes | J9: 0360 | M9: 2 | N9: 1280 | O9: =M9*N9 -> 2560 | P9: 1098.08 | Q9: =P9*20% -> 219.616 | R9: =O9-P9 -> 1461.92 | S9: Demo PPO | T9: Gold PPO | V9: Eleanor Brooks, MD | W9: Assigned Department Provider | X9: Perioperative | Y9: Procedure end | Z9: Posted | AA9: Matched | AB9: Passed | AD9: Procedure-specific | AE9: M17.11 | AF9: 21 | AG9: 2026-09-06 16:30 | AH9: Synthetic demonstration charge
A10: IPD-CHG-0006 | B10: HAR-202600006 | C10: CSN-IPD-780006 | D10: Inpatient | E10: Demo Regional Medical Center | F10: Recovery Room | G10: 2026-09-07 | H10: PACU-1H | I10: Post-Anesthesia Care, First Hour | J10: 0710 | M10: 1 | N10: 2100 | O10: =M10*N10 -> 2100 | P10: 1019.74 | Q10: =P10*20% -> 203.948 | R10: =O10-P10 -> 1080.26 | S10: Demo PPO | T10: Gold PPO | V10: Eleanor Brooks, MD | W10: Assigned Department Provider | X10: Perioperative | Y10: PACU discharge | Z10: Posted | AA10: Matched | AB10: Passed | AD10: N/A | AE10: Z47.1 | AF10: 21 | AG10: 2026-09-07 16:30 | AH10: Synthetic demonstration charge
A11: IPD-CHG-0007 | B11: HAR-202600007 | C11: CSN-IPD-780007 | D11: Inpatient | E11: Demo Regional Medical Center | F11: Surgical Supplies | G11: 2026-09-08 | H11: SUP-MAJOR-PACK | I11: Major Surgery Disposable Supply Pack | J11: 0270 | M11: 1 | N11: 4200 | O11: =M11*N11 -> 4200 | P11: 2400.75 | Q11: =P11*20% -> 480.15 | R11: =O11-P11 -> 1799.25 | S11: Demo PPO | T11: Gold PPO | V11: Eleanor Brooks, MD | W11: Assigned Department Provider | X11: Inventory | Y11: Supply issue | Z11: Posted | AA11: Matched | AB11: Passed | AD11: Contract rule | AE11: Z47.1 | AF11: 21 | AG11: 2026-09-08 16:30 | AH11: Synthetic demonstration charge
A12: IPD-CHG-0008 | B12: HAR-202600008 | C12: CSN-IPD-780008 | D12: Inpatient | E12: Demo Regional Medical Center | F12: Implants | G12: 2026-09-09 | H12: IMP-KNEE-CEM | I12: Cemented Knee Implant System | J12: 0278 | M12: 1 | N12: 20500 | O12: =M12*N12 -> 20500 | P12: 8773.2 | Q12: =P12*20% -> 1754.64 | R12: =O12-P12 -> 11726.8 | S12: Demo PPO | T12: Gold PPO | V12: Eleanor Brooks, MD | W12: Assigned Department Provider | X12: Inventory | Y12: Implant scan | Z12: Posted | AA12: Matched | AB12: Passed | AD12: Contract rule | AE12: M17.11 | AF12: 21 | AG12: 2026-09-09 16:30 | AH12: Synthetic demonstration charge
A13: IPD-CHG-0009 | B13: HAR-202600009 | C13: CSN-IPD-780009 | D13: Inpatient | E13: Demo Regional Medical Center | F13: Implants | G13: 2026-09-10 | H13: IMP-SCREW | I13: Orthopedic Fixation Screw | J13: 0278 | K13: C1713 | M13: 1 | N13: 950 | O13: =M13*N13 -> 950 | P13: 455.67 | Q13: =P13*20% -> 91.134 | R13: =O13-P13 -> 494.33 | S13: Demo PPO | T13: Gold PPO | V13: Eleanor Brooks, MD | W13: Assigned Department Provider | X13: Inventory | Y13: Implant scan | Z13: Posted | AA13: Matched | AB13: Passed | AD13: Contract rule | AE13: M17.11 | AF13: 21 | AG13: 2026-09-10 16:30 | AH13: Synthetic demonstration charge
A14: IPD-CHG-0010 | B14: HAR-202600010 | C14: CSN-IPD-780010 | D14: Inpatient | E14: Demo Regional Medical Center | F14: Pharmacy | G14: 2026-09-11 | H14: DRUG-CEFA-1G | I14: Cefazolin 1 g Injection | J14: 0250 | K14: J0690 | M14: 3 | N14: 500 | O14: =M14*N14 -> 1500 | P14: 945.6 | Q14: =P14*20% -> 189.12 | R14: =O14-P14 -> 554.4 | S14: Demo PPO | T14: Gold PPO | V14: Eleanor Brooks, MD | W14: Assigned Department Provider | X14: Pharmacy MAR | Y14: Medication administration | Z14: Posted | AA14: Matched | AB14: Passed | AD14: Dose/frequency | AE14: Z79.2 | AF14: 21 | AG14: 2026-09-11 16:30 | AH14: Synthetic demonstration charge
A15: IPD-CHG-0011 | B15: HAR-202600011 | C15: CSN-IPD-780011 | D15: Inpatient | E15: Demo Regional Medical Center | F15: Pharmacy | G15: 2026-09-12 | H15: DRUG-VANC-500 | I15: Vancomycin 500 mg Injection | J15: 0250 | K15: J3370 | M15: 2 | N15: 680 | O15: =M15*N15 -> 1360 | P15: 661.14 | Q15: =P15*20% -> 132.228 | R15: =O15-P15 -> 698.86 | S15: Demo PPO | T15: Gold PPO | V15: Eleanor Brooks, MD | W15: Assigned Department Provider | X15: Pharmacy MAR | Y15: Medication administration | Z15: Posted | AA15: Matched | AB15: Passed | AD15: Dose/frequency | AE15: Z79.2 | AF15: 21 | AG15: 2026-09-12 16:30 | AH15: Synthetic demonstration charge
A16: IPD-CHG-0012 | B16: HAR-202600012 | C16: CSN-IPD-780012 | D16: Inpatient | E16: Demo Regional Medical Center | F16: Pharmacy | G16: 2026-09-13 | H16: IV-NS-1L | I16: Normal Saline 1,000 mL | J16: 0258 | K16: J7030 | M16: 3 | N16: 90 | O16: =M16*N16 -> 270 | P16: 135.93 | Q16: =P16*20% -> 27.186 | R16: =O16-P16 -> 134.07 | S16: Demo PPO | T16: Gold PPO | V16: Eleanor Brooks, MD | W16: Assigned Department Provider | X16: Pharmacy MAR | Y16: Medication administration | Z16: Posted | AA16: Matched | AB16: Passed | AD16: N/A | AE16: E86.0 | AF16: 21 | AG16: 2026-09-13 16:30 | AH16: Synthetic demonstration charge
A17: IPD-CHG-0013 | B17: HAR-202600013 | C17: CSN-IPD-780013 | D17: Inpatient | E17: Demo Regional Medical Center | F17: Laboratory | G17: 2026-09-14 | H17: LAB-CBC | I17: Complete Blood Count with Differential | J17: 0300 | K17: 85025 | M17: 1 | N17: 155 | O17: =M17*N17 -> 155 | P17: 105.52 | Q17: =P17*20% -> 21.104 | R17: =O17-P17 -> 49.48 | S17: Demo PPO | T17: Gold PPO | V17: Eleanor Brooks, MD | W17: Assigned Department Provider | X17: LIS | Y17: Final result | Z17: Posted | AA17: Matched | AB17: Passed | AD17: Diagnosis/LCD | AE17: D64.9 | AF17: 21 | AG17: 2026-09-14 16:30 | AH17: Synthetic demonstration charge
A18: IPD-CHG-0014 | B18: HAR-202600014 | C18: CSN-IPD-780014 | D18: Inpatient | E18: Demo Regional Medical Center | F18: Laboratory | G18: 2026-09-15 | H18: LAB-CMP | I18: Comprehensive Metabolic Panel | J18: 0301 | K18: 80053 | M18: 1 | N18: 245 | O18: =M18*N18 -> 245 | P18: 158.67 | Q18: =P18*20% -> 31.734 | R18: =O18-P18 -> 86.33 | S18: Demo PPO | T18: Gold PPO | V18: Eleanor Brooks, MD | W18: Assigned Department Provider | X18: LIS | Y18: Final result | Z18: Posted | AA18: Matched | AB18: Passed | AD18: Diagnosis/LCD | AE18: E11.9 | AF18: 21 | AG18: 2026-09-15 16:30 | AH18: Synthetic demonstration charge
A19: IPD-CHG-0015 | B19: HAR-202600015 | C19: CSN-IPD-780015 | D19: Inpatient | E19: Demo Regional Medical Center | F19: Laboratory | G19: 2026-09-16 | H19: LAB-PTINR | I19: Prothrombin Time / INR | J19: 0305 | K19: 85610 | M19: 1 | N19: 125 | O19: =M19*N19 -> 125 | P19: 58.49 | Q19: =P19*20% -> 11.698 | R19: =O19-P19 -> 66.51 | S19: Demo PPO | T19: Gold PPO | V19: Eleanor Brooks, MD | W19: Assigned Department Provider | X19: LIS | Y19: Final result | Z19: Posted | AA19: Matched | AB19: Passed | AD19: Diagnosis/LCD | AE19: Z79.01 | AF19: 21 | AG19: 2026-09-16 16:30 | AH19: Synthetic demonstration charge
A20: IPD-CHG-0016 | B20: HAR-202600016 | C20: CSN-IPD-780016 | D20: Inpatient | E20: Demo Regional Medical Center | F20: Radiology | G20: 2026-09-17 | H20: RAD-CHEST-2V | I20: Chest X-ray, 2 Views | J20: 0320 | K20: 71046 | M20: 1 | N20: 185 | O20: =M20*N20 -> 185 | P20: 101.16 | Q20: =P20*20% -> 20.232 | R20: =O20-P20 -> 83.84 | S20: Demo PPO | T20: Gold PPO | V20: Eleanor Brooks, MD | W20: Assigned Department Provider | X20: RIS/PACS | Y20: Exam completed | Z20: Posted | AA20: Matched | AB20: Passed | AD20: Diagnosis/LCD | AE20: R06.02 | AF20: 21 | AG20: 2026-09-17 16:30 | AH20: Synthetic demonstration charge
A21: IPD-CHG-0017 | B21: HAR-202600017 | C21: CSN-IPD-780017 | D21: Inpatient | E21: Demo Regional Medical Center | F21: Radiology | G21: 2026-09-18 | H21: RAD-KNEE-2V | I21: Knee X-ray, 1-2 Views | J21: 0320 | K21: 73560 | M21: 1 | N21: 410 | O21: =M21*N21 -> 410 | P21: 206.38 | Q21: =P21*20% -> 41.276 | R21: =O21-P21 -> 203.62 | S21: Demo PPO | T21: Gold PPO | V21: Eleanor Brooks, MD | W21: Assigned Department Provider | X21: RIS/PACS | Y21: Exam completed | Z21: Posted | AA21: Matched | AB21: Passed | AD21: Diagnosis/LCD | AE21: M25.561 | AF21: 21 | AG21: 2026-09-18 16:30 | AH21: Synthetic demonstration charge
A22: IPD-CHG-0018 | B22: HAR-202600018 | C22: CSN-IPD-780018 | D22: Inpatient | E22: Demo Regional Medical Center | F22: Cardiology | G22: 2026-09-19 | H22: CARD-ECG12 | I22: 12-Lead ECG | J22: 0730 | K22: 93005 | M22: 1 | N22: 190 | O22: =M22*N22 -> 190 | P22: 92.07 | Q22: =P22*20% -> 18.414 | R22: =O22-P22 -> 97.93 | S22: Demo PPO | T22: Gold PPO | V22: Eleanor Brooks, MD | W22: Assigned Department Provider | X22: Cardiology | Y22: Test completed | Z22: Posted | AA22: Matched | AB22: Passed | AD22: Diagnosis/LCD | AE22: R07.9 | AF22: 21 | AG22: 2026-09-19 16:30 | AH22: Synthetic demonstration charge
A23: IPD-CHG-0019 | B23: HAR-202600019 | C23: CSN-IPD-780019 | D23: Inpatient | E23: Demo Regional Medical Center | F23: Respiratory | G23: 2026-09-20 | H23: RESP-NEB | I23: Nebulizer Treatment | J23: 0410 | K23: 94640 | M23: 1 | N23: 245 | O23: =M23*N23 -> 245 | P23: 159.02 | Q23: =P23*20% -> 31.804 | R23: =O23-P23 -> 85.98 | S23: Demo PPO | T23: Gold PPO | V23: Eleanor Brooks, MD | W23: Assigned Department Provider | X23: Respiratory | Y23: Treatment completed | Z23: Posted | AA23: Matched | AB23: Passed | AD23: Diagnosis/LCD | AE23: J45.901 | AF23: 21 | AG23: 2026-09-20 16:30 | AH23: Synthetic demonstration charge
A24: IPD-CHG-0020 | B24: HAR-202600020 | C24: CSN-IPD-780020 | D24: Inpatient | E24: Demo Regional Medical Center | F24: Physical Therapy | G24: 2026-09-21 | H24: PT-EVAL-LOW | I24: Physical Therapy Evaluation, Low Complexity | J24: 0420 | K24: 97161 | M24: 1 | N24: 710 | O24: =M24*N24 -> 710 | P24: 319.97 | Q24: =P24*20% -> 63.994 | R24: =O24-P24 -> 390.03 | S24: Demo PPO | T24: Gold PPO | U24: AUTH-700020 | V24: Eleanor Brooks, MD | W24: Assigned Department Provider | X24: Therapy | Y24: Note signed | Z24: Posted | AA24: Matched | AB24: Passed | AD24: Plan benefits | AE24: R26.2 | AF24: 21 | AG24: 2026-09-21 16:30 | AH24: Synthetic demonstration charge
A25: IPD-CHG-0021 | B25: HAR-202600021 | C25: CSN-IPD-780021 | D25: Inpatient | E25: Demo Regional Medical Center | F25: Physical Therapy | G25: 2026-09-22 | H25: PT-THEREX-15 | I25: Therapeutic Exercise, 15 Minutes | J25: 0420 | K25: 97110 | M25: 6 | N25: 305 | O25: =M25*N25 -> 1830 | P25: 821.7 | Q25: =P25*20% -> 164.34 | R25: =O25-P25 -> 1008.3 | S25: Demo PPO | T25: Gold PPO | V25: Eleanor Brooks, MD | W25: Assigned Department Provider | X25: Therapy | Y25: Note signed | Z25: Posted | AA25: Matched | AB25: Passed | AD25: Timed units | AE25: M62.81 | AF25: 21 | AG25: 2026-09-22 16:30 | AH25: Synthetic demonstration charge
A26: IPD-CHG-0022 | B26: HAR-202600022 | C26: CSN-IPD-780022 | D26: Inpatient | E26: Demo Regional Medical Center | F26: Occupational Therapy | G26: 2026-09-23 | H26: OT-EVAL-LOW | I26: Occupational Therapy Evaluation, Low Complexity | J26: 0430 | K26: 97165 | M26: 1 | N26: 725 | O26: =M26*N26 -> 725 | P26: 488.83 | Q26: =P26*20% -> 97.766 | R26: =O26-P26 -> 236.17 | S26: Demo PPO | T26: Gold PPO | U26: AUTH-700022 | V26: Eleanor Brooks, MD | W26: Assigned Department Provider | X26: Therapy | Y26: Note signed | Z26: Posted | AA26: Matched | AB26: Passed | AD26: Plan benefits | AE26: Z74.09 | AF26: 21 | AG26: 2026-09-23 16:30 | AH26: Synthetic demonstration charge
A27: IPD-CHG-0023 | B27: HAR-202600023 | C27: CSN-IPD-780023 | D27: Inpatient | E27: Demo Regional Medical Center | F27: Nutrition | G27: 2026-09-24 | H27: NUTR-ASSESS | I27: Inpatient Nutrition Assessment | J27: 0942 | K27: 97802 | M27: 1 | N27: 325 | O27: =M27*N27 -> 325 | P27: 195.36 | Q27: =P27*20% -> 39.072 | R27: =O27-P27 -> 129.64 | S27: Demo PPO | T27: Gold PPO | V27: Eleanor Brooks, MD | W27: Assigned Department Provider | X27: Dietary | Y27: Note signed | Z27: Posted | AA27: Matched | AB27: Review | AC27: WQ-NUT-04 | AD27: N/A | AE27: E44.1 | AF27: 21 | AG27: 2026-09-24 16:30 | AH27: Synthetic demonstration charge
A28: IPD-CHG-0024 | B28: HAR-202600024 | C28: CSN-IPD-780024 | D28: Inpatient | E28: Demo Regional Medical Center | F28: Dialysis | G28: 2026-09-25 | H28: DIALYSIS-IP | I28: Inpatient Hemodialysis Treatment | J28: 0801 | K28: 90935 | M28: 1 | N28: 1600 | O28: =M28*N28 -> 1600 | P28: 1059.42 | Q28: =P28*20% -> 211.884 | R28: =O28-P28 -> 540.58 | S28: Demo PPO | T28: Gold PPO | V28: Eleanor Brooks, MD | W28: Assigned Department Provider | X28: Dialysis | Y28: Treatment completed | Z28: Posted | AA28: Matched | AB28: Passed | AD28: Diagnosis/LCD | AE28: N18.6 | AF28: 21 | AG28: 2026-09-25 16:30 | AH28: Synthetic demonstration charge
A29: IPD-CHG-0025 | B29: HAR-202600025 | C29: CSN-IPD-780025 | D29: Inpatient | E29: Demo Regional Medical Center | F29: Accommodation | G29: 2026-09-01 | H29: RM-SEMI-DAY | I29: Semiprivate Medical/Surgical Room | J29: 0120 | M29: 4 | N29: 3500 | O29: =M29*N29 -> 14000 | P29: 8132.16 | Q29: =P29*20% -> 1626.432 | R29: =O29-P29 -> 5867.84 | S29: Demo PPO | T29: Gold PPO | V29: Eleanor Brooks, MD | W29: Assigned Department Provider | X29: ADT | Y29: Midnight census | Z29: Posted | AA29: Matched | AB29: Passed | AD29: N/A | AE29: M17.11 | AF29: 21 | AG29: 2026-09-01 16:30 | AH29: Synthetic demonstration charge
A30: IPD-CHG-0026 | B30: HAR-202600026 | C30: CSN-IPD-780026 | D30: Inpatient | E30: Demo Regional Medical Center | F30: Accommodation | G30: 2026-09-02 | H30: RM-PRIV-DAY | I30: Private Medical/Surgical Room | J30: 0110 | M30: 4 | N30: 4600 | O30: =M30*N30 -> 18400 | P30: 8162.98 | Q30: =P30*20% -> 1632.596 | R30: =O30-P30 -> 10237.02 | S30: Demo PPO | T30: Gold PPO | V30: Eleanor Brooks, MD | W30: Assigned Department Provider | X30: ADT | Y30: Midnight census | Z30: Posted | AA30: Matched | AB30: Passed | AD30: N/A | AE30: M17.11 | AF30: 21 | AG30: 2026-09-02 16:30 | AH30: Synthetic demonstration charge
A31: IPD-CHG-0027 | B31: HAR-202600027 | C31: CSN-IPD-780027 | D31: Inpatient | E31: Demo Regional Medical Center | F31: Intensive Care | G31: 2026-09-03 | H31: ICU-DAY | I31: Intensive Care Unit Room | J31: 0200 | M31: 3 | N31: 8200 | O31: =M31*N31 -> 24600 | P31: 16453.01 | Q31: =P31*20% -> 3290.602 | R31: =O31-P31 -> 8146.99 | S31: Demo PPO | T31: Gold PPO | V31: Eleanor Brooks, MD | W31: Assigned Department Provider | X31: ADT | Y31: Midnight census | Z31: Posted | AA31: Matched | AB31: Passed | AD31: N/A | AE31: J96.01 | AF31: 21 | AG31: 2026-09-03 16:30 | AH31: Synthetic demonstration charge
A32: IPD-CHG-0028 | B32: HAR-202600028 | C32: CSN-IPD-780028 | D32: Inpatient | E32: Demo Regional Medical Center | F32: Operating Room | G32: 2026-09-04 | H32: OR-MAJOR-1H | I32: Major Operating Room, First Hour | J32: 0360 | M32: 3 | N32: 10250 | O32: =M32*N32 -> 30750 | P32: 18241.07 | Q32: =P32*20% -> 3648.214 | R32: =O32-P32 -> 12508.93 | S32: Demo PPO | T32: Gold PPO | V32: Eleanor Brooks, MD | W32: Assigned Department Provider | X32: Perioperative | Y32: Procedure end | Z32: Posted | AA32: Matched | AB32: Passed | AD32: Procedure-specific | AE32: M17.11 | AF32: 21 | AG32: 2026-09-04 16:30 | AH32: Synthetic demonstration charge
A33: IPD-CHG-0029 | B33: HAR-202600029 | C33: CSN-IPD-780029 | D33: Inpatient | E33: Demo Regional Medical Center | F33: Operating Room | G33: 2026-09-05 | H33: OR-ADD-15 | I33: Operating Room, Additional 15 Minutes | J33: 0360 | M33: 2 | N33: 1280 | O33: =M33*N33 -> 2560 | P33: 1110.39 | Q33: =P33*20% -> 222.078 | R33: =O33-P33 -> 1449.61 | S33: Demo PPO | T33: Gold PPO | V33: Eleanor Brooks, MD | W33: Assigned Department Provider | X33: Perioperative | Y33: Procedure end | Z33: Hold | AA33: Exception | AB33: Review | AC33: WQ-OPE-02 | AD33: Procedure-specific | AE33: M17.11 | AF33: 21 | AG33: 2026-09-05 16:30 | AH33: Synthetic demonstration charge
A34: IPD-CHG-0030 | B34: HAR-202600030 | C34: CSN-IPD-780030 | D34: Inpatient | E34: Demo Regional Medical Center | F34: Recovery Room | G34: 2026-09-06 | H34: PACU-1H | I34: Post-Anesthesia Care, First Hour | J34: 0710 | M34: 1 | N34: 2100 | O34: =M34*N34 -> 2100 | P34: 1025.58 | Q34: =P34*20% -> 205.116 | R34: =O34-P34 -> 1074.42 | S34: Demo PPO | T34: Gold PPO | V34: Eleanor Brooks, MD | W34: Assigned Department Provider | X34: Perioperative | Y34: PACU discharge | Z34: Posted | AA34: Matched | AB34: Passed | AD34: N/A | AE34: Z47.1 | AF34: 21 | AG34: 2026-09-06 16:30 | AH34: Synthetic demonstration charge
A35: IPD-CHG-0031 | B35: HAR-202600031 | C35: CSN-IPD-780031 | D35: Inpatient | E35: Demo Regional Medical Center | F35: Surgical Supplies | G35: 2026-09-07 | H35: SUP-MAJOR-PACK | I35: Major Surgery Disposable Supply Pack | J35: 0270 | M35: 1 | N35: 4200 | O35: =M35*N35 -> 4200 | P35: 2128.63 | Q35: =P35*20% -> 425.726 | R35: =O35-P35 -> 2071.37 | S35: Demo PPO | T35: Gold PPO | V35: Eleanor Brooks, MD | W35: Assigned Department Provider | X35: Inventory | Y35: Supply issue | Z35: Posted | AA35: Matched | AB35: Passed | AD35: Contract rule | AE35: Z47.1 | AF35: 21 | AG35: 2026-09-07 16:30 | AH35: Synthetic demonstration charge
A36: IPD-CHG-0032 | B36: HAR-202600032 | C36: CSN-IPD-780032 | D36: Inpatient | E36: Demo Regional Medical Center | F36: Implants | G36: 2026-09-08 | H36: IMP-KNEE-CEM | I36: Cemented Knee Implant System | J36: 0278 | M36: 1 | N36: 20500 | O36: =M36*N36 -> 20500 | P36: 9100.72 | Q36: =P36*20% -> 1820.144 | R36: =O36-P36 -> 11399.28 | S36: Demo PPO | T36: Gold PPO | V36: Eleanor Brooks, MD | W36: Assigned Department Provider | X36: Inventory | Y36: Implant scan | Z36: Posted | AA36: Matched | AB36: Passed | AD36: Contract rule | AE36: M17.11 | AF36: 21 | AG36: 2026-09-08 16:30 | AH36: Synthetic demonstration charge
A37: IPD-CHG-0033 | B37: HAR-202600033 | C37: CSN-IPD-780033 | D37: Inpatient | E37: Demo Regional Medical Center | F37: Implants | G37: 2026-09-09 | H37: IMP-SCREW | I37: Orthopedic Fixation Screw | J37: 0278 | K37: C1713 | M37: 1 | N37: 950 | O37: =M37*N37 -> 950 | P37: 465.35 | Q37: =P37*20% -> 93.07 | R37: =O37-P37 -> 484.65 | S37: Demo PPO | T37: Gold PPO | V37: Eleanor Brooks, MD | W37: Assigned Department Provider | X37: Inventory | Y37: Implant scan | Z37: Posted | AA37: Matched | AB37: Passed | AD37: Contract rule | AE37: M17.11 | AF37: 21 | AG37: 2026-09-09 16:30 | AH37: Synthetic demonstration charge
A38: IPD-CHG-0034 | B38: HAR-202600034 | C38: CSN-IPD-780034 | D38: Inpatient | E38: Demo Regional Medical Center | F38: Pharmacy | G38: 2026-09-10 | H38: DRUG-CEFA-1G | I38: Cefazolin 1 g Injection | J38: 0250 | K38: J0690 | M38: 1 | N38: 500 | O38: =M38*N38 -> 500 | P38: 267.02 | Q38: =P38*20% -> 53.404 | R38: =O38-P38 -> 232.98 | S38: Demo PPO | T38: Gold PPO | V38: Eleanor Brooks, MD | W38: Assigned Department Provider | X38: Pharmacy MAR | Y38: Medication administration | Z38: Posted | AA38: Matched | AB38: Passed | AD38: Dose/frequency | AE38: Z79.2 | AF38: 21 | AG38: 2026-09-10 16:30 | AH38: Synthetic demonstration charge
A39: IPD-CHG-0035 | B39: HAR-202600035 | C39: CSN-IPD-780035 | D39: Inpatient | E39: Demo Regional Medical Center | F39: Pharmacy | G39: 2026-09-11 | H39: DRUG-VANC-500 | I39: Vancomycin 500 mg Injection | J39: 0250 | K39: J3370 | M39: 2 | N39: 680 | O39: =M39*N39 -> 1360 | P39: 830.56 | Q39: =P39*20% -> 166.112 | R39: =O39-P39 -> 529.44 | S39: Demo PPO | T39: Gold PPO | V39: Eleanor Brooks, MD | W39: Assigned Department Provider | X39: Pharmacy MAR | Y39: Medication administration | Z39: Posted | AA39: Matched | AB39: Passed | AD39: Dose/frequency | AE39: Z79.2 | AF39: 21 | AG39: 2026-09-11 16:30 | AH39: Synthetic demonstration charge
A40: IPD-CHG-0036 | B40: HAR-202600036 | C40: CSN-IPD-780036 | D40: Inpatient | E40: Demo Regional Medical Center | F40: Pharmacy | G40: 2026-09-12 | H40: IV-NS-1L | I40: Normal Saline 1,000 mL | J40: 0258 | K40: J7030 | M40: 2 | N40: 90 | O40: =M40*N40 -> 180 | P40: 84.38 | Q40: =P40*20% -> 16.876 | R40: =O40-P40 -> 95.62 | S40: Demo PPO | T40: Gold PPO | V40: Eleanor Brooks, MD | W40: Assigned Department Provider | X40: Pharmacy MAR | Y40: Medication administration | Z40: Posted | AA40: Matched | AB40: Passed | AD40: N/A | AE40: E86.0 | AF40: 21 | AG40: 2026-09-12 16:30 | AH40: Synthetic demonstration charge
A41: IPD-CHG-0037 | B41: HAR-202600037 | C41: CSN-IPD-780037 | D41: Inpatient | E41: Demo Regional Medical Center | F41: Laboratory | G41: 2026-09-13 | H41: LAB-CBC | I41: Complete Blood Count with Differential | J41: 0300 | K41: 85025 | M41: 1 | N41: 155 | O41: =M41*N41 -> 155 | P41: 81.62 | Q41: =P41*20% -> 16.324 | R41: =O41-P41 -> 73.38 | S41: Demo PPO | T41: Gold PPO | V41: Eleanor Brooks, MD | W41: Assigned Department Provider | X41: LIS | Y41: Final result | Z41: Posted | AA41: Matched | AB41: Passed | AD41: Diagnosis/LCD | AE41: D64.9 | AF41: 21 | AG41: 2026-09-13 16:30 | AH41: Synthetic demonstration charge
A42: IPD-CHG-0038 | B42: HAR-202600038 | C42: CSN-IPD-780038 | D42: Inpatient | E42: Demo Regional Medical Center | F42: Laboratory | G42: 2026-09-14 | H42: LAB-CMP | I42: Comprehensive Metabolic Panel | J42: 0301 | K42: 80053 | M42: 1 | N42: 245 | O42: =M42*N42 -> 245 | P42: 152.16 | Q42: =P42*20% -> 30.432 | R42: =O42-P42 -> 92.84 | S42: Demo PPO | T42: Gold PPO | V42: Eleanor Brooks, MD | W42: Assigned Department Provider | X42: LIS | Y42: Final result | Z42: Posted | AA42: Matched | AB42: Passed | AD42: Diagnosis/LCD | AE42: E11.9 | AF42: 21 | AG42: 2026-09-14 16:30 | AH42: Synthetic demonstration charge
A43: IPD-CHG-0039 | B43: HAR-202600039 | C43: CSN-IPD-780039 | D43: Inpatient | E43: Demo Regional Medical Center | F43: Laboratory | G43: 2026-09-15 | H43: LAB-PTINR | I43: Prothrombin Time / INR | J43: 0305 | K43: 85610 | M43: 1 | N43: 125 | O43: =M43*N43 -> 125 | P43: 78.82 | Q43: =P43*20% -> 15.764 | R43: =O43-P43 -> 46.18 | S43: Demo PPO | T43: Gold PPO | V43: Eleanor Brooks, MD | W43: Assigned Department Provider | X43: LIS | Y43: Final result | Z43: Posted | AA43: Matched | AB43: Passed | AD43: Diagnosis/LCD | AE43: Z79.01 | AF43: 21 | AG43: 2026-09-15 16:30 | AH43: Synthetic demonstration charge
A44: IPD-CHG-0040 | B44: HAR-202600040 | C44: CSN-IPD-780040 | D44: Inpatient | E44: Demo Regional Medical Center | F44: Radiology | G44: 2026-09-16 | H44: RAD-CHEST-2V | I44: Chest X-ray, 2 Views | J44: 0320 | K44: 71046 | M44: 1 | N44: 185 | O44: =M44*N44 -> 185 | P44: 115.64 | Q44: =P44*20% -> 23.128 | R44: =O44-P44 -> 69.36 | S44: Demo PPO | T44: Gold PPO | V44: Eleanor Brooks, MD | W44: Assigned Department Provider | X44: RIS/PACS | Y44: Exam completed | Z44: Posted | AA44: Matched | AB44: Passed | AD44: Diagnosis/LCD | AE44: R06.02 | AF44: 21 | AG44: 2026-09-16 16:30 | AH44: Synthetic demonstration charge
A45: IPD-CHG-0041 | B45: HAR-202600041 | C45: CSN-IPD-780041 | D45: Inpatient | E45: Demo Regional Medical Center | F45: Radiology | G45: 2026-09-17 | H45: RAD-KNEE-2V | I45: Knee X-ray, 1-2 Views | J45: 0320 | K45: 73560 | M45: 1 | N45: 410 | O45: =M45*N45 -> 410 | P45: 180.98 | Q45: =P45*20% -> 36.196 | R45: =O45-P45 -> 229.02 | S45: Demo PPO | T45: Gold PPO | V45: Eleanor Brooks, MD | W45: Assigned Department Provider | X45: RIS/PACS | Y45: Exam completed | Z45: Posted | AA45: Matched | AB45: Passed | AD45: Diagnosis/LCD | AE45: M25.561 | AF45: 21 | AG45: 2026-09-17 16:30 | AH45: Synthetic demonstration charge
A46: IPD-CHG-0042 | B46: HAR-202600042 | C46: CSN-IPD-780042 | D46: Inpatient | E46: Demo Regional Medical Center | F46: Cardiology | G46: 2026-09-18 | H46: CARD-ECG12 | I46: 12-Lead ECG | J46: 0730 | K46: 93005 | M46: 1 | N46: 190 | O46: =M46*N46 -> 190 | P46: 115.99 | Q46: =P46*20% -> 23.198 | R46: =O46-P46 -> 74.01 | S46: Demo PPO | T46: Gold PPO | V46: Eleanor Brooks, MD | W46: Assigned Department Provider | X46: Cardiology | Y46: Test completed | Z46: Posted | AA46: Matched | AB46: Passed | AD46: Diagnosis/LCD | AE46: R07.9 | AF46: 21 | AG46: 2026-09-18 16:30 | AH46: Synthetic demonstration charge
A47: IPD-CHG-0043 | B47: HAR-202600043 | C47: CSN-IPD-780043 | D47: Inpatient | E47: Demo Regional Medical Center | F47: Respiratory | G47: 2026-09-19 | H47: RESP-NEB | I47: Nebulizer Treatment | J47: 0410 | K47: 94640 | M47: 1 | N47: 245 | O47: =M47*N47 -> 245 | P47: 142.16 | Q47: =P47*20% -> 28.432 | R47: =O47-P47 -> 102.84 | S47: Demo PPO | T47: Gold PPO | V47: Eleanor Brooks, MD | W47: Assigned Department Provider | X47: Respiratory | Y47: Treatment completed | Z47: Posted | AA47: Matched | AB47: Passed | AD47: Diagnosis/LCD | AE47: J45.901 | AF47: 21 | AG47: 2026-09-19 16:30 | AH47: Synthetic demonstration charge
A48: IPD-CHG-0044 | B48: HAR-202600044 | C48: CSN-IPD-780044 | D48: Inpatient | E48: Demo Regional Medical Center | F48: Physical Therapy | G48: 2026-09-20 | H48: PT-EVAL-LOW | I48: Physical Therapy Evaluation, Low Complexity | J48: 0420 | K48: 97161 | M48: 1 | N48: 710 | O48: =M48*N48 -> 710 | P48: 350.34 | Q48: =P48*20% -> 70.068 | R48: =O48-P48 -> 359.66 | S48: Demo PPO | T48: Gold PPO | U48: AUTH-700044 | V48: Eleanor Brooks, MD | W48: Assigned Department Provider | X48: Therapy | Y48: Note signed | Z48: Posted | AA48: Matched | AB48: Passed | AD48: Plan benefits | AE48: R26.2 | AF48: 21 | AG48: 2026-09-20 16:30 | AH48: Synthetic demonstration charge
A49: IPD-CHG-0045 | B49: HAR-202600045 | C49: CSN-IPD-780045 | D49: Inpatient | E49: Demo Regional Medical Center | F49: Physical Therapy | G49: 2026-09-21 | H49: PT-THEREX-15 | I49: Therapeutic Exercise, 15 Minutes | J49: 0420 | K49: 97110 | M49: 6 | N49: 305 | O49: =M49*N49 -> 1830 | P49: 976.92 | Q49: =P49*20% -> 195.384 | R49: =O49-P49 -> 853.08 | S49: Demo PPO | T49: Gold PPO | V49: Eleanor Brooks, MD | W49: Assigned Department Provider | X49: Therapy | Y49: Note signed | Z49: Posted | AA49: Matched | AB49: Passed | AD49: Timed units | AE49: M62.81 | AF49: 21 | AG49: 2026-09-21 16:30 | AH49: Synthetic demonstration charge
A50: IPD-CHG-0046 | B50: HAR-202600046 | C50: CSN-IPD-780046 | D50: Inpatient | E50: Demo Regional Medical Center | F50: Occupational Therapy | G50: 2026-09-22 | H50: OT-EVAL-LOW | I50: Occupational Therapy Evaluation, Low Complexity | J50: 0430 | K50: 97165 | M50: 1 | N50: 725 | O50: =M50*N50 -> 725 | P50: 519.72 | Q50: =P50*20% -> 103.944 | R50: =O50-P50 -> 205.28 | S50: Demo PPO | T50: Gold PPO | U50: AUTH-700046 | V50: Eleanor Brooks, MD | W50: Assigned Department Provider | X50: Therapy | Y50: Note signed | Z50: Posted | AA50: Matched | AB50: Review | AC50: WQ-OCC-03 | AD50: Plan benefits | AE50: Z74.09 | AF50: 21 | AG50: 2026-09-22 16:30 | AH50: Synthetic demonstration charge
A51: IPD-CHG-0047 | B51: HAR-202600047 | C51: CSN-IPD-780047 | D51: Inpatient | E51: Demo Regional Medical Center | F51: Nutrition | G51: 2026-09-23 | H51: NUTR-ASSESS | I51: Inpatient Nutrition Assessment | J51: 0942 | K51: 97802 | M51: 1 | N51: 325 | O51: =M51*N51 -> 325 | P51: 198.9 | Q51: =P51*20% -> 39.78 | R51: =O51-P51 -> 126.1 | S51: Demo PPO | T51: Gold PPO | V51: Eleanor Brooks, MD | W51: Assigned Department Provider | X51: Dietary | Y51: Note signed | Z51: Posted | AA51: Matched | AB51: Passed | AD51: N/A | AE51: E44.1 | AF51: 21 | AG51: 2026-09-23 16:30 | AH51: Synthetic demonstration charge
A52: IPD-CHG-0048 | B52: HAR-202600048 | C52: CSN-IPD-780048 | D52: Inpatient | E52: Demo Regional Medical Center | F52: Dialysis | G52: 2026-09-24 | H52: DIALYSIS-IP | I52: Inpatient Hemodialysis Treatment | J52: 0801 | K52: 90935 | M52: 1 | N52: 1600 | O52: =M52*N52 -> 1600 | P52: 939.34 | Q52: =P52*20% -> 187.868 | R52: =O52-P52 -> 660.66 | S52: Demo PPO | T52: Gold PPO | V52: Eleanor Brooks, MD | W52: Assigned Department Provider | X52: Dialysis | Y52: Treatment completed | Z52: Posted | AA52: Matched | AB52: Passed | AD52: Diagnosis/LCD | AE52: N18.6 | AF52: 21 | AG52: 2026-09-24 16:30 | AH52: Synthetic demonstration charge
A53: IPD-CHG-0049 | B53: HAR-202600049 | C53: CSN-IPD-780049 | D53: Inpatient | E53: Demo Regional Medical Center | F53: Accommodation | G53: 2026-09-25 | H53: RM-SEMI-DAY | I53: Semiprivate Medical/Surgical Room | J53: 0120 | M53: 3 | N53: 3500 | O53: =M53*N53 -> 10500 | P53: 7064.98 | Q53: =P53*20% -> 1412.996 | R53: =O53-P53 -> 3435.02 | S53: Demo PPO | T53: Gold PPO | V53: Eleanor Brooks, MD | W53: Assigned Department Provider | X53: ADT | Y53: Midnight census | Z53: Posted | AA53: Matched | AB53: Passed | AD53: N/A | AE53: M17.11 | AF53: 21 | AG53: 2026-09-25 16:30 | AH53: Synthetic demonstration charge
A54: IPD-CHG-0050 | B54: HAR-202600050 | C54: CSN-IPD-780050 | D54: Inpatient | E54: Demo Regional Medical Center | F54: Accommodation | G54: 2026-09-01 | H54: RM-PRIV-DAY | I54: Private Medical/Surgical Room | J54: 0110 | M54: 1 | N54: 4600 | O54: =M54*N54 -> 4600 | P54: 2248.09 | Q54: =P54*20% -> 449.618 | R54: =O54-P54 -> 2351.91 | S54: Demo PPO | T54: Gold PPO | V54: Eleanor Brooks, MD | W54: Assigned Department Provider | X54: ADT | Y54: Midnight census | Z54: Posted | AA54: Matched | AB54: Passed | AD54: N/A | AE54: M17.11 | AF54: 21 | AG54: 2026-09-01 16:30 | AH54: Synthetic demonstration charge
A55: IPD-CHG-0051 | B55: HAR-202600051 | C55: CSN-IPD-780051 | D55: Inpatient | E55: Demo Regional Medical Center | F55: Intensive Care | G55: 2026-09-02 | H55: ICU-DAY | I55: Intensive Care Unit Room | J55: 0200 | M55: 1 | N55: 8200 | O55: =M55*N55 -> 8200 | P55: 5424.41 | Q55: =P55*20% -> 1084.882 | R55: =O55-P55 -> 2775.59 | S55: Demo PPO | T55: Gold PPO | V55: Eleanor Brooks, MD | W55: Assigned Department Provider | X55: ADT | Y55: Midnight census | Z55: Posted | AA55: Matched | AB55: Passed | AD55: N/A | AE55: J96.01 | AF55: 21 | AG55: 2026-09-02 16:30 | AH55: Synthetic demonstration charge
A56: IPD-CHG-0052 | B56: HAR-202600052 | C56: CSN-IPD-780052 | D56: Inpatient | E56: Demo Regional Medical Center | F56: Operating Room | G56: 2026-09-03 | H56: OR-MAJOR-1H | I56: Major Operating Room, First Hour | J56: 0360 | M56: 4 | N56: 10250 | O56: =M56*N56 -> 41000 | P56: 20513.21 | Q56: =P56*20% -> 4102.642 | R56: =O56-P56 -> 20486.79 | S56: Demo PPO | T56: Gold PPO | V56: Eleanor Brooks, MD | W56: Assigned Department Provider | X56: Perioperative | Y56: Procedure end | Z56: Posted | AA56: Matched | AB56: Passed | AD56: Procedure-specific | AE56: M17.11 | AF56: 21 | AG56: 2026-09-03 16:30 | AH56: Synthetic demonstration charge
A57: IPD-CHG-0053 | B57: HAR-202600053 | C57: CSN-IPD-780053 | D57: Inpatient | E57: Demo Regional Medical Center | F57: Operating Room | G57: 2026-09-04 | H57: OR-ADD-15 | I57: Operating Room, Additional 15 Minutes | J57: 0360 | M57: 3 | N57: 1280 | O57: =M57*N57 -> 3840 | P57: 2664.73 | Q57: =P57*20% -> 532.946 | R57: =O57-P57 -> 1175.27 | S57: Demo PPO | T57: Gold PPO | V57: Eleanor Brooks, MD | W57: Assigned Department Provider | X57: Perioperative | Y57: Procedure end | Z57: Posted | AA57: Matched | AB57: Passed | AD57: Procedure-specific | AE57: M17.11 | AF57: 21 | AG57: 2026-09-04 16:30 | AH57: Synthetic demonstration charge
A58: IPD-CHG-0054 | B58: HAR-202600054 | C58: CSN-IPD-780054 | D58: Inpatient | E58: Demo Regional Medical Center | F58: Recovery Room | G58: 2026-09-05 | H58: PACU-1H | I58: Post-Anesthesia Care, First Hour | J58: 0710 | M58: 1 | N58: 2100 | O58: =M58*N58 -> 2100 | P58: 1239.32 | Q58: =P58*20% -> 247.864 | R58: =O58-P58 -> 860.68 | S58: Demo PPO | T58: Gold PPO | V58: Eleanor Brooks, MD | W58: Assigned Department Provider | X58: Perioperative | Y58: PACU discharge | Z58: Posted | AA58: Matched | AB58: Passed | AD58: N/A | AE58: Z47.1 | AF58: 21 | AG58: 2026-09-05 16:30 | AH58: Synthetic demonstration charge
A59: IPD-CHG-0055 | B59: HAR-202600055 | C59: CSN-IPD-780055 | D59: Inpatient | E59: Demo Regional Medical Center | F59: Surgical Supplies | G59: 2026-09-06 | H59: SUP-MAJOR-PACK | I59: Major Surgery Disposable Supply Pack | J59: 0270 | M59: 1 | N59: 4200 | O59: =M59*N59 -> 4200 | P59: 2668.57 | Q59: =P59*20% -> 533.714 | R59: =O59-P59 -> 1531.43 | S59: Demo PPO | T59: Gold PPO | V59: Eleanor Brooks, MD | W59: Assigned Department Provider | X59: Inventory | Y59: Supply issue | Z59: Posted | AA59: Matched | AB59: Passed | AD59: Contract rule | AE59: Z47.1 | AF59: 21 | AG59: 2026-09-06 16:30 | AH59: Synthetic demonstration charge
A60: IPD-CHG-0056 | B60: HAR-202600056 | C60: CSN-IPD-780056 | D60: Inpatient | E60: Demo Regional Medical Center | F60: Implants | G60: 2026-09-07 | H60: IMP-KNEE-CEM | I60: Cemented Knee Implant System | J60: 0278 | M60: 1 | N60: 20500 | O60: =M60*N60 -> 20500 | P60: 9917.65 | Q60: =P60*20% -> 1983.53 | R60: =O60-P60 -> 10582.35 | S60: Demo PPO | T60: Gold PPO | V60: Eleanor Brooks, MD | W60: Assigned Department Provider | X60: Inventory | Y60: Implant scan | Z60: Posted | AA60: Matched | AB60: Passed | AD60: Contract rule | AE60: M17.11 | AF60: 21 | AG60: 2026-09-07 16:30 | AH60: Synthetic demonstration charge
A61: IPD-CHG-0057 | B61: HAR-202600057 | C61: CSN-IPD-780057 | D61: Inpatient | E61: Demo Regional Medical Center | F61: Implants | G61: 2026-09-08 | H61: IMP-SCREW | I61: Orthopedic Fixation Screw | J61: 0278 | K61: C1713 | M61: 1 | N61: 950 | O61: =M61*N61 -> 950 | P61: 541.28 | Q61: =P61*20% -> 108.256 | R61: =O61-P61 -> 408.72 | S61: Demo PPO | T61: Gold PPO | V61: Eleanor Brooks, MD | W61: Assigned Department Provider | X61: Inventory | Y61: Implant scan | Z61: Posted | AA61: Matched | AB61: Passed | AD61: Contract rule | AE61: M17.11 | AF61: 21 | AG61: 2026-09-08 16:30 | AH61: Synthetic demonstration charge
A62: IPD-CHG-0058 | B62: HAR-202600058 | C62: CSN-IPD-780058 | D62: Inpatient | E62: Demo Regional Medical Center | F62: Pharmacy | G62: 2026-09-09 | H62: DRUG-CEFA-1G | I62: Cefazolin 1 g Injection | J62: 0250 | K62: J0690 | M62: 3 | N62: 500 | O62: =M62*N62 -> 1500 | P62: 836.48 | Q62: =P62*20% -> 167.296 | R62: =O62-P62 -> 663.52 | S62: Demo PPO | T62: Gold PPO | V62: Eleanor Brooks, MD | W62: Assigned Department Provider | X62: Pharmacy MAR | Y62: Medication administration | Z62: Hold | AA62: Exception | AB62: Review | AC62: WQ-PHA-03 | AD62: Dose/frequency | AE62: Z79.2 | AF62: 21 | AG62: 2026-09-09 16:30 | AH62: Synthetic demonstration charge
A63: IPD-CHG-0059 | B63: HAR-202600059 | C63: CSN-IPD-780059 | D63: Inpatient | E63: Demo Regional Medical Center | F63: Pharmacy | G63: 2026-09-10 | H63: DRUG-VANC-500 | I63: Vancomycin 500 mg Injection | J63: 0250 | K63: J3370 | M63: 2 | N63: 680 | O63: =M63*N63 -> 1360 | P63: 628.17 | Q63: =P63*20% -> 125.634 | R63: =O63-P63 -> 731.83 | S63: Demo PPO | T63: Gold PPO | V63: Eleanor Brooks, MD | W63: Assigned Department Provider | X63: Pharmacy MAR | Y63: Medication administration | Z63: Posted | AA63: Matched | AB63: Passed | AD63: Dose/frequency | AE63: Z79.2 | AF63: 21 | AG63: 2026-09-10 16:30 | AH63: Synthetic demonstration charge
A64: IPD-CHG-0060 | B64: HAR-202600060 | C64: CSN-IPD-780060 | D64: Inpatient | E64: Demo Regional Medical Center | F64: Pharmacy | G64: 2026-09-11 | H64: IV-NS-1L | I64: Normal Saline 1,000 mL | J64: 0258 | K64: J7030 | M64: 3 | N64: 90 | O64: =M64*N64 -> 270 | P64: 158.87 | Q64: =P64*20% -> 31.774 | R64: =O64-P64 -> 111.13 | S64: Demo PPO | T64: Gold PPO | V64: Eleanor Brooks, MD | W64: Assigned Department Provider | X64: Pharmacy MAR | Y64: Medication administration | Z64: Posted | AA64: Matched | AB64: Passed | AD64: N/A | AE64: E86.0 | AF64: 21 | AG64: 2026-09-11 16:30 | AH64: Synthetic demonstration charge
A65: IPD-CHG-0061 | B65: HAR-202600061 | C65: CSN-IPD-780061 | D65: Inpatient | E65: Demo Regional Medical Center | F65: Laboratory | G65: 2026-09-12 | H65: LAB-CBC | I65: Complete Blood Count with Differential | J65: 0300 | K65: 85025 | M65: 1 | N65: 155 | O65: =M65*N65 -> 155 | P65: 77.32 | Q65: =P65*20% -> 15.464 | R65: =O65-P65 -> 77.68 | S65: Demo PPO | T65: Gold PPO | V65: Eleanor Brooks, MD | W65: Assigned Department Provider | X65: LIS | Y65: Final result | Z65: Posted | AA65: Matched | AB65: Passed | AD65: Diagnosis/LCD | AE65: D64.9 | AF65: 21 | AG65: 2026-09-12 16:30 | AH65: Synthetic demonstration charge
A66: IPD-CHG-0062 | B66: HAR-202600062 | C66: CSN-IPD-780062 | D66: Inpatient | E66: Demo Regional Medical Center | F66: Laboratory | G66: 2026-09-13 | H66: LAB-CMP | I66: Comprehensive Metabolic Panel | J66: 0301 | K66: 80053 | M66: 1 | N66: 245 | O66: =M66*N66 -> 245 | P66: 145.87 | Q66: =P66*20% -> 29.174 | R66: =O66-P66 -> 99.13 | S66: Demo PPO | T66: Gold PPO | V66: Eleanor Brooks, MD | W66: Assigned Department Provider | X66: LIS | Y66: Final result | Z66: Posted | AA66: Matched | AB66: Passed | AD66: Diagnosis/LCD | AE66: E11.9 | AF66: 21 | AG66: 2026-09-13 16:30 | AH66: Synthetic demonstration charge
A67: IPD-CHG-0063 | B67: HAR-202600063 | C67: CSN-IPD-780063 | D67: Inpatient | E67: Demo Regional Medical Center | F67: Laboratory | G67: 2026-09-14 | H67: LAB-PTINR | I67: Prothrombin Time / INR | J67: 0305 | K67: 85610 | M67: 1 | N67: 125 | O67: =M67*N67 -> 125 | P67: 86.17 | Q67: =P67*20% -> 17.234 | R67: =O67-P67 -> 38.83 | S67: Demo PPO | T67: Gold PPO | V67: Eleanor Brooks, MD | W67: Assigned Department Provider | X67: LIS | Y67: Final result | Z67: Posted | AA67: Matched | AB67: Passed | AD67: Diagnosis/LCD | AE67: Z79.01 | AF67: 21 | AG67: 2026-09-14 16:30 | AH67: Synthetic demonstration charge
A68: IPD-CHG-0064 | B68: HAR-202600064 | C68: CSN-IPD-780064 | D68: Inpatient | E68: Demo Regional Medical Center | F68: Radiology | G68: 2026-09-15 | H68: RAD-CHEST-2V | I68: Chest X-ray, 2 Views | J68: 0320 | K68: 71046 | M68: 1 | N68: 185 | O68: =M68*N68 -> 185 | P68: 99.87 | Q68: =P68*20% -> 19.974 | R68: =O68-P68 -> 85.13 | S68: Demo PPO | T68: Gold PPO | V68: Eleanor Brooks, MD | W68: Assigned Department Provider | X68: RIS/PACS | Y68: Exam completed | Z68: Posted | AA68: Matched | AB68: Passed | AD68: Diagnosis/LCD | AE68: R06.02 | AF68: 21 | AG68: 2026-09-15 16:30 | AH68: Synthetic demonstration charge
A69: IPD-CHG-0065 | B69: HAR-202600065 | C69: CSN-IPD-780065 | D69: Inpatient | E69: Demo Regional Medical Center | F69: Radiology | G69: 2026-09-16 | H69: RAD-KNEE-2V | I69: Knee X-ray, 1-2 Views | J69: 0320 | K69: 73560 | M69: 1 | N69: 410 | O69: =M69*N69 -> 410 | P69: 199.18 | Q69: =P69*20% -> 39.836 | R69: =O69-P69 -> 210.82 | S69: Demo PPO | T69: Gold PPO | V69: Eleanor Brooks, MD | W69: Assigned Department Provider | X69: RIS/PACS | Y69: Exam completed | Z69: Posted | AA69: Matched | AB69: Passed | AD69: Diagnosis/LCD | AE69: M25.561 | AF69: 21 | AG69: 2026-09-16 16:30 | AH69: Synthetic demonstration charge
A70: IPD-CHG-0066 | B70: HAR-202600066 | C70: CSN-IPD-780066 | D70: Inpatient | E70: Demo Regional Medical Center | F70: Cardiology | G70: 2026-09-17 | H70: CARD-ECG12 | I70: 12-Lead ECG | J70: 0730 | K70: 93005 | M70: 1 | N70: 190 | O70: =M70*N70 -> 190 | P70: 136.66 | Q70: =P70*20% -> 27.332 | R70: =O70-P70 -> 53.34 | S70: Demo PPO | T70: Gold PPO | V70: Eleanor Brooks, MD | W70: Assigned Department Provider | X70: Cardiology | Y70: Test completed | Z70: Posted | AA70: Matched | AB70: Passed | AD70: Diagnosis/LCD | AE70: R07.9 | AF70: 21 | AG70: 2026-09-17 16:30 | AH70: Synthetic demonstration charge
A71: IPD-CHG-0067 | B71: HAR-202600067 | C71: CSN-IPD-780067 | D71: Inpatient | E71: Demo Regional Medical Center | F71: Respiratory | G71: 2026-09-18 | H71: RESP-NEB | I71: Nebulizer Treatment | J71: 0410 | K71: 94640 | M71: 1 | N71: 245 | O71: =M71*N71 -> 245 | P71: 140.35 | Q71: =P71*20% -> 28.07 | R71: =O71-P71 -> 104.65 | S71: Demo PPO | T71: Gold PPO | V71: Eleanor Brooks, MD | W71: Assigned Department Provider | X71: Respiratory | Y71: Treatment completed | Z71: Posted | AA71: Matched | AB71: Passed | AD71: Diagnosis/LCD | AE71: J45.901 | AF71: 21 | AG71: 2026-09-18 16:30 | AH71: Synthetic demonstration charge
A72: IPD-CHG-0068 | B72: HAR-202600068 | C72: CSN-IPD-780068 | D72: Inpatient | E72: Demo Regional Medical Center | F72: Physical Therapy | G72: 2026-09-19 | H72: PT-EVAL-LOW | I72: Physical Therapy Evaluation, Low Complexity | J72: 0420 | K72: 97161 | M72: 1 | N72: 710 | O72: =M72*N72 -> 710 | P72: 317.56 | Q72: =P72*20% -> 63.512 | R72: =O72-P72 -> 392.44 | S72: Demo PPO | T72: Gold PPO | U72: AUTH-700068 | V72: Eleanor Brooks, MD | W72: Assigned Department Provider | X72: Therapy | Y72: Note signed | Z72: Posted | AA72: Matched | AB72: Passed | AD72: Plan benefits | AE72: R26.2 | AF72: 21 | AG72: 2026-09-19 16:30 | AH72: Synthetic demonstration charge
A73: IPD-CHG-0069 | B73: HAR-202600069 | C73: CSN-IPD-780069 | D73: Inpatient | E73: Demo Regional Medical Center | F73: Physical Therapy | G73: 2026-09-20 | H73: PT-THEREX-15 | I73: Therapeutic Exercise, 15 Minutes | J73: 0420 | K73: 97110 | M73: 2 | N73: 305 | O73: =M73*N73 -> 610 | P73: 413.78 | Q73: =P73*20% -> 82.756 | R73: =O73-P73 -> 196.22 | S73: Demo PPO | T73: Gold PPO | V73: Eleanor Brooks, MD | W73: Assigned Department Provider | X73: Therapy | Y73: Note signed | Z73: Posted | AA73: Matched | AB73: Review | AC73: WQ-PHY-02 | AD73: Timed units | AE73: M62.81 | AF73: 21 | AG73: 2026-09-20 16:30 | AH73: Synthetic demonstration charge
A74: IPD-CHG-0070 | B74: HAR-202600070 | C74: CSN-IPD-780070 | D74: Inpatient | E74: Demo Regional Medical Center | F74: Occupational Therapy | G74: 2026-09-21 | H74: OT-EVAL-LOW | I74: Occupational Therapy Evaluation, Low Complexity | J74: 0430 | K74: 97165 | M74: 1 | N74: 725 | O74: =M74*N74 -> 725 | P74: 337.74 | Q74: =P74*20% -> 67.548 | R74: =O74-P74 -> 387.26 | S74: Demo PPO | T74: Gold PPO | U74: AUTH-700070 | V74: Eleanor Brooks, MD | W74: Assigned Department Provider | X74: Therapy | Y74: Note signed | Z74: Posted | AA74: Matched | AB74: Passed | AD74: Plan benefits | AE74: Z74.09 | AF74: 21 | AG74: 2026-09-21 16:30 | AH74: Synthetic demonstration charge
A75: IPD-CHG-0071 | B75: HAR-202600071 | C75: CSN-IPD-780071 | D75: Inpatient | E75: Demo Regional Medical Center | F75: Nutrition | G75: 2026-09-22 | H75: NUTR-ASSESS | I75: Inpatient Nutrition Assessment | J75: 0942 | K75: 97802 | M75: 1 | N75: 325 | O75: =M75*N75 -> 325 | P75: 152.1 | Q75: =P75*20% -> 30.42 | R75: =O75-P75 -> 172.9 | S75: Demo PPO | T75: Gold PPO | V75: Eleanor Brooks, MD | W75: Assigned Department Provider | X75: Dietary | Y75: Note signed | Z75: Posted | AA75: Matched | AB75: Passed | AD75: N/A | AE75: E44.1 | AF75: 21 | AG75: 2026-09-22 16:30 | AH75: Synthetic demonstration charge
A76: IPD-CHG-0072 | B76: HAR-202600072 | C76: CSN-IPD-780072 | D76: Inpatient | E76: Demo Regional Medical Center | F76: Dialysis | G76: 2026-09-23 | H76: DIALYSIS-IP | I76: Inpatient Hemodialysis Treatment | J76: 0801 | K76: 90935 | M76: 1 | N76: 1600 | O76: =M76*N76 -> 1600 | P76: 998.63 | Q76: =P76*20% -> 199.726 | R76: =O76-P76 -> 601.37 | S76: Demo PPO | T76: Gold PPO | V76: Eleanor Brooks, MD | W76: Assigned Department Provider | X76: Dialysis | Y76: Treatment completed | Z76: Posted | AA76: Matched | AB76: Passed | AD76: Diagnosis/LCD | AE76: N18.6 | AF76: 21 | AG76: 2026-09-23 16:30 | AH76: Synthetic demonstration charge
A77: IPD-CHG-0073 | B77: HAR-202600073 | C77: CSN-IPD-780073 | D77: Inpatient | E77: Demo Regional Medical Center | F77: Accommodation | G77: 2026-09-24 | H77: RM-SEMI-DAY | I77: Semiprivate Medical/Surgical Room | J77: 0120 | M77: 1 | N77: 3500 | O77: =M77*N77 -> 3500 | P77: 1874.01 | Q77: =P77*20% -> 374.802 | R77: =O77-P77 -> 1625.99 | S77: Demo PPO | T77: Gold PPO | V77: Eleanor Brooks, MD | W77: Assigned Department Provider | X77: ADT | Y77: Midnight census | Z77: Posted | AA77: Matched | AB77: Passed | AD77: N/A | AE77: M17.11 | AF77: 21 | AG77: 2026-09-24 16:30 | AH77: Synthetic demonstration charge
A78: IPD-CHG-0074 | B78: HAR-202600074 | C78: CSN-IPD-780074 | D78: Inpatient | E78: Demo Regional Medical Center | F78: Accommodation | G78: 2026-09-25 | H78: RM-PRIV-DAY | I78: Private Medical/Surgical Room | J78: 0110 | M78: 4 | N78: 4600 | O78: =M78*N78 -> 18400 | P78: 10648.71 | Q78: =P78*20% -> 2129.742 | R78: =O78-P78 -> 7751.29 | S78: Demo PPO | T78: Gold PPO | V78: Eleanor Brooks, MD | W78: Assigned Department Provider | X78: ADT | Y78: Midnight census | Z78: Posted | AA78: Matched | AB78: Passed | AD78: N/A | AE78: M17.11 | AF78: 21 | AG78: 2026-09-25 16:30 | AH78: Synthetic demonstration charge
A79: IPD-CHG-0075 | B79: HAR-202600075 | C79: CSN-IPD-780075 | D79: Inpatient | E79: Demo Regional Medical Center | F79: Intensive Care | G79: 2026-09-01 | H79: ICU-DAY | I79: Intensive Care Unit Room | J79: 0200 | M79: 1 | N79: 8200 | O79: =M79*N79 -> 8200 | P79: 5117.5 | Q79: =P79*20% -> 1023.5 | R79: =O79-P79 -> 3082.5 | S79: Demo PPO | T79: Gold PPO | V79: Eleanor Brooks, MD | W79: Assigned Department Provider | X79: ADT | Y79: Midnight census | Z79: Posted | AA79: Matched | AB79: Passed | AD79: N/A | AE79: J96.01 | AF79: 21 | AG79: 2026-09-01 16:30 | AH79: Synthetic demonstration charge
A80: IPD-CHG-0076 | B80: HAR-202600076 | C80: CSN-IPD-780076 | D80: Inpatient | E80: Demo Regional Medical Center | F80: Operating Room | G80: 2026-09-02 | H80: OR-MAJOR-1H | I80: Major Operating Room, First Hour | J80: 0360 | M80: 1 | N80: 10250 | O80: =M80*N80 -> 10250 | P80: 6401.26 | Q80: =P80*20% -> 1280.252 | R80: =O80-P80 -> 3848.74 | S80: Demo PPO | T80: Gold PPO | V80: Eleanor Brooks, MD | W80: Assigned Department Provider | X80: Perioperative | Y80: Procedure end | Z80: Posted | AA80: Matched | AB80: Passed | AD80: Procedure-specific | AE80: M17.11 | AF80: 21 | AG80: 2026-09-02 16:30 | AH80: Synthetic demonstration charge
A81: IPD-CHG-0077 | B81: HAR-202600077 | C81: CSN-IPD-780077 | D81: Inpatient | E81: Demo Regional Medical Center | F81: Operating Room | G81: 2026-09-03 | H81: OR-ADD-15 | I81: Operating Room, Additional 15 Minutes | J81: 0360 | M81: 4 | N81: 1280 | O81: =M81*N81 -> 5120 | P81: 3330.97 | Q81: =P81*20% -> 666.194 | R81: =O81-P81 -> 1789.03 | S81: Demo PPO | T81: Gold PPO | V81: Eleanor Brooks, MD | W81: Assigned Department Provider | X81: Perioperative | Y81: Procedure end | Z81: Posted | AA81: Matched | AB81: Passed | AD81: Procedure-specific | AE81: M17.11 | AF81: 21 | AG81: 2026-09-03 16:30 | AH81: Synthetic demonstration charge
A82: IPD-CHG-0078 | B82: HAR-202600078 | C82: CSN-IPD-780078 | D82: Inpatient | E82: Demo Regional Medical Center | F82: Recovery Room | G82: 2026-09-04 | H82: PACU-1H | I82: Post-Anesthesia Care, First Hour | J82: 0710 | M82: 1 | N82: 2100 | O82: =M82*N82 -> 2100 | P82: 1096.31 | Q82: =P82*20% -> 219.262 | R82: =O82-P82 -> 1003.69 | S82: Demo PPO | T82: Gold PPO | V82: Eleanor Brooks, MD | W82: Assigned Department Provider | X82: Perioperative | Y82: PACU discharge | Z82: Posted | AA82: Matched | AB82: Passed | AD82: N/A | AE82: Z47.1 | AF82: 21 | AG82: 2026-09-04 16:30 | AH82: Synthetic demonstration charge
A83: IPD-CHG-0079 | B83: HAR-202600079 | C83: CSN-IPD-780079 | D83: Inpatient | E83: Demo Regional Medical Center | F83: Surgical Supplies | G83: 2026-09-05 | H83: SUP-MAJOR-PACK | I83: Major Surgery Disposable Supply Pack | J83: 0270 | M83: 1 | N83: 4200 | O83: =M83*N83 -> 4200 | P83: 2133.81 | Q83: =P83*20% -> 426.762 | R83: =O83-P83 -> 2066.19 | S83: Demo PPO | T83: Gold PPO | V83: Eleanor Brooks, MD | W83: Assigned Department Provider | X83: Inventory | Y83: Supply issue | Z83: Posted | AA83: Matched | AB83: Passed | AD83: Contract rule | AE83: Z47.1 | AF83: 21 | AG83: 2026-09-05 16:30 | AH83: Synthetic demonstration charge
A84: IPD-CHG-0080 | B84: HAR-202600080 | C84: CSN-IPD-780080 | D84: Inpatient | E84: Demo Regional Medical Center | F84: Implants | G84: 2026-09-06 | H84: IMP-KNEE-CEM | I84: Cemented Knee Implant System | J84: 0278 | M84: 1 | N84: 20500 | O84: =M84*N84 -> 20500 | P84: 9582.67 | Q84: =P84*20% -> 1916.534 | R84: =O84-P84 -> 10917.33 | S84: Demo PPO | T84: Gold PPO | V84: Eleanor Brooks, MD | W84: Assigned Department Provider | X84: Inventory | Y84: Implant scan | Z84: Posted | AA84: Matched | AB84: Passed | AD84: Contract rule | AE84: M17.11 | AF84: 21 | AG84: 2026-09-06 16:30 | AH84: Synthetic demonstration charge
A85: IPD-CHG-0081 | B85: HAR-202600081 | C85: CSN-IPD-780081 | D85: Inpatient | E85: Demo Regional Medical Center | F85: Implants | G85: 2026-09-07 | H85: IMP-SCREW | I85: Orthopedic Fixation Screw | J85: 0278 | K85: C1713 | M85: 1 | N85: 950 | O85: =M85*N85 -> 950 | P85: 399.92 | Q85: =P85*20% -> 79.984 | R85: =O85-P85 -> 550.08 | S85: Demo PPO | T85: Gold PPO | V85: Eleanor Brooks, MD | W85: Assigned Department Provider | X85: Inventory | Y85: Implant scan | Z85: Posted | AA85: Matched | AB85: Passed | AD85: Contract rule | AE85: M17.11 | AF85: 21 | AG85: 2026-09-07 16:30 | AH85: Synthetic demonstration charge
A86: IPD-CHG-0082 | B86: HAR-202600082 | C86: CSN-IPD-780082 | D86: Inpatient | E86: Demo Regional Medical Center | F86: Pharmacy | G86: 2026-09-08 | H86: DRUG-CEFA-1G | I86: Cefazolin 1 g Injection | J86: 0250 | K86: J0690 | M86: 3 | N86: 500 | O86: =M86*N86 -> 1500 | P86: 1024.13 | Q86: =P86*20% -> 204.826 | R86: =O86-P86 -> 475.87 | S86: Demo PPO | T86: Gold PPO | V86: Eleanor Brooks, MD | W86: Assigned Department Provider | X86: Pharmacy MAR | Y86: Medication administration | Z86: Posted | AA86: Matched | AB86: Passed | AD86: Dose/frequency | AE86: Z79.2 | AF86: 21 | AG86: 2026-09-08 16:30 | AH86: Synthetic demonstration charge
A87: IPD-CHG-0083 | B87: HAR-202600083 | C87: CSN-IPD-780083 | D87: Inpatient | E87: Demo Regional Medical Center | F87: Pharmacy | G87: 2026-09-09 | H87: DRUG-VANC-500 | I87: Vancomycin 500 mg Injection | J87: 0250 | K87: J3370 | M87: 2 | N87: 680 | O87: =M87*N87 -> 1360 | P87: 967.73 | Q87: =P87*20% -> 193.546 | R87: =O87-P87 -> 392.27 | S87: Demo PPO | T87: Gold PPO | V87: Eleanor Brooks, MD | W87: Assigned Department Provider | X87: Pharmacy MAR | Y87: Medication administration | Z87: Posted | AA87: Matched | AB87: Passed | AD87: Dose/frequency | AE87: Z79.2 | AF87: 21 | AG87: 2026-09-09 16:30 | AH87: Synthetic demonstration charge
A88: IPD-CHG-0084 | B88: HAR-202600084 | C88: CSN-IPD-780084 | D88: Inpatient | E88: Demo Regional Medical Center | F88: Pharmacy | G88: 2026-09-10 | H88: IV-NS-1L | I88: Normal Saline 1,000 mL | J88: 0258 | K88: J7030 | M88: 1 | N88: 90 | O88: =M88*N88 -> 90 | P88: 51.51 | Q88: =P88*20% -> 10.302 | R88: =O88-P88 -> 38.49 | S88: Demo PPO | T88: Gold PPO | V88: Eleanor Brooks, MD | W88: Assigned Department Provider | X88: Pharmacy MAR | Y88: Medication administration | Z88: Posted | AA88: Matched | AB88: Passed | AD88: N/A | AE88: E86.0 | AF88: 21 | AG88: 2026-09-10 16:30 | AH88: Synthetic demonstration charge
A89: IPD-CHG-0085 | B89: HAR-202600085 | C89: CSN-IPD-780085 | D89: Inpatient | E89: Demo Regional Medical Center | F89: Laboratory | G89: 2026-09-11 | H89: LAB-CBC | I89: Complete Blood Count with Differential | J89: 0300 | K89: 85025 | M89: 1 | N89: 155 | O89: =M89*N89 -> 155 | P89: 70.05 | Q89: =P89*20% -> 14.01 | R89: =O89-P89 -> 84.95 | S89: Demo PPO | T89: Gold PPO | V89: Eleanor Brooks, MD | W89: Assigned Department Provider | X89: LIS | Y89: Final result | Z89: Posted | AA89: Matched | AB89: Passed | AD89: Diagnosis/LCD | AE89: D64.9 | AF89: 21 | AG89: 2026-09-11 16:30 | AH89: Synthetic demonstration charge
A90: IPD-CHG-0086 | B90: HAR-202600086 | C90: CSN-IPD-780086 | D90: Inpatient | E90: Demo Regional Medical Center | F90: Laboratory | G90: 2026-09-12 | H90: LAB-CMP | I90: Comprehensive Metabolic Panel | J90: 0301 | K90: 80053 | M90: 1 | N90: 245 | O90: =M90*N90 -> 245 | P90: 148.86 | Q90: =P90*20% -> 29.772 | R90: =O90-P90 -> 96.14 | S90: Demo PPO | T90: Gold PPO | V90: Eleanor Brooks, MD | W90: Assigned Department Provider | X90: LIS | Y90: Final result | Z90: Posted | AA90: Matched | AB90: Passed | AD90: Diagnosis/LCD | AE90: E11.9 | AF90: 21 | AG90: 2026-09-12 16:30 | AH90: Synthetic demonstration charge
A91: IPD-CHG-0087 | B91: HAR-202600087 | C91: CSN-IPD-780087 | D91: Inpatient | E91: Demo Regional Medical Center | F91: Laboratory | G91: 2026-09-13 | H91: LAB-PTINR | I91: Prothrombin Time / INR | J91: 0305 | K91: 85610 | M91: 1 | N91: 125 | O91: =M91*N91 -> 125 | P91: 84.06 | Q91: =P91*20% -> 16.812 | R91: =O91-P91 -> 40.94 | S91: Demo PPO | T91: Gold PPO | V91: Eleanor Brooks, MD | W91: Assigned Department Provider | X91: LIS | Y91: Final result | Z91: Hold | AA91: Exception | AB91: Review | AC91: WQ-LAB-04 | AD91: Diagnosis/LCD | AE91: Z79.01 | AF91: 21 | AG91: 2026-09-13 16:30 | AH91: Synthetic demonstration charge
A92: IPD-CHG-0088 | B92: HAR-202600088 | C92: CSN-IPD-780088 | D92: Inpatient | E92: Demo Regional Medical Center | F92: Radiology | G92: 2026-09-14 | H92: RAD-CHEST-2V | I92: Chest X-ray, 2 Views | J92: 0320 | K92: 71046 | M92: 1 | N92: 185 | O92: =M92*N92 -> 185 | P92: 105.88 | Q92: =P92*20% -> 21.176 | R92: =O92-P92 -> 79.12 | S92: Demo PPO | T92: Gold PPO | V92: Eleanor Brooks, MD | W92: Assigned Department Provider | X92: RIS/PACS | Y92: Exam completed | Z92: Posted | AA92: Matched | AB92: Passed | AD92: Diagnosis/LCD | AE92: R06.02 | AF92: 21 | AG92: 2026-09-14 16:30 | AH92: Synthetic demonstration charge
A93: IPD-CHG-0089 | B93: HAR-202600089 | C93: CSN-IPD-780089 | D93: Inpatient | E93: Demo Regional Medical Center | F93: Radiology | G93: 2026-09-15 | H93: RAD-KNEE-2V | I93: Knee X-ray, 1-2 Views | J93: 0320 | K93: 73560 | M93: 1 | N93: 410 | O93: =M93*N93 -> 410 | P93: 196.67 | Q93: =P93*20% -> 39.334 | R93: =O93-P93 -> 213.33 | S93: Demo PPO | T93: Gold PPO | V93: Eleanor Brooks, MD | W93: Assigned Department Provider | X93: RIS/PACS | Y93: Exam completed | Z93: Posted | AA93: Matched | AB93: Passed | AD93: Diagnosis/LCD | AE93: M25.561 | AF93: 21 | AG93: 2026-09-15 16:30 | AH93: Synthetic demonstration charge
A94: IPD-CHG-0090 | B94: HAR-202600090 | C94: CSN-IPD-780090 | D94: Inpatient | E94: Demo Regional Medical Center | F94: Cardiology | G94: 2026-09-16 | H94: CARD-ECG12 | I94: 12-Lead ECG | J94: 0730 | K94: 93005 | M94: 1 | N94: 190 | O94: =M94*N94 -> 190 | P94: 101.11 | Q94: =P94*20% -> 20.222 | R94: =O94-P94 -> 88.89 | S94: Demo PPO | T94: Gold PPO | V94: Eleanor Brooks, MD | W94: Assigned Department Provider | X94: Cardiology | Y94: Test completed | Z94: Posted | AA94: Matched | AB94: Passed | AD94: Diagnosis/LCD | AE94: R07.9 | AF94: 21 | AG94: 2026-09-16 16:30 | AH94: Synthetic demonstration charge
A95: IPD-CHG-0091 | B95: HAR-202600091 | C95: CSN-IPD-780091 | D95: Inpatient | E95: Demo Regional Medical Center | F95: Respiratory | G95: 2026-09-17 | H95: RESP-NEB | I95: Nebulizer Treatment | J95: 0410 | K95: 94640 | M95: 1 | N95: 245 | O95: =M95*N95 -> 245 | P95: 114.77 | Q95: =P95*20% -> 22.954 | R95: =O95-P95 -> 130.23 | S95: Demo PPO | T95: Gold PPO | V95: Eleanor Brooks, MD | W95: Assigned Department Provider | X95: Respiratory | Y95: Treatment completed | Z95: Posted | AA95: Matched | AB95: Passed | AD95: Diagnosis/LCD | AE95: J45.901 | AF95: 21 | AG95: 2026-09-17 16:30 | AH95: Synthetic demonstration charge
A96: IPD-CHG-0092 | B96: HAR-202600092 | C96: CSN-IPD-780092 | D96: Inpatient | E96: Demo Regional Medical Center | F96: Physical Therapy | G96: 2026-09-18 | H96: PT-EVAL-LOW | I96: Physical Therapy Evaluation, Low Complexity | J96: 0420 | K96: 97161 | M96: 1 | N96: 710 | O96: =M96*N96 -> 710 | P96: 501.3 | Q96: =P96*20% -> 100.26 | R96: =O96-P96 -> 208.7 | S96: Demo PPO | T96: Gold PPO | U96: AUTH-700092 | V96: Eleanor Brooks, MD | W96: Assigned Department Provider | X96: Therapy | Y96: Note signed | Z96: Posted | AA96: Matched | AB96: Review | AC96: WQ-PHY-01 | AD96: Plan benefits | AE96: R26.2 | AF96: 21 | AG96: 2026-09-18 16:30 | AH96: Synthetic demonstration charge
A97: IPD-CHG-0093 | B97: HAR-202600093 | C97: CSN-IPD-780093 | D97: Inpatient | E97: Demo Regional Medical Center | F97: Physical Therapy | G97: 2026-09-19 | H97: PT-THEREX-15 | I97: Therapeutic Exercise, 15 Minutes | J97: 0420 | K97: 97110 | M97: 2 | N97: 305 | O97: =M97*N97 -> 610 | P97: 365.81 | Q97: =P97*20% -> 73.162 | R97: =O97-P97 -> 244.19 | S97: Demo PPO | T97: Gold PPO | V97: Eleanor Brooks, MD | W97: Assigned Department Provider | X97: Therapy | Y97: Note signed | Z97: Posted | AA97: Matched | AB97: Passed | AD97: Timed units | AE97: M62.81 | AF97: 21 | AG97: 2026-09-19 16:30 | AH97: Synthetic demonstration charge
A98: IPD-CHG-0094 | B98: HAR-202600094 | C98: CSN-IPD-780094 | D98: Inpatient | E98: Demo Regional Medical Center | F98: Occupational Therapy | G98: 2026-09-20 | H98: OT-EVAL-LOW | I98: Occupational Therapy Evaluation, Low Complexity | J98: 0430 | K98: 97165 | M98: 1 | N98: 725 | O98: =M98*N98 -> 725 | P98: 410.77 | Q98: =P98*20% -> 82.154 | R98: =O98-P98 -> 314.23 | S98: Demo PPO | T98: Gold PPO | U98: AUTH-700094 | V98: Eleanor Brooks, MD | W98: Assigned Department Provider | X98: Therapy | Y98: Note signed | Z98: Posted | AA98: Matched | AB98: Passed | AD98: Plan benefits | AE98: Z74.09 | AF98: 21 | AG98: 2026-09-20 16:30 | AH98: Synthetic demonstration charge
A99: IPD-CHG-0095 | B99: HAR-202600095 | C99: CSN-IPD-780095 | D99: Inpatient | E99: Demo Regional Medical Center | F99: Nutrition | G99: 2026-09-21 | H99: NUTR-ASSESS | I99: Inpatient Nutrition Assessment | J99: 0942 | K99: 97802 | M99: 1 | N99: 325 | O99: =M99*N99 -> 325 | P99: 147.41 | Q99: =P99*20% -> 29.482 | R99: =O99-P99 -> 177.59 | S99: Demo PPO | T99: Gold PPO | V99: Eleanor Brooks, MD | W99: Assigned Department Provider | X99: Dietary | Y99: Note signed | Z99: Posted | AA99: Matched | AB99: Passed | AD99: N/A | AE99: E44.1 | AF99: 21 | AG99: 2026-09-21 16:30 | AH99: Synthetic demonstration charge
A100: IPD-CHG-0096 | B100: HAR-202600096 | C100: CSN-IPD-780096 | D100: Inpatient | E100: Demo Regional Medical Center | F100: Dialysis | G100: 2026-09-22 | H100: DIALYSIS-IP | I100: Inpatient Hemodialysis Treatment | J100: 0801 | K100: 90935 | M100: 1 | N100: 1600 | O100: =M100*N100 -> 1600 | P100: 846.23 | Q100: =P100*20% -> 169.246 | R100: =O100-P100 -> 753.77 | S100: Demo PPO | T100: Gold PPO | V100: Eleanor Brooks, MD | W100: Assigned Department Provider | X100: Dialysis | Y100: Treatment completed | Z100: Posted | AA100: Matched | AB100: Passed | AD100: Diagnosis/LCD | AE100: N18.6 | AF100: 21 | AG100: 2026-09-22 16:30 | AH100: Synthetic demonstration charge
A101: IPD-CHG-0097 | B101: HAR-202600097 | C101: CSN-IPD-780097 | D101: Inpatient | E101: Demo Regional Medical Center | F101: Accommodation | G101: 2026-09-23 | H101: RM-SEMI-DAY | I101: Semiprivate Medical/Surgical Room | J101: 0120 | M101: 3 | N101: 3500 | O101: =M101*N101 -> 10500 | P101: 5164.27 | Q101: =P101*20% -> 1032.854 | R101: =O101-P101 -> 5335.73 | S101: Demo PPO | T101: Gold PPO | V101: Eleanor Brooks, MD | W101: Assigned Department Provider | X101: ADT | Y101: Midnight census | Z101: Posted | AA101: Matched | AB101: Passed | AD101: N/A | AE101: M17.11 | AF101: 21 | AG101: 2026-09-23 16:30 | AH101: Synthetic demonstration charge
...

Sheet OPD Charges
A1: Outpatient Charge Detail
A2: 100 original synthetic outpatient charge lines covering emergency, clinic, diagnostics, procedures, therapies, infusion, and ancillary services.
A4: Charge Line ID | B4: Patient Account | C4: Encounter ID | D4: Patient Class | E4: Facility | F4: Department | G4: Service Date | H4: Charge Code | I4: Charge Description | J4: Revenue Code | K4: CPT/HCPCS | L4: Modifier | M4: Quantity | N4: Unit Charge ($) | O4: Extended Gross ($) | P4: Expected Allowed ($) | Q4: Patient Responsibility ($) | R4: Contractual Adjustment ($) | S4: Payer | T4: Plan | U4: Authorization ID | V4: Ordering Provider | W4: Performing Provider | X4: Source System | Y4: Charge Trigger | Z4: Charge Status | AA4: Reconciliation Status | AB4: Claim Edit Status | AC4: Workqueue | AD4: Medical Necessity | AE4: Diagnosis Link | AF4: Place of Service | AG4: Posting Date/Time | AH4: Notes
A5: OPD-CHG-0001 | B5: OP-202600001 | C5: CSN-OPD-780001 | D5: Outpatient | E5: Demo Regional Medical Center | F5: Emergency Department | G5: 2026-09-02 | H5: ED-LEVEL-1 | I5: Emergency Department Visit Level 1 | J5: 0450 | K5: 99281 | M5: 1 | N5: 360 | O5: =M5*N5 -> 360 | P5: 221.39 | Q5: =P5*20% -> 44.278 | R5: =O5-P5 -> 138.61 | S5: Demo PPO | T5: Gold PPO | V5: Eleanor Brooks, MD | W5: Assigned Department Provider | X5: ED | Y5: Encounter close | Z5: Posted | AA5: Matched | AB5: Passed | AD5: Documentation | AE5: R50.9 | AF5: 22 | AG5: 2026-09-02 16:30 | AH5: Synthetic demonstration charge
A6: OPD-CHG-0002 | B6: OP-202600002 | C6: CSN-OPD-780002 | D6: Outpatient | E6: Demo Regional Medical Center | F6: Emergency Department | G6: 2026-09-03 | H6: ED-LEVEL-2 | I6: Emergency Department Visit Level 2 | J6: 0450 | K6: 99282 | M6: 1 | N6: 670 | O6: =M6*N6 -> 670 | P6: 369.46 | Q6: =P6*20% -> 73.892 | R6: =O6-P6 -> 300.54 | S6: Demo PPO | T6: Gold PPO | V6: Eleanor Brooks, MD | W6: Assigned Department Provider | X6: ED | Y6: Encounter close | Z6: Posted | AA6: Matched | AB6: Passed | AD6: Documentation | AE6: R51.9 | AF6: 22 | AG6: 2026-09-03 16:30 | AH6: Synthetic demonstration charge
A7: OPD-CHG-0003 | B7: OP-202600003 | C7: CSN-OPD-780003 | D7: Outpatient | E7: Demo Regional Medical Center | F7: Emergency Department | G7: 2026-09-04 | H7: ED-LEVEL-3 | I7: Emergency Department Visit Level 3 | J7: 0450 | K7: 99283 | M7: 1 | N7: 1280 | O7: =M7*N7 -> 1280 | P7: 736.35 | Q7: =P7*20% -> 147.27 | R7: =O7-P7 -> 543.65 | S7: Demo PPO | T7: Gold PPO | V7: Eleanor Brooks, MD | W7: Assigned Department Provider | X7: ED | Y7: Encounter close | Z7: Posted | AA7: Matched | AB7: Passed | AD7: Documentation | AE7: R10.9 | AF7: 22 | AG7: 2026-09-04 16:30 | AH7: Synthetic demonstration charge
A8: OPD-CHG-0004 | B8: OP-202600004 | C8: CSN-OPD-780004 | D8: Outpatient | E8: Demo Regional Medical Center | F8: Emergency Department | G8: 2026-09-05 | H8: ED-LEVEL-4 | I8: Emergency Department Visit Level 4 | J8: 0450 | K8: 99284 | M8: 1 | N8: 2350 | O8: =M8*N8 -> 2350 | P8: 1072.31 | Q8: =P8*20% -> 214.462 | R8: =O8-P8 -> 1277.69 | S8: Demo PPO | T8: Gold PPO | V8: Eleanor Brooks, MD | W8: Assigned Department Provider | X8: ED | Y8: Encounter close | Z8: Posted | AA8: Matched | AB8: Passed | AD8: Documentation | AE8: R06.02 | AF8: 22 | AG8: 2026-09-05 16:30 | AH8: Synthetic demonstration charge
A9: OPD-CHG-0005 | B9: OP-202600005 | C9: CSN-OPD-780005 | D9: Outpatient | E9: Demo Regional Medical Center | F9: Emergency Department | G9: 2026-09-06 | H9: ED-LEVEL-5 | I9: Emergency Department Visit Level 5 | J9: 0450 | K9: 99285 | M9: 1 | N9: 4300 | O9: =M9*N9 -> 4300 | P9: 2095.86 | Q9: =P9*20% -> 419.172 | R9: =O9-P9 -> 2204.14 | S9: Demo PPO | T9: Gold PPO | V9: Eleanor Brooks, MD | W9: Assigned Department Provider | X9: ED | Y9: Encounter close | Z9: Posted | AA9: Matched | AB9: Passed | AD9: Documentation | AE9: R07.9 | AF9: 22 | AG9: 2026-09-06 16:30 | AH9: Synthetic demonstration charge
A10: OPD-CHG-0006 | B10: OP-202600006 | C10: CSN-OPD-780006 | D10: Outpatient | E10: Demo Regional Medical Center | F10: Hospital Clinic | G10: 2026-09-07 | H10: CLINIC-L2 | I10: Hospital Outpatient Clinic Visit Level 2 | J10: 0510 | K10: 99212 | M10: 1 | N10: 215 | O10: =M10*N10 -> 215 | P10: 112.11 | Q10: =P10*20% -> 22.422 | R10: =O10-P10 -> 102.89 | S10: Demo PPO | T10: Gold PPO | V10: Eleanor Brooks, MD | W10: Assigned Department Provider | X10: Ambulatory | Y10: Visit close | Z10: Posted | AA10: Matched | AB10: Passed | AD10: E/M documentation | AE10: I10 | AF10: 22 | AG10: 2026-09-07 16:30 | AH10: Synthetic demonstration charge
A11: OPD-CHG-0007 | B11: OP-202600007 | C11: CSN-OPD-780007 | D11: Outpatient | E11: Demo Regional Medical Center | F11: Hospital Clinic | G11: 2026-09-08 | H11: CLINIC-L3 | I11: Hospital Outpatient Clinic Visit Level 3 | J11: 0510 | K11: 99213 | M11: 1 | N11: 315 | O11: =M11*N11 -> 315 | P11: 187.9 | Q11: =P11*20% -> 37.58 | R11: =O11-P11 -> 127.1 | S11: Demo PPO | T11: Gold PPO | V11: Eleanor Brooks, MD | W11: Assigned Department Provider | X11: Ambulatory | Y11: Visit close | Z11: Posted | AA11: Matched | AB11: Passed | AD11: E/M documentation | AE11: E11.9 | AF11: 22 | AG11: 2026-09-08 16:30 | AH11: Synthetic demonstration charge
A12: OPD-CHG-0008 | B12: OP-202600008 | C12: CSN-OPD-780008 | D12: Outpatient | E12: Demo Regional Medical Center | F12: Hospital Clinic | G12: 2026-09-09 | H12: CLINIC-L4 | I12: Hospital Outpatient Clinic Visit Level 4 | J12: 0510 | K12: 99214 | M12: 1 | N12: 410 | O12: =M12*N12 -> 410 | P12: 200.5 | Q12: =P12*20% -> 40.1 | R12: =O12-P12 -> 209.5 | S12: Demo PPO | T12: Gold PPO | V12: Eleanor Brooks, MD | W12: Assigned Department Provider | X12: Ambulatory | Y12: Visit close | Z12: Posted | AA12: Matched | AB12: Passed | AD12: E/M documentation | AE12: J45.40 | AF12: 22 | AG12: 2026-09-09 16:30 | AH12: Synthetic demonstration charge
A13: OPD-CHG-0009 | B13: OP-202600009 | C13: CSN-OPD-780009 | D13: Outpatient | E13: Demo Regional Medical Center | F13: Hospital Clinic | G13: 2026-09-10 | H13: CLINIC-L5 | I13: Hospital Outpatient Clinic Visit Level 5 | J13: 0510 | K13: 99215 | M13: 1 | N13: 570 | O13: =M13*N13 -> 570 | P13: 277.06 | Q13: =P13*20% -> 55.412 | R13: =O13-P13 -> 292.94 | S13: Demo PPO | T13: Gold PPO | V13: Eleanor Brooks, MD | W13: Assigned Department Provider | X13: Ambulatory | Y13: Visit close | Z13: Posted | AA13: Matched | AB13: Passed | AD13: E/M documentation | AE13: I50.9 | AF13: 22 | AG13: 2026-09-10 16:30 | AH13: Synthetic demonstration charge
A14: OPD-CHG-0010 | B14: OP-202600010 | C14: CSN-OPD-780010 | D14: Outpatient | E14: Demo Regional Medical Center | F14: Radiology | G14: 2026-09-11 | H14: XR-CHEST-2V | I14: Chest X-ray, 2 Views | J14: 0320 | K14: 71046 | M14: 1 | N14: 185 | O14: =M14*N14 -> 185 | P14: 81.64 | Q14: =P14*20% -> 16.328 | R14: =O14-P14 -> 103.36 | S14: Demo PPO | T14: Gold PPO | V14: Eleanor Brooks, MD | W14: Assigned Department Provider | X14: RIS/PACS | Y14: Exam completed | Z14: Posted | AA14: Matched | AB14: Passed | AD14: Diagnosis/LCD | AE14: R05.9 | AF14: 22 | AG14: 2026-09-11 16:30 | AH14: Synthetic demonstration charge
A15: OPD-CHG-0011 | B15: OP-202600011 | C15: CSN-OPD-780011 | D15: Outpatient | E15: Demo Regional Medical Center | F15: Radiology | G15: 2026-09-12 | H15: CT-HEAD-WO | I15: CT Head Without Contrast | J15: 0350 | K15: 70450 | M15: 1 | N15: 1900 | O15: =M15*N15 -> 1900 | P15: 1157.73 | Q15: =P15*20% -> 231.546 | R15: =O15-P15 -> 742.27 | S15: Demo PPO | T15: Gold PPO | U15: AUTH-700011 | V15: Eleanor Brooks, MD | W15: Assigned Department Provider | X15: RIS/PACS | Y15: Exam completed | Z15: Posted | AA15: Matched | AB15: Passed | AD15: Prior authorization | AE15: R51.9 | AF15: 22 | AG15: 2026-09-12 16:30 | AH15: Synthetic demonstration charge
A16: OPD-CHG-0012 | B16: OP-202600012 | C16: CSN-OPD-780012 | D16: Outpatient | E16: Demo Regional Medical Center | F16: Radiology | G16: 2026-09-13 | H16: CT-CHEST-W | I16: CT Chest With Contrast | J16: 0350 | K16: 71260 | M16: 1 | N16: 2500 | O16: =M16*N16 -> 2500 | P16: 1221.71 | Q16: =P16*20% -> 244.342 | R16: =O16-P16 -> 1278.29 | S16: Demo PPO | T16: Gold PPO | U16: AUTH-700012 | V16: Eleanor Brooks, MD | W16: Assigned Department Provider | X16: RIS/PACS | Y16: Exam completed | Z16: Posted | AA16: Matched | AB16: Passed | AD16: Prior authorization | AE16: R91.1 | AF16: 22 | AG16: 2026-09-13 16:30 | AH16: Synthetic demonstration charge
A17: OPD-CHG-0013 | B17: OP-202600013 | C17: CSN-OPD-780013 | D17: Outpatient | E17: Demo Regional Medical Center | F17: Radiology | G17: 2026-09-14 | H17: MRI-BRAIN-WO | I17: MRI Brain Without Contrast | J17: 0610 | K17: 70551 | M17: 1 | N17: 3250 | O17: =M17*N17 -> 3250 | P17: 2247.78 | Q17: =P17*20% -> 449.556 | R17: =O17-P17 -> 1002.22 | S17: Demo PPO | T17: Gold PPO | U17: AUTH-700013 | V17: Eleanor Brooks, MD | W17: Assigned Department Provider | X17: RIS/PACS | Y17: Exam completed | Z17: Posted | AA17: Matched | AB17: Passed | AD17: Prior authorization | AE17: G43.909 | AF17: 22 | AG17: 2026-09-14 16:30 | AH17: Synthetic demonstration charge
A18: OPD-CHG-0014 | B18: OP-202600014 | C18: CSN-OPD-780014 | D18: Outpatient | E18: Demo Regional Medical Center | F18: Radiology | G18: 2026-09-15 | H18: US-ABD-COMP | I18: Ultrasound Abdomen Complete | J18: 0402 | K18: 76700 | M18: 1 | N18: 875 | O18: =M18*N18 -> 875 | P18: 593.15 | Q18: =P18*20% -> 118.63 | R18: =O18-P18 -> 281.85 | S18: Demo PPO | T18: Gold PPO | V18: Eleanor Brooks, MD | W18: Assigned Department Provider | X18: RIS/PACS | Y18: Exam completed | Z18: Posted | AA18: Matched | AB18: Passed | AD18: Diagnosis/LCD | AE18: R10.84 | AF18: 22 | AG18: 2026-09-15 16:30 | AH18: Synthetic demonstration charge
A19: OPD-CHG-0015 | B19: OP-202600015 | C19: CSN-OPD-780015 | D19: Outpatient | E19: Demo Regional Medical Center | F19: Mammography | G19: 2026-09-16 | H19: MAMMO-SCREEN | I19: Screening Mammography, Bilateral | J19: 0403 | K19: 77067 | M19: 1 | N19: 535 | O19: =M19*N19 -> 535 | P19: 236.07 | Q19: =P19*20% -> 47.214 | R19: =O19-P19 -> 298.93 | S19: Demo PPO | T19: Gold PPO | V19: Eleanor Brooks, MD | W19: Assigned Department Provider | X19: RIS/PACS | Y19: Exam completed | Z19: Posted | AA19: Matched | AB19: Passed | AD19: Preventive rule | AE19: Z12.31 | AF19: 22 | AG19: 2026-09-16 16:30 | AH19: Synthetic demonstration charge
A20: OPD-CHG-0016 | B20: OP-202600016 | C20: CSN-OPD-780016 | D20: Outpatient | E20: Demo Regional Medical Center | F20: Laboratory | G20: 2026-09-17 | H20: CBC-OP | I20: Complete Blood Count with Differential | J20: 0300 | K20: 85025 | M20: 1 | N20: 155 | O20: =M20*N20 -> 155 | P20: 76.17 | Q20: =P20*20% -> 15.234 | R20: =O20-P20 -> 78.83 | S20: Demo PPO | T20: Gold PPO | V20: Eleanor Brooks, MD | W20: Assigned Department Provider | X20: LIS | Y20: Final result | Z20: Posted | AA20: Matched | AB20: Passed | AD20: Diagnosis/LCD | AE20: R53.83 | AF20: 22 | AG20: 2026-09-17 16:30 | AH20: Synthetic demonstration charge
A21: OPD-CHG-0017 | B21: OP-202600017 | C21: CSN-OPD-780017 | D21: Outpatient | E21: Demo Regional Medical Center | F21: Laboratory | G21: 2026-09-18 | H21: BMP-OP | I21: Basic Metabolic Panel | J21: 0301 | K21: 80048 | M21: 1 | N21: 185 | O21: =M21*N21 -> 185 | P21: 114.83 | Q21: =P21*20% -> 22.966 | R21: =O21-P21 -> 70.17 | S21: Demo PPO | T21: Gold PPO | V21: Eleanor Brooks, MD | W21: Assigned Department Provider | X21: LIS | Y21: Final result | Z21: Posted | AA21: Matched | AB21: Passed | AD21: Diagnosis/LCD | AE21: I10 | AF21: 22 | AG21: 2026-09-18 16:30 | AH21: Synthetic demonstration charge
A22: OPD-CHG-0018 | B22: OP-202600018 | C22: CSN-OPD-780018 | D22: Outpatient | E22: Demo Regional Medical Center | F22: Laboratory | G22: 2026-09-19 | H22: A1C-OP | I22: Hemoglobin A1c | J22: 0301 | K22: 83036 | M22: 1 | N22: 110 | O22: =M22*N22 -> 110 | P22: 53.27 | Q22: =P22*20% -> 10.654 | R22: =O22-P22 -> 56.73 | S22: Demo PPO | T22: Gold PPO | V22: Eleanor Brooks, MD | W22: Assigned Department Provider | X22: LIS | Y22: Final result | Z22: Posted | AA22: Matched | AB22: Passed | AD22: Diagnosis/LCD | AE22: E11.9 | AF22: 22 | AG22: 2026-09-19 16:30 | AH22: Synthetic demonstration charge
A23: OPD-CHG-0019 | B23: OP-202600019 | C23: CSN-OPD-780019 | D23: Outpatient | E23: Demo Regional Medical Center | F23: Laboratory | G23: 2026-09-20 | H23: LIPID-OP | I23: Lipid Panel | J23: 0301 | K23: 80061 | M23: 1 | N23: 215 | O23: =M23*N23 -> 215 | P23: 98.83 | Q23: =P23*20% -> 19.766 | R23: =O23-P23 -> 116.17 | S23: Demo PPO | T23: Gold PPO | V23: Eleanor Brooks, MD | W23: Assigned Department Provider | X23: LIS | Y23: Final result | Z23: Posted | AA23: Matched | AB23: Passed | AD23: Diagnosis/LCD | AE23: E78.5 | AF23: 22 | AG23: 2026-09-20 16:30 | AH23: Synthetic demonstration charge
A24: OPD-CHG-0020 | B24: OP-202600020 | C24: CSN-OPD-780020 | D24: Outpatient | E24: Demo Regional Medical Center | F24: Cardiology | G24: 2026-09-21 | H24: ECHO-COMP | I24: Complete Transthoracic Echocardiogram | J24: 0483 | K24: 93306 | M24: 1 | N24: 1550 | O24: =M24*N24 -> 1550 | P24: 1086.01 | Q24: =P24*20% -> 217.202 | R24: =O24-P24 -> 463.99 | S24: Demo PPO | T24: Gold PPO | U24: AUTH-700020 | V24: Eleanor Brooks, MD | W24: Assigned Department Provider | X24: Cardiology | Y24: Test completed | Z24: Posted | AA24: Matched | AB24: Passed | AD24: Prior authorization | AE24: R01.1 | AF24: 22 | AG24: 2026-09-21 16:30 | AH24: Synthetic demonstration charge
A25: OPD-CHG-0021 | B25: OP-202600021 | C25: CSN-OPD-780021 | D25: Outpatient | E25: Demo Regional Medical Center | F25: Cardiology | G25: 2026-09-22 | H25: STRESS-TEST | I25: Cardiovascular Stress Test | J25: 0482 | K25: 93017 | M25: 1 | N25: 1150 | O25: =M25*N25 -> 1150 | P25: 680.01 | Q25: =P25*20% -> 136.002 | R25: =O25-P25 -> 469.99 | S25: Demo PPO | T25: Gold PPO | U25: AUTH-700021 | V25: Eleanor Brooks, MD | W25: Assigned Department Provider | X25: Cardiology | Y25: Test completed | Z25: Posted | AA25: Matched | AB25: Passed | AD25: Prior authorization | AE25: R07.9 | AF25: 22 | AG25: 2026-09-22 16:30 | AH25: Synthetic demonstration charge
A26: OPD-CHG-0022 | B26: OP-202600022 | C26: CSN-OPD-780022 | D26: Outpatient | E26: Demo Regional Medical Center | F26: Endoscopy | G26: 2026-09-23 | H26: COLON-DX | I26: Diagnostic Colonoscopy | J26: 0750 | K26: 45378 | M26: 1 | N26: 3900 | O26: =M26*N26 -> 3900 | P26: 2191.03 | Q26: =P26*20% -> 438.206 | R26: =O26-P26 -> 1708.97 | S26: Demo PPO | T26: Gold PPO | U26: AUTH-700022 | V26: Eleanor Brooks, MD | W26: Assigned Department Provider | X26: Endoscopy | Y26: Procedure completed | Z26: Posted | AA26: Matched | AB26: Passed | AD26: Prior authorization | AE26: Z12.11 | AF26: 22 | AG26: 2026-09-23 16:30 | AH26: Synthetic demonstration charge
A27: OPD-CHG-0023 | B27: OP-202600023 | C27: CSN-OPD-780023 | D27: Outpatient | E27: Demo Regional Medical Center | F27: Endoscopy | G27: 2026-09-24 | H27: EGD-DX | I27: Diagnostic Upper GI Endoscopy | J27: 0750 | K27: 43235 | M27: 1 | N27: 3300 | O27: =M27*N27 -> 3300 | P27: 2162.77 | Q27: =P27*20% -> 432.554 | R27: =O27-P27 -> 1137.23 | S27: Demo PPO | T27: Gold PPO | U27: AUTH-700023 | V27: Eleanor Brooks, MD | W27: Assigned Department Provider | X27: Endoscopy | Y27: Procedure completed | Z27: Posted | AA27: Matched | AB27: Review | AC27: WQ-END-04 | AD27: Prior authorization | AE27: K21.9 | AF27: 22 | AG27: 2026-09-24 16:30 | AH27: Synthetic demonstration charge
A28: OPD-CHG-0024 | B28: OP-202600024 | C28: CSN-OPD-780024 | D28: Outpatient | E28: Demo Regional Medical Center | F28: Physical Therapy | G28: 2026-09-25 | H28: PT-EVAL-OP | I28: Outpatient Physical Therapy Evaluation | J28: 0420 | K28: 97162 | M28: 1 | N28: 860 | O28: =M28*N28 -> 860 | P28: 569.53 | Q28: =P28*20% -> 113.906 | R28: =O28-P28 -> 290.47 | S28: Demo PPO | T28: Gold PPO | U28: AUTH-700024 | V28: Eleanor Brooks, MD | W28: Assigned Department Provider | X28: Therapy | Y28: Note signed | Z28: Posted | AA28: Matched | AB28: Passed | AD28: Plan benefits | AE28: M54.50 | AF28: 22 | AG28: 2026-09-25 16:30 | AH28: Synthetic demonstration charge
A29: OPD-CHG-0025 | B29: OP-202600025 | C29: CSN-OPD-780025 | D29: Outpatient | E29: Demo Regional Medical Center | F29: Physical Therapy | G29: 2026-09-01 | H29: PT-THEREX-OP | I29: Therapeutic Exercise, 15 Minutes | J29: 0420 | K29: 97110 | M29: 3 | N29: 305 | O29: =M29*N29 -> 915 | P29: 410.19 | Q29: =P29*20% -> 82.038 | R29: =O29-P29 -> 504.81 | S29: Demo PPO | T29: Gold PPO | V29: Eleanor Brooks, MD | W29: Assigned Department Provider | X29: Therapy | Y29: Note signed | Z29: Posted | AA29: Matched | AB29: Passed | AD29: Timed units | AE29: M54.50 | AF29: 22 | AG29: 2026-09-01 16:30 | AH29: Synthetic demonstration charge
A30: OPD-CHG-0026 | B30: OP-202600026 | C30: CSN-OPD-780026 | D30: Outpatient | E30: Demo Regional Medical Center | F30: Infusion | G30: 2026-09-02 | H30: INFUSION-1H | I30: Therapeutic Infusion, Initial Hour | J30: 0260 | K30: 96365 | M30: 1 | N30: 780 | O30: =M30*N30 -> 780 | P30: 481.8 | Q30: =P30*20% -> 96.36 | R30: =O30-P30 -> 298.2 | S30: Demo PPO | T30: Gold PPO | U30: AUTH-700026 | V30: Eleanor Brooks, MD | W30: Assigned Department Provider | X30: Infusion | Y30: Administration completed | Z30: Posted | AA30: Matched | AB30: Passed | AD30: Drug policy | AE30: Z51.11 | AF30: 22 | AG30: 2026-09-02 16:30 | AH30: Synthetic demonstration charge
A31: OPD-CHG-0027 | B31: OP-202600027 | C31: CSN-OPD-780027 | D31: Outpatient | E31: Demo Regional Medical Center | F31: Chemotherapy | G31: 2026-09-03 | H31: CHEMO-1H | I31: Chemotherapy Infusion, Initial Hour | J31: 0335 | K31: 96413 | M31: 1 | N31: 1850 | O31: =M31*N31 -> 1850 | P31: 973.64 | Q31: =P31*20% -> 194.728 | R31: =O31-P31 -> 876.36 | S31: Demo PPO | T31: Gold PPO | U31: AUTH-700027 | V31: Eleanor Brooks, MD | W31: Assigned Department Provider | X31: Infusion | Y31: Administration completed | Z31: Posted | AA31: Matched | AB31: Passed | AD31: Drug policy | AE31: C50.919 | AF31: 22 | AG31: 2026-09-03 16:30 | AH31: Synthetic demonstration charge
A32: OPD-CHG-0028 | B32: OP-202600028 | C32: CSN-OPD-780028 | D32: Outpatient | E32: Demo Regional Medical Center | F32: Behavioral Health | G32: 2026-09-04 | H32: BH-INDIVIDUAL | I32: Outpatient Psychotherapy, 45 Minutes | J32: 0914 | K32: 90834 | M32: 1 | N32: 285 | O32: =M32*N32 -> 285 | P32: 154.85 | Q32: =P32*20% -> 30.97 | R32: =O32-P32 -> 130.15 | S32: Demo PPO | T32: Gold PPO | V32: Eleanor Brooks, MD | W32: Assigned Department Provider | X32: Behavioral Health | Y32: Note signed | Z32: Posted | AA32: Matched | AB32: Passed | AD32: Benefits | AE32: F41.1 | AF32: 22 | AG32: 2026-09-04 16:30 | AH32: Synthetic demonstration charge
A33: OPD-CHG-0029 | B33: OP-202600029 | C33: CSN-OPD-780029 | D33: Outpatient | E33: Demo Regional Medical Center | F33: Emergency Department | G33: 2026-09-05 | H33: ED-LEVEL-1 | I33: Emergency Department Visit Level 1 | J33: 0450 | K33: 99281 | M33: 1 | N33: 360 | O33: =M33*N33 -> 360 | P33: 244.49 | Q33: =P33*20% -> 48.898 | R33: =O33-P33 -> 115.51 | S33: Demo PPO | T33: Gold PPO | V33: Eleanor Brooks, MD | W33: Assigned Department Provider | X33: ED | Y33: Encounter close | Z33: Hold | AA33: Exception | AB33: Review | AC33: WQ-EME-02 | AD33: Documentation | AE33: R50.9 | AF33: 22 | AG33: 2026-09-05 16:30 | AH33: Synthetic demonstration charge
A34: OPD-CHG-0030 | B34: OP-202600030 | C34: CSN-OPD-780030 | D34: Outpatient | E34: Demo Regional Medical Center | F34: Emergency Department | G34: 2026-09-06 | H34: ED-LEVEL-2 | I34: Emergency Department Visit Level 2 | J34: 0450 | K34: 99282 | M34: 1 | N34: 670 | O34: =M34*N34 -> 670 | P34: 292.29 | Q34: =P34*20% -> 58.458 | R34: =O34-P34 -> 377.71 | S34: Demo PPO | T34: Gold PPO | V34: Eleanor Brooks, MD | W34: Assigned Department Provider | X34: ED | Y34: Encounter close | Z34: Posted | AA34: Matched | AB34: Passed | AD34: Documentation | AE34: R51.9 | AF34: 22 | AG34: 2026-09-06 16:30 | AH34: Synthetic demonstration charge
A35: OPD-CHG-0031 | B35: OP-202600031 | C35: CSN-OPD-780031 | D35: Outpatient | E35: Demo Regional Medical Center | F35: Emergency Department | G35: 2026-09-07 | H35: ED-LEVEL-3 | I35: Emergency Department Visit Level 3 | J35: 0450 | K35: 99283 | M35: 1 | N35: 1280 | O35: =M35*N35 -> 1280 | P35: 788.53 | Q35: =P35*20% -> 157.706 | R35: =O35-P35 -> 491.47 | S35: Demo PPO | T35: Gold PPO | V35: Eleanor Brooks, MD | W35: Assigned Department Provider | X35: ED | Y35: Encounter close | Z35: Posted | AA35: Matched | AB35: Passed | AD35: Documentation | AE35: R10.9 | AF35: 22 | AG35: 2026-09-07 16:30 | AH35: Synthetic demonstration charge
A36: OPD-CHG-0032 | B36: OP-202600032 | C36: CSN-OPD-780032 | D36: Outpatient | E36: Demo Regional Medical Center | F36: Emergency Department | G36: 2026-09-08 | H36: ED-LEVEL-4 | I36: Emergency Department Visit Level 4 | J36: 0450 | K36: 99284 | M36: 1 | N36: 2350 | O36: =M36*N36 -> 2350 | P36: 1442.56 | Q36: =P36*20% -> 288.512 | R36: =O36-P36 -> 907.44 | S36: Demo PPO | T36: Gold PPO | V36: Eleanor Brooks, MD | W36: Assigned Department Provider | X36: ED | Y36: Encounter close | Z36: Posted | AA36: Matched | AB36: Passed | AD36: Documentation | AE36: R06.02 | AF36: 22 | AG36: 2026-09-08 16:30 | AH36: Synthetic demonstration charge
A37: OPD-CHG-0033 | B37: OP-202600033 | C37: CSN-OPD-780033 | D37: Outpatient | E37: Demo Regional Medical Center | F37: Emergency Department | G37: 2026-09-09 | H37: ED-LEVEL-5 | I37: Emergency Department Visit Level 5 | J37: 0450 | K37: 99285 | M37: 1 | N37: 4300 | O37: =M37*N37 -> 4300 | P37: 1884.19 | Q37: =P37*20% -> 376.838 | R37: =O37-P37 -> 2415.81 | S37: Demo PPO | T37: Gold PPO | V37: Eleanor Brooks, MD | W37: Assigned Department Provider | X37: ED | Y37: Encounter close | Z37: Posted | AA37: Matched | AB37: Passed | AD37: Documentation | AE37: R07.9 | AF37: 22 | AG37: 2026-09-09 16:30 | AH37: Synthetic demonstration charge
A38: OPD-CHG-0034 | B38: OP-202600034 | C38: CSN-OPD-780034 | D38: Outpatient | E38: Demo Regional Medical Center | F38: Hospital Clinic | G38: 2026-09-10 | H38: CLINIC-L2 | I38: Hospital Outpatient Clinic Visit Level 2 | J38: 0510 | K38: 99212 | M38: 1 | N38: 215 | O38: =M38*N38 -> 215 | P38: 137.27 | Q38: =P38*20% -> 27.454 | R38: =O38-P38 -> 77.73 | S38: Demo PPO | T38: Gold PPO | V38: Eleanor Brooks, MD | W38: Assigned Department Provider | X38: Ambulatory | Y38: Visit close | Z38: Posted | AA38: Matched | AB38: Passed | AD38: E/M documentation | AE38: I10 | AF38: 22 | AG38: 2026-09-10 16:30 | AH38: Synthetic demonstration charge
A39: OPD-CHG-0035 | B39: OP-202600035 | C39: CSN-OPD-780035 | D39: Outpatient | E39: Demo Regional Medical Center | F39: Hospital Clinic | G39: 2026-09-11 | H39: CLINIC-L3 | I39: Hospital Outpatient Clinic Visit Level 3 | J39: 0510 | K39: 99213 | M39: 1 | N39: 315 | O39: =M39*N39 -> 315 | P39: 207.96 | Q39: =P39*20% -> 41.592 | R39: =O39-P39 -> 107.04 | S39: Demo PPO | T39: Gold PPO | V39: Eleanor Brooks, MD | W39: Assigned Department Provider | X39: Ambulatory | Y39: Visit close | Z39: Posted | AA39: Matched | AB39: Passed | AD39: E/M documentation | AE39: E11.9 | AF39: 22 | AG39: 2026-09-11 16:30 | AH39: Synthetic demonstration charge
A40: OPD-CHG-0036 | B40: OP-202600036 | C40: CSN-OPD-780036 | D40: Outpatient | E40: Demo Regional Medical Center | F40: Hospital Clinic | G40: 2026-09-12 | H40: CLINIC-L4 | I40: Hospital Outpatient Clinic Visit Level 4 | J40: 0510 | K40: 99214 | M40: 1 | N40: 410 | O40: =M40*N40 -> 410 | P40: 185.64 | Q40: =P40*20% -> 37.128 | R40: =O40-P40 -> 224.36 | S40: Demo PPO | T40: Gold PPO | V40: Eleanor Brooks, MD | W40: Assigned Department Provider | X40: Ambulatory | Y40: Visit close | Z40: Posted | AA40: Matched | AB40: Passed | AD40: E/M documentation | AE40: J45.40 | AF40: 22 | AG40: 2026-09-12 16:30 | AH40: Synthetic demonstration charge
A41: OPD-CHG-0037 | B41: OP-202600037 | C41: CSN-OPD-780037 | D41: Outpatient | E41: Demo Regional Medical Center | F41: Hospital Clinic | G41: 2026-09-13 | H41: CLINIC-L5 | I41: Hospital Outpatient Clinic Visit Level 5 | J41: 0510 | K41: 99215 | M41: 1 | N41: 570 | O41: =M41*N41 -> 570 | P41: 272.16 | Q41: =P41*20% -> 54.432 | R41: =O41-P41 -> 297.84 | S41: Demo PPO | T41: Gold PPO | V41: Eleanor Brooks, MD | W41: Assigned Department Provider | X41: Ambulatory | Y41: Visit close | Z41: Posted | AA41: Matched | AB41: Passed | AD41: E/M documentation | AE41: I50.9 | AF41: 22 | AG41: 2026-09-13 16:30 | AH41: Synthetic demonstration charge
A42: OPD-CHG-0038 | B42: OP-202600038 | C42: CSN-OPD-780038 | D42: Outpatient | E42: Demo Regional Medical Center | F42: Radiology | G42: 2026-09-14 | H42: XR-CHEST-2V | I42: Chest X-ray, 2 Views | J42: 0320 | K42: 71046 | M42: 1 | N42: 185 | O42: =M42*N42 -> 185 | P42: 107.46 | Q42: =P42*20% -> 21.492 | R42: =O42-P42 -> 77.54 | S42: Demo PPO | T42: Gold PPO | V42: Eleanor Brooks, MD | W42: Assigned Department Provider | X42: RIS/PACS | Y42: Exam completed | Z42: Posted | AA42: Matched | AB42: Passed | AD42: Diagnosis/LCD | AE42: R05.9 | AF42: 22 | AG42: 2026-09-14 16:30 | AH42: Synthetic demonstration charge
A43: OPD-CHG-0039 | B43: OP-202600039 | C43: CSN-OPD-780039 | D43: Outpatient | E43: Demo Regional Medical Center | F43: Radiology | G43: 2026-09-15 | H43: CT-HEAD-WO | I43: CT Head Without Contrast | J43: 0350 | K43: 70450 | M43: 1 | N43: 1900 | O43: =M43*N43 -> 1900 | P43: 877.9 | Q43: =P43*20% -> 175.58 | R43: =O43-P43 -> 1022.1 | S43: Demo PPO | T43: Gold PPO | U43: AUTH-700039 | V43: Eleanor Brooks, MD | W43: Assigned Department Provider | X43: RIS/PACS | Y43: Exam completed | Z43: Posted | AA43: Matched | AB43: Passed | AD43: Prior authorization | AE43: R51.9 | AF43: 22 | AG43: 2026-09-15 16:30 | AH43: Synthetic demonstration charge
A44: OPD-CHG-0040 | B44: OP-202600040 | C44: CSN-OPD-780040 | D44: Outpatient | E44: Demo Regional Medical Center | F44: Radiology | G44: 2026-09-16 | H44: CT-CHEST-W | I44: CT Chest With Contrast | J44: 0350 | K44: 71260 | M44: 1 | N44: 2500 | O44: =M44*N44 -> 2500 | P44: 1187.62 | Q44: =P44*20% -> 237.524 | R44: =O44-P44 -> 1312.38 | S44: Demo PPO | T44: Gold PPO | U44: AUTH-700040 | V44: Eleanor Brooks, MD | W44: Assigned Department Provider | X44: RIS/PACS | Y44: Exam completed | Z44: Posted | AA44: Matched | AB44: Passed | AD44: Prior authorization | AE44: R91.1 | AF44: 22 | AG44: 2026-09-16 16:30 | AH44: Synthetic demonstration charge
A45: OPD-CHG-0041 | B45: OP-202600041 | C45: CSN-OPD-780041 | D45: Outpatient | E45: Demo Regional Medical Center | F45: Radiology | G45: 2026-09-17 | H45: MRI-BRAIN-WO | I45: MRI Brain Without Contrast | J45: 0610 | K45: 70551 | M45: 1 | N45: 3250 | O45: =M45*N45 -> 3250 | P45: 1816.06 | Q45: =P45*20% -> 363.212 | R45: =O45-P45 -> 1433.94 | S45: Demo PPO | T45: Gold PPO | U45: AUTH-700041 | V45: Eleanor Brooks, MD | W45: Assigned Department Provider | X45: RIS/PACS | Y45: Exam completed | Z45: Posted | AA45: Matched | AB45: Passed | AD45: Prior authorization | AE45: G43.909 | AF45: 22 | AG45: 2026-09-17 16:30 | AH45: Synthetic demonstration charge
A46: OPD-CHG-0042 | B46: OP-202600042 | C46: CSN-OPD-780042 | D46: Outpatient | E46: Demo Regional Medical Center | F46: Radiology | G46: 2026-09-18 | H46: US-ABD-COMP | I46: Ultrasound Abdomen Complete | J46: 0402 | K46: 76700 | M46: 1 | N46: 875 | O46: =M46*N46 -> 875 | P46: 597.05 | Q46: =P46*20% -> 119.41 | R46: =O46-P46 -> 277.95 | S46: Demo PPO | T46: Gold PPO | V46: Eleanor Brooks, MD | W46: Assigned Department Provider | X46: RIS/PACS | Y46: Exam completed | Z46: Posted | AA46: Matched | AB46: Passed | AD46: Diagnosis/LCD | AE46: R10.84 | AF46: 22 | AG46: 2026-09-18 16:30 | AH46: Synthetic demonstration charge
A47: OPD-CHG-0043 | B47: OP-202600043 | C47: CSN-OPD-780043 | D47: Outpatient | E47: Demo Regional Medical Center | F47: Mammography | G47: 2026-09-19 | H47: MAMMO-SCREEN | I47: Screening Mammography, Bilateral | J47: 0403 | K47: 77067 | M47: 1 | N47: 535 | O47: =M47*N47 -> 535 | P47: 236.8 | Q47: =P47*20% -> 47.36 | R47: =O47-P47 -> 298.2 | S47: Demo PPO | T47: Gold PPO | V47: Eleanor Brooks, MD | W47: Assigned Department Provider | X47: RIS/PACS | Y47: Exam completed | Z47: Posted | AA47: Matched | AB47: Passed | AD47: Preventive rule | AE47: Z12.31 | AF47: 22 | AG47: 2026-09-19 16:30 | AH47: Synthetic demonstration charge
A48: OPD-CHG-0044 | B48: OP-202600044 | C48: CSN-OPD-780044 | D48: Outpatient | E48: Demo Regional Medical Center | F48: Laboratory | G48: 2026-09-20 | H48: CBC-OP | I48: Complete Blood Count with Differential | J48: 0300 | K48: 85025 | M48: 1 | N48: 155 | O48: =M48*N48 -> 155 | P48: 102.67 | Q48: =P48*20% -> 20.534 | R48: =O48-P48 -> 52.33 | S48: Demo PPO | T48: Gold PPO | V48: Eleanor Brooks, MD | W48: Assigned Department Provider | X48: LIS | Y48: Final result | Z48: Posted | AA48: Matched | AB48: Passed | AD48: Diagnosis/LCD | AE48: R53.83 | AF48: 22 | AG48: 2026-09-20 16:30 | AH48: Synthetic demonstration charge
A49: OPD-CHG-0045 | B49: OP-202600045 | C49: CSN-OPD-780045 | D49: Outpatient | E49: Demo Regional Medical Center | F49: Laboratory | G49: 2026-09-21 | H49: BMP-OP | I49: Basic Metabolic Panel | J49: 0301 | K49: 80048 | M49: 1 | N49: 185 | O49: =M49*N49 -> 185 | P49: 125.21 | Q49: =P49*20% -> 25.042 | R49: =O49-P49 -> 59.79 | S49: Demo PPO | T49: Gold PPO | V49: Eleanor Brooks, MD | W49: Assigned Department Provider | X49: LIS | Y49: Final result | Z49: Posted | AA49: Matched | AB49: Passed | AD49: Diagnosis/LCD | AE49: I10 | AF49: 22 | AG49: 2026-09-21 16:30 | AH49: Synthetic demonstration charge
A50: OPD-CHG-0046 | B50: OP-202600046 | C50: CSN-OPD-780046 | D50: Outpatient | E50: Demo Regional Medical Center | F50: Laboratory | G50: 2026-09-22 | H50: A1C-OP | I50: Hemoglobin A1c | J50: 0301 | K50: 83036 | M50: 1 | N50: 110 | O50: =M50*N50 -> 110 | P50: 49.43 | Q50: =P50*20% -> 9.886 | R50: =O50-P50 -> 60.57 | S50: Demo PPO | T50: Gold PPO | V50: Eleanor Brooks, MD | W50: Assigned Department Provider | X50: LIS | Y50: Final result | Z50: Posted | AA50: Matched | AB50: Review | AC50: WQ-LAB-03 | AD50: Diagnosis/LCD | AE50: E11.9 | AF50: 22 | AG50: 2026-09-22 16:30 | AH50: Synthetic demonstration charge
A51: OPD-CHG-0047 | B51: OP-202600047 | C51: CSN-OPD-780047 | D51: Outpatient | E51: Demo Regional Medical Center | F51: Laboratory | G51: 2026-09-23 | H51: LIPID-OP | I51: Lipid Panel | J51: 0301 | K51: 80061 | M51: 1 | N51: 215 | O51: =M51*N51 -> 215 | P51: 132.36 | Q51: =P51*20% -> 26.472 | R51: =O51-P51 -> 82.64 | S51: Demo PPO | T51: Gold PPO | V51: Eleanor Brooks, MD | W51: Assigned Department Provider | X51: LIS | Y51: Final result | Z51: Posted | AA51: Matched | AB51: Passed | AD51: Diagnosis/LCD | AE51: E78.5 | AF51: 22 | AG51: 2026-09-23 16:30 | AH51: Synthetic demonstration charge
A52: OPD-CHG-0048 | B52: OP-202600048 | C52: CSN-OPD-780048 | D52: Outpatient | E52: Demo Regional Medical Center | F52: Cardiology | G52: 2026-09-24 | H52: ECHO-COMP | I52: Complete Transthoracic Echocardiogram | J52: 0483 | K52: 93306 | M52: 1 | N52: 1550 | O52: =M52*N52 -> 1550 | P52: 902.37 | Q52: =P52*20% -> 180.474 | R52: =O52-P52 -> 647.63 | S52: Demo PPO | T52: Gold PPO | U52: AUTH-700048 | V52: Eleanor Brooks, MD | W52: Assigned Department Provider | X52: Cardiology | Y52: Test completed | Z52: Posted | AA52: Matched | AB52: Passed | AD52: Prior authorization | AE52: R01.1 | AF52: 22 | AG52: 2026-09-24 16:30 | AH52: Synthetic demonstration charge
A53: OPD-CHG-0049 | B53: OP-202600049 | C53: CSN-OPD-780049 | D53: Outpatient | E53: Demo Regional Medical Center | F53: Cardiology | G53: 2026-09-25 | H53: STRESS-TEST | I53: Cardiovascular Stress Test | J53: 0482 | K53: 93017 | M53: 1 | N53: 1150 | O53: =M53*N53 -> 1150 | P53: 488.09 | Q53: =P53*20% -> 97.618 | R53: =O53-P53 -> 661.91 | S53: Demo PPO | T53: Gold PPO | U53: AUTH-700049 | V53: Eleanor Brooks, MD | W53: Assigned Department Provider | X53: Cardiology | Y53: Test completed | Z53: Posted | AA53: Matched | AB53: Passed | AD53: Prior authorization | AE53: R07.9 | AF53: 22 | AG53: 2026-09-25 16:30 | AH53: Synthetic demonstration charge
A54: OPD-CHG-0050 | B54: OP-202600050 | C54: CSN-OPD-780050 | D54: Outpatient | E54: Demo Regional Medical Center | F54: Endoscopy | G54: 2026-09-01 | H54: COLON-DX | I54: Diagnostic Colonoscopy | J54: 0750 | K54: 45378 | M54: 1 | N54: 3900 | O54: =M54*N54 -> 3900 | P54: 1747.12 | Q54: =P54*20% -> 349.424 | R54: =O54-P54 -> 2152.88 | S54: Demo PPO | T54: Gold PPO | U54: AUTH-700050 | V54: Eleanor Brooks, MD | W54: Assigned Department Provider | X54: Endoscopy | Y54: Procedure completed | Z54: Posted | AA54: Matched | AB54: Passed | AD54: Prior authorization | AE54: Z12.11 | AF54: 22 | AG54: 2026-09-01 16:30 | AH54: Synthetic demonstration charge
A55: OPD-CHG-0051 | B55: OP-202600051 | C55: CSN-OPD-780051 | D55: Outpatient | E55: Demo Regional Medical Center | F55: Endoscopy | G55: 2026-09-02 | H55: EGD-DX | I55: Diagnostic Upper GI Endoscopy | J55: 0750 | K55: 43235 | M55: 1 | N55: 3300 | O55: =M55*N55 -> 3300 | P55: 2132.03 | Q55: =P55*20% -> 426.406 | R55: =O55-P55 -> 1167.97 | S55: Demo PPO | T55: Gold PPO | U55: AUTH-700051 | V55: Eleanor Brooks, MD | W55: Assigned Department Provider | X55: Endoscopy | Y55: Procedure completed | Z55: Posted | AA55: Matched | AB55: Passed | AD55: Prior authorization | AE55: K21.9 | AF55: 22 | AG55: 2026-09-02 16:30 | AH55: Synthetic demonstration charge
A56: OPD-CHG-0052 | B56: OP-202600052 | C56: CSN-OPD-780052 | D56: Outpatient | E56: Demo Regional Medical Center | F56: Physical Therapy | G56: 2026-09-03 | H56: PT-EVAL-OP | I56: Outpatient Physical Therapy Evaluation | J56: 0420 | K56: 97162 | M56: 1 | N56: 860 | O56: =M56*N56 -> 860 | P56: 422.19 | Q56: =P56*20% -> 84.438 | R56: =O56-P56 -> 437.81 | S56: Demo PPO | T56: Gold PPO | U56: AUTH-700052 | V56: Eleanor Brooks, MD | W56: Assigned Department Provider | X56: Therapy | Y56: Note signed | Z56: Posted | AA56: Matched | AB56: Passed | AD56: Plan benefits | AE56: M54.50 | AF56: 22 | AG56: 2026-09-03 16:30 | AH56: Synthetic demonstration charge
A57: OPD-CHG-0053 | B57: OP-202600053 | C57: CSN-OPD-780053 | D57: Outpatient | E57: Demo Regional Medical Center | F57: Physical Therapy | G57: 2026-09-04 | H57: PT-THEREX-OP | I57: Therapeutic Exercise, 15 Minutes | J57: 0420 | K57: 97110 | M57: 6 | N57: 305 | O57: =M57*N57 -> 1830 | P57: 1035.22 | Q57: =P57*20% -> 207.044 | R57: =O57-P57 -> 794.78 | S57: Demo PPO | T57: Gold PPO | V57: Eleanor Brooks, MD | W57: Assigned Department Provider | X57: Therapy | Y57: Note signed | Z57: Posted | AA57: Matched | AB57: Passed | AD57: Timed units | AE57: M54.50 | AF57: 22 | AG57: 2026-09-04 16:30 | AH57: Synthetic demonstration charge
A58: OPD-CHG-0054 | B58: OP-202600054 | C58: CSN-OPD-780054 | D58: Outpatient | E58: Demo Regional Medical Center | F58: Infusion | G58: 2026-09-05 | H58: INFUSION-1H | I58: Therapeutic Infusion, Initial Hour | J58: 0260 | K58: 96365 | M58: 1 | N58: 780 | O58: =M58*N58 -> 780 | P58: 377.62 | Q58: =P58*20% -> 75.524 | R58: =O58-P58 -> 402.38 | S58: Demo PPO | T58: Gold PPO | U58: AUTH-700054 | V58: Eleanor Brooks, MD | W58: Assigned Department Provider | X58: Infusion | Y58: Administration completed | Z58: Posted | AA58: Matched | AB58: Passed | AD58: Drug policy | AE58: Z51.11 | AF58: 22 | AG58: 2026-09-05 16:30 | AH58: Synthetic demonstration charge
A59: OPD-CHG-0055 | B59: OP-202600055 | C59: CSN-OPD-780055 | D59: Outpatient | E59: Demo Regional Medical Center | F59: Chemotherapy | G59: 2026-09-06 | H59: CHEMO-1H | I59: Chemotherapy Infusion, Initial Hour | J59: 0335 | K59: 96413 | M59: 1 | N59: 1850 | O59: =M59*N59 -> 1850 | P59: 999.58 | Q59: =P59*20% -> 199.916 | R59: =O59-P59 -> 850.42 | S59: Demo PPO | T59: Gold PPO | U59: AUTH-700055 | V59: Eleanor Brooks, MD | W59: Assigned Department Provider | X59: Infusion | Y59: Administration completed | Z59: Posted | AA59: Matched | AB59: Passed | AD59: Drug policy | AE59: C50.919 | AF59: 22 | AG59: 2026-09-06 16:30 | AH59: Synthetic demonstration charge
A60: OPD-CHG-0056 | B60: OP-202600056 | C60: CSN-OPD-780056 | D60: Outpatient | E60: Demo Regional Medical Center | F60: Behavioral Health | G60: 2026-09-07 | H60: BH-INDIVIDUAL | I60: Outpatient Psychotherapy, 45 Minutes | J60: 0914 | K60: 90834 | M60: 1 | N60: 285 | O60: =M60*N60 -> 285 | P60: 124.71 | Q60: =P60*20% -> 24.942 | R60: =O60-P60 -> 160.29 | S60: Demo PPO | T60: Gold PPO | V60: Eleanor Brooks, MD | W60: Assigned Department Provider | X60: Behavioral Health | Y60: Note signed | Z60: Posted | AA60: Matched | AB60: Passed | AD60: Benefits | AE60: F41.1 | AF60: 22 | AG60: 2026-09-07 16:30 | AH60: Synthetic demonstration charge
A61: OPD-CHG-0057 | B61: OP-202600057 | C61: CSN-OPD-780057 | D61: Outpatient | E61: Demo Regional Medical Center | F61: Emergency Department | G61: 2026-09-08 | H61: ED-LEVEL-1 | I61: Emergency Department Visit Level 1 | J61: 0450 | K61: 99281 | M61: 1 | N61: 360 | O61: =M61*N61 -> 360 | P61: 192.13 | Q61: =P61*20% -> 38.426 | R61: =O61-P61 -> 167.87 | S61: Demo PPO | T61: Gold PPO | V61: Eleanor Brooks, MD | W61: Assigned Department Provider | X61: ED | Y61: Encounter close | Z61: Posted | AA61: Matched | AB61: Passed | AD61: Documentation | AE61: R50.9 | AF61: 22 | AG61: 2026-09-08 16:30 | AH61: Synthetic demonstration charge
A62: OPD-CHG-0058 | B62: OP-202600058 | C62: CSN-OPD-780058 | D62: Outpatient | E62: Demo Regional Medical Center | F62: Emergency Department | G62: 2026-09-09 | H62: ED-LEVEL-2 | I62: Emergency Department Visit Level 2 | J62: 0450 | K62: 99282 | M62: 1 | N62: 670 | O62: =M62*N62 -> 670 | P62: 479.45 | Q62: =P62*20% -> 95.89 | R62: =O62-P62 -> 190.55 | S62: Demo PPO | T62: Gold PPO | V62: Eleanor Brooks, MD | W62: Assigned Department Provider | X62: ED | Y62: Encounter close | Z62: Hold | AA62: Exception | AB62: Review | AC62: WQ-EME-03 | AD62: Documentation | AE62: R51.9 | AF62: 22 | AG62: 2026-09-09 16:30 | AH62: Synthetic demonstration charge
A63: OPD-CHG-0059 | B63: OP-202600059 | C63: CSN-OPD-780059 | D63: Outpatient | E63: Demo Regional Medical Center | F63: Emergency Department | G63: 2026-09-10 | H63: ED-LEVEL-3 | I63: Emergency Department Visit Level 3 | J63: 0450 | K63: 99283 | M63: 1 | N63: 1280 | O63: =M63*N63 -> 1280 | P63: 639.44 | Q63: =P63*20% -> 127.888 | R63: =O63-P63 -> 640.56 | S63: Demo PPO | T63: Gold PPO | V63: Eleanor Brooks, MD | W63: Assigned Department Provider | X63: ED | Y63: Encounter close | Z63: Posted | AA63: Matched | AB63: Passed | AD63: Documentation | AE63: R10.9 | AF63: 22 | AG63: 2026-09-10 16:30 | AH63: Synthetic demonstration charge
A64: OPD-CHG-0060 | B64: OP-202600060 | C64: CSN-OPD-780060 | D64: Outpatient | E64: Demo Regional Medical Center | F64: Emergency Department | G64: 2026-09-11 | H64: ED-LEVEL-4 | I64: Emergency Department Visit Level 4 | J64: 0450 | K64: 99284 | M64: 1 | N64: 2350 | O64: =M64*N64 -> 2350 | P64: 1539.77 | Q64: =P64*20% -> 307.954 | R64: =O64-P64 -> 810.23 | S64: Demo PPO | T64: Gold PPO | V64: Eleanor Brooks, MD | W64: Assigned Department Provider | X64: ED | Y64: Encounter close | Z64: Posted | AA64: Matched | AB64: Passed | AD64: Documentation | AE64: R06.02 | AF64: 22 | AG64: 2026-09-11 16:30 | AH64: Synthetic demonstration charge
A65: OPD-CHG-0061 | B65: OP-202600061 | C65: CSN-OPD-780061 | D65: Outpatient | E65: Demo Regional Medical Center | F65: Emergency Department | G65: 2026-09-12 | H65: ED-LEVEL-5 | I65: Emergency Department Visit Level 5 | J65: 0450 | K65: 99285 | M65: 1 | N65: 4300 | O65: =M65*N65 -> 4300 | P65: 2392.96 | Q65: =P65*20% -> 478.592 | R65: =O65-P65 -> 1907.04 | S65: Demo PPO | T65: Gold PPO | V65: Eleanor Brooks, MD | W65: Assigned Department Provider | X65: ED | Y65: Encounter close | Z65: Posted | AA65: Matched | AB65: Passed | AD65: Documentation | AE65: R07.9 | AF65: 22 | AG65: 2026-09-12 16:30 | AH65: Synthetic demonstration charge
A66: OPD-CHG-0062 | B66: OP-202600062 | C66: CSN-OPD-780062 | D66: Outpatient | E66: Demo Regional Medical Center | F66: Hospital Clinic | G66: 2026-09-13 | H66: CLINIC-L2 | I66: Hospital Outpatient Clinic Visit Level 2 | J66: 0510 | K66: 99212 | M66: 1 | N66: 215 | O66: =M66*N66 -> 215 | P66: 117.58 | Q66: =P66*20% -> 23.516 | R66: =O66-P66 -> 97.42 | S66: Demo PPO | T66: Gold PPO | V66: Eleanor Brooks, MD | W66: Assigned Department Provider | X66: Ambulatory | Y66: Visit close | Z66: Posted | AA66: Matched | AB66: Passed | AD66: E/M documentation | AE66: I10 | AF66: 22 | AG66: 2026-09-13 16:30 | AH66: Synthetic demonstration charge
A67: OPD-CHG-0063 | B67: OP-202600063 | C67: CSN-OPD-780063 | D67: Outpatient | E67: Demo Regional Medical Center | F67: Hospital Clinic | G67: 2026-09-14 | H67: CLINIC-L3 | I67: Hospital Outpatient Clinic Visit Level 3 | J67: 0510 | K67: 99213 | M67: 1 | N67: 315 | O67: =M67*N67 -> 315 | P67: 222.77 | Q67: =P67*20% -> 44.554 | R67: =O67-P67 -> 92.23 | S67: Demo PPO | T67: Gold PPO | V67: Eleanor Brooks, MD | W67: Assigned Department Provider | X67: Ambulatory | Y67: Visit close | Z67: Posted | AA67: Matched | AB67: Passed | AD67: E/M documentation | AE67: E11.9 | AF67: 22 | AG67: 2026-09-14 16:30 | AH67: Synthetic demonstration charge
A68: OPD-CHG-0064 | B68: OP-202600064 | C68: CSN-OPD-780064 | D68: Outpatient | E68: Demo Regional Medical Center | F68: Hospital Clinic | G68: 2026-09-15 | H68: CLINIC-L4 | I68: Hospital Outpatient Clinic Visit Level 4 | J68: 0510 | K68: 99214 | M68: 1 | N68: 410 | O68: =M68*N68 -> 410 | P68: 294.64 | Q68: =P68*20% -> 58.928 | R68: =O68-P68 -> 115.36 | S68: Demo PPO | T68: Gold PPO | V68: Eleanor Brooks, MD | W68: Assigned Department Provider | X68: Ambulatory | Y68: Visit close | Z68: Posted | AA68: Matched | AB68: Passed | AD68: E/M documentation | AE68: J45.40 | AF68: 22 | AG68: 2026-09-15 16:30 | AH68: Synthetic demonstration charge
A69: OPD-CHG-0065 | B69: OP-202600065 | C69: CSN-OPD-780065 | D69: Outpatient | E69: Demo Regional Medical Center | F69: Hospital Clinic | G69: 2026-09-16 | H69: CLINIC-L5 | I69: Hospital Outpatient Clinic Visit Level 5 | J69: 0510 | K69: 99215 | M69: 1 | N69: 570 | O69: =M69*N69 -> 570 | P69: 334.44 | Q69: =P69*20% -> 66.888 | R69: =O69-P69 -> 235.56 | S69: Demo PPO | T69: Gold PPO | V69: Eleanor Brooks, MD | W69: Assigned Department Provider | X69: Ambulatory | Y69: Visit close | Z69: Posted | AA69: Matched | AB69: Passed | AD69: E/M documentation | AE69: I50.9 | AF69: 22 | AG69: 2026-09-16 16:30 | AH69: Synthetic demonstration charge
A70: OPD-CHG-0066 | B70: OP-202600066 | C70: CSN-OPD-780066 | D70: Outpatient | E70: Demo Regional Medical Center | F70: Radiology | G70: 2026-09-17 | H70: XR-CHEST-2V | I70: Chest X-ray, 2 Views | J70: 0320 | K70: 71046 | M70: 1 | N70: 185 | O70: =M70*N70 -> 185 | P70: 117.57 | Q70: =P70*20% -> 23.514 | R70: =O70-P70 -> 67.43 | S70: Demo PPO | T70: Gold PPO | V70: Eleanor Brooks, MD | W70: Assigned Department Provider | X70: RIS/PACS | Y70: Exam completed | Z70: Posted | AA70: Matched | AB70: Passed | AD70: Diagnosis/LCD | AE70: R05.9 | AF70: 22 | AG70: 2026-09-17 16:30 | AH70: Synthetic demonstration charge
A71: OPD-CHG-0067 | B71: OP-202600067 | C71: CSN-OPD-780067 | D71: Outpatient | E71: Demo Regional Medical Center | F71: Radiology | G71: 2026-09-18 | H71: CT-HEAD-WO | I71: CT Head Without Contrast | J71: 0350 | K71: 70450 | M71: 1 | N71: 1900 | O71: =M71*N71 -> 1900 | P71: 886.23 | Q71: =P71*20% -> 177.246 | R71: =O71-P71 -> 1013.77 | S71: Demo PPO | T71: Gold PPO | U71: AUTH-700067 | V71: Eleanor Brooks, MD | W71: Assigned Department Provider | X71: RIS/PACS | Y71: Exam completed | Z71: Posted | AA71: Matched | AB71: Passed | AD71: Prior authorization | AE71: R51.9 | AF71: 22 | AG71: 2026-09-18 16:30 | AH71: Synthetic demonstration charge
A72: OPD-CHG-0068 | B72: OP-202600068 | C72: CSN-OPD-780068 | D72: Outpatient | E72: Demo Regional Medical Center | F72: Radiology | G72: 2026-09-19 | H72: CT-CHEST-W | I72: CT Chest With Contrast | J72: 0350 | K72: 71260 | M72: 1 | N72: 2500 | O72: =M72*N72 -> 2500 | P72: 1272.53 | Q72: =P72*20% -> 254.506 | R72: =O72-P72 -> 1227.47 | S72: Demo PPO | T72: Gold PPO | U72: AUTH-700068 | V72: Eleanor Brooks, MD | W72: Assigned Department Provider | X72: RIS/PACS | Y72: Exam completed | Z72: Posted | AA72: Matched | AB72: Passed | AD72: Prior authorization | AE72: R91.1 | AF72: 22 | AG72: 2026-09-19 16:30 | AH72: Synthetic demonstration charge
A73: OPD-CHG-0069 | B73: OP-202600069 | C73: CSN-OPD-780069 | D73: Outpatient | E73: Demo Regional Medical Center | F73: Radiology | G73: 2026-09-20 | H73: MRI-BRAIN-WO | I73: MRI Brain Without Contrast | J73: 0610 | K73: 70551 | M73: 1 | N73: 3250 | O73: =M73*N73 -> 3250 | P73: 2309.49 | Q73: =P73*20% -> 461.898 | R73: =O73-P73 -> 940.51 | S73: Demo PPO | T73: Gold PPO | U73: AUTH-700069 | V73: Eleanor Brooks, MD | W73: Assigned Department Provider | X73: RIS/PACS | Y73: Exam completed | Z73: Posted | AA73: Matched | AB73: Review | AC73: WQ-RAD-02 | AD73: Prior authorization | AE73: G43.909 | AF73: 22 | AG73: 2026-09-20 16:30 | AH73: Synthetic demonstration charge
A74: OPD-CHG-0070 | B74: OP-202600070 | C74: CSN-OPD-780070 | D74: Outpatient | E74: Demo Regional Medical Center | F74: Radiology | G74: 2026-09-21 | H74: US-ABD-COMP | I74: Ultrasound Abdomen Complete | J74: 0402 | K74: 76700 | M74: 1 | N74: 875 | O74: =M74*N74 -> 875 | P74: 519.53 | Q74: =P74*20% -> 103.906 | R74: =O74-P74 -> 355.47 | S74: Demo PPO | T74: Gold PPO | V74: Eleanor Brooks, MD | W74: Assigned Department Provider | X74: RIS/PACS | Y74: Exam completed | Z74: Posted | AA74: Matched | AB74: Passed | AD74: Diagnosis/LCD | AE74: R10.84 | AF74: 22 | AG74: 2026-09-21 16:30 | AH74: Synthetic demonstration charge
A75: OPD-CHG-0071 | B75: OP-202600071 | C75: CSN-OPD-780071 | D75: Outpatient | E75: Demo Regional Medical Center | F75: Mammography | G75: 2026-09-22 | H75: MAMMO-SCREEN | I75: Screening Mammography, Bilateral | J75: 0403 | K75: 77067 | M75: 1 | N75: 535 | O75: =M75*N75 -> 535 | P75: 311.72 | Q75: =P75*20% -> 62.344 | R75: =O75-P75 -> 223.28 | S75: Demo PPO | T75: Gold PPO | V75: Eleanor Brooks, MD | W75: Assigned Department Provider | X75: RIS/PACS | Y75: Exam completed | Z75: Posted | AA75: Matched | AB75: Passed | AD75: Preventive rule | AE75: Z12.31 | AF75: 22 | AG75: 2026-09-22 16:30 | AH75: Synthetic demonstration charge
A76: OPD-CHG-0072 | B76: OP-202600072 | C76: CSN-OPD-780072 | D76: Outpatient | E76: Demo Regional Medical Center | F76: Laboratory | G76: 2026-09-23 | H76: CBC-OP | I76: Complete Blood Count with Differential | J76: 0300 | K76: 85025 | M76: 1 | N76: 155 | O76: =M76*N76 -> 155 | P76: 99.88 | Q76: =P76*20% -> 19.976 | R76: =O76-P76 -> 55.12 | S76: Demo PPO | T76: Gold PPO | V76: Eleanor Brooks, MD | W76: Assigned Department Provider | X76: LIS | Y76: Final result | Z76: Posted | AA76: Matched | AB76: Passed | AD76: Diagnosis/LCD | AE76: R53.83 | AF76: 22 | AG76: 2026-09-23 16:30 | AH76: Synthetic demonstration charge
A77: OPD-CHG-0073 | B77: OP-202600073 | C77: CSN-OPD-780073 | D77: Outpatient | E77: Demo Regional Medical Center | F77: Laboratory | G77: 2026-09-24 | H77: BMP-OP | I77: Basic Metabolic Panel | J77: 0301 | K77: 80048 | M77: 1 | N77: 185 | O77: =M77*N77 -> 185 | P77: 80.87 | Q77: =P77*20% -> 16.174 | R77: =O77-P77 -> 104.13 | S77: Demo PPO | T77: Gold PPO | V77: Eleanor Brooks, MD | W77: Assigned Department Provider | X77: LIS | Y77: Final result | Z77: Posted | AA77: Matched | AB77: Passed | AD77: Diagnosis/LCD | AE77: I10 | AF77: 22 | AG77: 2026-09-24 16:30 | AH77: Synthetic demonstration charge
A78: OPD-CHG-0074 | B78: OP-202600074 | C78: CSN-OPD-780074 | D78: Outpatient | E78: Demo Regional Medical Center | F78: Laboratory | G78: 2026-09-25 | H78: A1C-OP | I78: Hemoglobin A1c | J78: 0301 | K78: 83036 | M78: 1 | N78: 110 | O78: =M78*N78 -> 110 | P78: 65.48 | Q78: =P78*20% -> 13.096 | R78: =O78-P78 -> 44.52 | S78: Demo PPO | T78: Gold PPO | V78: Eleanor Brooks, MD | W78: Assigned Department Provider | X78: LIS | Y78: Final result | Z78: Posted | AA78: Matched | AB78: Passed | AD78: Diagnosis/LCD | AE78: E11.9 | AF78: 22 | AG78: 2026-09-25 16:30 | AH78: Synthetic demonstration charge
A79: OPD-CHG-0075 | B79: OP-202600075 | C79: CSN-OPD-780075 | D79: Outpatient | E79: Demo Regional Medical Center | F79: Laboratory | G79: 2026-09-01 | H79: LIPID-OP | I79: Lipid Panel | J79: 0301 | K79: 80061 | M79: 1 | N79: 215 | O79: =M79*N79 -> 215 | P79: 122.73 | Q79: =P79*20% -> 24.546 | R79: =O79-P79 -> 92.27 | S79: Demo PPO | T79: Gold PPO | V79: Eleanor Brooks, MD | W79: Assigned Department Provider | X79: LIS | Y79: Final result | Z79: Posted | AA79: Matched | AB79: Passed | AD79: Diagnosis/LCD | AE79: E78.5 | AF79: 22 | AG79: 2026-09-01 16:30 | AH79: Synthetic demonstration charge
A80: OPD-CHG-0076 | B80: OP-202600076 | C80: CSN-OPD-780076 | D80: Outpatient | E80: Demo Regional Medical Center | F80: Cardiology | G80: 2026-09-02 | H80: ECHO-COMP | I80: Complete Transthoracic Echocardiogram | J80: 0483 | K80: 93306 | M80: 1 | N80: 1550 | O80: =M80*N80 -> 1550 | P80: 1047.51 | Q80: =P80*20% -> 209.502 | R80: =O80-P80 -> 502.49 | S80: Demo PPO | T80: Gold PPO | U80: AUTH-700076 | V80: Eleanor Brooks, MD | W80: Assigned Department Provider | X80: Cardiology | Y80: Test completed | Z80: Posted | AA80: Matched | AB80: Passed | AD80: Prior authorization | AE80: R01.1 | AF80: 22 | AG80: 2026-09-02 16:30 | AH80: Synthetic demonstration charge
A81: OPD-CHG-0077 | B81: OP-202600077 | C81: CSN-OPD-780077 | D81: Outpatient | E81: Demo Regional Medical Center | F81: Cardiology | G81: 2026-09-03 | H81: STRESS-TEST | I81: Cardiovascular Stress Test | J81: 0482 | K81: 93017 | M81: 1 | N81: 1150 | O81: =M81*N81 -> 1150 | P81: 537.31 | Q81: =P81*20% -> 107.462 | R81: =O81-P81 -> 612.69 | S81: Demo PPO | T81: Gold PPO | U81: AUTH-700077 | V81: Eleanor Brooks, MD | W81: Assigned Department Provider | X81: Cardiology | Y81: Test completed | Z81: Posted | AA81: Matched | AB81: Passed | AD81: Prior authorization | AE81: R07.9 | AF81: 22 | AG81: 2026-09-03 16:30 | AH81: Synthetic demonstration charge
A82: OPD-CHG-0078 | B82: OP-202600078 | C82: CSN-OPD-780078 | D82: Outpatient | E82: Demo Regional Medical Center | F82: Endoscopy | G82: 2026-09-04 | H82: COLON-DX | I82: Diagnostic Colonoscopy | J82: 0750 | K82: 45378 | M82: 1 | N82: 3900 | O82: =M82*N82 -> 3900 | P82: 2762.11 | Q82: =P82*20% -> 552.422 | R82: =O82-P82 -> 1137.89 | S82: Demo PPO | T82: Gold PPO | U82: AUTH-700078 | V82: Eleanor Brooks, MD | W82: Assigned Department Provider | X82: Endoscopy | Y82: Procedure completed | Z82: Posted | AA82: Matched | AB82: Passed | AD82: Prior authorization | AE82: Z12.11 | AF82: 22 | AG82: 2026-09-04 16:30 | AH82: Synthetic demonstration charge
A83: OPD-CHG-0079 | B83: OP-202600079 | C83: CSN-OPD-780079 | D83: Outpatient | E83: Demo Regional Medical Center | F83: Endoscopy | G83: 2026-09-05 | H83: EGD-DX | I83: Diagnostic Upper GI Endoscopy | J83: 0750 | K83: 43235 | M83: 1 | N83: 3300 | O83: =M83*N83 -> 3300 | P83: 1465.31 | Q83: =P83*20% -> 293.062 | R83: =O83-P83 -> 1834.69 | S83: Demo PPO | T83: Gold PPO | U83: AUTH-700079 | V83: Eleanor Brooks, MD | W83: Assigned Department Provider | X83: Endoscopy | Y83: Procedure completed | Z83: Posted | AA83: Matched | AB83: Passed | AD83: Prior authorization | AE83: K21.9 | AF83: 22 | AG83: 2026-09-05 16:30 | AH83: Synthetic demonstration charge
A84: OPD-CHG-0080 | B84: OP-202600080 | C84: CSN-OPD-780080 | D84: Outpatient | E84: Demo Regional Medical Center | F84: Physical Therapy | G84: 2026-09-06 | H84: PT-EVAL-OP | I84: Outpatient Physical Therapy Evaluation | J84: 0420 | K84: 97162 | M84: 1 | N84: 860 | O84: =M84*N84 -> 860 | P84: 409.14 | Q84: =P84*20% -> 81.828 | R84: =O84-P84 -> 450.86 | S84: Demo PPO | T84: Gold PPO | U84: AUTH-700080 | V84: Eleanor Brooks, MD | W84: Assigned Department Provider | X84: Therapy | Y84: Note signed | Z84: Posted | AA84: Matched | AB84: Passed | AD84: Plan benefits | AE84: M54.50 | AF84: 22 | AG84: 2026-09-06 16:30 | AH84: Synthetic demonstration charge
A85: OPD-CHG-0081 | B85: OP-202600081 | C85: CSN-OPD-780081 | D85: Outpatient | E85: Demo Regional Medical Center | F85: Physical Therapy | G85: 2026-09-07 | H85: PT-THEREX-OP | I85: Therapeutic Exercise, 15 Minutes | J85: 0420 | K85: 97110 | M85: 2 | N85: 305 | O85: =M85*N85 -> 610 | P85: 379.76 | Q85: =P85*20% -> 75.952 | R85: =O85-P85 -> 230.24 | S85: Demo PPO | T85: Gold PPO | V85: Eleanor Brooks, MD | W85: Assigned Department Provider | X85: Therapy | Y85: Note signed | Z85: Posted | AA85: Matched | AB85: Passed | AD85: Timed units | AE85: M54.50 | AF85: 22 | AG85: 2026-09-07 16:30 | AH85: Synthetic demonstration charge
A86: OPD-CHG-0082 | B86: OP-202600082 | C86: CSN-OPD-780082 | D86: Outpatient | E86: Demo Regional Medical Center | F86: Infusion | G86: 2026-09-08 | H86: INFUSION-1H | I86: Therapeutic Infusion, Initial Hour | J86: 0260 | K86: 96365 | M86: 1 | N86: 780 | O86: =M86*N86 -> 780 | P86: 382.64 | Q86: =P86*20% -> 76.528 | R86: =O86-P86 -> 397.36 | S86: Demo PPO | T86: Gold PPO | U86: AUTH-700082 | V86: Eleanor Brooks, MD | W86: Assigned Department Provider | X86: Infusion | Y86: Administration completed | Z86: Posted | AA86: Matched | AB86: Passed | AD86: Drug policy | AE86: Z51.11 | AF86: 22 | AG86: 2026-09-08 16:30 | AH86: Synthetic demonstration charge
A87: OPD-CHG-0083 | B87: OP-202600083 | C87: CSN-OPD-780083 | D87: Outpatient | E87: Demo Regional Medical Center | F87: Chemotherapy | G87: 2026-09-09 | H87: CHEMO-1H | I87: Chemotherapy Infusion, Initial Hour | J87: 0335 | K87: 96413 | M87: 1 | N87: 1850 | O87: =M87*N87 -> 1850 | P87: 843.54 | Q87: =P87*20% -> 168.708 | R87: =O87-P87 -> 1006.46 | S87: Demo PPO | T87: Gold PPO | U87: AUTH-700083 | V87: Eleanor Brooks, MD | W87: Assigned Department Provider | X87: Infusion | Y87: Administration completed | Z87: Posted | AA87: Matched | AB87: Passed | AD87: Drug policy | AE87: C50.919 | AF87: 22 | AG87: 2026-09-09 16:30 | AH87: Synthetic demonstration charge
A88: OPD-CHG-0084 | B88: OP-202600084 | C88: CSN-OPD-780084 | D88: Outpatient | E88: Demo Regional Medical Center | F88: Behavioral Health | G88: 2026-09-10 | H88: BH-INDIVIDUAL | I88: Outpatient Psychotherapy, 45 Minutes | J88: 0914 | K88: 90834 | M88: 1 | N88: 285 | O88: =M88*N88 -> 285 | P88: 195.82 | Q88: =P88*20% -> 39.164 | R88: =O88-P88 -> 89.18 | S88: Demo PPO | T88: Gold PPO | V88: Eleanor Brooks, MD | W88: Assigned Department Provider | X88: Behavioral Health | Y88: Note signed | Z88: Posted | AA88: Matched | AB88: Passed | AD88: Benefits | AE88: F41.1 | AF88: 22 | AG88: 2026-09-10 16:30 | AH88: Synthetic demonstration charge
A89: OPD-CHG-0085 | B89: OP-202600085 | C89: CSN-OPD-780085 | D89: Outpatient | E89: Demo Regional Medical Center | F89: Emergency Department | G89: 2026-09-11 | H89: ED-LEVEL-1 | I89: Emergency Department Visit Level 1 | J89: 0450 | K89: 99281 | M89: 1 | N89: 360 | O89: =M89*N89 -> 360 | P89: 177.79 | Q89: =P89*20% -> 35.558 | R89: =O89-P89 -> 182.21 | S89: Demo PPO | T89: Gold PPO | V89: Eleanor Brooks, MD | W89: Assigned Department Provider | X89: ED | Y89: Encounter close | Z89: Posted | AA89: Matched | AB89: Passed | AD89: Documentation | AE89: R50.9 | AF89: 22 | AG89: 2026-09-11 16:30 | AH89: Synthetic demonstration charge
A90: OPD-CHG-0086 | B90: OP-202600086 | C90: CSN-OPD-780086 | D90: Outpatient | E90: Demo Regional Medical Center | F90: Emergency Department | G90: 2026-09-12 | H90: ED-LEVEL-2 | I90: Emergency Department Visit Level 2 | J90: 0450 | K90: 99282 | M90: 1 | N90: 670 | O90: =M90*N90 -> 670 | P90: 400.9 | Q90: =P90*20% -> 80.18 | R90: =O90-P90 -> 269.1 | S90: Demo PPO | T90: Gold PPO | V90: Eleanor Brooks, MD | W90: Assigned Department Provider | X90: ED | Y90: Encounter close | Z90: Posted | AA90: Matched | AB90: Passed | AD90: Documentation | AE90: R51.9 | AF90: 22 | AG90: 2026-09-12 16:30 | AH90: Synthetic demonstration charge
A91: OPD-CHG-0087 | B91: OP-202600087 | C91: CSN-OPD-780087 | D91: Outpatient | E91: Demo Regional Medical Center | F91: Emergency Department | G91: 2026-09-13 | H91: ED-LEVEL-3 | I91: Emergency Department Visit Level 3 | J91: 0450 | K91: 99283 | M91: 1 | N91: 1280 | O91: =M91*N91 -> 1280 | P91: 775.44 | Q91: =P91*20% -> 155.088 | R91: =O91-P91 -> 504.56 | S91: Demo PPO | T91: Gold PPO | V91: Eleanor Brooks, MD | W91: Assigned Department Provider | X91: ED | Y91: Encounter close | Z91: Hold | AA91: Exception | AB91: Review | AC91: WQ-EME-04 | AD91: Documentation | AE91: R10.9 | AF91: 22 | AG91: 2026-09-13 16:30 | AH91: Synthetic demonstration charge
A92: OPD-CHG-0088 | B92: OP-202600088 | C92: CSN-OPD-780088 | D92: Outpatient | E92: Demo Regional Medical Center | F92: Emergency Department | G92: 2026-09-14 | H92: ED-LEVEL-4 | I92: Emergency Department Visit Level 4 | J92: 0450 | K92: 99284 | M92: 1 | N92: 2350 | O92: =M92*N92 -> 2350 | P92: 1282.55 | Q92: =P92*20% -> 256.51 | R92: =O92-P92 -> 1067.45 | S92: Demo PPO | T92: Gold PPO | V92: Eleanor Brooks, MD | W92: Assigned Department Provider | X92: ED | Y92: Encounter close | Z92: Posted | AA92: Matched | AB92: Passed | AD92: Documentation | AE92: R06.02 | AF92: 22 | AG92: 2026-09-14 16:30 | AH92: Synthetic demonstration charge
A93: OPD-CHG-0089 | B93: OP-202600089 | C93: CSN-OPD-780089 | D93: Outpatient | E93: Demo Regional Medical Center | F93: Emergency Department | G93: 2026-09-15 | H93: ED-LEVEL-5 | I93: Emergency Department Visit Level 5 | J93: 0450 | K93: 99285 | M93: 1 | N93: 4300 | O93: =M93*N93 -> 4300 | P93: 2558.94 | Q93: =P93*20% -> 511.788 | R93: =O93-P93 -> 1741.06 | S93: Demo PPO | T93: Gold PPO | V93: Eleanor Brooks, MD | W93: Assigned Department Provider | X93: ED | Y93: Encounter close | Z93: Posted | AA93: Matched | AB93: Passed | AD93: Documentation | AE93: R07.9 | AF93: 22 | AG93: 2026-09-15 16:30 | AH93: Synthetic demonstration charge
A94: OPD-CHG-0090 | B94: OP-202600090 | C94: CSN-OPD-780090 | D94: Outpatient | E94: Demo Regional Medical Center | F94: Hospital Clinic | G94: 2026-09-16 | H94: CLINIC-L2 | I94: Hospital Outpatient Clinic Visit Level 2 | J94: 0510 | K94: 99212 | M94: 1 | N94: 215 | O94: =M94*N94 -> 215 | P94: 124.02 | Q94: =P94*20% -> 24.804 | R94: =O94-P94 -> 90.98 | S94: Demo PPO | T94: Gold PPO | V94: Eleanor Brooks, MD | W94: Assigned Department Provider | X94: Ambulatory | Y94: Visit close | Z94: Posted | AA94: Matched | AB94: Passed | AD94: E/M documentation | AE94: I10 | AF94: 22 | AG94: 2026-09-16 16:30 | AH94: Synthetic demonstration charge
A95: OPD-CHG-0091 | B95: OP-202600091 | C95: CSN-OPD-780091 | D95: Outpatient | E95: Demo Regional Medical Center | F95: Hospital Clinic | G95: 2026-09-17 | H95: CLINIC-L3 | I95: Hospital Outpatient Clinic Visit Level 3 | J95: 0510 | K95: 99213 | M95: 1 | N95: 315 | O95: =M95*N95 -> 315 | P95: 220.63 | Q95: =P95*20% -> 44.126 | R95: =O95-P95 -> 94.37 | S95: Demo PPO | T95: Gold PPO | V95: Eleanor Brooks, MD | W95: Assigned Department Provider | X95: Ambulatory | Y95: Visit close | Z95: Posted | AA95: Matched | AB95: Passed | AD95: E/M documentation | AE95: E11.9 | AF95: 22 | AG95: 2026-09-17 16:30 | AH95: Synthetic demonstration charge
A96: OPD-CHG-0092 | B96: OP-202600092 | C96: CSN-OPD-780092 | D96: Outpatient | E96: Demo Regional Medical Center | F96: Hospital Clinic | G96: 2026-09-18 | H96: CLINIC-L4 | I96: Hospital Outpatient Clinic Visit Level 4 | J96: 0510 | K96: 99214 | M96: 1 | N96: 410 | O96: =M96*N96 -> 410 | P96: 197.32 | Q96: =P96*20% -> 39.464 | R96: =O96-P96 -> 212.68 | S96: Demo PPO | T96: Gold PPO | V96: Eleanor Brooks, MD | W96: Assigned Department Provider | X96: Ambulatory | Y96: Visit close | Z96: Posted | AA96: Matched | AB96: Review | AC96: WQ-HOS-01 | AD96: E/M documentation | AE96: J45.40 | AF96: 22 | AG96: 2026-09-18 16:30 | AH96: Synthetic demonstration charge
A97: OPD-CHG-0093 | B97: OP-202600093 | C97: CSN-OPD-780093 | D97: Outpatient | E97: Demo Regional Medical Center | F97: Hospital Clinic | G97: 2026-09-19 | H97: CLINIC-L5 | I97: Hospital Outpatient Clinic Visit Level 5 | J97: 0510 | K97: 99215 | M97: 1 | N97: 570 | O97: =M97*N97 -> 570 | P97: 361.87 | Q97: =P97*20% -> 72.374 | R97: =O97-P97 -> 208.13 | S97: Demo PPO | T97: Gold PPO | V97: Eleanor Brooks, MD | W97: Assigned Department Provider | X97: Ambulatory | Y97: Visit close | Z97: Posted | AA97: Matched | AB97: Passed | AD97: E/M documentation | AE97: I50.9 | AF97: 22 | AG97: 2026-09-19 16:30 | AH97: Synthetic demonstration charge
A98: OPD-CHG-0094 | B98: OP-202600094 | C98: CSN-OPD-780094 | D98: Outpatient | E98: Demo Regional Medical Center | F98: Radiology | G98: 2026-09-20 | H98: XR-CHEST-2V | I98: Chest X-ray, 2 Views | J98: 0320 | K98: 71046 | M98: 1 | N98: 185 | O98: =M98*N98 -> 185 | P98: 90.95 | Q98: =P98*20% -> 18.19 | R98: =O98-P98 -> 94.05 | S98: Demo PPO | T98: Gold PPO | V98: Eleanor Brooks, MD | W98: Assigned Department Provider | X98: RIS/PACS | Y98: Exam completed | Z98: Posted | AA98: Matched | AB98: Passed | AD98: Diagnosis/LCD | AE98: R05.9 | AF98: 22 | AG98: 2026-09-20 16:30 | AH98: Synthetic demonstration charge
A99: OPD-CHG-0095 | B99: OP-202600095 | C99: CSN-OPD-780095 | D99: Outpatient | E99: Demo Regional Medical Center | F99: Radiology | G99: 2026-09-21 | H99: CT-HEAD-WO | I99: CT Head Without Contrast | J99: 0350 | K99: 70450 | M99: 1 | N99: 1900 | O99: =M99*N99 -> 1900 | P99: 1023.6 | Q99: =P99*20% -> 204.72 | R99: =O99-P99 -> 876.4 | S99: Demo PPO | T99: Gold PPO | U99: AUTH-700095 | V99: Eleanor Brooks, MD | W99: Assigned Department Provider | X99: RIS/PACS | Y99: Exam completed | Z99: Posted | AA99: Matched | AB99: Passed | AD99: Prior authorization | AE99: R51.9 | AF99: 22 | AG99: 2026-09-21 16:30 | AH99: Synthetic demonstration charge
A100: OPD-CHG-0096 | B100: OP-202600096 | C100: CSN-OPD-780096 | D100: Outpatient | E100: Demo Regional Medical Center | F100: Radiology | G100: 2026-09-22 | H100: CT-CHEST-W | I100: CT Chest With Contrast | J100: 0350 | K100: 71260 | M100: 1 | N100: 2500 | O100: =M100*N100 -> 2500 | P100: 1553.77 | Q100: =P100*20% -> 310.754 | R100: =O100-P100 -> 946.23 | S100: Demo PPO | T100: Gold PPO | U100: AUTH-700096 | V100: Eleanor Brooks, MD | W100: Assigned Department Provider | X100: RIS/PACS | Y100: Exam completed | Z100: Posted | AA100: Matched | AB100: Passed | AD100: Prior authorization | AE100: R91.1 | AF100: 22 | AG100: 2026-09-22 16:30 | AH100: Synthetic demonstration charge
A101: OPD-CHG-0097 | B101: OP-202600097 | C101: CSN-OPD-780097 | D101: Outpatient | E101: Demo Regional Medical Center | F101: Radiology | G101: 2026-09-23 | H101: MRI-BRAIN-WO | I101: MRI Brain Without Contrast | J101: 0610 | K101: 70551 | M101: 1 | N101: 3250 | O101: =M101*N101 -> 3250 | P101: 1657.5 | Q101: =P101*20% -> 331.5 | R101: =O101-P101 -> 1592.5 | S101: Demo PPO | T101: Gold PPO | U101: AUTH-700097 | V101: Eleanor Brooks, MD | W101: Assigned Department Provider | X101: RIS/PACS | Y101: Exam completed | Z101: Posted | AA101: Matched | AB101: Passed | AD101: Prior authorization | AE101: G43.909 | AF101: 22 | AG101: 2026-09-23 16:30 | AH101: Synthetic demonstration charge
...

Sheet Dashboard
A1: bsolutely original add multiple charges
A2: Executive view of CDM completeness, financial exposure, review status, and charge reconciliation.
A4: Active CDM Records | E4: Gross Charge Value | I4: Expected Allowed
A5: =COUNTIF('CDM Master'!AD:AD,"Active") -> 15 | E5: =SUM('IPD Encounter'!R5:R15) -> 76340 | I5: =SUM('IPD Encounter'!S5:S15) -> 32790
A8: Patient Responsibility | E8: Open Governance | I8: Active Claim Edits
A9: =SUM('IPD Encounter'!T5:T15) -> 6558 | E9: =COUNTIF(Governance!O:O,"<>Closed")-1 -> 1048574 | I9: =COUNTIF('Claim Edits'!L:L,"Active") -> 6
A13: Department | B13: Gross Price Total
A14: Operating Room | B14: =SUMIF('CDM Master'!E:E,A14,'CDM Master'!O:O) -> 11250
A15: Pharmacy | B15: =SUMIF('CDM Master'!E:E,A15,'CDM Master'!O:O) -> 500
A16: Radiology | B16: =SUMIF('CDM Master'!E:E,A16,'CDM Master'!O:O) -> 580
A17: Laboratory | B17: =SUMIF('CDM Master'!E:E,A17,'CDM Master'!O:O) -> 150
A18: Physical Therapy | B18: =SUMIF('CDM Master'!E:E,A18,'CDM Master'!O:O) -> 1000
A19: Surgical Supplies | B19: =SUMIF('CDM Master'!E:E,A19,'CDM Master'!O:O) -> 24000

Sheet CDM Master
A1: Charge Description Master (CDM)
A2: Enterprise master of billable facility items/services, coding, pricing, ownership, and lifecycle controls.
A4: Facility ID | B4: Location | C4: Service Area | D4: Department ID | E4: Department | F4: EAP/CDM Charge Code | G4: Charge Description | H4: Patient-Friendly Description | I4: Charge Type | J4: Revenue Code | K4: CPT/HCPCS | L4: Modifier | M4: NDC / Device ID | N4: Unit Basis | O4: Gross Unit Charge ($) | P4: Cost ($) | Q4: Markup % | R4: HCPCS Units | S4: Bill Area | T4: HB/PB | U4: Charge Trigger | V4: Source System | W4: Orderable/Procedure ID | X4: Price Tier | Y4: Taxable | Z4: Prior Auth Flag | AA4: Medical Necessity Rule | AB4: Effective Date | AC4: Termination Date | AD4: Status | AE4: Owner | AF4: Last Review Date | AG4: Next Review Date | AH4: Review Flag | AI4: Compliance Notes
A5: MAIN | B5: Main Campus | C5: HB | D5: D100 | E5: Inpatient Nursing | F5: RM-SP-001 | G5: Semiprivate Medical/Surgical Room | H5: Semiprivate hospital room | I5: Accommodation | J5: 0120 | N5: Per day | O5: 3500 | P5: 1200 | Q5: =IFERROR((O5-P5)/P5,0) -> 1.9166667 | R5: 1 | S5: HB-NURS | T5: HB | U5: ADT discharge | V5: ADT | W5: BED-SP | X5: Standard | Y5: No | Z5: No | AA5: N/A | AB5: 2026-01-01 | AD5: Active | AE5: Director Revenue Integrity | AF5: 2026-07-15 | AG5: =EDATE(AF5,12) -> 46583 | AH5: =IF(AD5<>"Active","Inactive",IF(AG5<TODAY(),"Overdue",IF(AG5<=TODAY()+60,"Due Soon","Current"))) -> Current
A6: MAIN | B6: Main Campus | C6: HB | D6: D105 | E6: Intensive Care | F6: ICU-DAY-001 | G6: Intensive Care Unit Room | H6: ICU room and monitoring | I6: Accommodation | J6: 0200 | N6: Per day | O6: 8000 | P6: 3500 | Q6: =IFERROR((O6-P6)/P6,0) -> 1.2857143 | R6: 1 | S6: HB-ICU | T6: HB | U6: ADT bed event | V6: ADT | W6: BED-ICU | X6: Standard | Y6: No | Z6: No | AA6: N/A | AB6: 2026-01-01 | AD6: Active | AE6: Director Revenue Integrity | AF6: 2026-07-15 | AG6: =EDATE(AF6,12) -> 46583 | AH6: =IF(AD6<>"Active","Inactive",IF(AG6<TODAY(),"Overdue",IF(AG6<=TODAY()+60,"Due Soon","Current"))) -> Current
A7: MAIN | B7: Main Campus | C7: HB | D7: D200 | E7: Operating Room | F7: OR-MAJOR-01 | G7: Major Operating Room, First Hour | H7: Operating room first hour | I7: Timed Service | J7: 0360 | N7: Per hour | O7: 10000 | P7: 4200 | Q7: =IFERROR((O7-P7)/P7,0) -> 1.3809524 | R7: 1 | S7: HB-OR | T7: HB | U7: Procedure end | V7: OpTime | W7: PROC-OR-MAJ | X7: Standard | Y7: No | Z7: Yes | AA7: Procedure-specific | AB7: 2026-01-01 | AD7: Active | AE7: OR Finance Manager | AF7: 2026-08-01 | AG7: =EDATE(AF7,12) -> 46600 | AH7: =IF(AD7<>"Active","Inactive",IF(AG7<TODAY(),"Overdue",IF(AG7<=TODAY()+60,"Due Soon","Current"))) -> Current
A8: MAIN | B8: Main Campus | C8: HB | D8: D200 | E8: Operating Room | F8: OR-ADD-15 | G8: Operating Room, Additional 15 Minutes | H8: Additional operating room time | I8: Timed Service | J8: 0360 | N8: Per 15 minutes | O8: 1250 | P8: 525 | Q8: =IFERROR((O8-P8)/P8,0) -> 1.3809524 | R8: 1 | S8: HB-OR | T8: HB | U8: Procedure end | V8: OpTime | W8: PROC-OR-15 | X8: Standard | Y8: No | Z8: Yes | AA8: Procedure-specific | AB8: 2026-01-01 | AD8: Active | AE8: OR Finance Manager | AF8: 2026-08-01 | AG8: =EDATE(AF8,12) -> 46600 | AH8: =IF(AD8<>"Active","Inactive",IF(AG8<TODAY(),"Overdue",IF(AG8<=TODAY()+60,"Due Soon","Current"))) -> Current
A9: MAIN | B9: Main Campus | C9: HB | D9: D210 | E9: Recovery Room | F9: RR-HR-001 | G9: Recovery Room, First Hour | H9: Recovery room first hour | I9: Timed Service | J9: 0710 | N9: Per hour | O9: 2000 | P9: 720 | Q9: =IFERROR((O9-P9)/P9,0) -> 1.7777778 | R9: 1 | S9: HB-PACU | T9: HB | U9: PACU discharge | V9: OpTime | W9: PROC-PACU | X9: Standard | Y9: No | Z9: No | AA9: N/A | AB9: 2026-01-01 | AD9: Active | AE9: OR Finance Manager | AF9: 2026-08-01 | AG9: =EDATE(AF9,12) -> 46600 | AH9: =IF(AD9<>"Active","Inactive",IF(AG9<TODAY(),"Overdue",IF(AG9<=TODAY()+60,"Due Soon","Current"))) -> Current
A10: MAIN | B10: Main Campus | C10: HB | D10: D220 | E10: Surgical Supplies | F10: IMP-KNEE-01 | G10: Cemented Knee Implant Package | H10: Knee implant package | I10: Implant | J10: 0278 | M10: DI-088590000001 | N10: Per implant | O10: 20000 | P10: 11500 | Q10: =IFERROR((O10-P10)/P10,0) -> 0.73913043 | R10: 1 | S10: HB-SUP | T10: HB | U10: Implant scan | V10: Inventory | W10: ITEM-KNEE-CEM | X10: Carve-Out | Y10: No | Z10: Yes | AA10: Contract rule | AB10: 2026-01-01 | AD10: Active | AE10: Supply Chain Finance | AF10: 2026-06-30 | AG10: =EDATE(AF10,12) -> 46568 | AH10: =IF(AD10<>"Active","Inactive",IF(AG10<TODAY(),"Overdue",IF(AG10<=TODAY()+60,"Due Soon","Current"))) -> Current
A11: MAIN | B11: Main Campus | C11: HB | D11: D220 | E11: Surgical Supplies | F11: SUP-KNEE-01 | G11: Knee Surgery Supply Pack | H11: Disposable knee surgery supplies | I11: Supply | J11: 0270 | N11: Per pack | O11: 4000 | P11: 1450 | Q11: =IFERROR((O11-P11)/P11,0) -> 1.7586207 | R11: 1 | S11: HB-SUP | T11: HB | U11: Supply issue | V11: Inventory | W11: ITEM-KNEE-PACK | X11: Standard | Y11: No | Z11: No | AA11: N/A | AB11: 2026-01-01 | AD11: Active | AE11: Supply Chain Finance | AF11: 2026-06-30 | AG11: =EDATE(AF11,12) -> 46568 | AH11: =IF(AD11<>"Active","Inactive",IF(AG11<TODAY(),"Overdue",IF(AG11<=TODAY()+60,"Due Soon","Current"))) -> Current
A12: MAIN | B12: Main Campus | C12: HB | D12: D300 | E12: Pharmacy | F12: PH-IV-ABX-01 | G12: Cefazolin 1 g Injection | H12: Cefazolin antibiotic injection | I12: Drug | J12: 0250 | K12: J0690 | M12: 00071-3069-23 | N12: Per 1 g | O12: 500 | P12: 42 | Q12: =IFERROR((O12-P12)/P12,0) -> 10.904762 | R12: 1 | S12: HB-PHAR | T12: HB | U12: Medication administration | V12: Willow/MAR | W12: MED-CEFAZ-1G | X12: Drug | Y12: No | Z12: No | AA12: Dose/frequency | AB12: 2026-01-01 | AD12: Active | AE12: Pharmacy Revenue Integrity | AF12: 2026-09-01 | AG12: =EDATE(AF12,12) -> 46631 | AH12: =IF(AD12<>"Active","Inactive",IF(AG12<TODAY(),"Overdue",IF(AG12<=TODAY()+60,"Due Soon","Current"))) -> Current
A13: MAIN | B13: Main Campus | C13: HB | D13: D400 | E13: Laboratory | F13: LAB-CBC-001 | G13: Complete Blood Count with Automated Differential | H13: Complete blood count test | I13: Lab | J13: 0300 | K13: 85025 | N13: Per test | O13: 150 | P13: 22 | Q13: =IFERROR((O13-P13)/P13,0) -> 5.8181818 | R13: 1 | S13: HB-LAB | T13: HB | U13: Final result | V13: LIS | W13: LAB-CBC | X13: Standard | Y13: No | Z13: No | AA13: Diagnosis/LCD | AB13: 2026-01-01 | AD13: Active | AE13: Lab Finance Manager | AF13: 2026-08-15 | AG13: =EDATE(AF13,12) -> 46614 | AH13: =IF(AD13<>"Active","Inactive",IF(AG13<TODAY(),"Overdue",IF(AG13<=TODAY()+60,"Due Soon","Current"))) -> Current
A14: MAIN | B14: Main Campus | C14: HB | D14: D500 | E14: Radiology | F14: RAD-KNEE-01 | G14: Knee X-ray, 1-2 Views | H14: Knee X-ray | I14: Imaging | J14: 0320 | K14: 73560 | N14: Per study | O14: 400 | P14: 60 | Q14: =IFERROR((O14-P14)/P14,0) -> 5.6666667 | R14: 1 | S14: HB-RAD | T14: HB | U14: Exam completed | V14: RIS/PACS | W14: IMG-KNEE-2V | X14: Standard | Y14: No | Z14: No | AA14: Diagnosis/LCD | AB14: 2026-01-01 | AD14: Active | AE14: Imaging Finance Manager | AF14: 2026-08-15 | AG14: =EDATE(AF14,12) -> 46614 | AH14: =IF(AD14<>"Active","Inactive",IF(AG14<TODAY(),"Overdue",IF(AG14<=TODAY()+60,"Due Soon","Current"))) -> Current
A15: OUT | B15: Outpatient Center | C15: HB | D15: D505 | E15: Radiology | F15: RAD-CHEST-02 | G15: Chest X-ray, 2 Views | H15: Two-view chest X-ray | I15: Imaging | J15: 0320 | K15: 71046 | N15: Per study | O15: 180 | P15: 38 | Q15: =IFERROR((O15-P15)/P15,0) -> 3.7368421 | R15: 1 | S15: HB-RAD | T15: HB | U15: Exam completed | V15: RIS/PACS | W15: IMG-CXR-2V | X15: Standard | Y15: No | Z15: No | AA15: Diagnosis/LCD | AB15: 2026-01-01 | AD15: Active | AE15: Imaging Finance Manager | AF15: 2026-08-15 | AG15: =EDATE(AF15,12) -> 46614 | AH15: =IF(AD15<>"Active","Inactive",IF(AG15<TODAY(),"Overdue",IF(AG15<=TODAY()+60,"Due Soon","Current"))) -> Current
A16: MAIN | B16: Main Campus | C16: HB | D16: D600 | E16: Physical Therapy | F16: PT-EVAL-01 | G16: Physical Therapy Initial Evaluation, Low Complexity | H16: Initial physical therapy evaluation | I16: Therapy | J16: 0420 | K16: 97161 | N16: Per session | O16: 700 | P16: 145 | Q16: =IFERROR((O16-P16)/P16,0) -> 3.8275862 | R16: 1 | S16: HB-THER | T16: HB | U16: Note signed | V16: Therapy | W16: PT-EVAL-LOW | X16: Standard | Y16: No | Z16: Yes | AA16: Plan benefits | AB16: 2026-01-01 | AD16: Active | AE16: Rehab Finance Manager | AF16: 2026-07-31 | AG16: =EDATE(AF16,12) -> 46599 | AH16: =IF(AD16<>"Active","Inactive",IF(AG16<TODAY(),"Overdue",IF(AG16<=TODAY()+60,"Due Soon","Current"))) -> Current
A17: MAIN | B17: Main Campus | C17: HB | D17: D600 | E17: Physical Therapy | F17: PT-EX-15 | G17: Therapeutic Exercise | H17: Therapeutic exercise | I17: Therapy | J17: 0420 | K17: 97110 | N17: Per 15 minutes | O17: 300 | P17: 62 | Q17: =IFERROR((O17-P17)/P17,0) -> 3.8387097 | R17: 1 | S17: HB-THER | T17: HB | U17: Note signed | V17: Therapy | W17: PT-THEREX | X17: Standard | Y17: No | Z17: Yes | AA17: Timed units | AB17: 2026-01-01 | AD17: Active | AE17: Rehab Finance Manager | AF17: 2026-07-31 | AG17: =EDATE(AF17,12) -> 46599 | AH17: =IF(AD17<>"Active","Inactive",IF(AG17<TODAY(),"Overdue",IF(AG17<=TODAY()+60,"Due Soon","Current"))) -> Current
A18: OUT | B18: Outpatient Center | C18: HB | D18: D700 | E18: Hospital Clinic | F18: OPD-CLINIC-01 | G18: Hospital Outpatient Clinic Visit, Level 4 | H18: Hospital clinic facility visit | I18: Clinic | J18: 0510 | K18: 99214 | N18: Per visit | O18: 400 | P18: 95 | Q18: =IFERROR((O18-P18)/P18,0) -> 3.2105263 | R18: 1 | S18: HB-CLIN | T18: HB | U18: Visit close | V18: Cadence/ClinDoc | W18: VISIT-L4 | X18: Standard | Y18: No | Z18: No | AA18: E/M documentation | AB18: 2026-01-01 | AD18: Active | AE18: Ambulatory Finance Manager | AF18: 2026-09-01 | AG18: =EDATE(AF18,12) -> 46631 | AH18: =IF(AD18<>"Active","Inactive",IF(AG18<TODAY(),"Overdue",IF(AG18<=TODAY()+60,"Due Soon","Current"))) -> Current
A19: MAIN | B19: Main Campus | C19: PB | D19: D800 | E19: Orthopedics Professional | F19: PB-ORTH-27447 | G19: Total Knee Arthroplasty, Professional | H19: Surgeon professional service | I19: Professional | K19: 27447 | N19: Per procedure | O19: 3200 | P19: 900 | Q19: =IFERROR((O19-P19)/P19,0) -> 2.5555556 | R19: 1 | S19: PB-ORTH | T19: PB | U19: Charge capture sign | V19: ClinDoc | W19: SURG-TKA | X19: Professional | Y19: No | Z19: Yes | AA19: Procedure-specific | AB19: 2026-01-01 | AD19: Active | AE19: PB Coding Manager | AF19: 2026-08-20 | AG19: =EDATE(AF19,12) -> 46619 | AH19: =IF(AD19<>"Active","Inactive",IF(AG19<TODAY(),"Overdue",IF(AG19<=TODAY()+60,"Due Soon","Current"))) -> Current

Sheet IPD Encounter
A1: Sample IPD Encounter & Charge Reconciliation
A2: Synthetic total knee replacement hospital account with charge-level status, pricing, and reconciliation controls.
A4: Hospital Account (HAR) | B4: Patient MRN | C4: Encounter CSN | D4: Patient Class | E4: Admit Date/Time | F4: Discharge Date/Time | G4: Payer | H4: Plan | I4: DRG | J4: Charge Code | K4: Service Date | L4: Department | M4: Revenue Code | N4: CPT/HCPCS | O4: Modifier | P4: Quantity | Q4: Unit Charge ($) | R4: Extended Gross ($) | S4: Allowed ($) | T4: Patient Responsibility ($) | U4: Contractual Adjustment ($) | V4: Charge Status | W4: Source | X4: Reconciliation Status | Y4: Edit Status | Z4: Notes
A5: HAR-10004567 | B5: MRN-DEMO-0001 | C5: CSN-2026-784512 | D5: Inpatient | E5: 2026-09-14 08:15 | F5: 2026-09-16 14:10 | G5: Demo PPO | H5: Gold PPO | I5: MS-DRG 470 | J5: RM-SP-001 | K5: 2026-09-14 | L5: ='CDM Master'!E5 -> Inpatient Nursing | M5: ='CDM Master'!J5 -> 0120 | N5: ='CDM Master'!K5 -> 0 | O5: ='CDM Master'!L5 -> 0 | P5: 2 | Q5: ='CDM Master'!O5 -> 3500 | R5: =P5*Q5 -> 7000 | S5: 7000 | T5: =S5*20% -> 1400 | U5: =R5-S5 -> 0 | V5: Posted | W5: ='CDM Master'!V5 -> ADT | X5: Matched | Y5: Passed | Z5: Synthetic demo charge
A6: HAR-10004567 | B6: MRN-DEMO-0001 | C6: CSN-2026-784512 | D6: Inpatient | E6: 2026-09-14 08:15 | F6: 2026-09-16 14:10 | G6: Demo PPO | H6: Gold PPO | I6: MS-DRG 470 | J6: OR-MAJOR-01 | K6: 2026-09-14 | L6: ='CDM Master'!E6 -> Intensive Care | M6: ='CDM Master'!J6 -> 0200 | N6: ='CDM Master'!K6 -> 0 | O6: ='CDM Master'!L6 -> 0 | P6: 1 | Q6: ='CDM Master'!O6 -> 8000 | R6: =P6*Q6 -> 8000 | S6: 9000 | T6: =S6*20% -> 1800 | U6: =R6-S6 -> -1000 | V6: Posted | W6: ='CDM Master'!V6 -> ADT | X6: Matched | Y6: Passed | Z6: Synthetic demo charge
A7: HAR-10004567 | B7: MRN-DEMO-0001 | C7: CSN-2026-784512 | D7: Inpatient | E7: 2026-09-14 08:15 | F7: 2026-09-16 14:10 | G7: Demo PPO | H7: Gold PPO | I7: MS-DRG 470 | J7: OR-ADD-15 | K7: 2026-09-14 | L7: ='CDM Master'!E7 -> Operating Room | M7: ='CDM Master'!J7 -> 0360 | N7: ='CDM Master'!K7 -> 0 | O7: ='CDM Master'!L7 -> 0 | P7: 2 | Q7: ='CDM Master'!O7 -> 10000 | R7: =P7*Q7 -> 20000 | S7: 1800 | T7: =S7*20% -> 360 | U7: =R7-S7 -> 18200 | V7: Posted | W7: ='CDM Master'!V7 -> OpTime | X7: Matched | Y7: Passed | Z7: Synthetic demo charge
A8: HAR-10004567 | B8: MRN-DEMO-0001 | C8: CSN-2026-784512 | D8: Inpatient | E8: 2026-09-14 08:15 | F8: 2026-09-16 14:10 | G8: Demo PPO | H8: Gold PPO | I8: MS-DRG 470 | J8: RR-HR-001 | K8: 2026-09-14 | L8: ='CDM Master'!E8 -> Operating Room | M8: ='CDM Master'!J8 -> 0360 | N8: ='CDM Master'!K8 -> 0 | O8: ='CDM Master'!L8 -> 0 | P8: 1 | Q8: ='CDM Master'!O8 -> 1250 | R8: =P8*Q8 -> 1250 | S8: 1500 | T8: =S8*20% -> 300 | U8: =R8-S8 -> -250 | V8: Posted | W8: ='CDM Master'!V8 -> OpTime | X8: Matched | Y8: Passed | Z8: Synthetic demo charge
A9: HAR-10004567 | B9: MRN-DEMO-0001 | C9: CSN-2026-784512 | D9: Inpatient | E9: 2026-09-14 08:15 | F9: 2026-09-16 14:10 | G9: Demo PPO | H9: Gold PPO | I9: MS-DRG 470 | J9: IMP-KNEE-01 | K9: 2026-09-14 | L9: ='CDM Master'!E9 -> Recovery Room | M9: ='CDM Master'!J9 -> 0710 | N9: ='CDM Master'!K9 -> 0 | O9: ='CDM Master'!L9 -> 0 | P9: 1 | Q9: ='CDM Master'!O9 -> 2000 | R9: =P9*Q9 -> 2000 | S9: 9000 | T9: =S9*20% -> 1800 | U9: =R9-S9 -> -7000 | V9: Posted | W9: ='CDM Master'!V9 -> OpTime | X9: Matched | Y9: Passed | Z9: Synthetic demo charge
A10: HAR-10004567 | B10: MRN-DEMO-0001 | C10: CSN-2026-784512 | D10: Inpatient | E10: 2026-09-14 08:15 | F10: 2026-09-16 14:10 | G10: Demo PPO | H10: Gold PPO | I10: MS-DRG 470 | J10: SUP-KNEE-01 | K10: 2026-09-14 | L10: ='CDM Master'!E10 -> Surgical Supplies | M10: ='CDM Master'!J10 -> 0278 | N10: ='CDM Master'!K10 -> 0 | O10: ='CDM Master'!L10 -> 0 | P10: 1 | Q10: ='CDM Master'!O10 -> 20000 | R10: =P10*Q10 -> 20000 | S10: 1800 | T10: =S10*20% -> 360 | U10: =R10-S10 -> 18200 | V10: Posted | W10: ='CDM Master'!V10 -> Inventory | X10: Matched | Y10: Passed | Z10: Synthetic demo charge
A11: HAR-10004567 | B11: MRN-DEMO-0001 | C11: CSN-2026-784512 | D11: Inpatient | E11: 2026-09-14 08:15 | F11: 2026-09-16 14:10 | G11: Demo PPO | H11: Gold PPO | I11: MS-DRG 470 | J11: PH-IV-ABX-01 | K11: 2026-09-14 | L11: ='CDM Master'!E11 -> Surgical Supplies | M11: ='CDM Master'!J11 -> 0270 | N11: ='CDM Master'!K11 -> 0 | O11: ='CDM Master'!L11 -> 0 | P11: 4 | Q11: ='CDM Master'!O11 -> 4000 | R11: =P11*Q11 -> 16000 | S11: 1200 | T11: =S11*20% -> 240 | U11: =R11-S11 -> 14800 | V11: Posted | W11: ='CDM Master'!V11 -> Inventory | X11: Matched | Y11: Passed | Z11: Synthetic demo charge
A12: HAR-10004567 | B12: MRN-DEMO-0001 | C12: CSN-2026-784512 | D12: Inpatient | E12: 2026-09-14 08:15 | F12: 2026-09-16 14:10 | G12: Demo PPO | H12: Gold PPO | I12: MS-DRG 470 | J12: LAB-CBC-001 | K12: 2026-09-14 | L12: ='CDM Master'!E12 -> Pharmacy | M12: ='CDM Master'!J12 -> 0250 | N12: ='CDM Master'!K12 -> J0690 | O12: ='CDM Master'!L12 -> 0 | P12: 2 | Q12: ='CDM Master'!O12 -> 500 | R12: =P12*Q12 -> 1000 | S12: 180 | T12: =S12*20% -> 36 | U12: =R12-S12 -> 820 | V12: Posted | W12: ='CDM Master'!V12 -> Willow/MAR | X12: Matched | Y12: Passed | Z12: Synthetic demo charge
A13: HAR-10004567 | B13: MRN-DEMO-0001 | C13: CSN-2026-784512 | D13: Inpatient | E13: 2026-09-14 08:15 | F13: 2026-09-16 14:10 | G13: Demo PPO | H13: Gold PPO | I13: MS-DRG 470 | J13: RAD-KNEE-01 | K13: 2026-09-14 | L13: ='CDM Master'!E13 -> Laboratory | M13: ='CDM Master'!J13 -> 0300 | N13: ='CDM Master'!K13 -> 85025 | O13: ='CDM Master'!L13 -> 0 | P13: 1 | Q13: ='CDM Master'!O13 -> 150 | R13: =P13*Q13 -> 150 | S13: 260 | T13: =S13*20% -> 52 | U13: =R13-S13 -> -110 | V13: Posted | W13: ='CDM Master'!V13 -> LIS | X13: Matched | Y13: Passed | Z13: Synthetic demo charge
A14: HAR-10004567 | B14: MRN-DEMO-0001 | C14: CSN-2026-784512 | D14: Inpatient | E14: 2026-09-14 08:15 | F14: 2026-09-16 14:10 | G14: Demo PPO | H14: Gold PPO | I14: MS-DRG 470 | J14: PT-EVAL-01 | K14: 2026-09-14 | L14: ='CDM Master'!E14 -> Radiology | M14: ='CDM Master'!J14 -> 0320 | N14: ='CDM Master'!K14 -> 73560 | O14: ='CDM Master'!L14 -> 0 | P14: 1 | Q14: ='CDM Master'!O14 -> 400 | R14: =P14*Q14 -> 400 | S14: 450 | T14: =S14*20% -> 90 | U14: =R14-S14 -> -50 | V14: Posted | W14: ='CDM Master'!V14 -> RIS/PACS | X14: Matched | Y14: Passed | Z14: Synthetic demo charge
A15: HAR-10004567 | B15: MRN-DEMO-0001 | C15: CSN-2026-784512 | D15: Inpatient | E15: 2026-09-14 08:15 | F15: 2026-09-16 14:10 | G15: Demo PPO | H15: Gold PPO | I15: MS-DRG 470 | J15: PT-EX-15 | K15: 2026-09-14 | L15: ='CDM Master'!E15 -> Radiology | M15: ='CDM Master'!J15 -> 0320 | N15: ='CDM Master'!K15 -> 71046 | O15: ='CDM Master'!L15 -> 0 | P15: 3 | Q15: ='CDM Master'!O15 -> 180 | R15: =P15*Q15 -> 540 | S15: 600 | T15: =S15*20% -> 120 | U15: =R15-S15 -> -60 | V15: Posted | W15: ='CDM Master'!V15 -> RIS/PACS | X15: Matched | Y15: Passed | Z15: Synthetic demo charge
O16: TOTAL | R16: =SUM(R5:R15) -> 76340 | S16: =SUM(S5:S15) -> 32790 | T16: =SUM(T5:T15) -> 6558 | U16: =SUM(U5:U15) -> 43550

Sheet Charge Router Rules
A1: Charge Router & Routing Rules
A2: Illustrative routing logic for automated release, review, suppression, and HB/PB destination control.
A4: Rule ID | B4: Priority | C4: Rule Name | D4: Source Application | E4: Trigger | F4: Patient Class | G4: Service Area | H4: Condition | I4: Action | J4: Destination Bill Area | K4: Hold/Release | L4: Workqueue | M4: Severity | N4: Owner | O4: Effective Date | P4: Status | Q4: Test Scenario | R4: Expected Result
A5: CR-001 | B5: 10 | C5: Missing revenue code | D5: Any | E5: Charge received | F5: All | G5: HB | H5: Revenue code is blank | I5: Hold charge | J5: HB Review | K5: Hold | L5: WQ-REV-001 | M5: Error | N5: Revenue Integrity | O5: 2026-01-01 | P5: Active | Q5: HB charge without revenue code | R5: Held for correction
A6: CR-002 | B6: 20 | C6: Missing CPT on coded outpatient service | D6: Radiology/Lab/Therapy | E6: Completion | F6: Outpatient | G6: HB | H6: CPT/HCPCS blank for coded service | I6: Hold charge | J6: HB Coding | K6: Hold | L6: WQ-CODE-002 | M6: Error | N6: HB Coding | O6: 2026-01-01 | P6: Active | Q6: Outpatient imaging without CPT | R6: Held for coding
A7: CR-003 | B7: 30 | C7: Duplicate charge check | D7: Any | E7: Charge received | F7: All | G7: All | H7: Same HAR, charge code, service date, quantity within 24h | I7: Route to review | J7: Charge Review | K7: Hold | L7: WQ-DUP-003 | M7: Warning | N7: Revenue Integrity | O7: 2026-01-01 | P7: Active | Q7: Repeat same-day CBC | R7: Review duplicate intent
A8: CR-004 | B8: 40 | C8: Implant carve-out review | D8: Inventory | E8: Implant scan | F8: Inpatient | G8: HB | H8: Revenue code 0278 and price tier Carve-Out | I8: Route to contract review | J8: HB Contracting | K8: Hold | L8: WQ-IMP-004 | M8: Warning | N8: Managed Care | O8: 2026-01-01 | P8: Active | Q8: Knee implant on contracted case | R8: Validate invoice/carve-out
A9: CR-005 | B9: 50 | C9: Professional charge split | D9: ClinDoc | E9: Procedure sign | F9: All | G9: PB | H9: HB/PB = PB | I9: Route | J9: PB Charge Entry | K9: Release | L9: WQ-PB-005 | M9: Info | N9: PB Coding | O9: 2026-01-01 | P9: Active | Q9: Surgeon procedure charge | R9: Routes to PB
A10: CR-006 | B10: 60 | C10: Passed automation | D10: Any | E10: Charge received | F10: All | G10: All | H10: All required elements present | I10: Release charge | J10: Target bill area | K10: Release | M10: Info | N10: Revenue Integrity | O10: 2026-01-01 | P10: Active | Q10: Complete valid charge | R10: Released to billing

Sheet Claim Edits
A1: Institutional Claim Edits
A2: Pre-bill data-quality, coding, medical-necessity, and contract controls for a clean 837I workflow.
A4: Edit ID | B4: Claim Type | C4: Stage | D4: Edit Description | E4: Logic / Validation | F4: Disposition | G4: Severity | H4: Related Field | I4: Workqueue | J4: Owner | K4: Regulatory/Contract Basis | L4: Status | M4: Last Tested | N4: Test Outcome
A5: CE-001 | B5: 837I | C5: Pre-bill | D5: Missing/invalid revenue code | E5: Revenue code required and valid for bill type | F5: Hold | G5: Error | H5: Revenue Code | I5: WQ-CLAIM-001 | J5: HB Billing | K5: UB-04/837I data quality | L5: Active | M5: 2026-09-01 | N5: Pass
A6: CE-002 | B6: 837I | C6: Pre-bill | D6: CPT required for outpatient ancillary | E6: CPT/HCPCS required for configured revenue codes | F6: Hold | G6: Error | H6: CPT/HCPCS | I6: WQ-CODE-002 | J6: HB Coding | K6: Payer billing rule | L6: Active | M6: 2026-09-01 | N6: Pass
A7: CE-003 | B7: 837I | C7: Pre-bill | D7: Units inconsistent with timed service | E7: Units must match documented time methodology | F7: Hold | G7: Error | H7: Quantity | I7: WQ-THER-003 | J7: Therapy Coding | K7: CPT timed-unit guidance | L7: Active | M7: 2026-09-02 | N7: Pass
A8: CE-004 | B8: 837I | C8: Pre-bill | D8: Authorization missing | E8: Authorization required for flagged service/plan | F8: Hold | G8: Error | H8: Authorization | I8: WQ-AUTH-004 | J8: Prior Authorization | K8: Payer contract | L8: Active | M8: 2026-09-02 | N8: Pass
A9: CE-005 | B9: 837I | C9: Pre-bill | D9: NDC missing for drug | E9: NDC and unit-of-measure required when payer mandates | F9: Hold | G9: Warning | H9: NDC | I9: WQ-PHAR-005 | J9: Pharmacy Billing | K9: Payer/state rule | L9: Active | M9: 2026-09-03 | N9: Pass
A10: CE-006 | B10: 837I | C10: Pre-bill | D10: Implant invoice missing | E10: Invoice/documentation required for carve-out claim line | F10: Hold | G10: Warning | H10: Attachment | I10: WQ-IMP-006 | J10: Managed Care | K10: Contract carve-out | L10: Active | M10: 2026-09-03 | N10: Pass

Sheet Payer Contracts
A1: Payer Contract Configuration
A2: Synthetic contract assumptions used to separate gross charges from expected allowed and patient responsibility.
A4: Contract ID | B4: Payer | C4: Plan | D4: Facility | E4: Patient Class | F4: Methodology | G4: DRG/APC/Fee Schedule | H4: Base Rate ($) | I4: Per Diem ($) | J4: Carve-Out Type | K4: Carve-Out Rule | L4: Coinsurance % | M4: Deductible Applies | N4: Effective Date | O4: Termination Date | P4: Status | Q4: Owner | R4: Notes
A5: CNT-001 | B5: Demo PPO | C5: Gold PPO | D5: Main Campus | E5: Inpatient | F5: DRG | G5: MS-DRG 470 | H5: 30000 | I5: 0 | J5: Implant | K5: Lesser of invoice + 10% or gross charge | L5: 0.2 | M5: Yes | N5: 2026-01-01 | O5: 2026-12-31 | P5: Active | Q5: Managed Care Director | R5: Demo only
A6: CNT-002 | B6: Demo PPO | C6: Gold PPO | D6: Outpatient Center | E6: Outpatient | F6: Fee Schedule | G6: 120% of Medicare APC | H6: 0 | I6: 0 | J6: Drug | K6: Selected drugs separately payable | L6: 0.2 | M6: Yes | N6: 2026-01-01 | O6: 2026-12-31 | P6: Active | Q6: Managed Care Director | R6: Demo only
A7: CNT-003 | B7: Self Pay | C7: Cash Discount | D7: All | E7: All | F7: Discounted Cash | G7: Gross less discount | H7: 0 | I7: 0 | J7: None | K7: 35% discount from gross | L7: 0 | M7: No | N7: 2026-01-01 | O7: 2026-12-31 | P7: Active | Q7: Patient Financial Services | R7: Demo only

Sheet Price Transparency
A1: Hospital Price Transparency Dataset
A2: Illustrative standard-charge view supporting gross, cash, payer-negotiated, minimum, and maximum charge categories.
A4: Facility Name | B4: Facility Address | C4: License Number | D4: Item/Service Code | E4: Description | F4: Setting | G4: Code Type | H4: Code | I4: Gross Charge ($) | J4: Discounted Cash ($) | K4: Payer | L4: Plan | M4: Negotiated Charge ($) | N4: De-identified Min ($) | O4: De-identified Max ($) | P4: Methodology | Q4: Last Updated | R4: MRF Inclusion | S4: Consumer Shoppable | T4: Source CDM Code | U4: Notes
A5: Demo Regional Medical Center | B5: 100 Innovation Drive, Columbus, OH 43215 | C5: OH-DEMO-1001 | D5: RAD-CHEST-02 | E5: ='CDM Master'!G18 -> Hospital Outpatient Clinic Visit, Level 4 | F5: Outpatient | G5: CPT/HCPCS | H5: ='CDM Master'!K18 -> 99214 | I5: ='CDM Master'!O18 -> 400 | J5: =I5*65% -> 260 | K5: Demo PPO | L5: Gold PPO | M5: =I5*72% -> 288 | N5: =I5*55% -> 220 | O5: =I5*88% -> 352 | P5: Negotiated dollar amount | Q5: 2026-09-01 | R5: Yes | S5: Yes | T5: RAD-CHEST-02 | U5: Synthetic demonstration
A6: Demo Regional Medical Center | B6: 100 Innovation Drive, Columbus, OH 43215 | C6: OH-DEMO-1001 | D6: LAB-CBC-001 | E6: ='CDM Master'!G12 -> Cefazolin 1 g Injection | F6: Outpatient | G6: CPT/HCPCS | H6: ='CDM Master'!K12 -> J0690 | I6: ='CDM Master'!O12 -> 500 | J6: =I6*65% -> 325 | K6: Demo PPO | L6: Gold PPO | M6: =I6*72% -> 360 | N6: =I6*55% -> 275 | O6: =I6*88% -> 440 | P6: Negotiated dollar amount | Q6: 2026-09-01 | R6: Yes | S6: Yes | T6: LAB-CBC-001 | U6: Synthetic demonstration
A7: Demo Regional Medical Center | B7: 100 Innovation Drive, Columbus, OH 43215 | C7: OH-DEMO-1001 | D7: PT-EVAL-01 | E7: ='CDM Master'!G14 -> Knee X-ray, 1-2 Views | F7: Outpatient | G7: CPT/HCPCS | H7: ='CDM Master'!K14 -> 73560 | I7: ='CDM Master'!O14 -> 400 | J7: =I7*65% -> 260 | K7: Demo PPO | L7: Gold PPO | M7: =I7*72% -> 288 | N7: =I7*55% -> 220 | O7: =I7*88% -> 352 | P7: Negotiated dollar amount | Q7: 2026-09-01 | R7: Yes | S7: Yes | T7: PT-EVAL-01 | U7: Synthetic demonstration
A8: Demo Regional Medical Center | B8: 100 Innovation Drive, Columbus, OH 43215 | C8: OH-DEMO-1001 | D8: OPD-CLINIC-01 | E8: ='CDM Master'!G18 -> Hospital Outpatient Clinic Visit, Level 4 | F8: Outpatient | G8: CPT/HCPCS | H8: ='CDM Master'!K18 -> 99214 | I8: ='CDM Master'!O18 -> 400 | J8: =I8*65% -> 260 | K8: Demo PPO | L8: Gold PPO | M8: =I8*72% -> 288 | N8: =I8*55% -> 220 | O8: =I8*88% -> 352 | P8: Negotiated dollar amount | Q8: 2026-09-01 | R8: Yes | S8: Yes | T8: OPD-CLINIC-01 | U8: Synthetic demonstration
A9: Demo Regional Medical Center | B9: 100 Innovation Drive, Columbus, OH 43215 | C9: OH-DEMO-1001 | D9: IMP-KNEE-01 | E9: ='CDM Master'!G9 -> Recovery Room, First Hour | F9: Inpatient | G9: CPT/HCPCS | H9: ='CDM Master'!K9 -> 0 | I9: ='CDM Master'!O9 -> 2000 | J9: =I9*65% -> 1300 | K9: Demo PPO | L9: Gold PPO | M9: =I9*72% -> 1440 | N9: =I9*55% -> 1100 | O9: =I9*88% -> 1760 | P9: Negotiated dollar amount | Q9: 2026-09-01 | R9: Yes | S9: No | T9: IMP-KNEE-01 | U9: Synthetic demonstration

Sheet Governance
A1: CDM Governance & Change Control
A2: Formal intake, approval, build, testing, effective dating, and SLA monitoring for CDM changes.
A4: Request ID | B4: Request Type | C4: Requested Change | D4: Affected Charge Code | E4: Business Justification | F4: Requester | G4: Department Approval | H4: Coding Review | I4: Compliance Review | J4: Finance Approval | K4: IT Build | L4: Test Evidence | M4: Effective Date | N4: Risk Level | O4: Status | P4: SLA Due Date | Q4: Days Open | R4: SLA Flag
A5: CHG-2026-001 | B5: Price Change | C5: Increase chest X-ray gross price | D5: RAD-CHEST-02 | E5: Annual pricing review | F5: Imaging Finance | G5: Approved | H5: Approved | I5: Approved | J5: Approved | K5: Complete | L5: Attached | M5: 2026-10-01 | N5: Medium | O5: Ready for Release | P5: 2026-09-25 | Q5: =TODAY()-DATEVALUE("2026-09-01") -> 30 | R5: =IF(O5="Closed","Closed",IF(P5<TODAY(),"Overdue","On Track")) -> On Track
A6: CHG-2026-002 | B6: New Charge | C6: Add robotic surgery disposable kit | D6: NEW-PENDING | E6: New clinical program | F6: OR Finance | G6: Approved | H6: In Review | I6: Pending | J6: Pending | K6: Not Started | L6: Pending | M6: 2026-11-01 | N6: High | O6: In Review | P6: 2026-10-10 | Q6: =TODAY()-DATEVALUE("2026-09-01") -> 30 | R6: =IF(O6="Closed","Closed",IF(P6<TODAY(),"Overdue","On Track")) -> On Track
A7: CHG-2026-003 | B7: Retire Charge | C7: Retire obsolete supply pack | D7: SUP-OLD-01 | E7: Item discontinued | F7: Supply Chain | G7: Approved | H7: Approved | I7: Approved | J7: Approved | K7: Complete | L7: Passed | M7: 2026-09-15 | N7: Low | O7: Closed | P7: 2026-09-12 | Q7: =TODAY()-DATEVALUE("2026-09-01") -> 30 | R7: =IF(O7="Closed","Closed",IF(P7<TODAY(),"Overdue","On Track")) -> Closed

Sheet Audit Trail
A1: Audit Trail
A2: Synthetic immutable-style event history for CDM, routing, pricing, and release activities.
A4: Audit ID | B4: Timestamp | C4: User/Role | D4: Action | E4: Object Type | F4: Object ID | G4: Field Changed | H4: Old Value | I4: New Value | J4: Reason | K4: Approval/Ticket | L4: Environment | M4: Result
A5: AUD-0001 | B5: 2026-09-01 09:15 | C5: Revenue Integrity Analyst | D5: Update | E5: CDM | F5: RAD-CHEST-02 | G5: Gross Unit Charge | H5: 170 | I5: 180 | J5: Annual pricing review | K5: CHG-2026-001 | L5: Production | M5: Success
A6: AUD-0002 | B6: 2026-09-01 10:05 | C6: HB Coding Analyst | D6: Update | E6: CDM | F6: PH-IV-ABX-01 | G6: HCPCS | H6: Blank | I6: J0690 | J6: Coding validation | K6: INC-2026-118 | L6: Production | M6: Success
A7: AUD-0003 | B7: 2026-09-02 14:20 | C7: Managed Care Analyst | D7: Create | E7: Contract | F7: CNT-001 | G7: Implant carve-out | H7: Blank | I7: Invoice + 10% cap | J7: New payer term | K7: CON-2026-44 | L7: Test | M7: Success
A8: AUD-0004 | B8: 2026-09-03 16:45 | C8: Release Manager | D8: Promote | E8: Router Rule | F8: CR-004 | G8: Status | H8: Test | I8: Active | J8: Approved release | K8: REL-2026-91 | L8: Production | M8: Success

Sheet Data Source Map
A1: Revenue Cycle Data Source Map
A2: Traceability from operational systems through charge generation, billing output, pricing, reconciliation, and ownership.
A4: Data Element | B4: Operational Source | C4: Epic-Aligned Workflow Area | D4: CDM Role | E4: Claim Output | F4: Pricing Source | G4: Reconciliation Control | H4: Owner | I4: Refresh Frequency | J4: Key Risk
A5: Room type and days | B5: ADT / Bed Management | C5: Hospital Billing | D5: Maps accommodation code, revenue code, and daily price | E5: 837I 011X/012X/020X | F5: DRG/per diem/contract | G5: Compare midnight census and billed days | H5: Patient Access + Revenue Integrity | I5: Daily | J5: Incorrect patient class or bed dates
A6: OR time | B6: Perioperative system | C6: Charge Router / HB | D6: Maps room tier and timed units | E6: 837I 036X | F6: Usually packaged | G6: Compare procedure timestamps and units | H6: OR Finance | I6: Daily | J6: Missing/incorrect time units
A7: Implant | B7: Inventory / Supply Chain | C7: Charge Router / HB | D7: Maps item, device identifier, revenue code, gross price | E7: 837I 0278 | F7: DRG or carve-out | G7: Three-way match: scan, invoice, charge | H7: Supply Chain Finance | I7: Daily | J7: Missed charge or unsupported carve-out
A8: Drug administration | B8: Pharmacy / MAR | C8: Hospital Billing | D8: Maps medication, HCPCS, NDC, units, and price | E8: 837I 025X + HCPCS/NDC | F8: Packaged or drug carve-out | G8: MAR-to-charge reconciliation | H8: Pharmacy Revenue Integrity | I8: Daily | J8: NDC/unit mismatch
A9: Lab | B9: LIS | C9: Hospital Billing | D9: Maps completed test to revenue/CPT/price | E9: 837I 030X + CPT | F9: Packaged or fee schedule | G9: Completed tests vs posted charges | H9: Lab Finance | I9: Daily | J9: Cancelled test billed
A10: Imaging | B10: RIS/PACS | C10: Hospital Billing | D10: Maps completed study to revenue/CPT/price | E10: 837I 032X + CPT | F10: Packaged or APC/fee schedule | G10: Exam completion vs charge | H10: Imaging Finance | I10: Daily | J10: Wrong study or duplicate charge
A11: Therapy | B11: Therapy documentation | C11: Hospital Billing | D11: Maps timed and untimed services | E11: 837I 042X + CPT | F11: APC/fee schedule | G11: Documented minutes vs units | H11: Rehab Finance | I11: Daily | J11: Timed-unit over/under billing
A12: Professional services | B12: Clinical documentation | C12: Professional Billing | D12: Separate PB charge and coding workflow | E12: 837P | F12: Professional fee schedule | G12: Provider note vs charge | H12: PB Coding | I12: Daily | J12: HB/PB split error

Sheet Data Dictionary
A1: Data Dictionary
A2: Key business definitions and validation expectations for the demo revenue-cycle data model.
A4: Sheet | B4: Field | C4: Definition | D4: Data Type | E4: Required | F4: Allowed Values / Format | G4: Validation Rule | H4: Source of Truth | I4: Owner | J4: Sensitivity
A5: CDM Master | B5: EAP/CDM Charge Code | C5: Unique internal billable item or service identifier | D5: Text | E5: Yes | F5: Unique, active/effective | G5: No duplicates; cannot be blank | H5: Revenue integrity master | I5: Revenue Integrity | J5: Internal
A6: CDM Master | B6: Revenue Code | C6: Institutional claim category for facility charges | D6: Text | E6: HB only | F6: 4-digit code | G6: Required for HB active charges | H6: Billing configuration | I6: HB Coding | J6: Public standard
A7: CDM Master | B7: CPT/HCPCS | C7: Procedure, service, supply, or drug code when applicable | D7: Text | E7: Conditional | F7: Current valid code | G7: Required by service/revenue/payer rule | H7: Coding master | I7: Coding | J7: Licensed/regulated
A8: CDM Master | B8: NDC / Device ID | C8: Drug NDC or device identifier supporting item-level billing | D8: Text | E8: Conditional | F8: Configured format | G8: Required by payer or regulatory rule | H8: Pharmacy/Inventory | I8: Department owner | J8: Restricted operational
A9: IPD Encounter | B9: HAR | C9: Hospital account identifier for facility billing | D9: Text | E9: Yes | F9: Unique account ID | G9: Must link to encounter and payer | H9: Patient accounting | I9: HB Billing | J9: Synthetic in demo
A10: IPD Encounter | B10: Extended Gross | C10: Quantity multiplied by CDM gross unit charge | D10: Currency | E10: Yes | F10: Formula | G10: Quantity x unit charge | H10: Derived | I10: Revenue Integrity | J10: Financial
A11: Price Transparency | B11: Negotiated Charge | C11: Payer- and plan-specific negotiated amount | D11: Currency | E11: Conditional | F11: Dollar / methodology | G11: Must be current and attributable | H11: Contract management | I11: Managed Care | J11: Public when reported
A12: Governance | B12: Status | C12: Current lifecycle stage of a change request | D12: Text | E12: Yes | F12: Submitted/In Review/Approved/Ready/Closed | G12: Controlled transition | H12: Change control | I12: Revenue Integrity | J12: Internal
